Workbook
Name Company_Name: Model!$G$7
Name Cost_of_Debt: WACC!$F$8
Name Cost_of_Preferred: WACC!$F$9
Name Diluted: Model!$G$10
Name Discount_Rate: DCF!$G$13
Name Equity_Risk_Premium: WACC!$F$7
Name Forward_Year_1: Model!$N$14
Name Forward_Year_2: Model!$N$15
Name Forward_Year_3: Model!$N$16
Name Hist_Year: Model!$N$7
Name LTM: Model!$N$13
Name Premium_Case: DCF!$G$6
Name Premium_Uplift: DCF!#REF!
Name Pub_Comps_Params: PubComps_Data!$C$3:$C$102
Name Pub_Comps_Range: PubComps_Data!$C$3:$AL$102
Name Pub_Comps_Tickers: PubComps_Data!$C$3:$AL$3
Name Risk_Free_Rate: WACC!$F$6
Name Scenario: DCF!$G$5
Name Share_Price: Model!$G$9
Name Tax_Rate: Model!$G$12
Name Terminal_Growth_Rate: DCF!$Q$10
Name Ticker: Model!$G$8
Name Units: Model!$G$15
Name Valuation_Date: Model!$N$10

Sheet Cover
B2: =Company_Name&" - Operating Model and Valuation - Cover Page and Navigation" -> Butterfly Network, inc. - Operating Model and Valuation - Cover Page and Navigation
C12: Company Name: | D12: =Company_Name -> Butterfly Network, inc.
C13: Model Name: | D13: Operating Model and Valuation (5-Year Forecast)
C14: Author: | D14: Glenn Rentrop
C16: File Name: | D16: =MID(CELL("filename"),SEARCH("[",CELL("filename"))+1, SEARCH("]",CELL("filename"))-SEARCH("[",CELL("filename"))-1) -> BFLYMODEL.xlsx
C17: Analysis Date: | D17: =Valuation_Date -> 45966
C19: Navigation, Summary, or Graph Worksheet:
C20: Financial Model Worksheet:
C21: Data and Back-End Calculation Worksheet:
B23: # | C23: Sheet Name | D23: Link to Sheet
B24: =_xlfn.SHEET(INDIRECT(D24&"!A1")) -> 2 | C24: Model and Valuation Summary | D24: Summary
B25: =_xlfn.SHEET(INDIRECT(D25&"!A1")) -> 3 | C25: Graphs and Dashboard | D25: Graphs
B26: =_xlfn.SHEET(INDIRECT(D26&"!A1")) -> 5 | C26: Operating Scenarios and 3-Statement Model | D26: Model
B27: =_xlfn.SHEET(INDIRECT(D27&"!A1")) -> 6 | C27: Revenue Drivers, Scenario Analysis, Capex, D&A | D27: Drivers
B28: =_xlfn.SHEET(INDIRECT(D28&"!A1")) -> 4 | C28: Stub Period Results from Q1 | D28: Q3
B29: =_xlfn.SHEET(INDIRECT(D29&"!A1")) -> 7 | C29: Discounted Cash Flow Analysis and Sensitivities | D29: DCF
B30: =_xlfn.SHEET(INDIRECT(D30&"!A1")) -> 8 | C30: Weighted Average Cost of Capital (WACC) Calculations | D30: WACC
B31: =_xlfn.SHEET(INDIRECT(D31&"!A1")) -> 9 | C31: Valuation Summary - Back-End Calculations | D31: ValSum
B32: =_xlfn.SHEET(INDIRECT(D32&"!A1")) -> 10 | C32: Valuation "Football Field" Chart | D32: ValGraph
B33: =_xlfn.SHEET(INDIRECT(D33&"!A1")) -> 11 | C33: Comparable Public Companies - Output | D33: PubComps
B34: =_xlfn.SHEET(INDIRECT(D34&"!A1")) -> 12 | C34: Comparable Public Companies - Data and Calculations | D34: PubComps_Data
B35: =_xlfn.SHEET(INDIRECT(D35&"!A1")) -> 13 | C35: Precedent Transactions | D35: MAComps

Sheet Summary
C3: =Company_Name&" - Summary of Operating Model and Valuation - "&Scenario&" Case" -> Butterfly Network, inc. - Summary of Operating Model and Valuation - Downside Case
C4: ($ in Thousands Except Per Share and Per Unit Data)
G6: Historical | H6: Projected: | P6: Projected
C7: Summary of Operational Performance: | E7: Units: | G7: 44592 | H7: 44957 | I7: 45322 | J7: 45688 | K7: 46053 | L7: 46418 | M7: 46783 | N7: 47149 | P7: CAGR:
C8: Segment-Level Statistics:
C10: Product Revenue | E10: $T | G10: =Drivers!G12 -> 50263 | H10: =Drivers!H12 -> 40036 | I10: =Drivers!I12 -> 54200 | J10: =Drivers!J12 -> 63443 | K10: =Drivers!K12 -> 56950 | L10: =Drivers!L12 -> 77000 | M10: =Drivers!M12 -> 84000 | N10: =Drivers!N12 -> 105000 | P10: =(M10/H10)^(1/YEARFRAC(G$7,L$7,))-1 -> 0.15975358
E11: % | H11: =H10/G10-1 -> -0.20346975 | I11: =I10/H10-1 -> 0.3537816 | J11: =J10/I10-1 -> 0.17053506 | K11: =K10/J10-1 -> -0.10234384 | L11: =L10/K10-1 -> 0.35206321 | M11: =M10/L10-1 -> 0.090909091 | N11: =N10/M10-1 -> 0.25
C12: Software Revenue | E12: $T | G12: =Drivers!G21 -> 23127.06 | H12: =Drivers!H21 -> 25863.902 | I12: =Drivers!I21 -> 27856.041 | J12: =Drivers!J21 -> 27400 | K12: =Drivers!K21 -> 30000 | L12: =Drivers!L21 -> 36000 | M12: =Drivers!M21 -> 51000 | N12: =Drivers!N21 -> 63000 | P12: =(M12/H12)^(1/YEARFRAC(G$7,L$7,))-1 -> 0.1454476
E13: % | H13: =H12/G12-1 -> 0.11833938 | I13: =I12/H12-1 -> 0.077023915 | J13: =J12/I12-1 -> -0.01637135 | K13: =K12/J12-1 -> 0.094890511 | L13: =L12/K12-1 -> 0.2 | M13: =M12/L12-1 -> 0.41666667 | N13: =N12/M12-1 -> 0.23529412
C14: Embedded Revenue | E14: $T | G14: =Drivers!G23 -> 0 | H14: =Drivers!H23 -> 0 | I14: =Drivers!I23 -> 0 | J14: =Drivers!J23 -> 6800 | K14: =Drivers!K23 -> 25000 | L14: =Drivers!L23 -> 25000 | M14: =Drivers!M23 -> 40000 | N14: =Drivers!N23 -> 40000
E15: % | K15: =K14/J14-1 -> 2.6764706 | L15: =L14/K14-1 -> 0 | M15: =M14/L14-1 -> 0.6 | N15: =N14/M14-1 -> 0
C16: Home Care Revenue | E16: $T | G16: =Drivers!G28 -> 0 | H16: =Drivers!H28 -> 0 | I16: =Drivers!I28 -> 0 | J16: =Drivers!J28 -> 0 | K16: =Drivers!K28 -> 1000 | L16: =Drivers!L28 -> 5000 | M16: =Drivers!M28 -> 15000 | N16: =Drivers!N28 -> 20000
E17: % | L17: =L16/K16-1 -> 4 | M17: =M16/L16-1 -> 2 | N17: =N16/M16-1 -> 0.33333333
C19: Company-Wide:
C21: Revenue: | E21: $T | G21: =Model!G72 -> 73390 | H21: =Model!H72 -> 65900 | I21: =Model!I72 -> 82056 | J21: =Model!J72 -> 97643 | K21: =Model!K72 -> 112950 | L21: =Model!L72 -> 143000 | M21: =Model!M72 -> 190000 | N21: =Model!N72 -> 228000 | P21: =(L21/G21)^(1/YEARFRAC(G$7,L$7,))-1 -> 0.14272
C22: Revenue Growth: | E22: % | H22: =H21/G21-1 -> -0.1020575 | I22: =I21/H21-1 -> 0.24515933 | J22: =J21/I21-1 -> 0.18995564 | K22: =K21/J21-1 -> 0.15676495 | L22: =L21/K21-1 -> 0.26604692 | M22: =M21/L21-1 -> 0.32867133 | N22: =N21/M21-1 -> 0.2
C24: Gross Profit: | E24: $T | G24: =Model!G78 -> 39460 | H24: =Model!H78 -> 16856 | I24: =Model!I78 -> 48831 | J24: =Model!J78 -> 45767 | K24: =Model!K78 -> 81170 | L24: =Model!L78 -> 101400 | M24: =Model!M78 -> 141100 | N24: =Model!N78 -> 167100 | P24: =(L24/G24)^(1/YEARFRAC(G$7,L$7,))-1 -> 0.20774758
C25: Profit Margin: | E25: % | G25: =G24/G21 -> 0.53767543 | H25: =H24/H21 -> 0.25578149 | I25: =I24/I21 -> 0.59509359 | J25: =J24/J21 -> 0.46871768 | K25: =K24/K21 -> 0.71863656 | L25: =L24/L21 -> 0.70909091 | M25: =M24/M21 -> 0.74263158 | N25: =N24/N21 -> 0.73289474
C27: =Model!C85 -> Total operating expenses | E27: $T | G27: =-Model!G85 -> 232480 | H27: =-Model!H85 -> 162466 | I27: =-Model!I85 -> 123242 | J27: =-Model!J85 -> 98619.43 | K27: =-Model!K85 -> 90360 | L27: =-Model!L85 -> 92950 | M27: =-Model!M85 -> 104500 | N27: =-Model!N85 -> 104880
C29: EBIT | G29: {=Model!G87:N87} -> -193020 | H29: -145610 | I29: -74411 | J29: -52852.43 | K29: -9190 | L29: 8450 | M29: 36600 | N29: 62220 | P29: =(L29/G29)^(1/YEARFRAC(G$7,L$7,))-1 -> -1.5348733
C30: Ebit Margin: | G30: =G29/G21 -> -2.6300586 | H30: =H29/H21 -> -2.2095599 | I30: =I29/I21 -> -0.90683192 | J30: =J29/J21 -> -0.54128232 | K30: =K29/K21 -> -0.081363435 | L30: =L29/L21 -> 0.059090909 | M30: =M29/M21 -> 0.19263158 | N30: =N29/N21 -> 0.27289474
C32: Comprehensive Income: | E32: $T | G32: =Model!G97 -> -168723 | H32: =Model!H97 -> -133700 | I32: =Model!I97 -> -72492 | J32: =Model!J97 -> -49463.491 | K32: =Model!K97 -> -8501.9708 | L32: =Model!L97 -> 10798.983 | M32: =Model!M97 -> 40699.678 | N32: =Model!N97 -> 69395.855 | P32: =(L32/G32)^(1/YEARFRAC(G$7,L$7,))-1 -> -1.5770876
C33: Basic Earnings per Share (EPS): | E33: $ as Stated | G33: =G32/(Diluted*Units) -> -0.74199833 | H33: =H32/(Diluted*Units) -> -0.5879766 | I33: =I32/(Diluted*Units) -> -0.3188003 | J33: =J32/(Diluted*Units) -> -0.21752711 | K33: =K32/(Diluted*Units) -> -0.037389379 | L33: =L32/(Diluted*Units) -> 0.047491019 | M33: =M32/(Diluted*Units) -> 0.17898623 | N33: =N32/(Diluted*Units) -> 0.30518429
C35: Capital expenditures: | E35: $T | G35: =Model!G170 -> -18302 | H35: =Model!H170 -> -5783 | I35: =Model!I170 -> -2694 | J35: =Model!J170 -> -2465.4858 | K35: =Model!K170 -> -2710.8 | L35: =Model!L170 -> -2788.5 | M35: =Model!M170 -> -3135 | N35: =Model!N170 -> -3146.4 | P35: =(L35/G35)^(1/YEARFRAC(G$7,L$7,))-1 -> -0.31360451
C36: % Revenue: | E36: %
C38: Cash Flow From Operations: | E38: $T | G38: =Model!G164 -> -169115 | H38: =Model!H164 -> -98820 | I38: =Model!I164 -> -41707 | J38: =Model!J164 -> -26415.297 | K38: =Model!K164 -> 19332.207 | L38: =Model!L164 -> 41923.908 | M38: =Model!M164 -> 62324.023 | N38: =Model!N164 -> 88317.806
C39: Cash Flow From Investing: | E39: $T | G39: =Model!G172 -> -93779 | H39: =Model!H172 -> 70414 | I39: =Model!I172 -> -2658 | J39: =Model!J172 -> -2431.1524 | K39: =Model!K172 -> -2676.4667 | L39: =Model!L172 -> -2754.1667 | M39: =Model!M172 -> -3100.6667 | N39: =Model!N172 -> -3112.0667
C40: Cash Flows From Financing Activities: | E40: $T | G40: =Model!G180 -> 2881 | H40: =Model!H180 -> 228 | I40: =Model!I180 -> -1495 | J40: =Model!J180 -> -542.5 | K40: =Model!K180 -> -424.15 | L40: =Model!L180 -> -317.635 | M40: =Model!M180 -> -221.7715 | N40: =Model!N180 -> -135.49435
C42: Total Assets: | E42: $T | H42: =Model!H118 -> 304274 | I42: =Model!I118 -> 256082 | J42: =Model!J118 -> 206567.46 | K42: =Model!K118 -> 217521.15 | L42: =Model!L118 -> 257365.92 | M42: =Model!M118 -> 333442.51 | N42: =Model!N118 -> 439663.33
C43: Cash and Cash Equivalents: | E43: $T | H43: =Model!H108 -> 134437 | I43: =Model!I108 -> 88775 | J43: =Model!J108 -> 59386.051 | K43: =Model!K108 -> 75617.641 | L43: =Model!L108 -> 114469.75 | M43: =Model!M108 -> 173471.33 | N43: =Model!N108 -> 258541.58
C45: EBITDA: | E45: $T | G45: =DCF!H62 -> -183703 | H45: =DCF!I62 -> -127586 | I45: =DCF!J62 -> -60310 | J45: =DCF!K62 -> -46163.568 | K45: =DCF!L62 -> -3779.9891 | L45: =DCF!M62 -> 14395.194 | M45: =DCF!N62 -> 44029.711 | N45: =DCF!O62 -> 71482.662 | P45: =(L45/G45)^(1/YEARFRAC(G$7,L$7,))-1 -> -1.600925
C46: EBITDA Margin: | E46: % | G46: =G45/G21 -> -2.5031067 | H46: =H45/H21 -> -1.9360546 | I46: =I45/I21 -> -0.73498586 | J46: =J45/J21 -> -0.47277908 | K46: =K45/K21 -> -0.033466039 | L46: =L45/L21 -> 0.10066569 | M46: =M45/M21 -> 0.23173532 | N46: =N45/N21 -> 0.31352045
G48: LTM | I48: Projected:
C49: Summary of Valuation Multiples: | E49: Units: | H49: =J7 -> 45688 | I49: =K7 -> 46053
C50: EV / Revenue - Comparables: | E50: x | G50: {=PubComps!N36:P36} -> 1.9782445 | H50: 2.1391078 | I50: 1.9808956
C51: ="EV / Revenue - "&Company_Name&":" -> EV / Revenue - Butterfly Network, inc.: | E51: x | G51: {=PubComps!N40:P40} -> 2.9859621 | H51: 9.5966092 | I51: 10.690741
C52: Projected Revenue Growth - Comparables: | E52: % | I52: =PubComps!W17 -> 0.044081831
C53: ="Projected Revenue Growth - "&Company_Name&":" -> Projected Revenue Growth - Butterfly Network, inc.: | E53: % | I53: =PubComps!W21 -> 0.026878436
C55: EV / EBITDA - Comparables: | E55: x | G55: {=PubComps!Q36:S36} -> 8.59825 | H55: 12.563107 | I55: 11.70442
C56: ="EV / EBITDA - "&Company_Name&":" -> EV / EBITDA - Butterfly Network, inc.: | E56: x | G56: {=PubComps!Q40:S40} -> 2.3516326 | H56: NM | I56: NM
C57: Projected EBITDA Growth - Comparables: | E57: % | I57: =PubComps!X17 -> 0.073364358
C58: ="Projected EBITDA Growth - "&Company_Name&":" -> Projected EBITDA Growth - Butterfly Network, inc.: | E58: % | I58: =PubComps!X21 -> 0.007751938
C60: P / E - Comparables: | E60: x | G60: {=PubComps!T36:V36} -> 11.486025 | H60: 14.310018 | I60: 13.606361
C61: ="P / E - "&Company_Name&":" -> P / E - Butterfly Network, inc.: | E61: x | G61: {=PubComps!T40:V40} -> NM | H61: NM | I61: NM

Sheet Graphs
B2: ="Graphs and Analysis of Financial Model Output - "&TEXT(Company_Name,"") -> Graphs and Analysis of Financial Model Output - Butterfly Network, inc.
P4: Year | Q4: Revenue | R4: EBITDA | S4: EBITDA Margin
P5: {=TRANSPOSE(Model!G66:N66)} -> 44926 | Q5: {=TRANSPOSE(Model!G72:N72)} -> 73390 | R5: {=TRANSPOSE(DCF!H62:O62)} -> -183703 | S5: =R5/Q5 -> -2.5031067 | X5: ="Revenue & Normalized Gross Margin" -> Revenue & Normalized Gross Margin
P6: 45291 | Q6: 65900 | R6: -127586 | S6: =R6/Q6 -> -1.9360546
P7: 45657 | Q7: 82056 | R7: -60310 | S7: =R7/Q7 -> -0.73498586
P8: 46022 | Q8: 97643 | R8: -46163.568 | S8: =R8/Q8 -> -0.47277908
P9: 46387 | Q9: 112950 | R9: -3779.9891 | S9: =R9/Q9 -> -0.033466039
P10: 46752 | Q10: 143000 | R10: 14395.194 | S10: =R10/Q10 -> 0.10066569
P11: 47118 | Q11: 190000 | R11: 44029.711 | S11: =R11/Q11 -> 0.23173532
P12: 47483 | Q12: 228000 | R12: 71482.662 | S12: =R12/Q12 -> 0.31352045
P16: Current Region Selected: | Q16: 1
P18: Status: | R18: TRUE | S18: TRUE
P19: Year | Q19: Revenue | R19: EBITDA | S19: EBITDA Margin
P20: =INDEX($P$4:$P$14,$Q$16+ROWS(P$21:$P23)) -> 45657 | Q20: =INDEX($Q$4:$Q$14,$Q$16+ROWS(Q$19:Q23)) -> 112950 | R20: =IF($Q$16,INDEX($R$4:$R$14,$Q$16+ROWS(R$19:R23)),"") -> -3779.9891 | S20: =IF($Q$16,INDEX($S$4:$S$14,$Q$16+ROWS(S$19:S23)),NA()) -> -0.033466039 | X20: Unlevered Free Cash Flow
P21: =INDEX($P$4:$P$14,$Q$16+ROWS(P$21:$P24)) -> 46022 | Q21: =INDEX($Q$4:$Q$14,$Q$16+ROWS(Q$19:Q24)) -> 143000 | R21: =IF($Q$16,INDEX($R$4:$R$14,$Q$16+ROWS(R$19:R24)),"") -> 14395.194 | S21: =IF($Q$16,INDEX($S$4:$S$14,$Q$16+ROWS(S$19:S24)),NA()) -> 0.10066569
P22: =INDEX($P$4:$P$14,$Q$16+ROWS(P$21:$P25)) -> 46387 | Q22: =INDEX($Q$4:$Q$14,$Q$16+ROWS(Q$19:Q25)) -> 190000 | R22: =IF($Q$16,INDEX($R$4:$R$14,$Q$16+ROWS(R$19:R25)),"") -> 44029.711 | S22: =IF($Q$16,INDEX($S$4:$S$14,$Q$16+ROWS(S$19:S25)),NA()) -> 0.23173532
P23: =INDEX($P$4:$P$14,$Q$16+ROWS(P$21:$P26)) -> 46752 | Q23: =INDEX($Q$4:$Q$14,$Q$16+ROWS(Q$19:Q26)) -> 228000 | R23: =IF($Q$16,INDEX($R$4:$R$14,$Q$16+ROWS(R$19:R26)),"") -> 71482.662 | S23: =IF($Q$16,INDEX($S$4:$S$14,$Q$16+ROWS(S$19:S26)),NA()) -> 0.31352045
P27: =Company_Name&": Revenue, EBITDA, and Margins, FY"&TEXT(P20,"yy")&" to FY"&TEXT(P23,"yy") -> Butterfly Network, inc.: Revenue, EBITDA, and Margins, FY24 to FY27
P33: =Company_Name&": Revenue, Operating Expenses, EBIT" -> Butterfly Network, inc.: Revenue, Operating Expenses, EBIT | X33: Revenue by Segment
P48: =Company_Name&": Revenue by Segment" -> Butterfly Network, inc.: Revenue by Segment
P65: ="Annual Revenue, FY"&TEXT(Forward_Year_1,"yy")&" - FY"&TEXT(Forward_Year_2,"yy") -> Annual Revenue, FY25 - FY26 | Q65: ="FY"&TEXT(Forward_Year_1,"yy") -> FY25 | R65: ="FY"&TEXT(Forward_Year_2,"yy") -> FY26
P66: ="Annual EBITDA, FY"&TEXT(Forward_Year_1,"yy")&" - FY"&TEXT(Forward_Year_2,"yy") -> Annual EBITDA, FY25 - FY26 | Q66: ="FY"&TEXT(Forward_Year_1,"yy") -> FY25 | R66: ="FY"&TEXT(Forward_Year_2,"yy") -> FY26
P80: ="Projected Revenue Growth, FY"&TEXT(Forward_Year_1,"yy")&" - FY"&TEXT(Forward_Year_2,"yy") -> Projected Revenue Growth, FY25 - FY26
P81: ="Projected EBITDA Growth, FY"&TEXT(Forward_Year_1,"yy")&" - FY"&TEXT(Forward_Year_2,"yy") -> Projected EBITDA Growth, FY25 - FY26
P83: ="FY"&TEXT(Forward_Year_2,"yy")&" Revenue Multiples" -> FY26 Revenue Multiples
P84: ="FY"&TEXT(Forward_Year_2,"yy")&" EBITDA Multiples" -> FY26 EBITDA Multiples
P90: Supporting Data (Sorted by revenue in ascending order): | Q90: Revenue: | T90: EBITDA: | W90: Rev. Multiples: | Z90: EBITDA Multiples:
Q91: =PubComps_Data!C73 -> 2025-12-31 Revenue: | R91: =PubComps_Data!C77 -> 2026-12-31 Revenue: | T91: =PubComps_Data!C74 -> 2025-12-31 EBITDA: | U91: =PubComps_Data!C78 -> 2026-12-31 EBITDA: | W91: =PubComps_Data!C96 -> 2025-12-31 EV / Revenue: | X91: =PubComps_Data!C100 -> 2026-12-31 EV / Revenue: | Z91: =PubComps_Data!C97 -> 2025-12-31 EV / EBITDA: | AA91: =PubComps_Data!C101 -> 2026-12-31 EV / EBITDA:
P92: GEHC | Q92: =INDEX(Pub_Comps_Range,MATCH(Q$91,Pub_Comps_Params,0),MATCH($P92,Pub_Comps_Tickers,0)) -> 20530 | R92: =INDEX(Pub_Comps_Range,MATCH(R$91,Pub_Comps_Params,0),MATCH($P92,Pub_Comps_Tickers,0)) -> 21435 | T92: =INDEX(Pub_Comps_Range,MATCH(T$91,Pub_Comps_Params,0),MATCH($P92,Pub_Comps_Tickers,0)) -> 3653 | U92: =INDEX(Pub_Comps_Range,MATCH(U$91,Pub_Comps_Params,0),MATCH($P92,Pub_Comps_Tickers,0)) -> 3921 | W92: =INDEX(Pub_Comps_Range,MATCH(W$91,Pub_Comps_Params,0),MATCH($P92,Pub_Comps_Tickers,0)) -> 2.2354131 | X92: =INDEX(Pub_Comps_Range,MATCH(X$91,Pub_Comps_Params,0),MATCH($P92,Pub_Comps_Tickers,0)) -> 2.1410324 | Z92: =INDEX(Pub_Comps_Range,MATCH(Z$91,Pub_Comps_Params,0),MATCH($P92,Pub_Comps_Tickers,0)) -> 12.563107 | AA92: =INDEX(Pub_Comps_Range,MATCH(AA$91,Pub_Comps_Params,0),MATCH($P92,Pub_Comps_Tickers,0)) -> 11.70442
P93: MASI | Q93: =INDEX(Pub_Comps_Range,MATCH(Q$91,Pub_Comps_Params,0),MATCH($P93,Pub_Comps_Tickers,0)) -> 1521 | R93: =INDEX(Pub_Comps_Range,MATCH(R$91,Pub_Comps_Params,0),MATCH($P93,Pub_Comps_Tickers,0)) -> 1639 | T93: =INDEX(Pub_Comps_Range,MATCH(T$91,Pub_Comps_Params,0),MATCH($P93,Pub_Comps_Tickers,0)) -> 497 | U93: =INDEX(Pub_Comps_Range,MATCH(U$91,Pub_Comps_Params,0),MATCH($P93,Pub_Comps_Tickers,0)) -> 544 | W93: =INDEX(Pub_Comps_Range,MATCH(W$91,Pub_Comps_Params,0),MATCH($P93,Pub_Comps_Tickers,0)) -> 5.4004997 | X93: =INDEX(Pub_Comps_Range,MATCH(X$91,Pub_Comps_Params,0),MATCH($P93,Pub_Comps_Tickers,0)) -> 5.0116901 | Z93: =INDEX(Pub_Comps_Range,MATCH(Z$91,Pub_Comps_Params,0),MATCH($P93,Pub_Comps_Tickers,0)) -> 16.527485 | AA93: =INDEX(Pub_Comps_Range,MATCH(AA$91,Pub_Comps_Params,0),MATCH($P93,Pub_Comps_Tickers,0)) -> 15.099559
P94: INMD | Q94: =INDEX(Pub_Comps_Range,MATCH(Q$91,Pub_Comps_Params,0),MATCH($P94,Pub_Comps_Tickers,0)) -> 368 | R94: =INDEX(Pub_Comps_Range,MATCH(R$91,Pub_Comps_Params,0),MATCH($P94,Pub_Comps_Tickers,0)) -> 383 | T94: =INDEX(Pub_Comps_Range,MATCH(T$91,Pub_Comps_Params,0),MATCH($P94,Pub_Comps_Tickers,0)) -> 94 | U94: =INDEX(Pub_Comps_Range,MATCH(U$91,Pub_Comps_Params,0),MATCH($P94,Pub_Comps_Tickers,0)) -> 101 | W94: =INDEX(Pub_Comps_Range,MATCH(W$91,Pub_Comps_Params,0),MATCH($P94,Pub_Comps_Tickers,0)) -> 1.1954076 | X94: =INDEX(Pub_Comps_Range,MATCH(X$91,Pub_Comps_Params,0),MATCH($P94,Pub_Comps_Tickers,0)) -> 1.1485901 | Z94: =INDEX(Pub_Comps_Range,MATCH(Z$91,Pub_Comps_Params,0),MATCH($P94,Pub_Comps_Tickers,0)) -> 4.6798936 | AA94: =INDEX(Pub_Comps_Range,MATCH(AA$91,Pub_Comps_Params,0),MATCH($P94,Pub_Comps_Tickers,0)) -> 4.3555446
P95: IART | Q95: =INDEX(Pub_Comps_Range,MATCH(Q$91,Pub_Comps_Params,0),MATCH($P95,Pub_Comps_Tickers,0)) -> 1637 | R95: =INDEX(Pub_Comps_Range,MATCH(R$91,Pub_Comps_Params,0),MATCH($P95,Pub_Comps_Tickers,0)) -> 1681 | T95: =INDEX(Pub_Comps_Range,MATCH(T$91,Pub_Comps_Params,0),MATCH($P95,Pub_Comps_Tickers,0)) -> 314 | U95: =INDEX(Pub_Comps_Range,MATCH(U$91,Pub_Comps_Params,0),MATCH($P95,Pub_Comps_Tickers,0)) -> 333 | W95: =INDEX(Pub_Comps_Range,MATCH(W$91,Pub_Comps_Params,0),MATCH($P95,Pub_Comps_Tickers,0)) -> 1.6958809 | X95: =INDEX(Pub_Comps_Range,MATCH(X$91,Pub_Comps_Params,0),MATCH($P95,Pub_Comps_Tickers,0)) -> 1.6514914 | Z95: =INDEX(Pub_Comps_Range,MATCH(Z$91,Pub_Comps_Params,0),MATCH($P95,Pub_Comps_Tickers,0)) -> 8.8412647 | AA95: =INDEX(Pub_Comps_Range,MATCH(AA$91,Pub_Comps_Params,0),MATCH($P95,Pub_Comps_Tickers,0)) -> 8.3368081
P96: CVAC | Q96: =INDEX(Pub_Comps_Range,MATCH(Q$91,Pub_Comps_Params,0),MATCH($P96,Pub_Comps_Tickers,0)) -> 77 | R96: =INDEX(Pub_Comps_Range,MATCH(R$91,Pub_Comps_Params,0),MATCH($P96,Pub_Comps_Tickers,0)) -> 99 | T96: =INDEX(Pub_Comps_Range,MATCH(T$91,Pub_Comps_Params,0),MATCH($P96,Pub_Comps_Tickers,0)) -> -129 | U96: =INDEX(Pub_Comps_Range,MATCH(U$91,Pub_Comps_Params,0),MATCH($P96,Pub_Comps_Tickers,0)) -> -130 | W96: =INDEX(Pub_Comps_Range,MATCH(W$91,Pub_Comps_Params,0),MATCH($P96,Pub_Comps_Tickers,0)) -> 9.7895338 | X96: =INDEX(Pub_Comps_Range,MATCH(X$91,Pub_Comps_Params,0),MATCH($P96,Pub_Comps_Tickers,0)) -> 7.6140819 | Z96: =INDEX(Pub_Comps_Range,MATCH(Z$91,Pub_Comps_Params,0),MATCH($P96,Pub_Comps_Tickers,0)) -> NM | AA96: =INDEX(Pub_Comps_Range,MATCH(AA$91,Pub_Comps_Params,0),MATCH($P96,Pub_Comps_Tickers,0)) -> NM
P97: CDNA | Q97: =INDEX(Pub_Comps_Range,MATCH(Q$91,Pub_Comps_Params,0),MATCH($P97,Pub_Comps_Tickers,0)) -> 369 | R97: =INDEX(Pub_Comps_Range,MATCH(R$91,Pub_Comps_Params,0),MATCH($P97,Pub_Comps_Tickers,0)) -> 414 | T97: =INDEX(Pub_Comps_Range,MATCH(T$91,Pub_Comps_Params,0),MATCH($P97,Pub_Comps_Tickers,0)) -> 30 | U97: =INDEX(Pub_Comps_Range,MATCH(U$91,Pub_Comps_Params,0),MATCH($P97,Pub_Comps_Tickers,0)) -> 46 | W97: =INDEX(Pub_Comps_Range,MATCH(W$91,Pub_Comps_Params,0),MATCH($P97,Pub_Comps_Tickers,0)) -> 2.0428025 | X97: =INDEX(Pub_Comps_Range,MATCH(X$91,Pub_Comps_Params,0),MATCH($P97,Pub_Comps_Tickers,0)) -> 1.8207587 | Z97: =INDEX(Pub_Comps_Range,MATCH(Z$91,Pub_Comps_Params,0),MATCH($P97,Pub_Comps_Tickers,0)) -> 25.12647 | AA97: =INDEX(Pub_Comps_Range,MATCH(AA$91,Pub_Comps_Params,0),MATCH($P97,Pub_Comps_Tickers,0)) -> 16.386828
P98: BFLY | Q98: =INDEX(Pub_Comps_Range,MATCH(Q$91,Pub_Comps_Params,0),MATCH($P98,Pub_Comps_Tickers,0)) -> 63.443 | R98: =INDEX(Pub_Comps_Range,MATCH(R$91,Pub_Comps_Params,0),MATCH($P98,Pub_Comps_Tickers,0)) -> 56.95 | T98: =INDEX(Pub_Comps_Range,MATCH(T$91,Pub_Comps_Params,0),MATCH($P98,Pub_Comps_Tickers,0)) -> -46.163568 | U98: =INDEX(Pub_Comps_Range,MATCH(U$91,Pub_Comps_Params,0),MATCH($P98,Pub_Comps_Tickers,0)) -> -3.7799891 | W98: =INDEX(Pub_Comps_Range,MATCH(W$91,Pub_Comps_Params,0),MATCH($P98,Pub_Comps_Tickers,0)) -> 9.5966092 | X98: =INDEX(Pub_Comps_Range,MATCH(X$91,Pub_Comps_Params,0),MATCH($P98,Pub_Comps_Tickers,0)) -> 10.690741 | Z98: =INDEX(Pub_Comps_Range,MATCH(Z$91,Pub_Comps_Params,0),MATCH($P98,Pub_Comps_Tickers,0)) -> NM | AA98: =INDEX(Pub_Comps_Range,MATCH(AA$91,Pub_Comps_Params,0),MATCH($P98,Pub_Comps_Tickers,0)) -> NM
P100: Data for Graphs (Sorted by revenue growth in ascending order):
Q101: Revenue Growth: | T101: EBITDA Growth: | W101: Year 2 Rev. Multiple: | Z101: Year 2 EBITDA Multiple:
Q102: =PubComps_Data!C85 -> Year 1 Projected Revenue Growth: | R102: Helper | T102: =PubComps_Data!C86 -> Year 1 Projected EBITDA Growth: | U102: Helper | W102: =PubComps_Data!C102 -> 2026-12-31 P / E: | X102: Helper | Z102: =PubComps_Data!C101 -> 2026-12-31 EV / EBITDA: | AA102: Helper
P103: GEHC | Q103: =INDEX(Pub_Comps_Range,MATCH(Q$102,Pub_Comps_Params,0),MATCH($P103,Pub_Comps_Tickers,0)) -> 0.044081831 | R103: =IF($P103=Ticker,Q103,NA()) -> #N/A | T103: =INDEX(Pub_Comps_Range,MATCH(T$102,Pub_Comps_Params,0),MATCH($P103,Pub_Comps_Tickers,0)) -> 0.073364358 | U103: =IF($P103=Ticker,T103,NA()) -> #N/A | W103: =INDEX(Pub_Comps_Range,MATCH(W$102,Pub_Comps_Params,0),MATCH($P103,Pub_Comps_Tickers,0)) -> 18.130894 | X103: =IF($P103=Ticker,W103,NA()) -> #N/A | Z103: =INDEX(Pub_Comps_Range,MATCH(Z$102,Pub_Comps_Params,0),MATCH($P103,Pub_Comps_Tickers,0)) -> 11.70442 | AA103: =IF($P103=Ticker,Z103,NA()) -> #N/A
P104: MASI | Q104: =INDEX(Pub_Comps_Range,MATCH(Q$102,Pub_Comps_Params,0),MATCH($P104,Pub_Comps_Tickers,0)) -> 0.077580539 | R104: =IF($P104=Ticker,Q104,NA()) -> #N/A | T104: =INDEX(Pub_Comps_Range,MATCH(T$102,Pub_Comps_Params,0),MATCH($P104,Pub_Comps_Tickers,0)) -> 0.094567404 | U104: =IF($P104=Ticker,T104,NA()) -> #N/A | W104: =INDEX(Pub_Comps_Range,MATCH(W$102,Pub_Comps_Params,0),MATCH($P104,Pub_Comps_Tickers,0)) -> 29.137962 | X104: =IF($P104=Ticker,W104,NA()) -> #N/A | Z104: =INDEX(Pub_Comps_Range,MATCH(Z$102,Pub_Comps_Params,0),MATCH($P104,Pub_Comps_Tickers,0)) -> 15.099559 | AA104: =IF($P104=Ticker,Z104,NA()) -> #N/A
P105: INMD | Q105: =INDEX(Pub_Comps_Range,MATCH(Q$102,Pub_Comps_Params,0),MATCH($P105,Pub_Comps_Tickers,0)) -> 0.04076087 | R105: =IF($P105=Ticker,Q105,NA()) -> #N/A | T105: =INDEX(Pub_Comps_Range,MATCH(T$102,Pub_Comps_Params,0),MATCH($P105,Pub_Comps_Tickers,0)) -> 0.074468085 | U105: =IF($P105=Ticker,T105,NA()) -> #N/A | W105: =INDEX(Pub_Comps_Range,MATCH(W$102,Pub_Comps_Params,0),MATCH($P105,Pub_Comps_Tickers,0)) -> 9.0818269 | X105: =IF($P105=Ticker,W105,NA()) -> #N/A | Z105: =INDEX(Pub_Comps_Range,MATCH(Z$102,Pub_Comps_Params,0),MATCH($P105,Pub_Comps_Tickers,0)) -> 4.3555446 | AA105: =IF($P105=Ticker,Z105,NA()) -> #N/A
P106: IART | Q106: =INDEX(Pub_Comps_Range,MATCH(Q$102,Pub_Comps_Params,0),MATCH($P106,Pub_Comps_Tickers,0)) -> 0.026878436 | R106: =IF($P106=Ticker,Q106,NA()) -> #N/A | T106: =INDEX(Pub_Comps_Range,MATCH(T$102,Pub_Comps_Params,0),MATCH($P106,Pub_Comps_Tickers,0)) -> 0.060509554 | U106: =IF($P106=Ticker,T106,NA()) -> #N/A | W106: =INDEX(Pub_Comps_Range,MATCH(W$102,Pub_Comps_Params,0),MATCH($P106,Pub_Comps_Tickers,0)) -> 5.7257299 | X106: =IF($P106=Ticker,W106,NA()) -> #N/A | Z106: =INDEX(Pub_Comps_Range,MATCH(Z$102,Pub_Comps_Params,0),MATCH($P106,Pub_Comps_Tickers,0)) -> 8.3368081 | AA106: =IF($P106=Ticker,Z106,NA()) -> #N/A
P107: CVAC | Q107: =INDEX(Pub_Comps_Range,MATCH(Q$102,Pub_Comps_Params,0),MATCH($P107,Pub_Comps_Tickers,0)) -> 0.28571429 | R107: =IF($P107=Ticker,Q107,NA()) -> #N/A | T107: =INDEX(Pub_Comps_Range,MATCH(T$102,Pub_Comps_Params,0),MATCH($P107,Pub_Comps_Tickers,0)) -> 0.007751938 | U107: =IF($P107=Ticker,T107,NA()) -> #N/A | W107: =INDEX(Pub_Comps_Range,MATCH(W$102,Pub_Comps_Params,0),MATCH($P107,Pub_Comps_Tickers,0)) -> NM | X107: =IF($P107=Ticker,W107,NA()) -> #N/A | Z107: =INDEX(Pub_Comps_Range,MATCH(Z$102,Pub_Comps_Params,0),MATCH($P107,Pub_Comps_Tickers,0)) -> NM | AA107: =IF($P107=Ticker,Z107,NA()) -> #N/A
P108: CDNA | Q108: =INDEX(Pub_Comps_Range,MATCH(Q$102,Pub_Comps_Params,0),MATCH($P108,Pub_Comps_Tickers,0)) -> 0.12195122 | R108: =IF($P108=Ticker,Q108,NA()) -> #N/A | T108: =INDEX(Pub_Comps_Range,MATCH(T$102,Pub_Comps_Params,0),MATCH($P108,Pub_Comps_Tickers,0)) -> 0.53333333 | U108: =IF($P108=Ticker,T108,NA()) -> #N/A | W108: =INDEX(Pub_Comps_Range,MATCH(W$102,Pub_Comps_Params,0),MATCH($P108,Pub_Comps_Tickers,0)) -> NM | X108: =IF($P108=Ticker,W108,NA()) -> #N/A | Z108: =INDEX(Pub_Comps_Range,MATCH(Z$102,Pub_Comps_Params,0),MATCH($P108,Pub_Comps_Tickers,0)) -> 16.386828 | AA108: =IF($P108=Ticker,Z108,NA()) -> #N/A
P109: BFLY | Q109: =INDEX(Pub_Comps_Range,MATCH(Q$102,Pub_Comps_Params,0),MATCH($P109,Pub_Comps_Tickers,0)) -> -0.10234384 | R109: =IF($P109=Ticker,Q109,NA()) -> -0.10234384 | T109: =INDEX(Pub_Comps_Range,MATCH(T$102,Pub_Comps_Params,0),MATCH($P109,Pub_Comps_Tickers,0)) -> -0.91811748 | U109: =IF($P109=Ticker,T109,NA()) -> -0.91811748 | W109: =INDEX(Pub_Comps_Range,MATCH(W$102,Pub_Comps_Params,0),MATCH($P109,Pub_Comps_Tickers,0)) -> NM | X109: =IF($P109=Ticker,W109,NA()) -> NM | Z109: =INDEX(Pub_Comps_Range,MATCH(Z$102,Pub_Comps_Params,0),MATCH($P109,Pub_Comps_Tickers,0)) -> NM | AA109: =IF($P109=Ticker,Z109,NA()) -> NM
P111: =Company_Name&"Price - Volume Chart" -> Butterfly Network, inc.Price - Volume Chart
P113: Date | Q113: Close | R113: Volume
P114: 45966 | Q114: 2.51 | R114: 5962215
P115: 45965 | Q115: 2.62 | R115: 9139300
P116: 45964 | Q116: 2.91 | R116: 16518800
P117: 45961 | Q117: 2.69 | R117: 20976600
P118: 45960 | Q118: 2.04 | R118: 3732000
P119: 45959 | Q119: 2.15 | R119: 3463200
P120: 45958 | Q120: 2.21 | R120: 3234000
P121: 45957 | Q121: 2.2 | R121: 3299600
P122: 45954 | Q122: 2.23 | R122: 3323900
P123: 45953 | Q123: 2.22 | R123: 2944000
P124: 45952 | Q124: 2.13 | R124: 5017200
P125: 45951 | Q125: 2.25 | R125: 3006500
... P363: 45602 | Q363: 2.57 | R363: 7348000

Sheet Q3
B2: =Company_Name&" - Q4 Financial Results" -> Butterfly Network, inc. - Q4 Financial Results
B3: ($ in Thousands Except Per Share and Per Unit Data)
B6: Reported Income Statement and Cash Flow Statement Figures from Q1: | E6: Q1-25 | F6: Q2-25 | G6: Q3-25 | H6: Q4-25
C8: Product revenue | E8: 14164 | F8: 16621 | G8: 14556 | H8: 18102
C9: Software and other services revenue | E9: 7061 | F9: 6762 | G9: 6933 | H9: 13412
C10: Embedded Revenue | E10: 0 | F10: 0 | G10: 0 | H10: 6800
C11: Revenue: | E11: 21225 | F11: 23383 | G11: 21489 | H11: 31514
C12: Annual Revenue Growth Rate: | F12: =F11/E11-1 -> 0.10167256 | G12: =G11/F11-1 -> -0.080999016 | H12: =H11/G11-1 -> 0.46651775
C14: Normalized Gross Profit | E14: 13380 | F14: 14891 | G14: 13839 | H14: 21221
C15: % Margin | E15: =E14/E11 -> 0.63038869 | F15: =F14/F11 -> 0.63683018 | G15: =G14/G11 -> 0.64400391 | H15: =H14/H11 -> 0.67338326
C17: Operating Income (EBIT): | E17: -18468 | F17: -16100 | G17: -35134 | H17: -16711
C18: % Quarterly Operating Margin | F18: =+F17/F11 -> -0.68853441 | G18: =+G17/G11 -> -1.634976 | H18: =+H17/H11 -> -0.53027226
C20: Taxes, Excluding Effect of Interest: | E20: 7 | F20: 20 | G20: 16 | H20: 66
C22: Net Operating Profit After Tax (NOPAT): | E22: =+E17+E20 -> -18461 | F22: =+F17+F20 -> -16080 | G22: =+G17+G20 -> -35118 | H22: =+H17+H20 -> -16645
C24: Adjustments for Non-Cash Charges:
C25: Depreciation & Amortization: | E25: 2360 | F25: 2082 | G25: 1885 | H25: 1754
C26: Deferred Income Taxes: | E26: 0 | F26: 0 | G26: 0 | H26: 0
C27: Other Operating Activities: | E27: 5912 | F27: 5741 | G27: 22766 | H27: 6629
C28: Total Adjustments for Non-Cash Charges: | E28: =SUM(E25:E27) -> 8272 | F28: =SUM(F25:F27) -> 7823 | G28: =SUM(G25:G27) -> 24651 | H28: =SUM(H25:H27) -> 8383
C30: Net Change in Working Capital:
C31: Accounts Receivable: | E31: 857 | F31: -4766 | G31: -63 | H31: -2781
C32: Inventories: | E32: 1423 | F32: 393 | G32: -1190 | H32: 799
C33: Accounts Payable: | E33: -1970 | F33: 1043 | G33: -16 | H33: 2138
C34: Other Liabilities: | E34: -6292 | F34: 2174 | G34: 7702 | H34: 15784
C35: Total Net Change in Working Capital: | E35: =SUM(E31:E34) -> -5982 | F35: =SUM(F31:F34) -> -1156 | G35: =SUM(G31:G34) -> 6433 | H35: =SUM(H31:H34) -> 15940
C37: Capital Expenditures and Acquisitions: | E37: -353 | F37: -896 | G37: -1016 | H37: -1083
C39: Q3 Unlevered Free Cash Flow: | E39: =SUM(E22,E28,E35,E37) -> -16524 | F39: =SUM(F22,F28,F35,F37) -> -10309 | G39: =SUM(G22,G28,G35,G37) -> -5050 | H39: =SUM(H22,H28,H35,H37) -> 6595

Sheet Model
H4: Historical | N4: Projected:
B5: =Company_Name -> Butterfly Network, inc. | E5: Units: | G5: 44926 | H5: =EOMONTH(G5,12) -> 45291 | I5: =EOMONTH(H5,12) -> 45657 | J5: =EOMONTH(I5,12) -> 46022 | K5: =EOMONTH(J5,12) -> 46387 | L5: =EOMONTH(K5,12) -> 46752 | M5: =EOMONTH(L5,12) -> 47118 | N5: =EOMONTH(M5,12) -> 47483 | O5: =EOMONTH(N5,12) -> 47848
C7: Company Name: | E7: Name | G7: Butterfly Network, inc. | K7: Last Fiscal Year: | N7: 45657
C8: Ticker: | E8: Name | G8: BFLY | K8: Next Fiscal Year: | N8: =EOMONTH(N7,12) -> 46022
C9: Current Share Price: | E9: $ / Share | G9: 3.06 | K9: Most Recent Quarter End Date: | N9: 45608
C10: Diluted Shares Outstanding: | E10: M Shares | G10: 227.39 | K10: Valuation Date: | N10: 45966
C12: Effective Tax Rate: | E12: % | G12: 0.12
C13: Discount Rate (WACC): | E13: % | G13: =Discount_Rate -> 0.10883792 | K13: LTM Period: | N13: 45930
K14: Forward Year 1: | N14: =EOMONTH(N7,12) -> 46022
C15: Conversion Units: | E15: # | G15: 1000 | K15: Forward Year 2: | N15: =EOMONTH(N14,12) -> 46387
K16: Forward Year 3: | N16: =EOMONTH(N15,12) -> 46752
H18: Historical | N18: Projected:
B19: =Company_Name&" - Model Drivers and Assumptions" -> Butterfly Network, inc. - Model Drivers and Assumptions | E19: Units: | G19: =G5 -> 44926 | H19: =H5 -> 45291 | I19: =I5 -> 45657 | J19: =J5 -> 46022 | K19: =K5 -> 46387 | L19: =L5 -> 46752 | M19: =M5 -> 47118 | N19: =N5 -> 47483 | O19: =O5 -> 47848
C20: Income Statement
C22: Cost of product revenue % Revenue | E22: % | G22: =G74/G68 -> 0.53327497 | H22: =(H74-21000)/H68 -> 0.49093316 | I22: =I74/I68 -> 0.4498155 | J22: 0.4 | K22: 0.4 | L22: 0.4 | M22: 0.4 | N22: 0.4 | O22: 0.4
C23: Cost of software and services revenue % Revenue | E23: % | G23: =G75/G69 -> 0.3081247 | H23: =H75/H69 -> 0.32435045 | I23: =I75/I69 -> 0.31752585 | J23: 0.3 | K23: 0.3 | L23: 0.3 | M23: 0.3 | N23: 0.3 | O23: 0.3
C25: Research and development | E25: % | G25: =G81/(SUM(G$68:G$69)) -> 1.199673 | H25: =H81/(SUM(H$68:H$69)) -> 0.84394537 | I25: =I81/(SUM(I$68:I$69)) -> 0.46066101 | J25: 0.32 | K25: 0.25 | L25: =K25-3% -> 0.22 | M25: =L25-3% -> 0.19 | N25: =M25-3% -> 0.16 | O25: =N25-3% -> 0.13
C26: Sales and marketing | E26: % | G26: =G82/(SUM(G$68:G$69)) -> 0.8106554 | H26: =H82/(SUM(H$68:H$69)) -> 0.59291351 | I26: =I82/(SUM(I$68:I$69)) -> 0.50656868 | J26: 0.34 | K26: 0.28 | L26: 0.22 | M26: 0.2 | N26: 0.15 | O26: 0.15
C27: General and administrative | E27: % | G27: =G83/(SUM(G$68:G$69)) -> 1.0573103 | H27: =H83/(SUM(H$68:H$69)) -> 0.75285281 | I27: =I83/(SUM(I$68:I$69)) -> 0.48515648 | J27: 0.31 | K27: 0.25 | L27: 0.2 | M27: 0.15 | N27: 0.14 | O27: 0.14
C28: Other operating expenses | E28: % | G28: =G84/(SUM(G$68:G$69)) -> 0.10009538 | H28: =H84/(SUM(H$68:H$69)) -> 0.27562974 | I28: =I84/(SUM(I$68:I$69)) -> 0.049539339 | J28: 0.04 | K28: 0.02 | L28: 0.01 | M28: 0.01 | N28: 0.01 | O28: 0.01
C30: Interest income | E30: % | I30: =I89/H108 -> 0.037340911 | J30: =I30 -> 0.037340911 | K30: =J30 -> 0.037340911 | L30: =K30 -> 0.037340911 | M30: =L30 -> 0.037340911 | N30: =M30 -> 0.037340911 | O30: =N30 -> 0.037340911
C32: Beginning Balance | E32: $T | G32: 0 | H32: =G35 -> 461681 | I32: =H35 -> 595299 | J32: =I35 -> 667823 | K32: =J35 -> 717286.49 | L32: =K35 -> 725788.46 | M32: =L35 -> 717351.76 | N32: =M35 -> 685555.13 | O32: =N35 -> 631339.62
C33: (+) NOLs Created | E33: $T | G33: 461681 | H33: =IF(H94<0,H94*-1,0) -> 133618 | I33: =IF(I94<0,I94*-1,0) -> 72524 | J33: =IF(J94<0,J94*-1,0) -> 49463.491 | K33: =IF(K94<0,K94*-1,0) -> 8501.9708 | L33: =IF(L94<0,L94*-1,0) -> 0 | M33: =IF(M94<0,M94*-1,0) -> 0 | N33: =IF(N94<0,N94*-1,0) -> 0 | O33: =IF(O94<0,O94*-1,0) -> 0
C34: (-) NOLs Used | E34: $T | G34: 0 | H34: =IF(H94>0,H94*-1,0) -> 0 | I34: 0 | J34: =-MIN(+J32+J33,MAX(J94*J39,0)) -> 0 | K34: =-MIN(+K32+K33,MAX(K94*K39,0)) -> 0 | L34: =-MIN(+L32+L33,MAX(L94*L39,0)) -> -8436.7053 | M34: =-MIN(+M32+M33,MAX(M94*M39,0)) -> -31796.624 | N34: =-MIN(+N32+N33,MAX(N94*N39,0)) -> -54215.512 | O34: =-MIN(+O32+O33,MAX(O94*O39,0)) -> -77532.617
C35: Ending Balance | E35: $T | G35: =SUM(G32:G34) -> 461681 | H35: =SUM(H32:H34) -> 595299 | I35: =SUM(I32:I34) -> 667823 | J35: =SUM(J32:J34) -> 717286.49 | K35: =SUM(K32:K34) -> 725788.46 | L35: =SUM(L32:L34) -> 717351.76 | M35: =SUM(M32:M34) -> 685555.13 | N35: =SUM(N32:N34) -> 631339.62 | O35: =SUM(O32:O34) -> 553807
C37: Taxable Income After NOL | E37: $T | G37: 0 | H37: 0 | I37: 0 | J37: =SUM(J94,J34) -> -49463.491 | K37: =SUM(K94,K34) -> -8501.9708 | L37: =SUM(L94,L34) -> 2109.1763 | M37: =SUM(M94,M34) -> 7949.1559 | N37: =SUM(N94,N34) -> 13553.878 | O37: =SUM(O94,O34) -> 19383.154
C38: Cash Taxes Payable | E38: $T | G38: 0 | H38: 0 | I38: 0 | J38: =IF(J37<0,0,J37*Tax_Rate) -> 0 | K38: =IF(K37<0,0,K37*Tax_Rate) -> 0 | L38: =IF(L37<0,0,L37*Tax_Rate) -> 253.10116 | M38: =IF(M37<0,0,M37*Tax_Rate) -> 953.89871 | N38: =IF(N37<0,0,N37*Tax_Rate) -> 1626.4654 | O38: =IF(O37<0,0,O37*Tax_Rate) -> 2325.9785
C39: NOL Utilization Limit (% of EBT) | E39: $T | G39: 1 | H39: 1 | I39: 1 | J39: 0.8 | K39: 0.8 | L39: 0.8 | M39: 0.8 | N39: 0.8 | O39: 0.8
C41: Balance Sheet
C43: Days Receivables Outstanding | E43: % | H43: =H109*(H105-EOMONTH(H105,-12))/H72 -> 74.318209 | I43: =I109*(I105-EOMONTH(I105,-12))/I72 -> 92.744443 | J43: 85 | K43: 80 | L43: 75 | M43: 70 | N43: 70 | O43: 70
C44: Days Inventory Outstanding | E44: % | H44: =H110*(H105-EOMONTH(H105,-12))/H72 -> 404.44659 | I44: =I110*(I105-EOMONTH(I105,-12))/I72 -> 315.74503 | J44: 240 | K44: 210 | L44: 160 | M44: 140 | N44: 140 | O44: 140
C45: Current portion of vendor advances % COGS | E45: % | H45: =-H76/H72 -> 0.74421851 | I45: =-I76/I72 -> 0.40490641 | J45: 0.06 | K45: 0.05 | L45: 0.04 | M45: 0.03 | N45: 0.03 | O45: 0.03
C46: Prepaid expenses and other current assets % OpEx | E46: % | H46: =H111/-H85 -> 0.046600519 | I46: =I111/-I85 -> 0.054437611 | J46: 0.05 | K46: 0.04 | L46: 0.04 | M46: 0.03 | N46: 0.03 | O46: 0.03
C48: Non-current vendor advances | E48: % | H48: =H115/-H76 -> 0.36887285 | I48: =I115/-I76 -> 0.61968397 | J48: 0.2 | K48: 0.18 | L48: 0.16 | M48: 0.15 | N48: 0.14 | O48: 0.14
C49: Other non-current assets % Revenue | E49: % | H49: =H117/H72 -> 0.097450683 | I49: =I117/I72 -> 0.070195964 | J49: 0.06 | K49: 0.06 | L49: 0.05 | M49: 0.05 | N49: 0.04 | O49: 0.04
C51: Days Payables Outstanding | E51: % | H51: =H122*(H105-EOMONTH(H105,-12))/H72 -> 28.191958 | I51: =I122*(I105-EOMONTH(I105,-12))/I72 -> 18.956566 | J51: =AVERAGE(H51:I51) -> 23.574262 | K51: 20 | L51: 18 | M51: 16 | N51: 16 | O51: 16
C52: Deferred revenue, current % Revenue | E52: % | H52: =H127/H72 -> 0.34930197 | I52: =I127/I72 -> 0.28582919 | J52: 0.19 | K52: 0.17 | L52: 0.15 | M52: 0.13 | N52: 0.11 | O52: 0.11
C53: Accrued expenses and other current liabilities % OpEx | E53: % | H53: =H124/-H85 -> 0.14418401 | I53: =I124/-I85 -> 0.22472047 | J53: 0.2 | K53: 0.18 | L53: 0.17 | M53: 0.16 | N53: 0.15 | O53: 0.15
C55: Deferred revenue, non-current | E55: % | H55: =H127/H72 -> 0.34930197 | I55: =I127/I72 -> 0.28582919 | J55: 0.08 | K55: 0.07 | L55: 0.07 | M55: 0.06 | N55: 0.06 | O55: 0.06
C56: Operating lease liabilities | E56: %
C57: Other non-current liabilities | E57: %
C59: Cash Flow Statement
C61: Stock-based compensation expense | E61: % | G61: =G149/G72 -> 0.57952037 | H61: =H149/H72 -> 0.41699545 | I61: =I149/I72 -> 0.25631276 | J61: 0.23 | K61: =J61-2% -> 0.21 | L61: =K61-2% -> 0.19 | M61: =L61-2% -> 0.17 | N61: =M61-2% -> 0.15 | O61: =N61-2% -> 0.13
H65: Historical | N65: Projected:
B66: =Company_Name&" - Income Statement" -> Butterfly Network, inc. - Income Statement | E66: Units: | G66: =G19 -> 44926 | H66: =H19 -> 45291 | I66: =I19 -> 45657 | J66: =J19 -> 46022 | K66: =K19 -> 46387 | L66: =L19 -> 46752 | M66: =M19 -> 47118 | N66: =N19 -> 47483 | O66: =O19 -> 47848
C68: Product revenue | E68: $T | G68: 50263 | H68: 40036 | I68: 54200 | J68: =Drivers!J12 -> 63443 | K68: =Drivers!K12 -> 56950 | L68: =Drivers!L12 -> 77000 | M68: =Drivers!M12 -> 84000 | N68: =Drivers!N12 -> 105000 | O68: =Drivers!O12 -> 120000
C69: Software and other services revenue | E69: $T | G69: 23127 | H69: 25864 | I69: 27856 | J69: =Drivers!J21 -> 27400 | K69: =Drivers!K21 -> 30000 | L69: =Drivers!L21 -> 36000 | M69: =Drivers!M21 -> 51000 | N69: =Drivers!N21 -> 63000 | O69: =Drivers!O21 -> 72000
C70: Octiv Revenue | E70: $T | G70: =Drivers!G23 -> 0 | H70: =Drivers!H23 -> 0 | I70: =Drivers!I23 -> 0 | J70: =Drivers!J23 -> 6800 | K70: =Drivers!K23 -> 25000 | L70: =Drivers!L23 -> 25000 | M70: =Drivers!M23 -> 40000 | N70: =Drivers!N23 -> 40000 | O70: =Drivers!O23 -> 60000
C71: Home-care revenue | E71: $T | G71: =Drivers!G24 -> 0 | H71: =Drivers!H24 -> 0 | I71: =Drivers!I24 -> 0 | J71: =Drivers!J28 -> 0 | K71: =Drivers!K28 -> 1000 | L71: =Drivers!L28 -> 5000 | M71: =Drivers!M28 -> 15000 | N71: =Drivers!N28 -> 20000 | O71: =Drivers!O28 -> 25000
C72: Total revenue | E72: $T | G72: =SUM(G68:G71) -> 73390 | H72: =SUM(H68:H71) -> 65900 | I72: =SUM(I68:I71) -> 82056 | J72: =SUM(J68:J71) -> 97643 | K72: =SUM(K68:K71) -> 112950 | L72: =SUM(L68:L71) -> 143000 | M72: =SUM(M68:M71) -> 190000 | N72: =SUM(N68:N71) -> 228000 | O72: =SUM(O68:O71) -> 277000
C74: Cost of product revenue | E74: $T | G74: 26804 | H74: 40655 | I74: 24380 | J74: 44065 | K74: =K22*K68 -> 22780 | L74: =L22*L68 -> 30800 | M74: =M22*M68 -> 33600 | N74: =N22*N68 -> 42000 | O74: =O22*O68 -> 48000
C75: Cost of software and services revenue | E75: $T | G75: 7126 | H75: 8389 | I75: 8845 | J75: 7811 | K75: =K23*K69 -> 9000 | L75: =L23*L69 -> 10800 | M75: =M23*M69 -> 15300 | N75: =N23*N69 -> 18900 | O75: =O23*O69 -> 21600
C76: Total cost of revenue | E76: $T | G76: =-SUM(G74:G75) -> -33930 | H76: =-SUM(H74:H75) -> -49044 | I76: =-SUM(I74:I75) -> -33225 | J76: =-SUM(J74:J75) -> -51876 | K76: =-SUM(K74:K75) -> -31780 | L76: =-SUM(L74:L75) -> -41600 | M76: =-SUM(M74:M75) -> -48900 | N76: =-SUM(N74:N75) -> -60900 | O76: =-SUM(O74:O75) -> -69600
C78: Gross profit | E78: $T | G78: =SUM(G72,G76) -> 39460 | H78: =SUM(H72,H76) -> 16856 | I78: =SUM(I72,I76) -> 48831 | J78: =SUM(J72,J76) -> 45767 | K78: =SUM(K72,K76) -> 81170 | L78: =SUM(L72,L76) -> 101400 | M78: =SUM(M72,M76) -> 141100 | N78: =SUM(N72,N76) -> 167100 | O78: =SUM(O72,O76) -> 207400
C79: % Margin | E79: % | G79: =G78/G72 -> 0.53767543 | H79: =H78/H72 -> 0.25578149 | I79: =I78/I72 -> 0.59509359 | J79: =J78/J72 -> 0.46871768 | K79: =K78/K72 -> 0.71863656 | L79: =L78/L72 -> 0.70909091 | M79: =M78/M72 -> 0.74263158 | N79: =N78/N72 -> 0.73289474 | O79: =O78/O72 -> 0.74873646
C81: Research and development | E81: $T | G81: 88044 | H81: 55616 | I81: 37800 | J81: =J25*J$72 -> 31245.76 | K81: =K25*K$72 -> 28237.5 | L81: =L25*L$72 -> 31460 | M81: =M25*M$72 -> 36100 | N81: =N25*N$72 -> 36480 | O81: =O25*O$72 -> 36010
C82: Sales and marketing | E82: $T | G82: 59494 | H82: 39073 | I82: 41567 | J82: =J26*J$72 -> 33198.62 | K82: =K26*K$72 -> 31626 | L82: =L26*L$72 -> 31460 | M82: =M26*M$72 -> 38000 | N82: =N26*N$72 -> 34200 | O82: =O26*O$72 -> 41550
C83: General and administrative | E83: $T | G83: 77596 | H83: 49613 | I83: 39810 | J83: =J27*J$72 -> 30269.33 | K83: =K27*K$72 -> 28237.5 | L83: =L27*L$72 -> 28600 | M83: =M27*M$72 -> 28500 | N83: =N27*N$72 -> 31920 | O83: =O27*O$72 -> 38780
C84: Other operating expenses | E84: $T | G84: 7346 | H84: 18164 | I84: 4065 | J84: =J28*J$72 -> 3905.72 | K84: =K28*K$72 -> 2259 | L84: =L28*L$72 -> 1430 | M84: =M28*M$72 -> 1900 | N84: =N28*N$72 -> 2280 | O84: =O28*O$72 -> 2770
C85: Total operating expenses | E85: $T | G85: =-SUM(G81:G84) -> -232480 | H85: =-SUM(H81:H84) -> -162466 | I85: =-SUM(I81:I84) -> -123242 | J85: =-SUM(J81:J84) -> -98619.43 | K85: =-SUM(K81:K84) -> -90360 | L85: =-SUM(L81:L84) -> -92950 | M85: =-SUM(M81:M84) -> -104500 | N85: =-SUM(N81:N84) -> -104880 | O85: =-SUM(O81:O84) -> -119110
C87: EBIT | E87: $T | G87: =SUM(G78,G85) -> -193020 | H87: =SUM(H78,H85) -> -145610 | I87: =SUM(I78,I85) -> -74411 | J87: =SUM(J78,J85) -> -52852.43 | K87: =SUM(K78,K85) -> -9190 | L87: =SUM(L78,L85) -> 8450 | M87: =SUM(M78,M85) -> 36600 | N87: =SUM(N78,N85) -> 62220 | O87: =SUM(O78,O85) -> 88290
C89: Interest income | E89: $T | G89: 3384 | H89: 7450 | I89: 5020 | J89: =I108*J30 -> 3314.9393 | K89: =J108*K30 -> 2217.5292 | L89: =K108*L30 -> 2823.6316 | M89: =L108*M30 -> 4274.4046 | N89: =M108*N30 -> 6477.5775 | O89: =N108*O30 -> 9654.1779
C90: Interest expense | E90: $T | G90: -2 | H90: 0 | I90: -1261 | J90: -1261 | K90: -1261 | L90: -1261 | M90: -1261 | N90: -1261 | O90: -1261
C91: Change in fair value of warrant liabilities | E91: $T | G91: 20957 | H91: 4542 | I91: -1872 | J91: =AVERAGE(H91:I91) -> 1335 | K91: =AVERAGE(I91:J91) -> -268.5 | L91: =AVERAGE(J91:K91) -> 533.25 | M91: =AVERAGE(K91:L91) -> 132.375 | N91: =AVERAGE(L91:M91) -> 332.8125 | O91: =AVERAGE(M91:N91) -> 232.59375
C92: Other income | E92: $T | G92: =SUM(G89:G91) -> 24339 | H92: =SUM(H89:H91) -> 11992 | I92: =SUM(I89:I91) -> 1887 | J92: =SUM(J89:J91) -> 3388.9393 | K92: =SUM(K89:K91) -> 688.02921 | L92: =SUM(L89:L91) -> 2095.8816 | M92: =SUM(M89:M91) -> 3145.7796 | N92: =SUM(N89:N91) -> 5549.39 | O92: =SUM(O89:O91) -> 8625.7717
C94: Loss before income taxes | E94: $T | G94: =SUM(G87,G92) -> -168681 | H94: =SUM(H87,H92) -> -133618 | I94: =SUM(I87,I92) -> -72524 | J94: =SUM(J87,J92) -> -49463.491 | K94: =SUM(K87,K92) -> -8501.9708 | L94: =SUM(L87,L92) -> 10545.882 | M94: =SUM(M87,M92) -> 39745.78 | N94: =SUM(N87,N92) -> 67769.39 | O94: =SUM(O87,O92) -> 96915.772
C96: Provision (benefit) for income taxes | E96: $T | G96: -42 | H96: -82 | I96: 32 | J96: =J38 -> 0 | K96: =K38 -> 0 | L96: =L38 -> 253.10116 | M96: =M38 -> 953.89871 | N96: =N38 -> 1626.4654 | O96: =O38 -> 2325.9785
C97: Net loss and comprehensive loss | E97: $T | G97: =SUM(G94,G96) -> -168723 | H97: =SUM(H94,H96) -> -133700 | I97: =SUM(I94,I96) -> -72492 | J97: =SUM(J94,J96) -> -49463.491 | K97: =SUM(K94,K96) -> -8501.9708 | L97: =SUM(L94,L96) -> 10798.983 | M97: =SUM(M94,M96) -> 40699.678 | N97: =SUM(N94,N96) -> 69395.855 | O97: =SUM(O94,O96) -> 99241.75
C99: EBITDA | E99: $T | G99: =G87+G148 -> -187085 | H99: =H87+H148 -> -135036 | I99: =I87+I148 -> -64069 | J99: =J87+J148 -> -48217.507 | K99: =K87+K148 -> -4736.5183 | L99: =L87+L148 -> 12832.562 | M99: =M87+M148 -> 41016.306 | N99: =N87+N148 -> 66266.084 | O99: =O87+O148 -> 92029.651
C101: Net loss per share (basic and diluted) | E101: $ | G101: -0.84 | H101: -0.65 | I101: -0.34 | J101: =J97/Units/Diluted -> -0.21752711 | K101: =K97/Units/Diluted -> -0.037389379 | L101: =L97/Units/Diluted -> 0.047491019 | M101: =M97/Units/Diluted -> 0.17898623 | N101: =N97/Units/Diluted -> 0.30518429 | O101: =O97/Units/Diluted -> 0.4364385
C102: Weighted-average shares outstanding | E102: # | G102: 199848386 | H102: 205385544 | I102: 211682760 | J102: 211682760 | K102: 211682760 | L102: 211682760 | M102: 211682760 | N102: 211682760 | O102: 211682760
H104: Historical | N104: Projected: | O104: Projected:
B105: =Company_Name&" - Balance Sheet" -> Butterfly Network, inc. - Balance Sheet | E105: Units: | G105: =G66 -> 44926 | H105: =H66 -> 45291 | I105: =I66 -> 45657 | J105: =J66 -> 46022 | K105: =K66 -> 46387 | L105: =L66 -> 46752 | M105: =M66 -> 47118 | N105: =N66 -> 47483 | O105: =O66 -> 47848
C106: ASSETS
C108: Cash and cash equivalents | E108: $T | H108: 134437 | I108: 88775 | J108: =J185 -> 59386.051 | K108: =K185 -> 75617.641 | L108: =L185 -> 114469.75 | M108: =M185 -> 173471.33 | N108: =N185 -> 258541.58 | O108: =O185 -> 369989.53
C109: Accounts receivable, net | E109: $T | H109: 13418 | I109: 20793 | J109: =J43/(J$66-EOMONTH(J$66,-12))*J$72 -> 22738.781 | K109: =K43/(K$66-EOMONTH(K$66,-12))*K$72 -> 24756.164 | L109: =L43/(L$66-EOMONTH(L$66,-12))*L$72 -> 29383.562 | M109: =M43/(M$66-EOMONTH(M$66,-12))*M$72 -> 36338.798 | N109: =N43/(N$66-EOMONTH(N$66,-12))*N$72 -> 43726.027 | O109: =O43/(O$66-EOMONTH(O$66,-12))*O$72 -> 53123.288
C110: Inventories | E110: $T | H110: 73022 | I110: 70789 | J110: =J44/(J$66-EOMONTH(J$66,-12))*J$72 -> 64203.616 | K110: =K44/(K$66-EOMONTH(K$66,-12))*K$72 -> 64984.932 | L110: =L44/(L$66-EOMONTH(L$66,-12))*L$72 -> 62684.932 | M110: =M44/(M$66-EOMONTH(M$66,-12))*M$72 -> 72677.596 | N110: =N44/(N$66-EOMONTH(N$66,-12))*N$72 -> 87452.055 | O110: =O44/(O$66-EOMONTH(O$66,-12))*O$72 -> 106246.58
C111: Prepaid expenses and other current assets | E111: $T | H111: 7571 | I111: 6709 | J111: =J46*-J85 -> 4930.9715 | K111: =K46*-K85 -> 3614.4 | L111: =L46*-L85 -> 3718 | M111: =M46*-M85 -> 3135 | N111: =N46*-N85 -> 3146.4 | O111: =O46*-O85 -> 3573.3
C112: Total current assets | E112: $T | H112: =SUM(H108:H111) -> 228448 | I112: =SUM(I108:I111) -> 187066 | J112: =SUM(J108:J111) -> 151259.42 | K112: =SUM(K108:K111) -> 168973.14 | L112: =SUM(L108:L111) -> 210256.24 | M112: =SUM(M108:M111) -> 285622.73 | N112: =SUM(N108:N111) -> 392866.06 | O112: =SUM(O108:O111) -> 532932.69
C114: Property and equipment and Intangible Assets | E114: $T | H114: 35638 | I114: 28434 | J114: =Drivers!J43 -> 26264.563 | K114: =Drivers!K43 -> 24521.881 | L114: =Drivers!L43 -> 22927.819 | M114: =Drivers!M43 -> 21646.513 | N114: =Drivers!N43 -> 20746.828 | O114: =Drivers!O43 -> 20580.478
C115: vendor advances | E115: $T | H115: 18091 | I115: 20589 | J115: =-J76*J48 -> 10375.2 | K115: =-K76*K48 -> 5720.4 | L115: =-L76*L48 -> 6656 | M115: =-M76*M48 -> 7335 | N115: =-N76*N48 -> 8526 | O115: =-O76*O48 -> 9744
C116: Operating lease assets | E116: $T | H116: 15675 | I116: 14233 | J116: =I116*0.9 -> 12809.7 | K116: =J116*0.9 -> 11528.73 | L116: =K116*0.9 -> 10375.857 | M116: =L116*0.9 -> 9338.2713 | N116: =M116*0.9 -> 8404.4442 | O116: =N116*0.9 -> 7563.9998
C117: Other non-current assets | E117: $T | H117: 6422 | I117: 5760 | J117: =J49*J72 -> 5858.58 | K117: =K49*K72 -> 6777 | L117: =L49*L72 -> 7150 | M117: =M49*M72 -> 9500 | N117: =N49*N72 -> 9120 | O117: =O49*O72 -> 11080
C118: Total assets | E118: $T | H118: =SUM(H112,H114:H117) -> 304274 | I118: =SUM(I112,I114:I117) -> 256082 | J118: =SUM(J112,J114:J117) -> 206567.46 | K118: =SUM(K112,K114:K117) -> 217521.15 | L118: =SUM(L112,L114:L117) -> 257365.92 | M118: =SUM(M112,M114:M117) -> 333442.51 | N118: =SUM(N112,N114:N117) -> 439663.33 | O118: =SUM(O112,O114:O117) -> 581901.17
C120: LIABILITIES AND SHAREHOLDERS' EQUITY
C122: Accounts payable | E122: $T | H122: 5090 | I122: 4250 | J122: =J51/(J66-EOMONTH(J66,-12))*J72 -> 6306.4703 | K122: =K51/(K66-EOMONTH(K66,-12))*K72 -> 6189.0411 | L122: =L51/(L66-EOMONTH(L66,-12))*L72 -> 7052.0548 | M122: =M51/(M66-EOMONTH(M66,-12))*M72 -> 8306.0109 | N122: =N51/(N66-EOMONTH(N66,-12))*N72 -> 9994.5205 | O122: =O51/(O66-EOMONTH(O66,-12))*O72 -> 12142.466
C123: Accrued purchase commitments, current | E123: $T | H123: 131 | I123: 131 | J123: 131 | K123: 131 | L123: 131 | M123: 131 | N123: 131 | O123: 131
C124: Accrued expenses and other current liabilities | E124: $T | H124: 23425 | I124: 27695 | J124: =-J85*J53 -> 19723.886 | K124: =-K85*K53 -> 16264.8 | L124: =-L85*L53 -> 15801.5 | M124: =-M85*M53 -> 16720 | N124: =-N85*N53 -> 15732 | O124: =-O85*O53 -> 17866.5
C125: Total current liabilities | E125: $T | H125: =SUM(H122:H124) -> 28646 | I125: =SUM(I122:I124) -> 32076 | J125: =SUM(J122:J124) -> 26161.356 | K125: =SUM(K122:K124) -> 22584.841 | L125: =SUM(L122:L124) -> 22984.555 | M125: =SUM(M122:M124) -> 25157.011 | N125: =SUM(N122:N124) -> 25857.521 | O125: =SUM(O122:O124) -> 30139.966
C127: Deferred revenue, non-current | E127: $T | H127: 23019 | I127: 23454 | J127: =J72*J55 -> 7811.44 | K127: =K72*K55 -> 7906.5 | L127: =L72*L55 -> 10010 | M127: =M72*M55 -> 11400 | N127: =N72*N55 -> 13680 | O127: =O72*O55 -> 16620
C128: Warrant liabilities | E128: $T | H128: 826 | I128: 2685 | J128: 2685 | K128: 2685 | L128: 2685 | M128: 2685 | N128: 2685 | O128: 2685
C129: Operating lease liabilities | E129: $T | H129: 22835 | I129: 20398 | J129: =I129*0.95 -> 19378.1 | K129: =J129*0.95 -> 18409.195 | L129: =K129*0.95 -> 17488.735 | M129: =L129*0.95 -> 16614.298 | N129: =M129*0.95 -> 15783.584 | O129: =N129*0.95 -> 14994.404
C130: Other non-current liabilities | E130: $T | H130: 8895 | I130: 8637 | J130: 8637 | K130: 8637 | L130: 8637 | M130: 8637 | N130: 8637 | O130: 8637
C131: Total liabilities | E131: $T | H131: =SUM(H125,H127:H130) -> 84221 | I131: =SUM(I125,I127:I130) -> 87250 | J131: =SUM(J125,J127:J130) -> 64672.896 | K131: =SUM(K125,K127:K130) -> 60222.536 | L131: =SUM(L125,L127:L130) -> 61805.29 | M131: =SUM(M125,M127:M130) -> 64493.309 | N131: =SUM(N125,N127:N130) -> 66643.104 | O131: =SUM(O125,O127:O130) -> 73076.37
C133: Class A common stock | E133: $T | H133: 18 | I133: 19 | J133: 19 | K133: 19 | L133: 19 | M133: 19 | N133: 19 | O133: 19
C134: Class B common stock | E134: $T | H134: 3 | I134: 3 | J134: 3 | K134: 3 | L134: 3 | M134: 3 | N134: 3 | O134: 3
C135: Additional paid-in capital | E135: $T | H135: 949670 | I135: 970940 | J135: =I135+J149 -> 993397.89 | K135: =J135+K149 -> 1017117.4 | L135: =K135+L149 -> 1044287.4 | M135: =L135+M149 -> 1076587.4 | N135: =M135+N149 -> 1110787.4 | O135: =N135+O149 -> 1146797.4
C136: Accumulated deficit | E136: $T | H136: -729638 | I136: -802130 | J136: =I136+J147+J151+J171+J180 -> -851525.32 | K136: =J136+K147+K151+K171+K180 -> -859840.78 | L136: =K136+L147+L151+L171+L180 -> -848748.76 | M136: =L136+M147+M151+M171+M180 -> -807660.19 | N136: =M136+N147+N151+N171+N180 -> -737789.16 | O136: =N136+O147+O151+O171+O180 -> -637994.59
C137: Total stockholders’ equity | E137: $T | H137: =SUM(H133:H136) -> 220053 | I137: =SUM(I133:I136) -> 168832 | J137: =SUM(J133:J136) -> 141894.57 | K137: =SUM(K133:K136) -> 157298.61 | L137: =SUM(L133:L136) -> 195560.63 | M137: =SUM(M133:M136) -> 268949.2 | N137: =SUM(N133:N136) -> 373020.23 | O137: =SUM(O133:O136) -> 508824.8
C139: Total liabilities and stockholders’ equity | E139: $T | H139: =SUM(H131,H137) -> 304274 | I139: =SUM(I131,I137) -> 256082 | J139: =SUM(J131,J137) -> 206567.46 | K139: =SUM(K131,K137) -> 217521.15 | L139: =SUM(L131,L137) -> 257365.92 | M139: =SUM(M131,M137) -> 333442.51 | N139: =SUM(N131,N137) -> 439663.33 | O139: =SUM(O131,O137) -> 581901.17
...

Sheet Drivers
H2: Historical | N2: Projected:
B3: =Company_Name&" - Revenue Drivers" -> Butterfly Network, inc. - Revenue Drivers | E3: Units: | G3: 44926 | H3: =EOMONTH(G3,12) -> 45291 | I3: =EOMONTH(H3,12) -> 45657 | J3: =EOMONTH(I3,12) -> 46022 | K3: =EOMONTH(J3,12) -> 46387 | L3: =EOMONTH(K3,12) -> 46752 | M3: =EOMONTH(L3,12) -> 47118 | N3: =EOMONTH(M3,12) -> 47483 | O3: =EOMONTH(N3,12) -> 47848
C5: Product
C6: Hardware Units (Consolidated) | D6: # | G6: 21853.478 | H6: 17406.957 | I6: 16424.242 | J6: =J12/J11*Units -> 18938.209 | K6: =INDEX($J$7:$N$9,MATCH(Scenario,$C$7:$C$9,0),2) -> 17000 | L6: =INDEX($J$7:$N$9,MATCH(Scenario,$C$7:$C$9,0),3) -> 22000 | M6: =INDEX($J$7:$N$9,MATCH(Scenario,$C$7:$C$9,0),4) -> 24000 | N6: =INDEX($J$7:$N$9,MATCH(Scenario,$C$7:$C$9,0),5) -> 28000 | O6: =INDEX($J$7:$O$9,MATCH(Scenario,$C$7:$C$9,0),6) -> 32000
C7: Upside | D7: # | K7: 25000 | L7: 31000 | M7: 34000 | N7: 36500 | O7: 39000
C8: Base | D8: # | K8: 20000 | L8: 25000 | M8: 33000 | N8: 38000 | O8: 42000
C9: Downside | D9: # | K9: 17000 | L9: 22000 | M9: 24000 | N9: 28000 | O9: 32000
C10: % Growth | D10: % | H10: =H6/G6-1 -> -0.20346975 | I10: =I6/H6-1 -> -0.056455251 | J10: =J6/I6-1 -> 0.15306438 | K10: =K6/J6-1 -> -0.10234384 | L10: =L6/K6-1 -> 0.29411765 | M10: =M6/L6-1 -> 0.090909091 | N10: =N6/M6-1 -> 0.16666667 | O10: =O6/N6-1 -> 0.14285714
C11: Consolidated ASP | D11: $ | G11: 2300 | H11: 2300 | I11: 3300 | J11: 3350 | K11: 3350 | L11: 3500 | M11: 3500 | N11: 3750 | O11: 3750
C12: Product Revenue | D12: $T | G12: =G6*G11/Units -> 50263 | H12: =H6*H11/Units -> 40036 | I12: =I6*I11/Units -> 54200 | J12: 63443 | K12: =K6*K11/Units -> 56950 | L12: =L6*L11/Units -> 77000 | M12: =M6*M11/Units -> 84000 | N12: =N6*N11/Units -> 105000 | O12: =O6*O11/Units -> 120000
C14: Software
C15: Paying Subscribers | D15: # | G15: 70082 | H15: 80074 | I15: 90149 | J15: =J21/J20*Units -> 78285.714 | K15: =INDEX($J$16:$N$18,MATCH(Scenario,$C$16:$C$18,0),2) -> 80000 | L15: =INDEX($J$16:$N$18,MATCH(Scenario,$C$16:$C$18,0),3) -> 90000 | M15: =INDEX($J$16:$N$18,MATCH(Scenario,$C$16:$C$18,0),4) -> 120000 | N15: =INDEX($J$16:$N$18,MATCH(Scenario,$C$16:$C$18,0),5) -> 140000 | O15: =INDEX($J$16:$O$18,MATCH(Scenario,$C$16:$C$18,0),6) -> 160000
C16: Upside | D16: # | K16: 90000 | L16: 120000 | M16: 150000 | N16: 180000 | O16: 210000
C17: Base | D17: # | K17: 82000 | L17: 100000 | M17: 130000 | N17: 160000 | O17: 190000
C18: Downside | D18: # | K18: 80000 | L18: 90000 | M18: 120000 | N18: 140000 | O18: 160000
C19: % Growth | D19: % | H19: =H15/G15-1 -> 0.14257584 | I19: =I15/H15-1 -> 0.12582112 | J19: =J15/I15-1 -> -0.13159642 | K19: =K15/J15-1 -> 0.02189781 | L19: =L15/K15-1 -> 0.125 | M19: =M15/L15-1 -> 0.33333333 | N19: =N15/M15-1 -> 0.16666667 | O19: =O15/N15-1 -> 0.14285714
C20: ARPU ($ per year) | D20: $ | G20: 330 | H20: 323 | I20: 309 | J20: 350 | K20: 375 | L20: 400 | M20: 425 | N20: 450 | O20: 450
C21: Software Revenue | D21: $T | G21: =G15*G20/Units -> 23127.06 | H21: =H15*H20/Units -> 25863.902 | I21: =I15*I20/Units -> 27856.041 | J21: 27400 | K21: =K15*K20/Units -> 30000 | L21: =L15*L20/Units -> 36000 | M21: =M15*M20/Units -> 51000 | N21: =N15*N20/Units -> 63000 | O21: =O15*O20/Units -> 72000
C23: Butterfly Embedded | D23: $T | G23: 0 | H23: 0 | I23: 0 | J23: 6800 | K23: =INDEX($J$24:$N$26,MATCH(Scenario,$C$24:$C$26,0),2) -> 25000 | L23: =INDEX($J$24:$N$26,MATCH(Scenario,$C$24:$C$26,0),3) -> 25000 | M23: =INDEX($J$24:$N$26,MATCH(Scenario,$C$24:$C$26,0),4) -> 40000 | N23: =INDEX($J$24:$N$26,MATCH(Scenario,$C$24:$C$26,0),5) -> 40000 | O23: =INDEX($J$24:$O$26,MATCH(Scenario,$C$24:$C$26,0),6) -> 60000
C24: Upside | D24: $T | K24: 45000 | L24: 85000 | M24: 140000 | N24: 200000 | O24: 260000
C25: Base | D25: $T | K25: 29100 | L25: 50000 | M25: 70000 | N25: 95000 | O25: 125000
C26: Downside | D26: $T | K26: 25000 | L26: 25000 | M26: 40000 | N26: 40000 | O26: 60000
C28: Home Care & AI Workflow Revenue | D28: $T | G28: 0 | H28: 0 | I28: 0 | J28: =INDEX($J$29:$N$31,MATCH(Scenario,$C$29:$C$31,0),1) -> 0 | K28: =INDEX($J$29:$N$31,MATCH(Scenario,$C$29:$C$31,0),2) -> 1000 | L28: =INDEX($J$29:$N$31,MATCH(Scenario,$C$29:$C$31,0),3) -> 5000 | M28: =INDEX($J$29:$N$31,MATCH(Scenario,$C$29:$C$31,0),4) -> 15000 | N28: =INDEX($J$29:$N$31,MATCH(Scenario,$C$29:$C$31,0),5) -> 20000 | O28: =INDEX($J$29:$O$31,MATCH(Scenario,$C$29:$C$31,0),6) -> 25000
C29: Upside | D29: $T | J29: 0 | K29: 5000 | L29: 15000 | M29: 25000 | N29: 35000 | O29: 45000
C30: Base | D30: $T | J30: 0 | K30: 3000 | L30: 10000 | M30: 20000 | N30: 30000 | O30: 40000
C31: Downside | D31: $T | J31: 0 | K31: 1000 | L31: 5000 | M31: 15000 | N31: 20000 | O31: 25000
C33: Total Revenue | D33: $T | G33: =SUM(G12,G21,G23,G28) -> 73390.06 | H33: =SUM(H12,H21,H23,H28) -> 65899.902 | I33: =SUM(I12,I21,I23,I28) -> 82056.041 | J33: =SUM(J12,J21,J23,J28) -> 97643 | K33: =SUM(K12,K21,K23,K28) -> 112950 | L33: =SUM(L12,L21,L23,L28) -> 143000 | M33: =SUM(M12,M21,M23,M28) -> 190000 | N33: =SUM(N12,N21,N23,N28) -> 228000 | O33: =SUM(O12,O21,O23,O28) -> 277000
C34: % Growth | H34: =H33/G33-1 -> -0.10205957 | I34: =I33/H33-1 -> 0.24516181 | J34: =J33/I33-1 -> 0.18995505 | K34: =K33/J33-1 -> 0.15676495 | L34: =L33/K33-1 -> 0.26604692 | M34: =M33/L33-1 -> 0.32867133 | N34: =N33/M33-1 -> 0.2 | O34: =O33/N33-1 -> 0.21491228
H37: Historical | L37: Projected:
B38: ="CapEx & Depreciation - "&Company_Name -> CapEx & Depreciation - Butterfly Network, inc. | E38: Units: | G38: =G3 -> 44926 | H38: =H3 -> 45291 | I38: =I3 -> 45657 | J38: =J3 -> 46022 | K38: =K3 -> 46387 | L38: =L3 -> 46752 | M38: =M3 -> 47118 | N38: =N3 -> 47483 | O38: =O3 -> 47848
C40: CapEx: | E40: $T | G40: =-Model!G170 -> 18302 | H40: =-Model!H170 -> 5783 | I40: =-Model!I170 -> 2694 | J40: =J41*-Model!J85 -> 2465.4858 | K40: =K41*-Model!K85 -> 2710.8 | L40: =L41*-Model!L85 -> 2788.5 | M40: =M41*-Model!M85 -> 3135 | N40: =N41*-Model!N85 -> 3146.4 | O40: =O41*-Model!O85 -> 3573.3
C41: CapEx % OpEx (Cash only): | E41: % | G41: =G40/-Model!G85 -> 0.078725052 | H41: =H40/-Model!H85 -> 0.03559514 | I41: =I40/-Model!I85 -> 0.021859431 | J41: 0.025 | K41: 0.03 | L41: 0.03 | M41: 0.03 | N41: 0.03 | O41: 0.03
C43: Property, Plant and Equipment, Net: | E43: $T | G43: 23271 | H43: =Model!H114 -> 35638 | I43: =Model!I114 -> 28434 | J43: =I43+J40-J55 -> 26264.563 | K43: =J43+K40-K55 -> 24521.881 | L43: =K43+L40-L55 -> 22927.819 | M43: =L43+M40-M55 -> 21646.513 | N43: =M43+N40-N55 -> 20746.828 | O43: =N43+O40-O55 -> 20580.478
C45: D&A of Existing Net PP&E and Intangibles: | E45: % | G45: =G48/G43 -> 0.25503846 | H45: =H48/H43 -> 0.29670576 | I45: =I48/I43 -> 0.36371949 | J45: 0.15 | K45: =J45-1% -> 0.14 | L45: =K45-1% -> 0.13 | M45: =L45-1% -> 0.12 | N45: =M45-1% -> 0.11 | O45: =N45-1% -> 0.1
C46: D&A of NEW CapEx & Intangible Purchases: | E46: % | J46: 0.15 | K46: 0.15 | L46: 0.15 | M46: 0.15 | N46: 0.15 | O46: 0.15
C48: D&A - Existing PP&E and Intangibles, Net: | E48: $T | G48: =Model!G148 -> 5935 | H48: =Model!H148 -> 10574 | I48: =Model!I148 -> 10342 | J48: =I43*J45 -> 4265.1 | K48: =J43*K45 -> 3677.0388 | L48: =K43*L45 -> 3187.8446 | M48: =L43*M45 -> 2751.3383 | N48: =M43*N45 -> 2381.1164 | O48: =N43*O45 -> 2074.6828
C49: D&A - Year 1 CapEx & Intangible Purchases: | E49: $T | J49: =$J$40*J46 -> 369.82286 | K49: =$J$40*K46 -> 369.82286 | L49: =$J$40*L46 -> 369.82286 | M49: =$J$40*M46 -> 369.82286 | N49: =$J$40*N46 -> 369.82286 | O49: =$J$40*O46 -> 369.82286
C50: D&A - Year 2 CapEx & Intangible Purchases: | E50: $T | K50: =$K$40*J46 -> 406.62 | L50: =$K$40*K46 -> 406.62 | M50: =$K$40*L46 -> 406.62 | N50: =$K$40*M46 -> 406.62 | O50: =$K$40*N46 -> 406.62
C51: D&A - Year 3 CapEx & Intangible Purchases: | E51: $T | L51: =$L$40*J46 -> 418.275 | M51: =$L$40*K46 -> 418.275 | N51: =$L$40*L46 -> 418.275 | O51: =$L$40*M46 -> 418.275
C52: D&A - Year 4 CapEx & Intangible Purchases: | E52: $T | M52: =$M$40*J46 -> 470.25 | N52: =$M$40*K46 -> 470.25 | O52: =$M$40*L46 -> 470.25
C53: D&A - Year 5 CapEx & Intangible Purchases: | E53: $T | N53: =$N$40*J46 -> 471.96 | O53: =$N$40*K46 -> 471.96
C54: D&A - Year 6 CapEx & Intangible Purchases: | E54: $T | O54: =$O$40*J46 -> 535.995
C55: Total Depreciation & Amortisation: | E55: $T | G55: =SUM(G48:G52) -> 5935 | H55: =SUM(H48:H52) -> 10574 | I55: =SUM(I48:I52) -> 10342 | J55: =SUM(J48:J52) -> 4634.9229 | K55: =SUM(K48:K52) -> 4453.4817 | L55: =SUM(L48:L52) -> 4382.5624 | M55: =SUM(M48:M52) -> 4416.3061 | N55: =SUM(N48:N52) -> 4046.0843 | O55: =SUM(O48:O52) -> 3739.6507

Sheet DCF
I2: Historical | M2: Projected:
B3: =Company_Name&" - Discounted Cash Flow Analysis" -> Butterfly Network, inc. - Discounted Cash Flow Analysis | E3: Units: | H3: 44926 | I3: 45291 | J3: 45657 | K3: 46022 | L3: 46387 | M3: 46752 | N3: 47118 | O3: 47483 | P3: 47848
E5: Scenario: | G5: Downside | I5: Terminal Value - Multiples Method: | N5: Terminal Value - Perpetuity Growth Method:
C7: Company Name: | E7: Name | G7: =Company_Name -> Butterfly Network, inc. | I7: Median CY 26 TEV / EBITDA of Comps: | L7: =PubComps!S36 -> 11.70442 | N7: Expected Long-Term GDP Growth: | Q7: 0.015
C8: Ticker: | E8: Name | G8: =Ticker -> BFLY | I8: Median CY 26 TEV / EBITDA of Target: | L8: =PubComps!S40 -> NM
C9: Current Share Price: | E9: $ / Share | G9: 3.79
C10: Diluted Shares Outstanding: | E10: M Shares | G10: =Diluted -> 227.39 | I10: Baseline Terminal EBITDA Multiple: | L10: =INDEX(L11:L13,MATCH(Scenario,I11:I13,0),1) -> 9 | N10: Baseline Terminal FCF Growth Rate: | Q10: =INDEX(Q11:Q13,MATCH(Scenario,N11:N13,0),1) -> 0.01
I11: Upside | L11: 11 | N11: Upside | Q11: 0.02
C12: Effective Tax Rate: | E12: % | G12: =Tax_Rate -> 0.12 | I12: Base | L12: 10 | N12: Base | Q12: 0.015
C13: Discount Rate (WACC): | E13: % | G13: =WACC!L40 -> 0.10883792 | I13: Downside | L13: 9 | N13: Downside | Q13: 0.01
I16: Baseline Terminal Value: | L16: =L10*(P62/Units) -> 903.80546 | N16: Baseline Terminal Value: | Q16: =(+P60*(1+Terminal_Growth_Rate)/(Discount_Rate-Q10)*(1+Discount_Rate)^0.5)/Units -> 1326.9554
I17: Implied Terminal FCF Growth Rate: | L17: =(O62*(1+Discount_Rate)^0.5*Discount_Rate - L16) / (O62*(1+Discount_Rate)^0.5 + L16) -> 0.095681891 | N17: Implied Terminal EBITDA Multiple: | Q17: =Q16/(O62/Units) -> 18.563318
I19: (+) Present Value of Terminal Value: | L19: =L16/((1+Discount_Rate)^5) -> 539.18105 | N19: (+) Present Value of Terminal Value: | Q19: =Q16/((1+Discount_Rate)^5) -> 791.61857
C20: Current Equity Value: | G20: =$G$9*$G$10 -> 861.8081 | I20: (+) Present Value of UFCF: | L20: =NPV(Discount_Rate,L60:P60)/Units -> 187.19541 | N20: (+) Present Value of UFCF: | Q20: =NPV(Discount_Rate,L60:P60)/Units -> 187.19541
C21: (-) Cash & Investments: | G21: =-Model!I108/Units -> -88.775 | I21: Implied Enterprise Value: | L21: =SUM(L19:L20) -> 726.37646 | N21: Implied Enterprise Value: | Q21: =SUM(Q19:Q20) -> 978.81398
C22: (-) Net Operating Losses: | G22: 0
C23: (+) Debt & Finance Leases: | G23: 0 | I23: % of implied TEV from Terminal Value: | L23: =L20/L19 -> 0.3471847 | N23: % of implied TEV from Terminal Value: | Q23: =Q20/Q19 -> 0.23647173
C24: (+) Preferred Stock: | G24: 0
C25: (+) Operating Leases: | G25: 0 | I25: (+) Cash and Investments: | L25: =-G21 -> 88.775 | N25: (+) Cash and Investments: | Q25: =L25 -> 88.775
C26: (+) Noncontrolling Interests: | G26: 0 | I26: (+) Net Operating Losses: | L26: =-G22 -> 0 | N26: (+) Net Operating Losses: | Q26: =L26 -> 0
C27: (+) Unfunded Pensions: | G27: 0 | I27: (-)Debt and Finance Leases: | L27: =-G23 -> 0 | N27: (-)Debt and Finance Leases: | Q27: =L27 -> 0
C28: Current Enterprise Value: | G28: =SUM($G$20:$G$27) -> 773.0331 | I28: (-)Preferred Stock: | L28: =-G24 -> 0 | N28: (-)Preferred Stock: | Q28: =L28 -> 0
I29: (-) Operating Leases: | L29: =-G25 -> 0 | N29: (-) Operating Leases: | Q29: =L29 -> 0
I30: (-) Noncontrolling Interests: | L30: =-G26 -> 0 | N30: (-) Noncontrolling Interests: | Q30: =L30 -> 0
I31: (-)Unfunded Pensions: | L31: =-G27 -> 0 | N31: (-)Unfunded Pensions: | Q31: =L31 -> 0
I33: Implied Equity Value: | L33: =L21+SUM(L25:L31) -> 815.15146 | N33: Implied Equity Value: | Q33: =SUM(Q21:Q32) -> 1067.8255
I35: Diluted Shares Outstanding: | L35: =_xlfn.SINGLE(Diluted) -> 227.39 | N35: Diluted Shares Outstanding: | Q35: =_xlfn.SINGLE(Diluted) -> 227.39
I37: Implied Share Price from DCF: | L37: =L33/L35 -> 3.5848166 | N37: Implied Share Price from DCF: | Q37: =Q33/Q35 -> 4.6960088
I38: Premium / (Discount) to Current: | L38: =L37/G9-1 -> -0.054138088 | N38: Premium / (Discount) to Current: | Q38: =Q37/G9-1 -> 0.23905246
I40: Historical | M40: Projected:
B41: =Company_Name&" - Free Cash Flow Calculation" -> Butterfly Network, inc. - Free Cash Flow Calculation | E41: Units: | H41: 44926 | I41: 45291 | J41: 45657 | K41: 46022 | L41: 46387 | M41: 46752 | N41: 47118 | O41: 47483 | P41: 47848
C43: Revenue | E43: $T | H43: =Model!G72 -> 73390 | I43: =Model!H72 -> 65900 | J43: =Model!I72 -> 82056 | K43: =Model!J72 -> 97643 | L43: =Model!K72 -> 112950 | M43: =Model!L72 -> 143000 | N43: =Model!M72 -> 190000 | O43: =Model!N72 -> 228000 | P43: =Model!O72 -> 277000
C44: % Change | H44: 0 | I44: =I43/H43-1 -> -0.1020575 | J44: =J43/I43-1 -> 0.24515933 | K44: =K43/J43-1 -> 0.18995564 | L44: =L43/K43-1 -> 0.15676495 | M44: =M43/L43-1 -> 0.26604692 | N44: =N43/M43-1 -> 0.32867133 | O44: =O43/N43-1 -> 0.2 | P44: =P43/O43-1 -> 0.21491228
C46: Operating Expenses | E46: $T | H46: =Model!G85 -> -232480 | I46: =Model!H85 -> -162466 | J46: =Model!I85 -> -123242 | K46: =Model!J85 -> -98619.43 | L46: =Model!K85 -> -90360 | M46: =Model!L85 -> -92950 | N46: =Model!M85 -> -104500 | O46: =Model!N85 -> -104880 | P46: =Model!O85 -> -119110
C48: Operating Income (EBIT) | E48: $T | H48: =Model!G87 -> -193020 | I48: =Model!H87 -> -145610 | J48: =Model!I87 -> -74411 | K48: =Model!J87 -> -52852.43 | L48: =Model!K87 -> -9190 | M48: =Model!L87 -> 8450 | N48: =Model!M87 -> 36600 | O48: =Model!N87 -> 62220 | P48: =Model!O87 -> 88290
C50: (-) Taxes, Excluding Effect of Interest | E50: $T | H50: =Model!G96 -> -42 | I50: =Model!H96 -> -82 | J50: =Model!I96 -> 32 | K50: =Model!J96 -> 0 | L50: =Model!K96 -> 0 | M50: =Model!L96 -> 253.10116 | N50: =Model!M96 -> 953.89871 | O50: =Model!N96 -> 1626.4654 | P50: =Model!O96 -> 2325.9785
C52: Net Operating Profit After Taxes (NOPAT) | E52: $T | H52: =Model!G97 -> -168723 | I52: =Model!H97 -> -133700 | J52: =Model!I97 -> -72492 | K52: =Model!J97 -> -49463.491 | L52: =Model!K97 -> -8501.9708 | M52: =Model!L97 -> 10798.983 | N52: =Model!M97 -> 40699.678 | O52: =Model!N97 -> 69395.855 | P52: =Model!O97 -> 99241.75
C54: Depreciation and amortization: | E54: $T | H54: =Model!G148 -> 5935 | I54: =Model!H148 -> 10574 | J54: =Model!I148 -> 10342 | K54: =Model!J148 -> 4634.9229 | L54: =Model!K148 -> 4453.4817 | M54: =Model!L148 -> 4382.5624 | N54: =Model!M148 -> 4416.3061 | O54: =Model!N148 -> 4046.0843 | P54: =Model!O148 -> 3739.6507
C56: Change in Working Capital | E56: $T | H56: 0 | I56: 0 | J56: =J65-I65 -> 1712 | K56: =K65-J65 -> 1275.041 | L56: =L65-K65 -> 6375.2138 | M56: =M65-L65 -> 1927.6836 | N56: =N65-M65 -> 14775.444 | O56: =O65-N65 -> 21461.179 | P56: =P65-O65 -> 23909.336
C58: Capital Expenditures: | E58: $T | H58: =Model!G170 -> -18302 | I58: =Model!H170 -> -5783 | J58: =Model!I170 -> -2694 | K58: =Model!J170 -> -2465.4858 | L58: =Model!K170 -> -2710.8 | M58: =Model!L170 -> -2788.5 | N58: =Model!M170 -> -3135 | O58: =Model!N170 -> -3146.4 | P58: =Model!O170 -> -3573.3
C60: Unlevered Free Cash Flow | E60: $T | H60: =SUM(H52,H54,H56,H58) -> -181090 | I60: =SUM(I52,I54,I56,I58) -> -128909 | J60: =SUM(J52,J54,J56,J58) -> -63132 | K60: =SUM(K52,K54,K56,K58) -> -46019.013 | L60: =SUM(L52,L54,L56,L58) -> -384.07531 | M60: =SUM(M52,M54,M56,M58) -> 14320.729 | N60: =SUM(N52,N54,N56,N58) -> 56756.429 | O60: =SUM(O52,O54,O56,O58) -> 91756.719 | P60: =SUM(P52,P54,P56,P58) -> 123317.44
C62: EBITDA | E62: $T | H62: =Model!G87+Model!G89+Model!G90+Model!G148 -> -183703 | I62: =Model!H87+Model!H89+Model!H90+Model!H148 -> -127586 | J62: =Model!I87+Model!I89+Model!I90+Model!I148 -> -60310 | K62: =Model!J87+Model!J89+Model!J90+Model!J148 -> -46163.568 | L62: =Model!K87+Model!K89+Model!K90+Model!K148 -> -3779.9891 | M62: =Model!L87+Model!L89+Model!L90+Model!L148 -> 14395.194 | N62: =Model!M87+Model!M89+Model!M90+Model!M148 -> 44029.711 | O62: =Model!N87+Model!N89+Model!N90+Model!N148 -> 71482.662 | P62: =Model!O87+Model!O89+Model!O90+Model!O148 -> 100422.83
C63: EBITDA Margin | E63: % | H63: =H62/H43 -> -2.5031067 | I63: =I62/I43 -> -1.9360546 | J63: =J62/J43 -> -0.73498586 | K63: =K62/K43 -> -0.47277908 | L63: =L62/L43 -> -0.033466039 | M63: =M62/M43 -> 0.10066569 | N63: =N62/N43 -> 0.23173532 | O63: =O62/O43 -> 0.31352045 | P63: =P62/P43 -> 0.36253729
C65: Operating Net Working Capital | E65: $T | H65: 0 | I65: =SUM(Model!H109:H110)-SUM(Model!H122:H124) -> 57794 | J65: =SUM(Model!I109:I110)-SUM(Model!I122:I124) -> 59506 | K65: =SUM(Model!J109:J110)-SUM(Model!J122:J124) -> 60781.041 | L65: =SUM(Model!K109:K110)-SUM(Model!K122:K124) -> 67156.255 | M65: =SUM(Model!L109:L110)-SUM(Model!L122:L124) -> 69083.938 | N65: =SUM(Model!M109:M110)-SUM(Model!M122:M124) -> 83859.383 | O65: =SUM(Model!N109:N110)-SUM(Model!N122:N124) -> 105320.56 | P65: =SUM(Model!O109:O110)-SUM(Model!O122:O124) -> 129229.9
B67: Sensitivity Analyses
K69: Discount Rate: (WACC)
E70: =L37 -> 3.5848166 | F70: 0.09 | G70: =F70+0.001 -> 0.091 | H70: =G70+0.001 -> 0.092 | I70: =H70+0.001 -> 0.093 | J70: =I70+0.001 -> 0.094 | K70: =J70+0.001 -> 0.095 | L70: =K70+0.001 -> 0.096 | M70: =L70+0.001 -> 0.097 | N70: =M70+0.001 -> 0.098 | ... P70: =O70+0.001 -> 0.1
E71: 11 | F71: 4.4302764 | G71: 4.4125488 | H71: 4.3949162 | I71: 4.377378 | J71: 4.3599337 | K71: 4.3425826 | L71: 4.3253242 | M71: 4.3081579 | N71: 4.2910831 | O71: 4.2740993 | P71: 4.2572058
E72: =E71-0.2 -> 10.8 | F72: 4.3728703 | G72: 4.3554052 | H72: 4.3380338 | I72: 4.3207553 | J72: 4.3035693 | K72: 4.2864751 | L72: 4.2694722 | M72: 4.2525601 | N72: 4.235738 | O72: 4.2190055 | P72: 4.202362
E73: =E72-0.2 -> 10.6 | F73: 4.3154641 | G73: 4.2982616 | H73: 4.2811514 | I73: 4.2641327 | J73: 4.247205 | K73: 4.2303677 | L73: 4.2136203 | M73: 4.1969622 | N73: 4.1803929 | O73: 4.1639117 | P73: 4.1475182
E74: =E73-0.2 -> 10.4 | F74: 4.2580579 | G74: 4.2411181 | H74: 4.224269 | I74: 4.20751 | J74: 4.1908406 | K74: 4.1742603 | L74: 4.1577684 | M74: 4.1413644 | N74: 4.1250477 | O74: 4.1088179 | P74: 4.0926744
C75: TEV / EBITDA Multiple: | E75: =E74-0.2 -> 10.2 | F75: 4.2006518 | G75: 4.1839745 | H75: 4.1673866 | I75: 4.1508873 | J75: 4.1344763 | K75: 4.1181528 | L75: 4.1019164 | M75: 4.0857665 | N75: 4.0697026 | O75: 4.0537241 | P75: 4.0378306
E76: =E75-0.2 -> 10 | F76: 4.1432456 | G76: 4.126831 | H76: 4.1105042 | I76: 4.0942647 | J76: 4.0781119 | K76: 4.0620454 | L76: 4.0460645 | M76: 4.0301687 | N76: 4.0143575 | O76: 3.9986303 | P76: 3.9829867
E77: =E76-0.2 -> 9.8 | F77: 4.0858394 | G77: 4.0696874 | H77: 4.0536218 | I77: 4.037642 | J77: 4.0217476 | K77: 4.0059379 | L77: 3.9902125 | M77: 3.9745708 | N77: 3.9590124 | O77: 3.9435366 | P77: 3.9281429
E78: =E77-0.2 -> 9.6 | F78: 4.0284332 | G78: 4.0125438 | H78: 3.9967394 | I78: 3.9810193 | J78: 3.9653832 | K78: 3.9498305 | L78: 3.9343606 | M78: 3.918973 | N78: 3.9036672 | O78: 3.8884428 | P78: 3.8732991
E79: =E78-0.2 -> 9.4 | F79: 3.9710271 | G79: 3.9554003 | H79: 3.939857 | I79: 3.9243967 | J79: 3.9090189 | K79: 3.893723 | L79: 3.8785086 | M79: 3.8633752 | N79: 3.8483221 | O79: 3.833349 | P79: 3.8184553
E80: =E79-0.2 -> 9.2 | F80: 3.9136209 | G80: 3.8982567 | H80: 3.8829746 | I80: 3.867774 | J80: 3.8526545 | K80: 3.8376156 | L80: 3.8226567 | M80: 3.8077773 | N80: 3.792977 | O80: 3.7782552 | P80: 3.7636115
E81: =E80-0.2 -> 9 | F81: 3.8562147 | G81: 3.8411131 | H81: 3.8260922 | I81: 3.8111514 | J81: 3.7962902 | K81: 3.7815081 | L81: 3.7668047 | M81: 3.7521795 | N81: 3.7376319 | O81: 3.7231614 | P81: 3.7087677
K84: Discount Rate: (WACC)
E85: =Q37 -> 4.6960088 | F85: 0.09 | G85: =F85+0.001 -> 0.091 | H85: =G85+0.001 -> 0.092 | I85: =H85+0.001 -> 0.093 | J85: =I85+0.001 -> 0.094 | K85: =J85+0.001 -> 0.095 | L85: =K85+0.001 -> 0.096 | M85: =L85+0.001 -> 0.097 | N85: =M85+0.001 -> 0.098 | ... P85: =O85+0.001 -> 0.1
E86: 0.04 | F86: 8.9275984 | G86: 8.743341 | H86: 8.5662127 | I86: 8.3958099 | J86: 8.2317589 | K86: 8.0737132 | L86: 7.921351 | M86: 7.774373 | N86: 7.6325007 | O86: 7.4954744 | P86: 7.3630518
E87: =E86-0.2% -> 0.038 | F87: 8.6190758 | G87: 8.4475267 | H87: 8.2823723 | I87: 8.1232638 | J87: 7.9698772 | K87: 7.8219112 | L87: 7.6790854 | M87: 7.5411384 | N87: 7.4078261 | O87: 7.2789205 | P87: 7.1542083
E88: =E87-0.2% -> 0.036 | F88: 8.3334083 | G88: 8.1732278 | H88: 8.0188079 | I88: 7.8698454 | J88: 7.7260578 | K88: 7.587182 | L88: 7.4529724 | M88: 7.3231993 | N88: 7.197648 | O88: 7.0761174 | P88: 6.958419
E89: =E88-0.2% -> 0.034 | F89: 8.0681473 | G89: 7.9181796 | H89: 7.7734219 | I89: 7.6336094 | J89: 7.4984946 | K89: 7.3678465 | L89: 7.2414488 | M89: 7.1190991 | N89: 7.0006075 | O89: 6.885796 | P89: 6.7744971
C90: Terminal FCF Growth Rates: | E90: =E89-0.2% -> 0.032 | F90: 7.8211817 | G90: 7.6804242 | H90: 7.5443965 | I90: 7.4128658 | J90: 7.2856143 | K90: 7.1624384 | L90: 7.0431469 | M90: 6.9275603 | N90: 6.8155103 | O90: 6.7068384 | P90: 6.6013954
E91: =E90-0.2% -> 0.03 | F91: 7.590682 | G91: 7.4582609 | H91: 7.3301484 | I91: 7.2061391 | J91: 7.0860406 | K91: 6.9696723 | L91: 6.8568646 | M91: 6.7474581 | N91: 6.6413025 | O91: 6.5382565 | P91: 6.4381867
E92: =E91-0.2% -> 0.028 | F92: 7.3750547 | G92: 7.2502047 | H92: 7.1292922 | I92: 7.0121354 | J92: 6.8985635 | K92: 6.788416 | L92: 6.6815415 | M92: 6.5777979 | N92: 6.4770508 | O92: 6.3791735 | P92: 6.2840464
E93: =E92-0.2% -> 0.026 | F93: 7.1729056 | G93: 7.0549534 | H93: 6.9406106 | I93: 6.8297155 | J93: 6.722116 | K93: 6.6176686 | L93: 6.5162382 | M93: 6.4176973 | N93: 6.3219254 | O93: 6.2288086 | P93: 6.1382393
E94: =E93-0.2% -> 0.024 | F94: 6.9830093 | G94: 6.8713602 | H94: 6.7630292 | I94: 6.657872 | J94: 6.5557524 | K94: 6.4565421 | L94: 6.3601198 | M94: 6.2663707 | N94: 6.1751865 | O94: 6.0864645 | P94: 6.0001075
E95: =E94-0.2% -> 0.022 | F95: 6.8042848 | G95: 6.6984115 | H95: 6.5955967 | I95: 6.4957111 | J95: 6.3986326 | K95: 6.3042458 | L95: 6.2124414 | M95: 6.1231161 | N95: 6.036172 | O95: 5.9515161 | P95: 5.8690606
E96: =E95-0.2% -> 0.02 | F96: 6.6357744 | G96: 6.5352077 | H96: 6.4374673 | I96: 6.3424371 | J96: 6.2500071 | K96: 6.1600732 | L96: 6.0725368 | M96: 5.9873045 | N96: 5.9042876 | O96: 5.8234018 | P96: 5.7445672

Sheet WACC
B2: ="WACC Analysis - "&_xlfn.SINGLE(Company_Name) -> WACC Analysis - Butterfly Network, inc.
B3: ($ USD in Millions Except Per Share Amounts in USD as Stated)
B5: Discount Rate Calculations - Assumptions:
B6: Risk-Free Rate: | F6: 0.045
B7: Equity Risk Premium: | F7: 0.035
B8: Pre-Tax Cost of Debt: | F8: 0.02532108
B9: Cost of Preferred Stock: | F9: 0
B11: Company Name: | C11: Ticker: | D11: Levered Beta: | E11: (+) Debt & Capital Leases: | G11: (+) Preferred Stock: | I11: Equity Value: | K11: Effective Tax Rate:
B12: Comparable Companies - Unlevered Beta Calculation:
D13: Levered | G13: Preferred | I13: Equity | L13: Unlevered
B14: Name | C14: Ticker | D14: Beta | E14: Debt | F14: % Debt | G14: Stock | H14: % Preferred | I14: Value | J14: % Equity | K14: Tax Rate | L14: Beta
B15: =INDEX(Pub_Comps_Range,MATCH(B$11,Pub_Comps_Params,0),MATCH($C15,Pub_Comps_Tickers,0)) -> GE Healthcare Technologies Inc. | C15: GEHC | D15: =INDEX(Pub_Comps_Range,MATCH(D$11,Pub_Comps_Params,0),MATCH($C15,Pub_Comps_Tickers,0)) -> 1.27 | E15: =INDEX(Pub_Comps_Range,MATCH(E$11,Pub_Comps_Params,0),MATCH($C15,Pub_Comps_Tickers,0)) -> 10744 | F15: =E15/(E15+G15+I15) -> 0.21630314 | G15: =INDEX(Pub_Comps_Range,MATCH(G$11,Pub_Comps_Params,0),MATCH($C15,Pub_Comps_Tickers,0)) -> 0 | H15: =G15/(E15+G15+I15) -> 0 | I15: =INDEX(Pub_Comps_Range,MATCH(I$11,Pub_Comps_Params,0),MATCH($C15,Pub_Comps_Tickers,0)) -> 38927.03 | J15: =$I15/($E15+$G15+$I15) -> 0.78369686 | K15: =INDEX(Pub_Comps_Range,MATCH(K$11,Pub_Comps_Params,0),MATCH($C15,Pub_Comps_Tickers,0)) -> 0.177 | L15: =IFERROR(D15/(1+(E15/I15)*(1-K15)+G15/I15),"N/A") -> 1.0349175
B16: =INDEX(Pub_Comps_Range,MATCH(B$11,Pub_Comps_Params,0),MATCH($C16,Pub_Comps_Tickers,0)) -> Masimo Corporation | C16: MASI | D16: =INDEX(Pub_Comps_Range,MATCH(D$11,Pub_Comps_Params,0),MATCH($C16,Pub_Comps_Tickers,0)) -> 1.26 | E16: =INDEX(Pub_Comps_Range,MATCH(E$11,Pub_Comps_Params,0),MATCH($C16,Pub_Comps_Tickers,0)) -> 642.2 | F16: =E16/(E16+G16+I16) -> 0.076783648 | G16: =INDEX(Pub_Comps_Range,MATCH(G$11,Pub_Comps_Params,0),MATCH($C16,Pub_Comps_Tickers,0)) -> 0 | H16: =G16/(E16+G16+I16) -> 0 | I16: =INDEX(Pub_Comps_Range,MATCH(I$11,Pub_Comps_Params,0),MATCH($C16,Pub_Comps_Tickers,0)) -> 7721.56 | J16: =$I16/($E16+$G16+$I16) -> 0.92321635 | K16: =INDEX(Pub_Comps_Range,MATCH(K$11,Pub_Comps_Params,0),MATCH($C16,Pub_Comps_Tickers,0)) -> 0.2 | L16: =IFERROR(D16/(1+(E16/I16)*(1-K16)+G16/I16),"N/A") -> 1.181395
B17: =INDEX(Pub_Comps_Range,MATCH(B$11,Pub_Comps_Params,0),MATCH($C17,Pub_Comps_Tickers,0)) -> InMode, Ltd. | C17: INMD | D17: =INDEX(Pub_Comps_Range,MATCH(D$11,Pub_Comps_Params,0),MATCH($C17,Pub_Comps_Tickers,0)) -> 2.15 | E17: =INDEX(Pub_Comps_Range,MATCH(E$11,Pub_Comps_Params,0),MATCH($C17,Pub_Comps_Tickers,0)) -> 6.1 | F17: =E17/(E17+G17+I17) -> 0.0064169323 | G17: =INDEX(Pub_Comps_Range,MATCH(G$11,Pub_Comps_Params,0),MATCH($C17,Pub_Comps_Tickers,0)) -> 0 | H17: =G17/(E17+G17+I17) -> 0 | I17: =INDEX(Pub_Comps_Range,MATCH(I$11,Pub_Comps_Params,0),MATCH($C17,Pub_Comps_Tickers,0)) -> 944.51 | J17: =$I17/($E17+$G17+$I17) -> 0.99358307 | K17: =INDEX(Pub_Comps_Range,MATCH(K$11,Pub_Comps_Params,0),MATCH($C17,Pub_Comps_Tickers,0)) -> 0.2 | L17: =IFERROR(D17/(1+(E17/I17)*(1-K17)+G17/I17),"N/A") -> 2.1389487
B18: =INDEX(Pub_Comps_Range,MATCH(B$11,Pub_Comps_Params,0),MATCH($C18,Pub_Comps_Tickers,0)) -> Integra LifeSciences Holdings Corporation | C18: IART | D18: =INDEX(Pub_Comps_Range,MATCH(D$11,Pub_Comps_Params,0),MATCH($C18,Pub_Comps_Tickers,0)) -> 1.08 | E18: =INDEX(Pub_Comps_Range,MATCH(E$11,Pub_Comps_Params,0),MATCH($C18,Pub_Comps_Tickers,0)) -> 2007.7 | F18: =E18/(E18+G18+I18) -> 0.65954742 | G18: =INDEX(Pub_Comps_Range,MATCH(G$11,Pub_Comps_Params,0),MATCH($C18,Pub_Comps_Tickers,0)) -> 0 | H18: =G18/(E18+G18+I18) -> 0 | I18: =INDEX(Pub_Comps_Range,MATCH(I$11,Pub_Comps_Params,0),MATCH($C18,Pub_Comps_Tickers,0)) -> 1036.3571 | J18: =$I18/($E18+$G18+$I18) -> 0.34045258 | K18: =INDEX(Pub_Comps_Range,MATCH(K$11,Pub_Comps_Params,0),MATCH($C18,Pub_Comps_Tickers,0)) -> 0.2 | L18: =IFERROR(D18/(1+(E18/I18)*(1-K18)+G18/I18),"N/A") -> 0.42356043
B19: =INDEX(Pub_Comps_Range,MATCH(B$11,Pub_Comps_Params,0),MATCH($C19,Pub_Comps_Tickers,0)) -> CureVac N.V. | C19: CVAC | D19: =INDEX(Pub_Comps_Range,MATCH(D$11,Pub_Comps_Params,0),MATCH($C19,Pub_Comps_Tickers,0)) -> 1.78 | E19: =INDEX(Pub_Comps_Range,MATCH(E$11,Pub_Comps_Params,0),MATCH($C19,Pub_Comps_Tickers,0)) -> 41.5 | F19: =E19/(E19+G19+I19) -> 0.034394333 | G19: =INDEX(Pub_Comps_Range,MATCH(G$11,Pub_Comps_Params,0),MATCH($C19,Pub_Comps_Tickers,0)) -> 0 | H19: =G19/(E19+G19+I19) -> 0 | I19: =INDEX(Pub_Comps_Range,MATCH(I$11,Pub_Comps_Params,0),MATCH($C19,Pub_Comps_Tickers,0)) -> 1165.0941 | J19: =$I19/($E19+$G19+$I19) -> 0.96560567 | K19: =INDEX(Pub_Comps_Range,MATCH(K$11,Pub_Comps_Params,0),MATCH($C19,Pub_Comps_Tickers,0)) -> 0.121 | L19: =IFERROR(D19/(1+(E19/I19)*(1-K19)+G19/I19),"N/A") -> 1.725961
B20: =INDEX(Pub_Comps_Range,MATCH(B$11,Pub_Comps_Params,0),MATCH($C20,Pub_Comps_Tickers,0)) -> CareDx, Inc | C20: CDNA | D20: =INDEX(Pub_Comps_Range,MATCH(D$11,Pub_Comps_Params,0),MATCH($C20,Pub_Comps_Tickers,0)) -> 2.56 | E20: =INDEX(Pub_Comps_Range,MATCH(E$11,Pub_Comps_Params,0),MATCH($C20,Pub_Comps_Tickers,0)) -> 29.1 | F20: =E20/(E20+G20+I20) -> 0.028672889 | G20: =INDEX(Pub_Comps_Range,MATCH(G$11,Pub_Comps_Params,0),MATCH($C20,Pub_Comps_Tickers,0)) -> 0 | H20: =G20/(E20+G20+I20) -> 0 | I20: =INDEX(Pub_Comps_Range,MATCH(I$11,Pub_Comps_Params,0),MATCH($C20,Pub_Comps_Tickers,0)) -> 985.796 | J20: =$I20/($E20+$G20+$I20) -> 0.97132711 | K20: =INDEX(Pub_Comps_Range,MATCH(K$11,Pub_Comps_Params,0),MATCH($C20,Pub_Comps_Tickers,0)) -> 0.005 | L20: =IFERROR(D20/(1+(E20/I20)*(1-K20)+G20/I20),"N/A") -> 2.4869539
B22: Median: | D22: =MEDIAN(D15:D19) -> 1.27 | E22: =MEDIAN(E15:E19) -> 642.2 | F22: =MEDIAN(F15:F19) -> 0.076783648 | G22: =MEDIAN(G15:G19) -> 0 | H22: =MEDIAN(H15:H19) -> 0 | I22: =MEDIAN(I15:I19) -> 1165.0941 | J22: =MEDIAN(J15:J19) -> 0.92321635 | K22: =MEDIAN(K15:K19) -> 0.2 | L22: =MEDIAN(L15:L19) -> 1.181395
B24: =Company_Name -> Butterfly Network, inc. | C24: =Ticker -> BFLY | D24: =INDEX(Pub_Comps_Range,MATCH(D$11,Pub_Comps_Params,0),MATCH($C24,Pub_Comps_Tickers,0)) -> 2.24 | E24: =INDEX(Pub_Comps_Range,MATCH(E$11,Pub_Comps_Params,0),MATCH($C24,Pub_Comps_Tickers,0)) -> 0 | F24: =E24/($E24+$G24+$I24) -> 0 | G24: =INDEX(Pub_Comps_Range,MATCH(G$11,Pub_Comps_Params,0),MATCH($C24,Pub_Comps_Tickers,0)) -> 0 | H24: =G24/($E24+$G24+$I24) -> 0 | I24: =INDEX(Pub_Comps_Range,MATCH(I$11,Pub_Comps_Params,0),MATCH($C24,Pub_Comps_Tickers,0)) -> 697.61268 | J24: =I24/($E24+$G24+$I24) -> 1 | K24: 0.132 | L24: =IFERROR(D24/(1+(E24/I24)*(1-K24)+G24/I24),"N/A") -> 2.24
B26: =TEXT(Company_Name,"")& " - Levered Beta & WACC Calculation:" -> Butterfly Network, inc. - Levered Beta & WACC Calculation:
D27: Unlevered | G27: Preferred | I27: Equity | L27: Levered
C28: Ticker | D28: Beta | E28: Debt | F28: % Debt | G28: Stock | H28: % Preferred | I28: Value | J28: % Equity | K28: Tax Rate | L28: Beta
B29: Current Capital Structure: | C29: =C24 -> BFLY | D29: =L24 -> 2.24 | E29: 5461 | F29: 0.033001557 | G29: 0 | H29: 0 | I29: 160016.04 | J29: 0.96699844 | K29: 0.132 | L29: =D29*(1+E29/I29*(1-K29)+G29/I29) -> 2.3063554
B30: "Optimal" Capital Structure: | D30: =L22 -> 1.181395 | E30: =(E29+I29)*F30 -> 12705.931 | F30: =F22 -> 0.076783648 | G30: 0 | H30: 0 | I30: =(I29+E29)*J30 -> 152771.11 | J30: =J22 -> 0.92321635 | K30: 0.132 | L30: =D30*(1+E30/I30*(1-K30)+G30/I30) -> 1.2666814
B32: Cost of Equity Based on Comparables, Current Capital Structure: | L32: =Risk_Free_Rate+Equity_Risk_Premium*L29 -> 0.12572244
B33: Cost of Equity Based on Comparables, "Optimal" Capital Structure: | L33: =Risk_Free_Rate+Equity_Risk_Premium*L30 -> 0.08933385
B34: Cost of Equity Based on Historical Beta: | L34: =Risk_Free_Rate+Equity_Risk_Premium*D24 -> 0.1234
B36: WACC, Current Capital Structure: | L36: =L32*J29+Cost_of_Debt*(1-K29)*F29+Cost_of_Preferred*H29 -> 0.12229873
B37: WACC, "Optimal" Capital Structure: | L37: =L33*J30+Cost_of_Debt*(1-K30)*F30+Cost_of_Preferred*H30 -> 0.084162076
B38: WACC, Current Capital Structure and Historical Cost of Equity: | L38: =L34*J29+Cost_of_Debt*(1-K29)*F29+Cost_of_Preferred*H29 -> 0.12005294
B40: Average WACC Produced by All Methods: | L40: =AVERAGE(L36:L38) -> 0.10883792

Sheet Valsum
B2: ="Valuation Summary - "&Company_Name -> Valuation Summary - Butterfly Network, inc.
B3: ($ USD in Millions Except Per Share Amounts in USD as Stated)
B5: ="Valuation Statistics - "&TEXT(Company_Name,"") -> Valuation Statistics - Butterfly Network, inc. | C5: Range of Valuation Multiples / Premiums | I5: Implied Per-Share Value Range
D7: 75th | F7: 25th | H7: Applicable | J7: 25th | L7: 75th
C8: Maximum | D8: Percentile | E8: Median | F8: Percentile | G8: Minimum | H8: Company | I8: Minimum | J8: Percentile | K8: Median | L8: Percentile | M8: Maximum
B9: Methodology Name | C9: Multiple | D9: Multiple | E9: Multiple | F9: Multiple | G9: Multiple | H9: Figure | I9: Multiple | J9: Multiple | K9: Multiple | L9: Multiple | M9: Multiple
B11: Public Company Comparables:
B12: LTM TEV / Revenue: | C12: {=TRANSPOSE(PubComps!N34:V38)} -> 3.8137989 | D12: 2.3900268 | E12: 1.9782445 | F12: 1.5900166 | G12: 1.0954753 | H12: {=TRANSPOSE(PubComps!N21:V21)} -> 203.9 | I12: =(I34+SUM($E$33:$E$39))/$E$42 -> 1.3727183 | J12: =(J34+SUM($E$33:$E$39))/$E$42 -> 1.8161721 | K12: =(K34+SUM($E$33:$E$39))/$E$42 -> 2.164295 | L12: =(L34+SUM($E$33:$E$39))/$E$42 -> 2.5335391 | M12: =(M34+SUM($E$33:$E$39))/$E$42 -> 3.8102317
B13: ="CY "&TEXT(EOMONTH(Hist_Year,12),"YY")&" TEV / Revenue:" -> CY 25 TEV / Revenue: | C13: 9.7895338 | D13: 4.609228 | E13: 2.1391078 | F13: 1.7826113 | G13: 1.1954076 | H13: 63.443 | I13: =(I35+SUM($E$33:$E$39))/$E$42 -> 0.72393353 | J13: =(J35+SUM($E$33:$E$39))/$E$42 -> 0.88776644 | K13: =(K35+SUM($E$33:$E$39))/$E$42 -> 0.98723081 | L13: =(L35+SUM($E$33:$E$39))/$E$42 -> 1.6764073 | M13: =(M35+SUM($E$33:$E$39))/$E$42 -> 3.1217397
B14: ="CY "&TEXT(EOMONTH(Hist_Year,24),"YY")&" TEV / Revenue:" -> CY 26 TEV / Revenue: | C14: 7.6140819 | D14: 4.2940256 | E14: 1.9808956 | F14: 1.6938083 | G14: 1.1485901 | H14: 56.95 | I14: =(I36+SUM($E$33:$E$39))/$E$42 -> 0.67807382 | J14: =(J36+SUM($E$33:$E$39))/$E$42 -> 0.81462413 | K14: =(K36+SUM($E$33:$E$39))/$E$42 -> 0.88652536 | L14: =(L36+SUM($E$33:$E$39))/$E$42 -> 1.4658506 | M14: =(M36+SUM($E$33:$E$39))/$E$42 -> 2.2973612
B15: LTM TEV / EBITDA: | C15: 19.048184 | D15: 14.799892 | E15: 8.59825 | F15: 3.7193967 | G15: 3.4394694 | H15: 258.9 | I15: =(I37+SUM($E$33:$E$39))/$E$42 -> 4.3064938 | J15: =(J37+SUM($E$33:$E$39))/$E$42 -> 4.6252114 | K15: =(K37+SUM($E$33:$E$39))/$E$42 -> 10.180139 | L15: =(L37+SUM($E$33:$E$39))/$E$42 -> 17.241158 | M15: =(M37+SUM($E$33:$E$39))/$E$42 -> 22.078147
B16: ="CY "&TEXT(EOMONTH(Hist_Year,12),"YY")&" TEV / EBITDA:" -> CY 25 TEV / EBITDA: | C16: 25.12647 | D16: 16.527485 | E16: 12.563107 | F16: 8.8412647 | G16: 4.6798936 | H16: -46.163568 | I16: =(I38+SUM($E$33:$E$39))/$E$42 -> -0.55967978 | J16: =(J38+SUM($E$33:$E$39))/$E$42 -> -1.4045003 | K16: =(K38+SUM($E$33:$E$39))/$E$42 -> -2.1600899 | L16: =(L38+SUM($E$33:$E$39))/$E$42 -> -2.9649179 | M16: =(M38+SUM($E$33:$E$39))/$E$42 -> -4.7106403
B17: ="CY "&TEXT(EOMONTH(Hist_Year,24),"YY")&" TEV / EBITDA:" -> CY 26 TEV / EBITDA: | C17: 16.386828 | D17: 15.099559 | E17: 11.70442 | F17: 8.3368081 | G17: 4.3555446 | H17: -3.7799891 | I17: =(I39+SUM($E$33:$E$39))/$E$42 -> 0.3180047 | J17: =(J39+SUM($E$33:$E$39))/$E$42 -> 0.25182267 | K17: =(K39+SUM($E$33:$E$39))/$E$42 -> 0.1958416 | L17: =(L39+SUM($E$33:$E$39))/$E$42 -> 0.13940293 | M17: =(M39+SUM($E$33:$E$39))/$E$42 -> 0.11800416
B18: LTM P / E: | C18: 16.998703 | D18: 16.966342 | E18: 11.486025 | F18: 5.8336593 | G18: 5.2851547 | H18: -65.4 | I18: =(I40+SUM($E$33:$E$39))/$E$42 -> -1.1296632 | J18: =(J40+SUM($E$33:$E$39))/$E$42 -> -1.2874195 | K18: =(K40+SUM($E$33:$E$39))/$E$42 -> -2.9131054 | L18: =(L40+SUM($E$33:$E$39))/$E$42 -> -4.4893082 | M18: =(M40+SUM($E$33:$E$39))/$E$42 -> -4.4986155
B19: ="CY "&TEXT(EOMONTH(Hist_Year,12),"YY")&" P / E:" -> CY 25 P / E: | C19: 36.945263 | D19: 23.165358 | E19: 14.310018 | F19: 9.0690567 | G19: 6.1322906 | H19: -49.463491 | I19: =(I41+SUM($E$33:$E$39))/$E$42 -> -0.94353093 | J19: =(J41+SUM($E$33:$E$39))/$E$42 -> -1.5823572 | K19: =(K41+SUM($E$33:$E$39))/$E$42 -> -2.7224083 | L19: =(L41+SUM($E$33:$E$39))/$E$42 -> -4.6486849 | M19: =(M41+SUM($E$33:$E$39))/$E$42 -> -7.646188
B20: ="CY "&TEXT(EOMONTH(Hist_Year,24),"YY")&" P / E:" -> CY 26 P / E: | C20: 29.137962 | D20: 20.882661 | E20: 13.606361 | F20: 8.2428027 | G20: 5.7257299 | H20: -8.5019708 | I20: =(I42+SUM($E$33:$E$39))/$E$42 -> 0.17632707 | J20: =(J42+SUM($E$33:$E$39))/$E$42 -> 0.08221528 | K20: =(K42+SUM($E$33:$E$39))/$E$42 -> -0.11832482 | L20: =(L42+SUM($E$33:$E$39))/$E$42 -> -0.39038118 | M20: =(M42+SUM($E$33:$E$39))/$E$42 -> -0.69904175
B22: Precedent Transactions:
B23: =TEXT(LTM,"yyyy-mm-dd")&" EV / Revenue:" -> 2025-09-30 EV / Revenue: | C23: {=TRANSPOSE(MAComps!H18:I22)} -> 12.75759 | D23: 8.5563396 | E23: 5.9381414 | F23: 4.3567005 | G23: 3 | H23: =PubComps!O21 -> 63.443 | I23: =(I44+SUM($E$33:$E$39))/$E$42 -> 1.2274242 | J23: =(J44+SUM($E$33:$E$39))/$E$42 -> 1.6059508 | K23: =(K44+SUM($E$33:$E$39))/$E$42 -> 2.0471811 | L23: =(L44+SUM($E$33:$E$39))/$E$42 -> 2.7776721 | M23: =(M44+SUM($E$33:$E$39))/$E$42 -> 3.9498429
B24: =TEXT(LTM,"yyyy-mm-dd")&" EV / EBITDA:" -> 2025-09-30 EV / EBITDA: | C24: 75.7 | D24: 39.909023 | E24: 27.308266 | F24: 25.197776 | G24: 20.877602 | H24: =PubComps!R21 -> -46.163568 | I24: =(I45+SUM($E$33:$E$39))/$E$42 -> -3.8480566 | J24: =(J45+SUM($E$33:$E$39))/$E$42 -> -4.7251165 | K24: =(K45+SUM($E$33:$E$39))/$E$42 -> -5.1535774 | L24: =(L45+SUM($E$33:$E$39))/$E$42 -> -7.7117194 | M24: =(M45+SUM($E$33:$E$39))/$E$42 -> -14.977823
B25: 1-Day Premiums: | C25: {=TRANSPOSE(MAComps!N18:P22)} -> 0.56657963 | D25: 0.26161926 | E25: 0.23848758 | F25: 0.18238958 | G25: 0.075417069 | H25: =Share_Price -> 3.06 | I25: =+$H25*(1+G25) -> 3.2907762 | J25: =+$H25*(1+F25) -> 3.6181121 | K25: =+$H25*(1+E25) -> 3.789772 | L25: =+$H25*(1+D25) -> 3.8605549 | M25: =+$H25*(1+C25) -> 4.7937337
B26: 1-Week Premiums: | C26: 0.54772141 | D26: 0.35647972 | E26: 0.22387773 | F26: 0.19115616 | G26: 0.14092881 | H26: =Share_Price -> 3.06 | I26: =+$H26*(1+G26) -> 3.4912422 | J26: =+$H26*(1+F26) -> 3.6449378 | K26: =+$H26*(1+E26) -> 3.7450659 | L26: =+$H26*(1+D26) -> 4.1508279 | M26: =+$H26*(1+C26) -> 4.7360275
B27: 1-Month Premiums: | C27: 0.62454874 | D27: 0.50157068 | E27: 0.41188271 | F27: 0.28054089 | G27: 0.12448641 | H27: =Share_Price -> 3.06 | I27: =+$H27*(1+G27) -> 3.4409284 | J27: =+$H27*(1+F27) -> 3.9184551 | K27: =+$H27*(1+E27) -> 4.3203611 | L27: =+$H27*(1+D27) -> 4.5948063 | M27: =+$H27*(1+C27) -> 4.9711191
B29: Discounted Cash Flow Analysis:
B30: (9.9% - 11.9% WACC, 5.5% - 8.5% Free Cash Flow Growth Rate | I30: =DCF!O79 -> 3.833349 | J30: =DCF!M78 -> 3.918973 | K30: =DCF!K76 -> 4.0620454 | L30: =DCF!I74 -> 4.20751 | M30: =DCF!G73 -> 4.2982616
B32: Implied Enterprise Value: | E32: =K36 -> 112.812
B33: (+) Cash and Investments: | E33: =DCF!L25 -> 88.775
B34: (+) Net Operating Losses: | E34: =DCF!L26 -> 0 | G34: Enterprise Value --> | I34: =IF(Premium_Case="yes",(G12*(1+Premium_Uplift))*$H12,G12*$H12) -> 223.36741 | J34: =IF(Premium_Case="yes",(F12*(1+Premium_Uplift))*$H12,F12*$H12) -> 324.20438 | K34: =IF(Premium_Case="yes",(E12*(1+Premium_Uplift))*$H12,E12*$H12) -> 403.36404 | L34: =IF(Premium_Case="yes",(D12*(1+Premium_Uplift))*$H12,D12*$H12) -> 487.32646 | M34: =IF(Premium_Case="yes",(C12*(1+Premium_Uplift))*$H12,C12*$H12) -> 777.63359
B35: (-)Debt and Finance Leases: | E35: =DCF!L27 -> 0 | G35: Enterprise Value --> | I35: =IF(Premium_Case="yes",(G13*(1+Premium_Uplift))*$H13,G13*$H13) -> 75.840245 | J35: =IF(Premium_Case="yes",(F13*(1+Premium_Uplift))*$H13,F13*$H13) -> 113.09421 | K35: =IF(Premium_Case="yes",(E13*(1+Premium_Uplift))*$H13,E13*$H13) -> 135.71141 | L35: =IF(Premium_Case="yes",(D13*(1+Premium_Uplift))*$H13,D13*$H13) -> 292.42325 | M35: =IF(Premium_Case="yes",(C13*(1+Premium_Uplift))*$H13,C13*$H13) -> 621.07739
B36: (-)Preferred Stock: | E36: =DCF!L28 -> 0 | G36: Enterprise Value --> | I36: =IF(Premium_Case="yes",(G14*(1+Premium_Uplift))*$H14,G14*$H14) -> 65.412205 | J36: =IF(Premium_Case="yes",(F14*(1+Premium_Uplift))*$H14,F14*$H14) -> 96.46238 | K36: =IF(Premium_Case="yes",(E14*(1+Premium_Uplift))*$H14,E14*$H14) -> 112.812 | L36: =IF(Premium_Case="yes",(D14*(1+Premium_Uplift))*$H14,D14*$H14) -> 244.54476 | M36: =IF(Premium_Case="yes",(C14*(1+Premium_Uplift))*$H14,C14*$H14) -> 433.62196
B37: (-) Operating Leases: | E37: =DCF!L29 -> 0 | G37: Enterprise Value --> | I37: =IF(Premium_Case="yes",(G15*(1+Premium_Uplift))*$H15,G15*$H15) -> 890.47862 | J37: =IF(Premium_Case="yes",(F15*(1+Premium_Uplift))*$H15,F15*$H15) -> 962.95181 | K37: =IF(Premium_Case="yes",(E15*(1+Premium_Uplift))*$H15,E15*$H15) -> 2226.0869 | L37: =IF(Premium_Case="yes",(D15*(1+Premium_Uplift))*$H15,D15*$H15) -> 3831.6919 | M37: =IF(Premium_Case="yes",(C15*(1+Premium_Uplift))*$H15,C15*$H15) -> 4931.5748
B38: (-) Noncontrolling Interests: | E38: =DCF!L30 -> 0 | G38: Enterprise Value --> | I38: =IF(Premium_Case="yes",(G16*(1+Premium_Uplift))*$H16,G16*$H16) -> -216.04059 | J38: =IF(Premium_Case="yes",(F16*(1+Premium_Uplift))*$H16,F16*$H16) -> -408.14432 | K38: =IF(Premium_Case="yes",(E16*(1+Premium_Uplift))*$H16,E16*$H16) -> -579.95784 | L38: =IF(Premium_Case="yes",(D16*(1+Premium_Uplift))*$H16,D16*$H16) -> -762.96767 | M38: =IF(Premium_Case="yes",(C16*(1+Premium_Uplift))*$H16,C16*$H16) -> -1159.9275
B39: (-)Unfunded Pensions: | E39: =DCF!L31 -> 0 | G39: Enterprise Value --> | I39: =IF(Premium_Case="yes",(G17*(1+Premium_Uplift))*$H17,G17*$H17) -> -16.463911 | J39: =IF(Premium_Case="yes",(F17*(1+Premium_Uplift))*$H17,F17*$H17) -> -31.513044 | K39: =IF(Premium_Case="yes",(E17*(1+Premium_Uplift))*$H17,E17*$H17) -> -44.24258 | L39: =IF(Premium_Case="yes",(D17*(1+Premium_Uplift))*$H17,D17*$H17) -> -57.076168 | M39: =IF(Premium_Case="yes",(C17*(1+Premium_Uplift))*$H17,C17*$H17) -> -61.942033
B40: Implied Equity Value: | E40: =SUM(E32:E39) -> 201.587 | G40: Equity Value --> | I40: =IF(Premium_Case="yes",(G18*(1+Premium_Uplift))*$H18,G18*$H18) -> -345.64912 | J40: =IF(Premium_Case="yes",(F18*(1+Premium_Uplift))*$H18,F18*$H18) -> -381.52132 | K40: =IF(Premium_Case="yes",(E18*(1+Premium_Uplift))*$H18,E18*$H18) -> -751.18603 | L40: =IF(Premium_Case="yes",(D18*(1+Premium_Uplift))*$H18,D18*$H18) -> -1109.5988 | M40: =IF(Premium_Case="yes",(C18*(1+Premium_Uplift))*$H18,C18*$H18) -> -1111.7152
G41: Equity Value --> | I41: =IF(Premium_Case="yes",(G19*(1+Premium_Uplift))*$H19,G19*$H19) -> -303.3245 | J41: =IF(Premium_Case="yes",(F19*(1+Premium_Uplift))*$H19,F19*$H19) -> -448.5872 | K41: =IF(Premium_Case="yes",(E19*(1+Premium_Uplift))*$H19,E19*$H19) -> -707.82342 | L41: =IF(Premium_Case="yes",(D19*(1+Premium_Uplift))*$H19,D19*$H19) -> -1145.8395 | M41: =IF(Premium_Case="yes",(C19*(1+Premium_Uplift))*$H19,C19*$H19) -> -1827.4417
B42: Diluted Shares Outstanding: | E42: =Diluted -> 227.39 | G42: Equity Value --> | I42: =IF(Premium_Case="yes",(G20*(1+Premium_Uplift))*$H20,G20*$H20) -> -48.679988 | J42: =IF(Premium_Case="yes",(F20*(1+Premium_Uplift))*$H20,F20*$H20) -> -70.080067 | K42: =IF(Premium_Case="yes",(E20*(1+Premium_Uplift))*$H20,E20*$H20) -> -115.68088 | L42: =IF(Premium_Case="yes",(D20*(1+Premium_Uplift))*$H20,D20*$H20) -> -177.54378 | M42: =IF(Premium_Case="yes",(C20*(1+Premium_Uplift))*$H20,C20*$H20) -> -247.7301
B44: Implied Share Price from DCF: | E44: =E40/E42 -> 0.88652536 | G44: Enterprise Value --> | I44: =+G23*$H23 -> 190.329 | J44: =H23*F23 -> 276.40215 | K44: =H23*E23 -> 376.73351 | L44: =H23*D23 -> 542.83986 | M44: =H23*C23 -> 809.37978
B45: Premium / (Discount) to Current: | E45: =E44/Share_Price-1 -> -0.71028583 | G45: Enterprise Value --> | I45: =+G24*$H24 -> -963.78459 | J45: =H24*F24 -> -1163.2192 | K45: =H24*E24 -> -1260.647 | L45: =H24*D24 -> -1842.3429 | M45: =H24*C24 -> -3494.5821

Sheet ValGraph
W3: =Company_Name&" Valuation - "&Scenario&" Case - Range of Implied Share Prices" -> Butterfly Network, inc. Valuation - Downside Case - Range of Implied Share Prices
E34: Min. | F34: 25th | G34: Median | H34: 75th | I34: Max | K34: Min Point | L34: 25th Point | M34: Median Point | N34: 75th Point | O34: Max Point
B36: (10% - 12% WACC, 4.5% - 7.5% Free Cash Flow Growth Rate | E36: =Valsum!I30 -> 3.833349 | F36: =Valsum!J30 -> 3.918973 | G36: =Valsum!K30 -> 4.0620454 | H36: =Valsum!L30 -> 4.20751 | I36: =Valsum!M30 -> 4.2982616 | K36: =E36 -> 3.833349 | L36: =F36-E36 -> 0.085624009 | M36: =G36-F36 -> 0.14307237 | N36: =H36-G36 -> 0.14546463 | O36: =I36-H36 -> 0.090751652
B37: DCF Output:
B38: =Valsum!B27 -> 1-Month Premiums: | E38: =Valsum!I27 -> 3.4409284 | F38: =Valsum!J27 -> 3.9184551 | G38: =Valsum!K27 -> 4.3203611 | H38: =Valsum!L27 -> 4.5948063 | I38: =Valsum!M27 -> 4.9711191
B39: =Valsum!B26 -> 1-Week Premiums: | E39: =Valsum!I26 -> 3.4912422 | F39: =Valsum!J26 -> 3.6449378 | G39: =Valsum!K26 -> 3.7450659 | H39: =Valsum!L26 -> 4.1508279 | I39: =Valsum!M26 -> 4.7360275 | K39: =+E39 -> 3.4912422 | L39: =+F39-E39 -> 0.15369567 | M39: =+G39-F39 -> 0.10012802 | N39: =+H39-G39 -> 0.40576208 | O39: =+I39-H39 -> 0.58519958
B40: =Valsum!B25 -> 1-Day Premiums: | E40: =Valsum!I25 -> 3.2907762 | F40: =Valsum!J25 -> 3.6181121 | G40: =Valsum!K25 -> 3.789772 | H40: =Valsum!L25 -> 3.8605549 | I40: =Valsum!M25 -> 4.7937337 | K40: =+E40 -> 3.2907762 | L40: =+F40-E40 -> 0.3273359 | M40: =+G40-F40 -> 0.17165988 | N40: =+H40-G40 -> 0.070782939 | O40: =+I40-H40 -> 0.93317873
B41: =Valsum!B24 -> 2025-09-30 EV / EBITDA: | E41: =Valsum!I24 -> -3.8480566 | F41: =Valsum!J24 -> -4.7251165 | G41: =Valsum!K24 -> -5.1535774 | H41: =Valsum!L24 -> -7.7117194 | I41: =Valsum!M24 -> -14.977823 | K41: =E41 -> -3.8480566 | L41: =F41-E41 -> -0.87705994 | M41: =G41-F41 -> -0.42846089 | N41: =H41-G41 -> -2.558142 | O41: =I41-H41 -> -7.2661032
B42: =Valsum!B23 -> 2025-09-30 EV / Revenue: | E42: =Valsum!I23 -> 1.2274242 | F42: =Valsum!J23 -> 1.6059508 | G42: =Valsum!K23 -> 2.0471811 | H42: =Valsum!L23 -> 2.7776721 | I42: =Valsum!M23 -> 3.9498429 | K42: =E42 -> 1.2274242 | L42: =F42-E42 -> 0.37852653 | M42: =G42-F42 -> 0.4412303 | N42: =H42-G42 -> 0.73049101 | O42: =I42-H42 -> 1.1721708
B43: =Valsum!B22 -> Precedent Transactions:
B44: CY 22 P / E: | E44: =Valsum!I20 -> 0.17632707 | F44: =Valsum!J20 -> 0.08221528 | G44: =Valsum!K20 -> -0.11832482 | H44: =Valsum!L20 -> -0.39038118 | I44: =Valsum!M20 -> -0.69904175 | K44: =E44 -> 0.17632707 | L44: =F44-E44 -> -0.094111787 | M44: =G44-F44 -> -0.2005401 | N44: =H44-G44 -> -0.27205636 | O44: =I44-H44 -> -0.30866057
B45: CY 21 P / E: | E45: =Valsum!I19 -> -0.94353093 | F45: =Valsum!J19 -> -1.5823572 | G45: =Valsum!K19 -> -2.7224083 | H45: =Valsum!L19 -> -4.6486849 | I45: =Valsum!M19 -> -7.646188 | K45: =E45 -> -0.94353093 | L45: =F45-E45 -> -0.63882626 | M45: =G45-F45 -> -1.1400511 | N45: =H45-G45 -> -1.9262767 | O45: =I45-H45 -> -2.997503
B46: LTM P / E: | E46: =Valsum!I18 -> -1.1296632 | F46: =Valsum!J18 -> -1.2874195 | G46: =Valsum!K18 -> -2.9131054 | H46: =Valsum!L18 -> -4.4893082 | I46: =Valsum!M18 -> -4.4986155 | K46: =E46 -> -1.1296632 | L46: =F46-E46 -> -0.15775629 | M46: =G46-F46 -> -1.6256859 | N46: =H46-G46 -> -1.5762029 | O46: =I46-H46 -> -0.0093072911
B47: CY 22 TEV / EBITDA: | E47: =Valsum!I17 -> 0.3180047 | F47: =Valsum!J17 -> 0.25182267 | G47: =Valsum!K17 -> 0.1958416 | H47: =Valsum!L17 -> 0.13940293 | I47: =Valsum!M17 -> 0.11800416 | K47: =E47 -> 0.3180047 | L47: =F47-E47 -> -0.066182035 | M47: =G47-F47 -> -0.05598107 | N47: =H47-G47 -> -0.056438668 | O47: =I47-H47 -> -0.021398764
B48: CY 21 TEV / EBITDA: | E48: =Valsum!I16 -> -0.55967978 | F48: =Valsum!J16 -> -1.4045003 | G48: =Valsum!K16 -> -2.1600899 | H48: =Valsum!L16 -> -2.9649179 | I48: =Valsum!M16 -> -4.7106403 | K48: =E48 -> -0.55967978 | L48: =F48-E48 -> -0.84482051 | M48: =G48-F48 -> -0.75558961 | N48: =H48-G48 -> -0.80482795 | O48: =I48-H48 -> -1.7457225
B49: LTM TEV / EBITDA: | E49: =Valsum!I15 -> 4.3064938 | F49: =Valsum!J15 -> 4.6252114 | G49: =Valsum!K15 -> 10.180139 | H49: =Valsum!L15 -> 17.241158 | I49: =Valsum!M15 -> 22.078147 | K49: =E49 -> 4.3064938 | L49: =F49-E49 -> 0.31871759 | M49: =G49-F49 -> 5.5549281 | N49: =H49-G49 -> 7.0610185 | O49: =I49-H49 -> 4.8369888
B50: CY 22 TEV / Revenue: | E50: =Valsum!I14 -> 0.67807382 | F50: =Valsum!J14 -> 0.81462413 | G50: =Valsum!K14 -> 0.88652536 | H50: =Valsum!L14 -> 1.4658506 | I50: =Valsum!M14 -> 2.2973612 | K50: =E50 -> 0.67807382 | L50: =F50-E50 -> 0.13655031 | M50: =G50-F50 -> 0.071901237 | N50: =H50-G50 -> 0.5793252 | O50: =I50-H50 -> 0.83151063
B51: CY 21 TEV / Revenue: | E51: =Valsum!I13 -> 0.72393353 | F51: =Valsum!J13 -> 0.88776644 | G51: =Valsum!K13 -> 0.98723081 | H51: =Valsum!L13 -> 1.6764073 | I51: =Valsum!M13 -> 3.1217397 | K51: =E51 -> 0.72393353 | L51: =F51-E51 -> 0.16383291 | M51: =G51-F51 -> 0.09946437 | N51: =H51-G51 -> 0.68917648 | O51: =I51-H51 -> 1.4453324
B52: LTM TEV / Revenue: | E52: =Valsum!I12 -> 1.3727183 | F52: =Valsum!J12 -> 1.8161721 | G52: =Valsum!K12 -> 2.164295 | H52: =Valsum!L12 -> 2.5335391 | I52: =Valsum!M12 -> 3.8102317 | K52: =E52 -> 1.3727183 | L52: =F52-E52 -> 0.44345386 | M52: =G52-F52 -> 0.34812289 | N52: =H52-G52 -> 0.36924409 | O52: =I52-H52 -> 1.2766926
B53: Comparable Public Companies:
B54: Current Share Price | E54: =Share_Price -> 3.06 | F54: =Share_Price -> 3.06 | G54: =Share_Price -> 3.06 | H54: =Share_Price -> 3.06 | I54: =Share_Price -> 3.06 | K54: 1000 | L54: 0 | M54: 0 | N54: 0 | O54: 0

Sheet PubComps
B2: Comparable Companies – Medical Device and Imaging Technology
B3: ($ USD in Millions Except Per Share Amounts in USD as Stated)
B5: Company Name: | C5: Ticker: | D5: Share Price: | E5: Total Diluted Shares: | F5: Equity Value: | G5: Levered Beta: | H5: Effective Tax Rate: | I5: (-) Cash & Cash-Equivalents: | J5: (+) Debt & Capital Leases: | K5: (+) Preferred Stock: | L5: (+) Noncontrolling Interests: | M5: Enterprise Value: | N5: LTM Revenue: | O5: 2025-12-31 Revenue: | P5: 2026-12-31 Revenue: | Q5: LTM EBITDA: | R5: 2025-12-31 EBITDA: | S5: 2026-12-31 EBITDA: | T5: LTM Reported Net Income: | U5: 2025-12-31 Reported Net Income: | V5: 2026-12-31 Reported Net Income: | W5: Year 1 Projected Revenue Growth: | X5: Year 1 Projected EBITDA Growth: | Y5: LTM EBITDA Margin: | Z5: 2025-12-31 EBITDA Margin: | AA5: 2026-12-31 EBITDA Margin:
B6: Operating Statistics: | F6: Capitalization | W6: Projected | X6: Projected
D7: Share | E7: Diluted | F7: Equity | L7: Other & | M7: Enterprise | N7: Revenue | Q7: EBITDA | T7: Net Income | W7: Revenue | X7: EBITDA | Y7: EBITDA Margin
B8: Company Name | C8: Ticker | D8: Price | E8: Shares | F8: Value | G8: Beta | H8: Tax Rate | I8: Cash | J8: Debt | K8: Preferred | L8: NCI | M8: Value | N8: LTM | O8: 46022 | P8: =EOMONTH(O8,12) -> 46387 | Q8: =$N$8 -> LTM | R8: =+$O$8 -> 46022 | S8: =+$P$8 -> 46387 | T8: =$N$8 -> LTM | U8: =+$O$8 -> 46022 | V8: =+$P$8 -> 46387 | W8: Growth | X8: Growth | Y8: =$N$8 -> LTM | Z8: =+$O$8 -> 46022 | AA8: =+$P$8 -> 46387
B9: =INDEX(Pub_Comps_Range,MATCH(B$5,Pub_Comps_Params,0),MATCH($C9,Pub_Comps_Tickers,0)) -> GE Healthcare Technologies Inc. | C9: GEHC | D9: =INDEX(Pub_Comps_Range,MATCH(D$5,Pub_Comps_Params,0),MATCH($C9,Pub_Comps_Tickers,0)) -> 85.46 | E9: =INDEX(Pub_Comps_Range,MATCH(E$5,Pub_Comps_Params,0),MATCH($C9,Pub_Comps_Tickers,0)) -> 455.5 | F9: =INDEX(Pub_Comps_Range,MATCH(F$5,Pub_Comps_Params,0),MATCH($C9,Pub_Comps_Tickers,0)) -> 38927.03 | G9: =INDEX(Pub_Comps_Range,MATCH(G$5,Pub_Comps_Params,0),MATCH($C9,Pub_Comps_Tickers,0)) -> 1.27 | H9: =INDEX(Pub_Comps_Range,MATCH(H$5,Pub_Comps_Params,0),MATCH($C9,Pub_Comps_Tickers,0)) -> 0.177 | I9: =INDEX(Pub_Comps_Range,MATCH(I$5,Pub_Comps_Params,0),MATCH($C9,Pub_Comps_Tickers,0)) -> -4005 | J9: =INDEX(Pub_Comps_Range,MATCH(J$5,Pub_Comps_Params,0),MATCH($C9,Pub_Comps_Tickers,0)) -> 10744 | K9: =INDEX(Pub_Comps_Range,MATCH(K$5,Pub_Comps_Params,0),MATCH($C9,Pub_Comps_Tickers,0)) -> 0 | ... AA9: =INDEX(Pub_Comps_Range,MATCH(AA$5,Pub_Comps_Params,0),MATCH($C9,Pub_Comps_Tickers,0)) -> 0.18292512
B10: =INDEX(Pub_Comps_Range,MATCH(B$5,Pub_Comps_Params,0),MATCH($C10,Pub_Comps_Tickers,0)) -> Masimo Corporation | C10: MASI | D10: =INDEX(Pub_Comps_Range,MATCH(D$5,Pub_Comps_Params,0),MATCH($C10,Pub_Comps_Tickers,0)) -> 141.68 | E10: =INDEX(Pub_Comps_Range,MATCH(E$5,Pub_Comps_Params,0),MATCH($C10,Pub_Comps_Tickers,0)) -> 54.5 | F10: =INDEX(Pub_Comps_Range,MATCH(F$5,Pub_Comps_Params,0),MATCH($C10,Pub_Comps_Tickers,0)) -> 7721.56 | G10: =INDEX(Pub_Comps_Range,MATCH(G$5,Pub_Comps_Params,0),MATCH($C10,Pub_Comps_Tickers,0)) -> 1.26 | H10: =INDEX(Pub_Comps_Range,MATCH(H$5,Pub_Comps_Params,0),MATCH($C10,Pub_Comps_Tickers,0)) -> 0.2 | I10: =INDEX(Pub_Comps_Range,MATCH(I$5,Pub_Comps_Params,0),MATCH($C10,Pub_Comps_Tickers,0)) -> -149.6 | J10: =INDEX(Pub_Comps_Range,MATCH(J$5,Pub_Comps_Params,0),MATCH($C10,Pub_Comps_Tickers,0)) -> 642.2 | K10: =INDEX(Pub_Comps_Range,MATCH(K$5,Pub_Comps_Params,0),MATCH($C10,Pub_Comps_Tickers,0)) -> 0 | ... AA10: =INDEX(Pub_Comps_Range,MATCH(AA$5,Pub_Comps_Params,0),MATCH($C10,Pub_Comps_Tickers,0)) -> 0.3319097
B11: =INDEX(Pub_Comps_Range,MATCH(B$5,Pub_Comps_Params,0),MATCH($C11,Pub_Comps_Tickers,0)) -> InMode, Ltd. | C11: INMD | D11: =INDEX(Pub_Comps_Range,MATCH(D$5,Pub_Comps_Params,0),MATCH($C11,Pub_Comps_Tickers,0)) -> 14.42 | E11: =INDEX(Pub_Comps_Range,MATCH(E$5,Pub_Comps_Params,0),MATCH($C11,Pub_Comps_Tickers,0)) -> 65.5 | F11: =INDEX(Pub_Comps_Range,MATCH(F$5,Pub_Comps_Params,0),MATCH($C11,Pub_Comps_Tickers,0)) -> 944.51 | G11: =INDEX(Pub_Comps_Range,MATCH(G$5,Pub_Comps_Params,0),MATCH($C11,Pub_Comps_Tickers,0)) -> 2.15 | H11: =INDEX(Pub_Comps_Range,MATCH(H$5,Pub_Comps_Params,0),MATCH($C11,Pub_Comps_Tickers,0)) -> 0.2 | I11: =INDEX(Pub_Comps_Range,MATCH(I$5,Pub_Comps_Params,0),MATCH($C11,Pub_Comps_Tickers,0)) -> -510.7 | J11: =INDEX(Pub_Comps_Range,MATCH(J$5,Pub_Comps_Params,0),MATCH($C11,Pub_Comps_Tickers,0)) -> 6.1 | K11: =INDEX(Pub_Comps_Range,MATCH(K$5,Pub_Comps_Params,0),MATCH($C11,Pub_Comps_Tickers,0)) -> 0 | ... AA11: =INDEX(Pub_Comps_Range,MATCH(AA$5,Pub_Comps_Params,0),MATCH($C11,Pub_Comps_Tickers,0)) -> 0.26370757
B12: =INDEX(Pub_Comps_Range,MATCH(B$5,Pub_Comps_Params,0),MATCH($C12,Pub_Comps_Tickers,0)) -> Integra LifeSciences Holdings Corporation | C12: IART | D12: =INDEX(Pub_Comps_Range,MATCH(D$5,Pub_Comps_Params,0),MATCH($C12,Pub_Comps_Tickers,0)) -> 13.24 | E12: =INDEX(Pub_Comps_Range,MATCH(E$5,Pub_Comps_Params,0),MATCH($C12,Pub_Comps_Tickers,0)) -> 78.274706 | F12: =INDEX(Pub_Comps_Range,MATCH(F$5,Pub_Comps_Params,0),MATCH($C12,Pub_Comps_Tickers,0)) -> 1036.3571 | G12: =INDEX(Pub_Comps_Range,MATCH(G$5,Pub_Comps_Params,0),MATCH($C12,Pub_Comps_Tickers,0)) -> 1.08 | H12: =INDEX(Pub_Comps_Range,MATCH(H$5,Pub_Comps_Params,0),MATCH($C12,Pub_Comps_Tickers,0)) -> 0.2 | I12: =INDEX(Pub_Comps_Range,MATCH(I$5,Pub_Comps_Params,0),MATCH($C12,Pub_Comps_Tickers,0)) -> -267.9 | J12: =INDEX(Pub_Comps_Range,MATCH(J$5,Pub_Comps_Params,0),MATCH($C12,Pub_Comps_Tickers,0)) -> 2007.7 | K12: =INDEX(Pub_Comps_Range,MATCH(K$5,Pub_Comps_Params,0),MATCH($C12,Pub_Comps_Tickers,0)) -> 0 | ... AA12: =INDEX(Pub_Comps_Range,MATCH(AA$5,Pub_Comps_Params,0),MATCH($C12,Pub_Comps_Tickers,0)) -> 0.19809637
B13: =INDEX(Pub_Comps_Range,MATCH(B$5,Pub_Comps_Params,0),MATCH($C13,Pub_Comps_Tickers,0)) -> CureVac N.V. | C13: CVAC | D13: =INDEX(Pub_Comps_Range,MATCH(D$5,Pub_Comps_Params,0),MATCH($C13,Pub_Comps_Tickers,0)) -> 5.12 | E13: =INDEX(Pub_Comps_Range,MATCH(E$5,Pub_Comps_Params,0),MATCH($C13,Pub_Comps_Tickers,0)) -> 227.55744 | F13: =INDEX(Pub_Comps_Range,MATCH(F$5,Pub_Comps_Params,0),MATCH($C13,Pub_Comps_Tickers,0)) -> 1165.0941 | G13: =INDEX(Pub_Comps_Range,MATCH(G$5,Pub_Comps_Params,0),MATCH($C13,Pub_Comps_Tickers,0)) -> 1.78 | H13: =INDEX(Pub_Comps_Range,MATCH(H$5,Pub_Comps_Params,0),MATCH($C13,Pub_Comps_Tickers,0)) -> 0.121 | I13: =INDEX(Pub_Comps_Range,MATCH(I$5,Pub_Comps_Params,0),MATCH($C13,Pub_Comps_Tickers,0)) -> -452.8 | J13: =INDEX(Pub_Comps_Range,MATCH(J$5,Pub_Comps_Params,0),MATCH($C13,Pub_Comps_Tickers,0)) -> 41.5 | K13: =INDEX(Pub_Comps_Range,MATCH(K$5,Pub_Comps_Params,0),MATCH($C13,Pub_Comps_Tickers,0)) -> 0 | ... AA13: =INDEX(Pub_Comps_Range,MATCH(AA$5,Pub_Comps_Params,0),MATCH($C13,Pub_Comps_Tickers,0)) -> -1.3131313
B14: =INDEX(Pub_Comps_Range,MATCH(B$5,Pub_Comps_Params,0),MATCH($C14,Pub_Comps_Tickers,0)) -> CareDx, Inc | C14: CDNA | D14: =INDEX(Pub_Comps_Range,MATCH(D$5,Pub_Comps_Params,0),MATCH($C14,Pub_Comps_Tickers,0)) -> 18.53 | E14: =INDEX(Pub_Comps_Range,MATCH(E$5,Pub_Comps_Params,0),MATCH($C14,Pub_Comps_Tickers,0)) -> 53.2 | F14: =INDEX(Pub_Comps_Range,MATCH(F$5,Pub_Comps_Params,0),MATCH($C14,Pub_Comps_Tickers,0)) -> 985.796 | G14: =INDEX(Pub_Comps_Range,MATCH(G$5,Pub_Comps_Params,0),MATCH($C14,Pub_Comps_Tickers,0)) -> 2.56 | H14: =INDEX(Pub_Comps_Range,MATCH(H$5,Pub_Comps_Params,0),MATCH($C14,Pub_Comps_Tickers,0)) -> 0.005 | I14: =INDEX(Pub_Comps_Range,MATCH(I$5,Pub_Comps_Params,0),MATCH($C14,Pub_Comps_Tickers,0)) -> -186.3 | J14: =INDEX(Pub_Comps_Range,MATCH(J$5,Pub_Comps_Params,0),MATCH($C14,Pub_Comps_Tickers,0)) -> 29.1 | K14: =INDEX(Pub_Comps_Range,MATCH(K$5,Pub_Comps_Params,0),MATCH($C14,Pub_Comps_Tickers,0)) -> 0 | ... AA14: =INDEX(Pub_Comps_Range,MATCH(AA$5,Pub_Comps_Params,0),MATCH($C14,Pub_Comps_Tickers,0)) -> 0.11111111
B15: Maximum | D15: =MAX(D9:D13) -> 141.68 | F15: =MAX(F9:F13) -> 38927.03 | M15: =MAX(M9:M13) -> 45893.03 | N15: =MAX(N9:N13) -> 20246 | O15: =MAX(O9:O13) -> 20530 | P15: =MAX(P9:P13) -> 21435 | Q15: =MAX(Q9:Q13) -> 3429 | R15: =MAX(R9:R13) -> 3653 | S15: =MAX(S9:S13) -> 3921 | T15: =MAX(T9:T13) -> 2290 | ... AA15: =MAX(AA9:AA13) -> 0.3319097
B16: 75th Percentile | D16: =QUARTILE(D9:D13,3) -> 85.46 | F16: =QUARTILE(F9:F13,3) -> 7721.56 | M16: =QUARTILE(M9:M13,3) -> 8214.16 | N16: =QUARTILE(N9:N13,3) -> 2153.8 | O16: =QUARTILE(O9:O13,3) -> 1637 | P16: =QUARTILE(P9:P13,3) -> 1681 | Q16: =QUARTILE(Q9:Q13,3) -> 219.16 | R16: =QUARTILE(R9:R13,3) -> 497 | S16: =QUARTILE(S9:S13,3) -> 544 | T16: =QUARTILE(T9:T13,3) -> 193.65 | ... AA16: =QUARTILE(AA9:AA13,3) -> 0.26370757
B17: Median | D17: =MEDIAN(D9:D13) -> 14.42 | F17: =MEDIAN(F9:F13) -> 1165.0941 | M17: =MEDIAN(M9:M13) -> 2776.1571 | N17: =MEDIAN(N9:N13) -> 1642.97 | O17: =MEDIAN(O9:O13) -> 1521 | P17: =MEDIAN(P9:P13) -> 1639 | Q17: =MEDIAN(Q9:Q13) -> 115.38 | R17: =MEDIAN(R9:R13) -> 314 | S17: =MEDIAN(S9:S13) -> 333 | T17: =MEDIAN(T9:T13) -> 178.71 | ... AA17: =MEDIAN(AA9:AA13) -> 0.19809637
B18: 25th Percentile | D18: =QUARTILE(D9:D13,1) -> 13.24 | F18: =QUARTILE(F9:F13,1) -> 1036.3571 | M18: =QUARTILE(M9:M13,1) -> 753.7941 | N18: =QUARTILE(N9:N13,1) -> 484.2 | O18: =QUARTILE(O9:O13,1) -> 368 | P18: =QUARTILE(P9:P13,1) -> 383 | Q18: =QUARTILE(Q9:Q13,1) -> -177.2 | R18: =QUARTILE(R9:R13,1) -> 94 | S18: =QUARTILE(S9:S13,1) -> 101 | T18: =QUARTILE(T9:T13,1) -> -459.2 | ... AA18: =QUARTILE(AA9:AA13,1) -> 0.18292512
B19: Minimum | D19: =MIN(D9:D13) -> 5.12 | F19: =MIN(F9:F13) -> 944.51 | M19: =MIN(M9:M13) -> 439.91 | N19: =MIN(N9:N13) -> 401.57 | O19: =MIN(O9:O13) -> 77 | P19: =MIN(P9:P13) -> 99 | Q19: =MIN(Q9:Q13) -> -313.56 | R19: =MIN(R9:R13) -> -129 | S19: =MIN(S9:S13) -> -130 | T19: =MIN(T9:T13) -> -495.33 | ... AA19: =MIN(AA9:AA13) -> -1.3131313
B21: =INDEX(Pub_Comps_Range,MATCH(B$5,Pub_Comps_Params,0),MATCH($C21,Pub_Comps_Tickers,0)) -> Butterfly Network, inc. | C21: =Ticker -> BFLY | D21: =Share_Price -> 3.06 | E21: =INDEX(Pub_Comps_Range,MATCH(E$5,Pub_Comps_Params,0),MATCH($C21,Pub_Comps_Tickers,0)) -> 227.978 | F21: =INDEX(Pub_Comps_Range,MATCH(F$5,Pub_Comps_Params,0),MATCH($C21,Pub_Comps_Tickers,0)) -> 697.61268 | G21: =INDEX(Pub_Comps_Range,MATCH(G$5,Pub_Comps_Params,0),MATCH($C21,Pub_Comps_Tickers,0)) -> 2.24 | H21: =INDEX(Pub_Comps_Range,MATCH(H$5,Pub_Comps_Params,0),MATCH($C21,Pub_Comps_Tickers,0)) -> 0.12 | I21: =INDEX(Pub_Comps_Range,MATCH(I$5,Pub_Comps_Params,0),MATCH($C21,Pub_Comps_Tickers,0)) -> -88.775 | J21: =INDEX(Pub_Comps_Range,MATCH(J$5,Pub_Comps_Params,0),MATCH($C21,Pub_Comps_Tickers,0)) -> 0 | K21: =INDEX(Pub_Comps_Range,MATCH(K$5,Pub_Comps_Params,0),MATCH($C21,Pub_Comps_Tickers,0)) -> 0 | L21: =INDEX(Pub_Comps_Range,MATCH(L$5,Pub_Comps_Params,0),MATCH($C21,Pub_Comps_Tickers,0)) -> 0 | ... V21: =INDEX(Pub_Comps_Range,MATCH(V$5,Pub_Comps_Params,0),MATCH($C21,Pub_Comps_Tickers,0)) -> -8.5019708 | W21: =MIN(W10:W15) -> 0.026878436 | X21: =MIN(X10:X15) -> 0.007751938 | Y21: =MIN(Y10:Y15) -> -0.1908495 | Z21: =MIN(Z10:Z15) -> -1.6753247 | AA21: =MIN(AA10:AA15) -> -1.3131313
B23: Company Name: | C23: Ticker: | D23: Share Price: | F23: Equity Value: | M23: Enterprise Value: | N23: LTM EV / Revenue: | O23: 2025-12-31 EV / Revenue: | P23: 2026-12-31 EV / Revenue: | Q23: LTM EV / EBITDA: | R23: 2025-12-31 EV / EBITDA: | S23: 2026-12-31 EV / EBITDA: | T23: LTM P / E: | U23: 2025-12-31 P / E: | V23: 2026-12-31 P / E:
B24: Valuation Statistics: | F24: Capitalization | N24: Enterprise Value / | Q24: Enterprise Value /
F25: Equity | M25: Enterprise | N25: Revenue | Q25: EBITDA | T25: P / E Multiple
B26: Company Name | F26: Value | M26: Value | N26: =$N$8 -> LTM | O26: =+$O$8 -> 46022 | P26: =+$P$8 -> 46387 | Q26: =$N$8 -> LTM | R26: =+$O$8 -> 46022 | S26: =+$P$8 -> 46387 | T26: =$N$8 -> LTM | U26: =+$O$8 -> 46022 | V26: =+$P$8 -> 46387
B27: =INDEX(Pub_Comps_Range,MATCH(B$23,Pub_Comps_Params,0),MATCH($C27,Pub_Comps_Tickers,0)) -> GE Healthcare Technologies Inc. | C27: GEHC | D27: =INDEX(Pub_Comps_Range,MATCH(D$23,Pub_Comps_Params,0),MATCH($C27,Pub_Comps_Tickers,0)) -> 85.46 | F27: =INDEX(Pub_Comps_Range,MATCH(F$23,Pub_Comps_Params,0),MATCH($C27,Pub_Comps_Tickers,0)) -> 38927.03 | M27: =INDEX(Pub_Comps_Range,MATCH(M$23,Pub_Comps_Params,0),MATCH($C27,Pub_Comps_Tickers,0)) -> 45893.03 | N27: =INDEX(Pub_Comps_Range,MATCH(N$23,Pub_Comps_Params,0),MATCH($C27,Pub_Comps_Tickers,0)) -> 2.2667702 | O27: =INDEX(Pub_Comps_Range,MATCH(O$23,Pub_Comps_Params,0),MATCH($C27,Pub_Comps_Tickers,0)) -> 2.2354131 | P27: =INDEX(Pub_Comps_Range,MATCH(P$23,Pub_Comps_Params,0),MATCH($C27,Pub_Comps_Tickers,0)) -> 2.1410324 | Q27: =INDEX(Pub_Comps_Range,MATCH(Q$23,Pub_Comps_Params,0),MATCH($C27,Pub_Comps_Tickers,0)) -> 13.383794 | R27: =INDEX(Pub_Comps_Range,MATCH(R$23,Pub_Comps_Params,0),MATCH($C27,Pub_Comps_Tickers,0)) -> 12.563107 | S27: =INDEX(Pub_Comps_Range,MATCH(S$23,Pub_Comps_Params,0),MATCH($C27,Pub_Comps_Tickers,0)) -> 11.70442 | T27: =INDEX(Pub_Comps_Range,MATCH(T$23,Pub_Comps_Params,0),MATCH($C27,Pub_Comps_Tickers,0)) -> 16.998703 | ... V27: =INDEX(Pub_Comps_Range,MATCH(V$23,Pub_Comps_Params,0),MATCH($C27,Pub_Comps_Tickers,0)) -> 18.130894
B28: =INDEX(Pub_Comps_Range,MATCH(B$23,Pub_Comps_Params,0),MATCH($C28,Pub_Comps_Tickers,0)) -> Masimo Corporation | C28: MASI | D28: =INDEX(Pub_Comps_Range,MATCH(D$23,Pub_Comps_Params,0),MATCH($C28,Pub_Comps_Tickers,0)) -> 141.68 | F28: =INDEX(Pub_Comps_Range,MATCH(F$23,Pub_Comps_Params,0),MATCH($C28,Pub_Comps_Tickers,0)) -> 7721.56 | M28: =INDEX(Pub_Comps_Range,MATCH(M$23,Pub_Comps_Params,0),MATCH($C28,Pub_Comps_Tickers,0)) -> 8214.16 | N28: =INDEX(Pub_Comps_Range,MATCH(N$23,Pub_Comps_Params,0),MATCH($C28,Pub_Comps_Tickers,0)) -> 3.8137989 | O28: =INDEX(Pub_Comps_Range,MATCH(O$23,Pub_Comps_Params,0),MATCH($C28,Pub_Comps_Tickers,0)) -> 5.4004997 | P28: =INDEX(Pub_Comps_Range,MATCH(P$23,Pub_Comps_Params,0),MATCH($C28,Pub_Comps_Tickers,0)) -> 5.0116901 | Q28: =INDEX(Pub_Comps_Range,MATCH(Q$23,Pub_Comps_Params,0),MATCH($C28,Pub_Comps_Tickers,0)) -> NM | R28: =INDEX(Pub_Comps_Range,MATCH(R$23,Pub_Comps_Params,0),MATCH($C28,Pub_Comps_Tickers,0)) -> 16.527485 | S28: =INDEX(Pub_Comps_Range,MATCH(S$23,Pub_Comps_Params,0),MATCH($C28,Pub_Comps_Tickers,0)) -> 15.099559 | T28: =INDEX(Pub_Comps_Range,MATCH(T$23,Pub_Comps_Params,0),MATCH($C28,Pub_Comps_Tickers,0)) -> NM | ... V28: =INDEX(Pub_Comps_Range,MATCH(V$23,Pub_Comps_Params,0),MATCH($C28,Pub_Comps_Tickers,0)) -> 29.137962
B29: =INDEX(Pub_Comps_Range,MATCH(B$23,Pub_Comps_Params,0),MATCH($C29,Pub_Comps_Tickers,0)) -> InMode, Ltd. | C29: INMD | D29: =INDEX(Pub_Comps_Range,MATCH(D$23,Pub_Comps_Params,0),MATCH($C29,Pub_Comps_Tickers,0)) -> 14.42 | F29: =INDEX(Pub_Comps_Range,MATCH(F$23,Pub_Comps_Params,0),MATCH($C29,Pub_Comps_Tickers,0)) -> 944.51 | M29: =INDEX(Pub_Comps_Range,MATCH(M$23,Pub_Comps_Params,0),MATCH($C29,Pub_Comps_Tickers,0)) -> 439.91 | N29: =INDEX(Pub_Comps_Range,MATCH(N$23,Pub_Comps_Params,0),MATCH($C29,Pub_Comps_Tickers,0)) -> 1.0954753 | O29: =INDEX(Pub_Comps_Range,MATCH(O$23,Pub_Comps_Params,0),MATCH($C29,Pub_Comps_Tickers,0)) -> 1.1954076 | P29: =INDEX(Pub_Comps_Range,MATCH(P$23,Pub_Comps_Params,0),MATCH($C29,Pub_Comps_Tickers,0)) -> 1.1485901 | Q29: =INDEX(Pub_Comps_Range,MATCH(Q$23,Pub_Comps_Params,0),MATCH($C29,Pub_Comps_Tickers,0)) -> 3.8127058 | R29: =INDEX(Pub_Comps_Range,MATCH(R$23,Pub_Comps_Params,0),MATCH($C29,Pub_Comps_Tickers,0)) -> 4.6798936 | S29: =INDEX(Pub_Comps_Range,MATCH(S$23,Pub_Comps_Params,0),MATCH($C29,Pub_Comps_Tickers,0)) -> 4.3555446 | T29: =INDEX(Pub_Comps_Range,MATCH(T$23,Pub_Comps_Params,0),MATCH($C29,Pub_Comps_Tickers,0)) -> 5.2851547 | ... V29: =INDEX(Pub_Comps_Range,MATCH(V$23,Pub_Comps_Params,0),MATCH($C29,Pub_Comps_Tickers,0)) -> 9.0818269
B30: =INDEX(Pub_Comps_Range,MATCH(B$23,Pub_Comps_Params,0),MATCH($C30,Pub_Comps_Tickers,0)) -> Integra LifeSciences Holdings Corporation | C30: IART | D30: =INDEX(Pub_Comps_Range,MATCH(D$23,Pub_Comps_Params,0),MATCH($C30,Pub_Comps_Tickers,0)) -> 13.24 | F30: =INDEX(Pub_Comps_Range,MATCH(F$23,Pub_Comps_Params,0),MATCH($C30,Pub_Comps_Tickers,0)) -> 1036.3571 | M30: =INDEX(Pub_Comps_Range,MATCH(M$23,Pub_Comps_Params,0),MATCH($C30,Pub_Comps_Tickers,0)) -> 2776.1571 | N30: =INDEX(Pub_Comps_Range,MATCH(N$23,Pub_Comps_Params,0),MATCH($C30,Pub_Comps_Tickers,0)) -> 1.6897187 | O30: =INDEX(Pub_Comps_Range,MATCH(O$23,Pub_Comps_Params,0),MATCH($C30,Pub_Comps_Tickers,0)) -> 1.6958809 | P30: =INDEX(Pub_Comps_Range,MATCH(P$23,Pub_Comps_Params,0),MATCH($C30,Pub_Comps_Tickers,0)) -> 1.6514914 | Q30: =INDEX(Pub_Comps_Range,MATCH(Q$23,Pub_Comps_Params,0),MATCH($C30,Pub_Comps_Tickers,0)) -> NM | R30: =INDEX(Pub_Comps_Range,MATCH(R$23,Pub_Comps_Params,0),MATCH($C30,Pub_Comps_Tickers,0)) -> 8.8412647 | S30: =INDEX(Pub_Comps_Range,MATCH(S$23,Pub_Comps_Params,0),MATCH($C30,Pub_Comps_Tickers,0)) -> 8.3368081 | T30: =INDEX(Pub_Comps_Range,MATCH(T$23,Pub_Comps_Params,0),MATCH($C30,Pub_Comps_Tickers,0)) -> NM | ... V30: =INDEX(Pub_Comps_Range,MATCH(V$23,Pub_Comps_Params,0),MATCH($C30,Pub_Comps_Tickers,0)) -> 5.7257299
B31: =INDEX(Pub_Comps_Range,MATCH(B$23,Pub_Comps_Params,0),MATCH($C31,Pub_Comps_Tickers,0)) -> CureVac N.V. | C31: CVAC | D31: =INDEX(Pub_Comps_Range,MATCH(D$23,Pub_Comps_Params,0),MATCH($C31,Pub_Comps_Tickers,0)) -> 5.12 | F31: =INDEX(Pub_Comps_Range,MATCH(F$23,Pub_Comps_Params,0),MATCH($C31,Pub_Comps_Tickers,0)) -> 1165.0941 | M31: =INDEX(Pub_Comps_Range,MATCH(M$23,Pub_Comps_Params,0),MATCH($C31,Pub_Comps_Tickers,0)) -> 753.7941 | N31: =INDEX(Pub_Comps_Range,MATCH(N$23,Pub_Comps_Params,0),MATCH($C31,Pub_Comps_Tickers,0)) -> 1.5567825 | O31: =INDEX(Pub_Comps_Range,MATCH(O$23,Pub_Comps_Params,0),MATCH($C31,Pub_Comps_Tickers,0)) -> 9.7895338 | P31: =INDEX(Pub_Comps_Range,MATCH(P$23,Pub_Comps_Params,0),MATCH($C31,Pub_Comps_Tickers,0)) -> 7.6140819 | Q31: =INDEX(Pub_Comps_Range,MATCH(Q$23,Pub_Comps_Params,0),MATCH($C31,Pub_Comps_Tickers,0)) -> 3.4394694 | R31: =INDEX(Pub_Comps_Range,MATCH(R$23,Pub_Comps_Params,0),MATCH($C31,Pub_Comps_Tickers,0)) -> NM | S31: =INDEX(Pub_Comps_Range,MATCH(S$23,Pub_Comps_Params,0),MATCH($C31,Pub_Comps_Tickers,0)) -> NM | T31: =INDEX(Pub_Comps_Range,MATCH(T$23,Pub_Comps_Params,0),MATCH($C31,Pub_Comps_Tickers,0)) -> 6.0164942 | ... V31: =INDEX(Pub_Comps_Range,MATCH(V$23,Pub_Comps_Params,0),MATCH($C31,Pub_Comps_Tickers,0)) -> NM
B32: =INDEX(Pub_Comps_Range,MATCH(B$23,Pub_Comps_Params,0),MATCH($C32,Pub_Comps_Tickers,0)) -> CareDx, Inc | C32: CDNA | D32: =INDEX(Pub_Comps_Range,MATCH(D$23,Pub_Comps_Params,0),MATCH($C32,Pub_Comps_Tickers,0)) -> 18.53 | F32: =INDEX(Pub_Comps_Range,MATCH(F$23,Pub_Comps_Params,0),MATCH($C32,Pub_Comps_Tickers,0)) -> 985.796 | M32: =INDEX(Pub_Comps_Range,MATCH(M$23,Pub_Comps_Params,0),MATCH($C32,Pub_Comps_Tickers,0)) -> 828.596 | N32: =INDEX(Pub_Comps_Range,MATCH(N$23,Pub_Comps_Params,0),MATCH($C32,Pub_Comps_Tickers,0)) -> 2.4311123 | O32: =INDEX(Pub_Comps_Range,MATCH(O$23,Pub_Comps_Params,0),MATCH($C32,Pub_Comps_Tickers,0)) -> 2.0428025 | P32: =INDEX(Pub_Comps_Range,MATCH(P$23,Pub_Comps_Params,0),MATCH($C32,Pub_Comps_Tickers,0)) -> 1.8207587 | Q32: =INDEX(Pub_Comps_Range,MATCH(Q$23,Pub_Comps_Params,0),MATCH($C32,Pub_Comps_Tickers,0)) -> 19.048184 | R32: =INDEX(Pub_Comps_Range,MATCH(R$23,Pub_Comps_Params,0),MATCH($C32,Pub_Comps_Tickers,0)) -> 25.12647 | S32: =INDEX(Pub_Comps_Range,MATCH(S$23,Pub_Comps_Params,0),MATCH($C32,Pub_Comps_Tickers,0)) -> 16.386828 | T32: =INDEX(Pub_Comps_Range,MATCH(T$23,Pub_Comps_Params,0),MATCH($C32,Pub_Comps_Tickers,0)) -> 16.955556 | ... V32: =INDEX(Pub_Comps_Range,MATCH(V$23,Pub_Comps_Params,0),MATCH($C32,Pub_Comps_Tickers,0)) -> NM
B34: Maximum | F34: =MAX(F27:F32) -> 38927.03 | M34: =MAX(M27:M32) -> 45893.03 | N34: =MAX(N27:N32) -> 3.8137989 | O34: =MAX(O27:O32) -> 9.7895338 | P34: =MAX(P27:P32) -> 7.6140819 | Q34: =MAX(Q27:Q32) -> 19.048184 | R34: =MAX(R27:R32) -> 25.12647 | S34: =MAX(S27:S32) -> 16.386828 | T34: =MAX(T27:T32) -> 16.998703 | ... V34: =MAX(V27:V32) -> 29.137962
B35: 75th Percentile | F35: =QUARTILE(F27:F32,3) -> 6082.4435 | M35: =QUARTILE(M27:M32,3) -> 6854.6593 | N35: =QUARTILE(N27:N32,3) -> 2.3900268 | O35: =QUARTILE(O27:O32,3) -> 4.609228 | P35: =QUARTILE(P27:P32,3) -> 4.2940256 | Q35: =QUARTILE(Q27:Q32,3) -> 14.799892 | R35: =QUARTILE(R27:R32,3) -> 16.527485 | S35: =QUARTILE(S27:S32,3) -> 15.099559 | T35: =QUARTILE(T27:T32,3) -> 16.966342 | ... V35: =QUARTILE(V27:V32,3) -> 20.882661
B36: Median | F36: =MEDIAN(F27:F32) -> 1100.7256 | M36: =MEDIAN(M27:M32) -> 1802.3766 | N36: =MEDIAN(N27:N32) -> 1.9782445 | O36: =MEDIAN(O27:O32) -> 2.1391078 | P36: =MEDIAN(P27:P32) -> 1.9808956 | Q36: =MEDIAN(Q27:Q32) -> 8.59825 | R36: =MEDIAN(R27:R32) -> 12.563107 | S36: =MEDIAN(S27:S32) -> 11.70442 | T36: =MEDIAN(T27:T32) -> 11.486025 | ... V36: =MEDIAN(V27:V32) -> 13.606361
B37: 25th Percentile | F37: =QUARTILE(F27:F32,1) -> 998.43628 | M37: =QUARTILE(M27:M32,1) -> 772.49458 | N37: =QUARTILE(N27:N32,1) -> 1.5900166 | O37: =QUARTILE(O27:O32,1) -> 1.7826113 | P37: =QUARTILE(P27:P32,1) -> 1.6938083 | Q37: =QUARTILE(Q27:Q32,1) -> 3.7193967 | R37: =QUARTILE(R27:R32,1) -> 8.8412647 | S37: =QUARTILE(S27:S32,1) -> 8.3368081 | T37: =QUARTILE(T27:T32,1) -> 5.8336593 | ... V37: =QUARTILE(V27:V32,1) -> 8.2428027
B38: Minimum | F38: =MIN(F27:F32) -> 944.51 | M38: =MIN(M27:M32) -> 439.91 | N38: =MIN(N27:N32) -> 1.0954753 | O38: =MIN(O27:O32) -> 1.1954076 | P38: =MIN(P27:P32) -> 1.1485901 | Q38: =MIN(Q27:Q32) -> 3.4394694 | R38: =MIN(R27:R32) -> 4.6798936 | S38: =MIN(S27:S32) -> 4.3555446 | T38: =MIN(T27:T32) -> 5.2851547 | ... V38: =MIN(V27:V32) -> 5.7257299
B40: =INDEX(Pub_Comps_Range,MATCH(B$23,Pub_Comps_Params,0),MATCH($C40,Pub_Comps_Tickers,0)) -> Butterfly Network, inc. | C40: =Ticker -> BFLY | F40: =INDEX(Pub_Comps_Range,MATCH(F$23,Pub_Comps_Params,0),MATCH($C40,Pub_Comps_Tickers,0)) -> 697.61268 | M40: =INDEX(Pub_Comps_Range,MATCH(M$23,Pub_Comps_Params,0),MATCH($C40,Pub_Comps_Tickers,0)) -> 608.83768 | N40: =INDEX(Pub_Comps_Range,MATCH(N$23,Pub_Comps_Params,0),MATCH($C40,Pub_Comps_Tickers,0)) -> 2.9859621 | O40: =INDEX(Pub_Comps_Range,MATCH(O$23,Pub_Comps_Params,0),MATCH($C40,Pub_Comps_Tickers,0)) -> 9.5966092 | P40: =INDEX(Pub_Comps_Range,MATCH(P$23,Pub_Comps_Params,0),MATCH($C40,Pub_Comps_Tickers,0)) -> 10.690741 | Q40: =INDEX(Pub_Comps_Range,MATCH(Q$23,Pub_Comps_Params,0),MATCH($C40,Pub_Comps_Tickers,0)) -> 2.3516326 | R40: =INDEX(Pub_Comps_Range,MATCH(R$23,Pub_Comps_Params,0),MATCH($C40,Pub_Comps_Tickers,0)) -> NM | S40: =INDEX(Pub_Comps_Range,MATCH(S$23,Pub_Comps_Params,0),MATCH($C40,Pub_Comps_Tickers,0)) -> NM | T40: =INDEX(Pub_Comps_Range,MATCH(T$23,Pub_Comps_Params,0),MATCH($C40,Pub_Comps_Tickers,0)) -> NM | ... V40: =INDEX(Pub_Comps_Range,MATCH(V$23,Pub_Comps_Params,0),MATCH($C40,Pub_Comps_Tickers,0)) -> NM

Sheet PubComps_Data
C3: Ticker: | H3: =Ticker -> BFLY | M3: GEHC | R3: MASI | W3: INMD | AB3: IART | AG3: CVAC | AL3: CDNA
C4: Company Name: | H4: =Company_Name -> Butterfly Network, inc. | M4: GE Healthcare Technologies Inc. | R4: Masimo Corporation | W4: InMode, Ltd. | AB4: Integra LifeSciences Holdings Corporation | AG4: CureVac N.V. | AL4: CareDx, Inc
E5: Calendarization: | J5: Calendarization: | O5: Calendarization: | T5: Calendarization: | Y5: Calendarization: | AD5: Calendarization: | AI5: Calendarization:
E6: N/A | F6: N/A | G6: =Hist_Year -> 45657 | H6: =Hist_Year -> 45657 | J6: 45565 | K6: 45930 | L6: 45657 | M6: 45930 | O6: 45472 | P6: 45836 | Q6: 45654 | R6: 45836 | T6: 45473 | U6: 45838 | V6: 45657 | W6: 45838 | Y6: 45565 | Z6: 45930 | AA6: 45657 | AB6: 45930 | AD6: 45565 | AE6: 45930 | AF6: 45657 | AG6: 45930 | AI6: 45473 | AJ6: 45838 | AK6: 45657 | AL6: 45838
E7: Old Partial | F7: New Partial | G7: FY | H7: LTM | J7: Old Partial | K7: New Partial | L7: FY | M7: LTM | O7: Old Partial | P7: New Partial | Q7: FY | R7: LTM | T7: Old Partial | U7: New Partial | V7: FY | W7: LTM | Y7: Old Partial | Z7: New Partial | AA7: FY | AB7: LTM | AD7: Old Partial | AE7: New Partial | AF7: FY | AG7: LTM | AI7: Old Partial | AJ7: New Partial | AK7: FY | AL7: LTM
C8: LTM Revenue: | G8: 203.9 | H8: =G8+F8-E8 -> 203.9 | J8: 14353 | K8: 14927 | L8: 19672 | M8: =L8+K8-J8 -> 20246 | O8: 683.5 | P8: 742.9 | Q8: 2094.4 | R8: =+Q8+P8-O8 -> 2153.8 | T8: 166.73 | U8: 173.48 | V8: 394.82 | W8: =+V8+U8-T8 -> 401.57 | Y8: 1167.88 | Z8: 1200.32 | AA8: 1610.53 | AB8: =+AA8+Z8-Y8 -> 1642.97 | AD8: -55.6 | AE8: -0.95 | AF8: 429.55 | AG8: =+AF8+AE8-AD8 -> 484.2 | AI8: 164.32 | AJ8: 171.36 | AK8: 333.79 | AL8: =+AK8+AJ8-AI8 -> 340.83
C9: LTM Reported Net Income: | G9: -65.4 | H9: =G9+F9-E9 -> -65.4 | J9: 1312 | K9: 1552 | L9: 2050 | M9: =L9+K9-J9 -> 2290 | O9: 34.9 | P9: -119.4 | Q9: -304.9 | R9: =+Q9+P9-O9 -> -459.2 | T9: 47.51 | U9: 44.94 | V9: 181.28 | W9: =+V9+U9-T9 -> 178.71 | Y9: -26.38 | Z9: -514.77 | AA9: -6.94 | AB9: =+AA9+Z9-Y9 -> -495.33 | AD9: -143.1 | AE9: -111.64 | AF9: 162.19 | AG9: =+AF9+AE9-AD9 -> 193.65 | AI9: -24.51 | AJ9: -18.92 | AK9: 52.55 | AL9: =+AK9+AJ9-AI9 -> 58.14
C11: LTM Operating Income (EBIT): | G11: -162.3 | H11: =G11+F11-E11 -> -162.3 | J11: 2140 | K11: 2168 | L11: 3026 | M11: =L11+K11-J11 -> 3054 | O11: 95.1 | P11: 145.2 | Q11: 27.8 | R11: =+Q11+P11-O11 -> 77.9 | T11: 36.41 | U11: 38.5 | V11: 112.53 | W11: =+V11+U11-T11 -> 114.62 | Y11: 113.06 | Z11: 84.5 | AA11: 181.98 | AB11: =+AA11+Z11-Y11 -> 153.42 | AD11: -143.69 | AE11: -116.57 | AF11: 209.78 | AG11: =+AF11+AE11-AD11 -> 236.9 | AI11: -29.89 | AJ11: -18.79 | AK11: -53.75 | AL11: =+AK11+AJ11-AI11 -> -42.65
C12: (+) Non-Recurring Items in EBIT: | G12: 61.5 | H12: =G12+F12-E12 -> 61.5 | J12: 0 | K12: 0 | L12: 97 | M12: =L12+K12-J12 -> 97 | Q12: -294 | R12: =+Q12+P12-O12 -> -294 | V12: 0 | W12: =+V12+U12-T12 -> 0 | Z12: -511.37 | AA12: 0 | AB12: =+AA12+Z12-Y12 -> -511.37 | AF12: -32.1 | AG12: =+AF12+AE12-AD12 -> -32.1 | AK12: -4.5 | AL12: =+AK12+AJ12-AI12 -> -4.5
C13: (+) Depreciation & Amortization: | G13: 359.7 | H13: =G13+F13-E13 -> 359.7 | J13: 203 | K13: 213 | L13: 268 | M13: =L13+K13-J13 -> 278 | O13: 15.3 | P13: 12.9 | Q13: 41.3 | R13: =+Q13+P13-O13 -> 38.9 | T13: 0.34 | U13: 0.37 | V13: 0.73 | W13: =+V13+U13-T13 -> 0.76 | Y13: 24.6 | Z13: 33.3 | AA13: 35.69 | AB13: =+AA13+Z13-Y13 -> 44.39 | AD13: 9.99 | AE13: 8.99 | AF13: 15.36 | AG13: =+AF13+AE13-AD13 -> 14.36 | AI13: 0 | AJ13: -5.71 | AK13: 96.36 | AL13: =+AK13+AJ13-AI13 -> 90.65
C14: LTM EBITDA: | H14: =SUM(H11:H13) -> 258.9 | M14: =SUM(M11:M13) -> 3429 | R14: =SUM(R11:R13) -> -177.2 | W14: =SUM(W11:W13) -> 115.38 | AB14: =SUM(AB11:AB13) -> -313.56 | AG14: =SUM(AG11:AG13) -> 219.16 | AL14: =SUM(AL11:AL13) -> 43.5
C16: Effective Tax Rate: | H16: =Tax_Rate -> 0.12 | M16: 0.177 | R16: 0.2 | W16: 0.2 | AB16: 0.2 | AG16: 0.121 | AL16: 0.005
E18: Balance Sheet Data: | J18: Balance Sheet Data: | O18: Balance Sheet Data: | T18: Balance Sheet Data: | Y18: Balance Sheet Data: | AD18: Balance Sheet Data: | AI18: Balance Sheet Data:
C19: (-) Cash & Cash-Equivalents: | H19: =DCF!G21 -> -88.775 | M19: -4005 | R19: -149.6 | W19: -510.7 | AB19: -267.9 | AG19: -452.8 | AL19: -186.3
C20: (-) Equity Investments: | H20: =DCF!G22 -> 0 | M20: 0 | R20: 0 | W20: 0 | AB20: 0 | AG20: 0 | AL20: 0
C21: (-) Other Non-Core Assets, Net: | H21: =DCF!G23 -> 0 | M21: 0 | R21: 0 | W21: 0 | AB21: 0 | AG21: 0 | AL21: 0
C22: (-) Net Operating Losses: | H22: =DCF!G24 -> 0 | M22: 0 | R22: 0 | W22: 0 | AB22: 0 | AG22: 0 | AL22: 0
C23: (+) Debt & Capital Leases: | H23: =DCF!G25 -> 0 | M23: 10744 | R23: 642.2 | W23: 6.1 | AB23: 2007.7 | AG23: 41.5 | AL23: 29.1
C24: (+) Preferred Stock: | H24: =DCF!G26 -> 0 | M24: 0 | R24: 0 | W24: 0 | AB24: 0 | AG24: 0 | AL24: 0
C25: (+) Noncontrolling Interests: | H25: =DCF!G27 -> 0 | M25: 227 | R25: 0 | W25: 0 | AB25: 0 | AG25: 0 | AL25: 0
C26: (+) Unfunded Pension Obligations: | H26: 0 | M26: 0 | R26: 0 | W26: 0 | AB26: 0 | AG26: 0 | AL26: 0
C27: (+) Restructuring & Other Liabilities: | H27: =DCF!G29 -> 0 | M27: 0 | R27: 0 | AB27: 0 | AG27: 0
E29: Projected Financials: | J29: Projected Financials: | O29: Projected Financials: | T29: Projected Financials: | Y29: Projected Financials: | AD29: Projected Financials: | AI29: Projected Financials:
E30: =Forward_Year_1 -> 46022 | F30: =Forward_Year_2 -> 46387 | G30: =Forward_Year_3 -> 46752 | J30: =Forward_Year_1 -> 46022 | K30: =Forward_Year_2 -> 46387 | L30: =Forward_Year_3 -> 46752 | O30: =Forward_Year_1 -> 46022 | P30: =Forward_Year_2 -> 46387 | Q30: =Forward_Year_3 -> 46752 | T30: =Forward_Year_1 -> 46022 | U30: =Forward_Year_2 -> 46387 | V30: =Forward_Year_3 -> 46752 | Y30: =Forward_Year_1 -> 46022 | Z30: =Forward_Year_2 -> 46387 | AA30: =Forward_Year_3 -> 46752 | AD30: =Forward_Year_1 -> 46022 | AE30: =Forward_Year_2 -> 46387 | AF30: =Forward_Year_3 -> 46752 | AI30: =Forward_Year_1 -> 46022 | AJ30: =Forward_Year_2 -> 46387 | AK30: =Forward_Year_3 -> 46752
C31: Revenue: | E31: =Model!J68/Units -> 63.443 | F31: =Model!K68/Units -> 56.95 | G31: =Model!L68/Units -> 77 | J31: 20530 | K31: 21435 | L31: 22411 | O31: 1521 | P31: 1639 | Q31: 1773 | T31: 368 | U31: 383 | V31: 402 | Y31: 1637 | Z31: 1681 | AA31: 1735 | AD31: 77 | AE31: 99 | AF31: 134 | AI31: 369 | AJ31: 414 | AK31: 462
C32: EBITDA: | E32: =Summary!J45/Units -> -46.163568 | F32: =Summary!K45/Units -> -3.7799891 | G32: =Summary!L45/Units -> 14.395194 | J32: 3653 | K32: 3921 | L32: 4197 | O32: 497 | P32: 544 | Q32: 530 | T32: 94 | U32: 101 | V32: 110 | Y32: 314 | Z32: 333 | AA32: 356 | AD32: -129 | AE32: -130 | AF32: -37 | AI32: 30 | AJ32: 46 | AK32: 71
C33: Reported Net Income: | E33: =Model!J97/Units -> -49.463491 | F33: =Model!K97/Units -> -8.5019708 | G33: =Model!L97/Units -> 10.798983 | J33: 2096 | K33: 2147 | L33: 2435 | O33: 209 | P33: 265 | Q33: 303 | T33: 94 | U33: 104 | V33: 113 | Y33: 169 | Z33: 181 | AA33: 201 | AD33: -165 | AE33: -197 | AF33: -214 | AI33: -27 | AJ33: -4 | AK33: 6
E35: Diluted Shares Calculations: | J35: Diluted Shares Calculations: | O35: Diluted Shares Calculations: | T35: Diluted Shares Calculations: | Y35: Diluted Shares Calculations: | AD35: Diluted Shares Calculations: | AI35: Diluted Shares Calculations:
C36: Share Price: | H36: =Share_Price -> 3.06 | M36: 85.46 | R36: 141.68 | W36: 14.42 | AB36: 13.24 | AG36: 5.12 | AL36: 18.53
C37: Common Shares Outstanding: | H37: =Diluted -> 227.39 | M37: 455.5 | R37: 54.5 | W37: 63.5 | AB37: 77.9 | AG37: 225.2 | AL37: 53.2
C38: Options and Warrants:
F39: Total | G39: Strike | H39: Dilution | K39: Total | L39: Strike | M39: Dilution | P39: Total | Q39: Strike | R39: Dilution | U39: Total | V39: Strike | W39: Dilution | Z39: Total | AA39: Strike | AB39: Dilution | AE39: Total | AF39: Strike | AG39: Dilution | AJ39: Total | AK39: Strike | AL39: Dilution
H40: =IF(G40<H$35,F40-((F40*G40)/H$35),0) -> 0 | M40: =IF(L40<M$35,K40-((K40*L40)/M$35),0) -> 0 | R40: =IF(Q40<R$35,P40-((P40*Q40)/R$35),0) -> 0 | W40: =IF(V40<W$35,U40-((U40*V40)/W$35),0) -> 0 | AB40: =IF(AA40<AB$35,Z40-((Z40*AA40)/AB$35),0) -> 0 | AG40: =IF(AF40<AG$35,AE40-((AE40*AF40)/AG$35),0) -> 0 | AL40: =IF(AK40<AL$35,AJ40-((AJ40*AK40)/AL$35),0) -> 0
H41: =IF(G41<H$35,F41-((F41*G41)/H$35),0) -> 0 | M41: =IF(L41<M$35,K41-((K41*L41)/M$35),0) -> 0 | R41: =IF(Q41<R$35,P41-((P41*Q41)/R$35),0) -> 0 | W41: =IF(V41<W$35,U41-((U41*V41)/W$35),0) -> 0 | AB41: =IF(AA41<AB$35,Z41-((Z41*AA41)/AB$35),0) -> 0 | AG41: =IF(AF41<AG$35,AE41-((AE41*AF41)/AG$35),0) -> 0 | AL41: =IF(AK41<AL$35,AJ41-((AJ41*AK41)/AL$35),0) -> 0
H42: =IF(G42<H$35,F42-((F42*G42)/H$35),0) -> 0 | M42: =IF(L42<M$35,K42-((K42*L42)/M$35),0) -> 0 | R42: =IF(Q42<R$35,P42-((P42*Q42)/R$35),0) -> 0 | W42: =IF(V42<W$35,U42-((U42*V42)/W$35),0) -> 0 | AB42: =IF(AA42<AB$35,Z42-((Z42*AA42)/AB$35),0) -> 0 | AG42: =IF(AF42<AG$35,AE42-((AE42*AF42)/AG$35),0) -> 0 | AL42: =IF(AK42<AL$35,AJ42-((AJ42*AK42)/AL$35),0) -> 0
H43: =IF(G43<H$35,F43-((F43*G43)/H$35),0) -> 0 | M43: =IF(L43<M$35,K43-((K43*L43)/M$35),0) -> 0 | R43: =IF(Q43<R$35,P43-((P43*Q43)/R$35),0) -> 0 | W43: =IF(V43<W$35,U43-((U43*V43)/W$35),0) -> 0 | AB43: =IF(AA43<AB$35,Z43-((Z43*AA43)/AB$35),0) -> 0 | AG43: =IF(AF43<AG$35,AE43-((AE43*AF43)/AG$35),0) -> 0 | AL43: =IF(AK43<AL$35,AJ43-((AJ43*AK43)/AL$35),0) -> 0
H44: =IF(G44<H$35,F44-((F44*G44)/H$35),0) -> 0 | M44: =IF(L44<M$35,K44-((K44*L44)/M$35),0) -> 0 | R44: =IF(Q44<R$35,P44-((P44*Q44)/R$35),0) -> 0 | W44: =IF(V44<W$35,U44-((U44*V44)/W$35),0) -> 0 | AB44: =IF(AA44<AB$35,Z44-((Z44*AA44)/AB$35),0) -> 0 | AG44: =IF(AF44<AG$35,AE44-((AE44*AF44)/AG$35),0) -> 0 | AL44: =IF(AK44<AL$35,AJ44-((AJ44*AK44)/AL$35),0) -> 0
H45: =IF(G45<H$35,F45-((F45*G45)/H$35),0) -> 0 | M45: =IF(L45<M$35,K45-((K45*L45)/M$35),0) -> 0 | R45: =IF(Q45<R$35,P45-((P45*Q45)/R$35),0) -> 0 | W45: =IF(V45<W$35,U45-((U45*V45)/W$35),0) -> 0 | AB45: =IF(AA45<AB$35,Z45-((Z45*AA45)/AB$35),0) -> 0 | AG45: =IF(AF45<AG$35,AE45-((AE45*AF45)/AG$35),0) -> 0 | AL45: =IF(AK45<AL$35,AJ45-((AJ45*AK45)/AL$35),0) -> 0
H46: =IF(G46<H$35,F46-((F46*G46)/H$35),0) -> 0 | M46: =IF(L46<M$35,K46-((K46*L46)/M$35),0) -> 0 | R46: =IF(Q46<R$35,P46-((P46*Q46)/R$35),0) -> 0 | W46: =IF(V46<W$35,U46-((U46*V46)/W$35),0) -> 0 | AB46: =IF(AA46<AB$35,Z46-((Z46*AA46)/AB$35),0) -> 0 | AG46: =IF(AF46<AG$35,AE46-((AE46*AF46)/AG$35),0) -> 0 | AL46: =IF(AK46<AL$35,AJ46-((AJ46*AK46)/AL$35),0) -> 0
H47: =IF(G47<H$35,F47-((F47*G47)/H$35),0) -> 0 | M47: =IF(L47<M$35,K47-((K47*L47)/M$35),0) -> 0 | R47: =IF(Q47<R$35,P47-((P47*Q47)/R$35),0) -> 0 | W47: =IF(V47<W$35,U47-((U47*V47)/W$35),0) -> 0 | AB47: =IF(AA47<AB$35,Z47-((Z47*AA47)/AB$35),0) -> 0 | AG47: =IF(AF47<AG$35,AE47-((AE47*AF47)/AG$35),0) -> 0 | AL47: =IF(AK47<AL$35,AJ47-((AJ47*AK47)/AL$35),0) -> 0
H48: =IF(G48<H$35,F48-((F48*G48)/H$35),0) -> 0 | M48: =IF(L48<M$35,K48-((K48*L48)/M$35),0) -> 0 | R48: =IF(Q48<R$35,P48-((P48*Q48)/R$35),0) -> 0 | W48: =IF(V48<W$35,U48-((U48*V48)/W$35),0) -> 0 | AB48: =IF(AA48<AB$35,Z48-((Z48*AA48)/AB$35),0) -> 0 | AG48: =IF(AF48<AG$35,AE48-((AE48*AF48)/AG$35),0) -> 0 | AL48: =IF(AK48<AL$35,AJ48-((AJ48*AK48)/AL$35),0) -> 0
C50: Convertible Bonds: | E50: $ Amount | F50: Par Value | G50: Conv. Price | H50: Dilution | J50: $ Amount | K50: Par Value | L50: Conv. Price | M50: Dilution | O50: $ Amount | P50: Par Value | Q50: Conv. Price | R50: Dilution | T50: $ Amount | U50: Par Value | V50: Conv. Price | W50: Dilution | Y50: $ Amount | Z50: Par Value | AA50: Conv. Price | AB50: Dilution | AD50: $ Amount | AE50: Par Value | AF50: Conv. Price | AG50: Dilution | AI50: $ Amount | AJ50: Par Value | AK50: Conv. Price | AL50: Dilution
H51: =IFERROR(IF(G51>H$35,0,(+F51/G51)*E51/F51), 0) -> 0 | M51: =IFERROR(IF(L51>M$35,0,(+K51/L51)*J51/K51),0) -> 0 | R51: =IFERROR(IF(Q51>R$35,0,(+P51/Q51)*O51/P51),0) -> 0 | W51: =IFERROR(IF(V51>W$35,0,(+U51/V51)*T51/U51),0) -> 0 | AB51: =IFERROR(IF(AA51>AB$35,0,+Y51/AA51-(AB$35*(Y51/AA51)-Y51)*0.5/AB$35),0) -> 0 | AG51: =IFERROR(IF(AF51>AG$35,0,+AD51/AF51-(AG$35*(AD51/AF51)-AD51)*0.5/AG$35),0) -> 0 | AL51: =IFERROR(IF(AK51>AL$35,0,+AI51/AK51-(AL$35*(AI51/AK51)-AI51)*0.5/AL$35),0) -> 0
H52: =IFERROR(IF(G52>H$35,0,(+F52/G52)*E52/F52),0) -> 0 | M52: =IFERROR(IF(L52>M$35,0,(+K52/L52)*J52/K52),0) -> 0 | R52: =IFERROR(IF(Q52>R$35,0,(+P52/Q52)*O52/P52),0) -> 0 | W52: =IFERROR(IF(V52>W$35,0,(+U52/V52)*T52/U52),0) -> 0 | AB52: =IFERROR(IF(AA52>AB$35,0,(+Z52/AA52)*Y52/Z52),0) -> 0 | AG52: =IFERROR(IF(AF52>AG$35,0,(+AE52/AF52)*AD52/AE52),0) -> 0 | AL52: =IFERROR(IF(AK52>AL$35,0,(+AJ52/AK52)*AI52/AJ52),0) -> 0
G54: # RSUs | H54: Dilution | L54: # RSUs | M54: Dilution | Q54: # RSUs | R54: Dilution | V54: # RSUs | W54: Dilution | AA54: # RSUs | AB54: Dilution | AF54: # RSUs | AG54: Dilution | AK54: # RSUs | AL54: Dilution
C55: Restricted Stock Units (RSUs): | G55: =(321+105+91+71)/Units -> 0.588 | H55: =+G55 -> 0.588 | L55: 0 | M55: =+L55 -> 0 | Q55: 0 | R55: =+Q55 -> 0 | V55: 2 | W55: =+V55 -> 2 | AA55: =(3470929+976862+513318)/AB36/1000000 -> 0.37470612 | AB55: =+AA55 -> 0.37470612 | AF55: =(8164661+1555793+809887+769882+769882)/AG36/1000000 -> 2.3574424 | AG55: =+AF55 -> 2.3574424 | AK55: 0 | AL55: =+AK55 -> 0
C57: Total Diluted Shares: | H57: =+H55+SUM(H40:H48)+SUM(H51:H52)+H37 -> 227.978 | M57: =+M55+SUM(M40:M48)+SUM(M51:M52)+M37 -> 455.5 | R57: =+R55+SUM(R40:R48)+SUM(R51:R52)+R37 -> 54.5 | W57: =+W55+SUM(W40:W48)+SUM(W51:W52)+W37 -> 65.5 | AB57: =+AB55+SUM(AB40:AB48)+SUM(AB51:AB52)+AB37 -> 78.274706 | AG57: =+AG55+SUM(AG40:AG48)+SUM(AG51:AG52)+AG37 -> 227.55744 | AL57: =+AL55+SUM(AL40:AL48)+SUM(AL51:AL52)+AL37 -> 53.2
E59: Valuation Metrics: | J59: Valuation Metrics: | O59: Valuation Metrics: | T59: Valuation Metrics: | Y59: Valuation Metrics: | AD59: Valuation Metrics: | AI59: Valuation Metrics:
C61: Equity Value: | H61: =+H57*H36 -> 697.61268 | M61: =+M57*M36 -> 38927.03 | R61: =+R57*R36 -> 7721.56 | W61: =+W57*W36 -> 944.51 | AB61: =+AB57*AB36 -> 1036.3571 | AG61: =+AG57*AG36 -> 1165.0941 | AL61: =+AL57*AL36 -> 985.796
C62: Enterprise Value: | H62: =+H61+SUM(H19:H27) -> 608.83768 | M62: =+M61+SUM(M19:M27) -> 45893.03 | R62: =+R61+SUM(R19:R27) -> 8214.16 | W62: =+W61+SUM(W19:W27) -> 439.91 | AB62: =+AB61+SUM(AB19:AB27) -> 2776.1571 | AG62: =+AG61+SUM(AG19:AG27) -> 753.7941 | AL62: =+AL61+SUM(AL19:AL27) -> 828.596
C63: Levered Beta: | H63: 2.24 | M63: 1.27 | R63: 1.26 | W63: 2.15 | AB63: 1.08 | AG63: 1.78 | AL63: 2.56
E65: Valuation Multiples: | J65: Valuation Multiples: | O65: Valuation Multiples: | T65: Valuation Multiples: | Y65: Valuation Multiples: | AD65: Valuation Multiples: | AI65: Valuation Multiples:
E66: =H7 -> LTM | F66: =E30 -> 46022 | G66: =F30 -> 46387 | H66: =G30 -> 46752 | J66: =M7 -> LTM | K66: =J30 -> 46022 | L66: =K30 -> 46387 | M66: =L30 -> 46752 | O66: =R7 -> LTM | P66: =O30 -> 46022 | Q66: =P30 -> 46387 | R66: =Q30 -> 46752 | T66: =W7 -> LTM | U66: =T30 -> 46022 | V66: =U30 -> 46387 | W66: =V30 -> 46752 | Y66: =AB7 -> LTM | Z66: =Y30 -> 46022 | AA66: =Z30 -> 46387 | AB66: =AA30 -> 46752 | AD66: =AG7 -> LTM | AE66: =AD30 -> 46022 | AF66: =AE30 -> 46387 | AG66: =AF30 -> 46752 | AI66: =AL7 -> LTM | AJ66: =AI30 -> 46022 | AK66: =AJ30 -> 46387 | AL66: =AK30 -> 46752
C67: EV / Revenue: | E67: =IFERROR(IF(OR(+H$62/H8<0,+H$62/H8>=100),"NM",+H$62/H8), "N/A") -> 2.9859621 | F67: =IFERROR(IF(OR(+H62/E31<0,+H62/E31>=100),"NM",+H62/E31), "N/A") -> 9.5966092 | G67: =IFERROR(IF(OR(+$H$62/F31<0,+$H$62/F31>=100),"NM",+$H$62/F31), "N/A") -> 10.690741 | H67: =IFERROR(IF(OR(+$H$62/G31<0,+$H$62/G31>=100),"NM",+$H$62/G31), "N/A") -> 7.9069829 | J67: =IFERROR(IF(OR(+M$62/M8<0,+M$62/M8>=100),"NM",+M$62/M8),"N/A") -> 2.2667702 | K67: =IFERROR(IF(OR(+$M$62/J31<0,+$M$62/J31>=100),"NM",+$M$62/J31), "N/A") -> 2.2354131 | L67: =IFERROR(IF(OR(+$M$62/K31<0,+$M$62/K31>=100),"NM",+$M$62/K31), "N/A") -> 2.1410324 | M67: =IFERROR(IF(OR(+$M$62/L31<0,+$M$62/L31>=100),"NM",+$M$62/L31), "N/A") -> 2.0477904 | O67: =IFERROR(IF(OR(+R$62/R8<0,+R$62/R8>=100),"NM",+R$62/R8),"N/A") -> 3.8137989 | P67: =IFERROR(IF(OR(+$R$62/O31<0,+$R$62/O31>=100),"NM",+$R$62/O31), "N/A") -> 5.4004997 | Q67: =IFERROR(IF(OR(+R62/P31<0,+R62/P31>=100),"NM",+R62/P31), "N/A") -> 5.0116901 | R67: =IFERROR(IF(OR(+R62/Q31<0,+R62/Q31>=100),"NM",+R62/Q31), "N/A") -> 4.632916 | T67: =IFERROR(IF(OR(+W$62/W8<0,+W$62/W8>=100),"NM",+W$62/W8),"N/A") -> 1.0954753 | U67: =IFERROR(IF(OR(+$W$62/T31<0,+$W$62/T31>=100),"NM",+$W$62/T31), "N/A") -> 1.1954076 | V67: =IFERROR(IF(OR(+$W$62/U31<0,+$W$62/U31>=100),"NM",+$W$62/U31), "N/A") -> 1.1485901 | W67: =IFERROR(IF(OR(+$W$62/V31<0,+$W$62/V31>=100),"NM",+$W$62/V31), "N/A") -> 1.0943035 | Y67: =IFERROR(IF(OR(+AB$62/AB8<0,+AB$62/AB8>=100),"NM",+AB$62/AB8),"N/A") -> 1.6897187 | Z67: =IFERROR(IF(OR(+$AB$62/Y31<0,+$AB$62/Y31>=100),"NM",+$AB$62/Y31), "N/A") -> 1.6958809 | AA67: =IFERROR(IF(OR(+$AB$62/Z31<0,+$AB$62/Z31>=100),"NM",+$AB$62/Z31), "N/A") -> 1.6514914 | AB67: =IFERROR(IF(OR(+$AB$62/AA31<0,+$AB$62/AA31>=100),"NM",+$AB$62/AA31), "N/A") -> 1.6000906 | AD67: =IFERROR(IF(OR(+AG$62/AG8<0,+AG$62/AG8>=100),"NM",+AG$62/AG8),"N/A") -> 1.5567825 | AE67: =IFERROR(IF(OR(+$AG$62/AD31<0,+$AG$62/AD31>=100),"NM",+$AG$62/AD31), "N/A") -> 9.7895338 | AF67: =IFERROR(IF(OR(+$AG$62/AE31<0,+$AG$62/AE31>=100),"NM",+$AG$62/AE31), "N/A") -> 7.6140819 | AG67: =IFERROR(IF(OR(+$AG$62/AF31<0,+$AG$62/AF31>=100),"NM",+$AG$62/AF31), "N/A") -> 5.6253291 | AI67: =IFERROR(IF(OR(+AL$62/AL8<0,+AL$62/AL8>=100),"NM",+AL$62/AL8),"N/A") -> 2.4311123 | AJ67: =IFERROR(IF(OR(+$AG$62/AI31<0,+$AG$62/AI31>=100),"NM",+$AG$62/AI31), "N/A") -> 2.0428025 | AK67: =IFERROR(IF(OR(+$AG$62/AJ31<0,+$AG$62/AJ31>=100),"NM",+$AG$62/AJ31), "N/A") -> 1.8207587 | AL67: =IFERROR(IF(OR(+$AG$62/AK31<0,+$AG$62/AK31>=100),"NM",+$AG$62/AK31), "N/A") -> 1.631589
C68: EV / EBITDA: | E68: =IFERROR(IF(OR(+H$62/H14<0,+H$62/H14>=100),"NM",+H$62/H14), "N/A") -> 2.3516326 | F68: =IFERROR(IF(OR(+$H$62/E32<0,+$H$62/E32>=100),"NM",+$H$62/E32), "N/A") -> NM | G68: =IFERROR(IF(OR(+$H$62/F32<0,+$H$62/F32>=100),"NM",+$H$62/F32), "N/A") -> NM | H68: =IFERROR(IF(OR(+$H$62/G32<0,+$H$62/G32>=100),"NM",+$H$62/G32), "N/A") -> 42.29451 | J68: =IFERROR(IF(OR(+M$62/M14<0,+M$62/M14>=100),"NM",+M$62/M14),"N/A") -> 13.383794 | K68: =IFERROR(IF(OR(+$M$62/J32<0,+$M$62/J32>=100),"NM",+$M$62/J32),"N/A") -> 12.563107 | L68: =IFERROR(IF(OR(+$M$62/K32<0,+$M$62/K32>=100),"NM",+$M$62/K32),"N/A") -> 11.70442 | M68: =IFERROR(IF(OR(+$M$62/L32<0,+$M$62/L32>=100),"NM",+$M$62/L32),"N/A") -> 10.934722 | O68: =IFERROR(IF(OR(+$R$62/R14<0,+$R$62/R14>=100),"NM",+$R$62/R14),"N/A") -> NM | P68: =IFERROR(IF(OR(+$R$62/O32<0,+$R$62/O32>=100),"NM",+$R$62/O32),"N/A") -> 16.527485 | Q68: =IFERROR(IF(OR(+$R$62/P32<0,+$R$62/P32>=100),"NM",+$R$62/P32),"N/A") -> 15.099559 | R68: =IFERROR(IF(OR(+$R$62/Q32<0,+$R$62/Q32>=100),"NM",+$R$62/Q32),"N/A") -> 15.498415 | T68: =IFERROR(IF(OR(+W$62/W14<0,+W$62/W14>=100),"NM",+W$62/W14),"N/A") -> 3.8127058 | U68: =IFERROR(IF(OR(+$W$62/T32<0,+$W$62/T32>=100),"NM",+$W$62/T32), "N/A") -> 4.6798936 | V68: =IFERROR(IF(OR(+$W$62/U32<0,+$W$62/U32>=100),"NM",+$W$62/U32), "N/A") -> 4.3555446 | W68: =IFERROR(IF(OR(+$W$62/V32<0,+$W$62/V32>=100),"NM",+$W$62/V32), "N/A") -> 3.9991818 | Y68: =IFERROR(IF(OR(+AB$62/AB14<0,+AB$62/AB14>=100),"NM",+AB$62/AB14),"N/A") -> NM | Z68: =IFERROR(IF(OR(+$AB$62/Y32<0,+$AB$62/Y32>=100),"NM",+$AB$62/Y32),"N/A") -> 8.8412647 | AA68: =IFERROR(IF(OR(+$AB$62/Z32<0,+$AB$62/Z32>=100),"NM",+$AB$62/Z32),"N/A") -> 8.3368081 | AB68: =IFERROR(IF(OR(+$AB$62/AA32<0,+$AB$62/AA32>=100),"NM",+$AB$62/AA32),"N/A") -> 7.7981941 | AD68: =IFERROR(IF(OR(+AG$62/AG14<0,+AG$62/AG14>=100),"NM",+AG$62/AG14),"N/A") -> 3.4394694 | AE68: =IFERROR(IF(OR(+$AG$62/AD32<0,+$AG$62/AD32>=100),"NM",+$AG$62/AD32),"N/A") -> NM | AF68: =IFERROR(IF(OR(+$AG$62/AE32<0,+$AG$62/AE32>=100),"NM",+$AG$62/AE32),"N/A") -> NM | AG68: =IFERROR(IF(OR(+$AG$62/AF32<0,+$AG$62/AF32>=100),"NM",+$AG$62/AF32),"N/A") -> NM | AI68: =IFERROR(IF(OR(+AL$62/AL14<0,+AL$62/AL14>=100),"NM",+AL$62/AL14),"N/A") -> 19.048184 | AJ68: =IFERROR(IF(OR(+$AG$62/AI32<0,+$AG$62/AI32>=100),"NM",+$AG$62/AI32),"N/A") -> 25.12647 | AK68: =IFERROR(IF(OR(+$AG$62/AJ32<0,+$AG$62/AJ32>=100),"NM",+$AG$62/AJ32),"N/A") -> 16.386828 | AL68: =IFERROR(IF(OR(+$AG$62/AK32<0,+$AG$62/AK32>=100),"NM",+$AG$62/AK32),"N/A") -> 10.616818
C69: P / E: | E69: =IFERROR(IF(OR(+H$61/H9<0,+H$61/H9>=100),"NM",+H$61/H9), "N/A") -> NM | F69: =IFERROR(IF(OR($H$61/E$33<0,+$H$61/E$33>=100),"NM",+$H$61/E$33), "N/A") -> NM | G69: =IFERROR(IF(OR(H61/F$33<0,+H61/F$33>=100),"NM",+H61/F$33), "N/A") -> NM | H69: =IFERROR(IF(OR(H61/G$33<0,+H61/G$33>=100),"NM",+H61/G$33), "N/A") -> 64.599851 | J69: =IFERROR(IF(OR(+M$61/M9<0,+M$61/M9>=100),"NM",+M$61/M9), "N/A") -> 16.998703 | K69: =IFERROR(IF(OR($M$61/J$33<0,+$M$61/J$33>=100),"NM",+$M$61/J$33), "N/A") -> 18.572056 | L69: =IFERROR(IF(OR(M61/K$33<0,+M61/K$33>=100),"NM",+M61/K$33), "N/A") -> 18.130894 | M69: =IFERROR(IF(OR(M61/L$33<0,+M61/L$33>=100),"NM",+M61/L$33), "N/A") -> 15.98646 | O69: =IFERROR(IF(OR(+R$61/R9<0,+R$61/R9>=100),"NM",+R$61/R9), "N/A") -> NM | P69: =IFERROR(IF(OR($R$61/O$33<0,+$R$61/O$33>=100),"NM",+$R$61/O$33), "N/A") -> 36.945263 | Q69: =IFERROR(IF(OR(R61/P$33<0,+R61/P$33>=100),"NM",+R61/P$33), "N/A") -> 29.137962 | R69: =IFERROR(IF(OR(R61/Q$33<0,+R61/Q$33>=100),"NM",+R61/Q$33), "N/A") -> 25.483696 | T69: =IFERROR(IF(OR(+W$61/W9<0,+W$61/W9>=100),"NM",+W$61/W9),"N/A") -> 5.2851547 | U69: =IFERROR(IF(OR(+W$61/T33<0,+W$61/T33>=100),"NM",+W$61/T33),"N/A") -> 10.047979 | V69: =IFERROR(IF(OR(+W$61/U33<0,+W$61/U33>=100),"NM",+W$61/U33),"N/A") -> 9.0818269 | W69: =IFERROR(IF(OR(+W$61/V33<0,+W$61/V33>=100),"NM",+W$61/V33),"N/A") -> 8.3584956 | Y69: =IFERROR(IF(OR(+AB$61/AB9<0,+AB$61/AB9>=100),"NM",+AB$61/AB9),"N/A") -> NM | Z69: =IFERROR(IF(OR(+$AB$61/Y33<0,+$AB$61/Y33>=100),"NM",+$AB$61/Y33),"N/A") -> 6.1322906 | AA69: =IFERROR(IF(OR(+$AB$61/Z33<0,+$AB$61/Z33>=100),"NM",+$AB$61/Z33),"N/A") -> 5.7257299 | AB69: =IFERROR(IF(OR(+$AB$61/AA33<0,+$AB$61/AA33>=100),"NM",+$AB$61/AA33),"N/A") -> 5.1560055 | AD69: =IFERROR(IF(OR(+AG$61/AG9<0,+AG$61/AG9>=100),"NM",+AG$61/AG9),"N/A") -> 6.0164942 | AE69: =IFERROR(IF(OR(+$AG$61/AD33<0,+$AG$61/AD33>=100),"NM",+$AG$61/AD33),"N/A") -> NM | AF69: =IFERROR(IF(OR(+$AG$61/AE33<0,+$AG$61/AE33>=100),"NM",+$AG$61/AE33),"N/A") -> NM | AG69: =IFERROR(IF(OR(+$AG$61/AF33<0,+$AG$61/AF33>=100),"NM",+$AG$61/AF33),"N/A") -> NM | AI69: =IFERROR(IF(OR(+AL$61/AL9<0,+AL$61/AL9>=100),"NM",+AL$61/AL9),"N/A") -> 16.955556 | AJ69: =IFERROR(IF(OR(+$AG$61/AI33<0,+$AG$61/AI33>=100),"NM",+$AG$61/AI33),"N/A") -> NM | AK69: =IFERROR(IF(OR(+$AG$61/AJ33<0,+$AG$61/AJ33>=100),"NM",+$AG$61/AJ33),"N/A") -> NM | AL69: =IFERROR(IF(OR(+$AG$61/AK33<0,+$AG$61/AK33>=100),"NM",+$AG$61/AK33),"N/A") -> NM
E71: Lookup Variables: | J71: Lookup Variables: | O71: Lookup Variables: | T71: Lookup Variables: | Y71: Lookup Variables: | AD71: Lookup Variables: | AI71: Lookup Variables:
C73: =TEXT(Forward_Year_1,"yyyy-mm-dd")&" "&C31 -> 2025-12-31 Revenue: | H73: =+E31 -> 63.443 | M73: =+J31 -> 20530 | R73: =+O31 -> 1521 | W73: =+T31 -> 368 | AB73: =+Y31 -> 1637 | AG73: =+AD31 -> 77 | AL73: =+AI31 -> 369
C74: =TEXT(Forward_Year_1,"yyyy-mm-dd")&" "&C32 -> 2025-12-31 EBITDA: | H74: =+E32 -> -46.163568 | M74: =+J32 -> 3653 | R74: =+O32 -> 497 | W74: =+T32 -> 94 | AB74: =+Y32 -> 314 | AG74: =+AD32 -> -129 | AL74: =+AI32 -> 30
C75: =TEXT(Forward_Year_1,"yyyy-mm-dd")&" "&C33 -> 2025-12-31 Reported Net Income: | H75: =+E33 -> -49.463491 | M75: =+J33 -> 2096 | R75: =+O33 -> 209 | W75: =+T33 -> 94 | AB75: =+Y33 -> 169 | AG75: =+AD33 -> -165 | AL75: =+AI33 -> -27
C77: =TEXT(Forward_Year_2,"yyyy-mm-dd")&" "&C31 -> 2026-12-31 Revenue: | H77: =+F31 -> 56.95 | M77: =+K31 -> 21435 | R77: =+P31 -> 1639 | W77: =+U31 -> 383 | AB77: =+Z31 -> 1681 | AG77: =+AE31 -> 99 | AL77: =+AJ31 -> 414
C78: =TEXT(Forward_Year_2,"yyyy-mm-dd")&" "&C32 -> 2026-12-31 EBITDA: | H78: =+F32 -> -3.7799891 | M78: =+K32 -> 3921 | R78: =+P32 -> 544 | W78: =+U32 -> 101 | AB78: =+Z32 -> 333 | AG78: =+AE32 -> -130 | AL78: =+AJ32 -> 46
C79: =TEXT(Forward_Year_2,"yyyy-mm-dd")&" "&C33 -> 2026-12-31 Reported Net Income: | H79: =+F33 -> -8.5019708 | M79: =+K33 -> 2147 | R79: =+P33 -> 265 | W79: =+U33 -> 104 | AB79: =+Z33 -> 181 | AG79: =+AE33 -> -197 | AL79: =+AJ33 -> -4
C81: =TEXT(Forward_Year_3,"yyyy-mm-dd")&" "&C31 -> 2027-12-31 Revenue: | H81: =+G31 -> 77 | M81: =+L31 -> 22411 | R81: =+Q31 -> 1773 | W81: =+V31 -> 402 | AB81: =+AA31 -> 1735 | AG81: =+AF31 -> 134 | AL81: =+AK31 -> 462
C82: =TEXT(Forward_Year_3,"yyyy-mm-dd")&" "&C32 -> 2027-12-31 EBITDA: | H82: =+G32 -> 14.395194 | M82: =+L32 -> 4197 | R82: =+Q32 -> 530 | W82: =+V32 -> 110 | AB82: =+AA32 -> 356 | AG82: =+AF32 -> -37 | AL82: =+AK32 -> 71
C83: =TEXT(Forward_Year_3,"yyyy-mm-dd")&" "&C33 -> 2027-12-31 Reported Net Income: | H83: =+G33 -> 10.798983 | M83: =+L33 -> 2435 | R83: =+Q33 -> 303 | W83: =+V33 -> 113 | AB83: =+AA33 -> 201 | AG83: =+AF33 -> -214 | AL83: =+AK33 -> 6
C85: Year 1 Projected Revenue Growth: | H85: =IFERROR(+H77/H73-1,"N/A") -> -0.10234384 | M85: =IFERROR(+M77/M73-1,"N/A") -> 0.044081831 | R85: =IFERROR(+R77/R73-1,"N/A") -> 0.077580539 | W85: =IFERROR(+W77/W73-1,"N/A") -> 0.04076087 | AB85: =IFERROR(+AB77/AB73-1,"N/A") -> 0.026878436 | AG85: =IFERROR(+AG77/AG73-1,"N/A") -> 0.28571429 | AL85: =IFERROR(+AL77/AL73-1,"N/A") -> 0.12195122
C86: Year 1 Projected EBITDA Growth: | H86: =IFERROR(+H78/H74-1,"N/A") -> -0.91811748 | M86: =IFERROR(+M78/M74-1,"N/A") -> 0.073364358 | R86: =IFERROR(+R78/R74-1,"N/A") -> 0.094567404 | W86: =IFERROR(+W78/W74-1,"N/A") -> 0.074468085 | AB86: =IFERROR(+AB78/AB74-1,"N/A") -> 0.060509554 | AG86: =IFERROR(+AG78/AG74-1,"N/A") -> 0.007751938 | AL86: =IFERROR(+AL78/AL74-1,"N/A") -> 0.53333333
C88: LTM EBITDA Margin: | H88: =IFERROR(+H14/H8,"N/A") -> 1.2697401 | M88: =IFERROR(+M14/M8,"N/A") -> 0.16936679 | R88: =IFERROR(+R14/R8,"N/A") -> -0.082273192 | W88: =IFERROR(+W14/W8,"N/A") -> 0.28732226 | AB88: =IFERROR(+AB14/AB8,"N/A") -> -0.1908495 | AG88: =IFERROR(+AG14/AG8,"N/A") -> 0.45262288 | AL88: =IFERROR(+AL14/AL8,"N/A") -> 0.12762961
C89: =TEXT(Forward_Year_1,"yyyy-mm-dd")&" EBITDA Margin:" -> 2025-12-31 EBITDA Margin: | H89: =IFERROR(+H74/H73,"N/A") -> -0.72763848 | M89: =IFERROR(+M74/M73,"N/A") -> 0.17793473 | R89: =IFERROR(+R74/R73,"N/A") -> 0.32675871 | W89: =IFERROR(+W74/W73,"N/A") -> 0.25543478 | AB89: =IFERROR(+AB74/AB73,"N/A") -> 0.19181429 | AG89: =IFERROR(+AG74/AG73,"N/A") -> -1.6753247 | AL89: =IFERROR(+AL74/AL73,"N/A") -> 0.081300813
C90: =TEXT(Forward_Year_2,"yyyy-mm-dd")&" EBITDA Margin:" -> 2026-12-31 EBITDA Margin: | H90: =IFERROR(+H78/H77,"N/A") -> -0.066373821 | M90: =IFERROR(+M78/M77,"N/A") -> 0.18292512 | R90: =IFERROR(+R78/R77,"N/A") -> 0.3319097 | W90: =IFERROR(+W78/W77,"N/A") -> 0.26370757 | AB90: =IFERROR(+AB78/AB77,"N/A") -> 0.19809637 | AG90: =IFERROR(+AG78/AG77,"N/A") -> -1.3131313 | AL90: =IFERROR(+AL78/AL77,"N/A") -> 0.11111111
C92: =TEXT(E66,"mm/dd/yyyy")&" "&C67 -> LTM EV / Revenue: | H92: =+E67 -> 2.9859621 | M92: =+J67 -> 2.2667702 | R92: =+O67 -> 3.8137989 | W92: =+T67 -> 1.0954753 | AB92: =+Y67 -> 1.6897187 | AG92: =+AD67 -> 1.5567825 | AL92: =+AI67 -> 2.4311123
C93: =TEXT(E66,"mm/dd/yyyy")&" "&C68 -> LTM EV / EBITDA: | H93: =+E68 -> 2.3516326 | M93: =+J68 -> 13.383794 | R93: =+O68 -> NM | W93: =+T68 -> 3.8127058 | AB93: =+Y68 -> NM | AG93: =+AD68 -> 3.4394694 | AL93: =+AI68 -> 19.048184
C94: =TEXT(E66,"mm/dd/yyyy")&" "&C69 -> LTM P / E: | H94: =+E69 -> NM | M94: =+J69 -> 16.998703 | R94: =+O69 -> NM | W94: =+T69 -> 5.2851547 | AB94: =+Y69 -> NM | AG94: =+AD69 -> 6.0164942 | AL94: =+AI69 -> 16.955556
C96: =TEXT(Forward_Year_1,"yyyy-mm-dd")&" "&C67 -> 2025-12-31 EV / Revenue: | H96: =+F67 -> 9.5966092 | M96: =+K67 -> 2.2354131 | R96: =+P67 -> 5.4004997 | W96: =+U67 -> 1.1954076 | AB96: =+Z67 -> 1.6958809 | AG96: =+AE67 -> 9.7895338 | AL96: =+AJ67 -> 2.0428025
C97: =TEXT(Forward_Year_1,"yyyy-mm-dd")&" "&C68 -> 2025-12-31 EV / EBITDA: | H97: =+F68 -> NM | M97: =+K68 -> 12.563107 | R97: =+P68 -> 16.527485 | W97: =+U68 -> 4.6798936 | AB97: =+Z68 -> 8.8412647 | AG97: =+AE68 -> NM | AL97: =+AJ68 -> 25.12647
C98: =TEXT(Forward_Year_1,"yyyy-mm-dd")&" "&C69 -> 2025-12-31 P / E: | H98: =+F69 -> NM | M98: =+K69 -> 18.572056 | R98: =+P69 -> 36.945263 | W98: =+U69 -> 10.047979 | AB98: =+Z69 -> 6.1322906 | AG98: =+AE69 -> NM | AL98: =+AJ69 -> NM
C100: =TEXT(Forward_Year_2,"yyyy-mm-dd")&" "&C67 -> 2026-12-31 EV / Revenue: | H100: =+G67 -> 10.690741 | M100: =+L67 -> 2.1410324 | R100: =+Q67 -> 5.0116901 | W100: =+V67 -> 1.1485901 | AB100: =+AA67 -> 1.6514914 | AG100: =+AF67 -> 7.6140819 | AL100: =+AK67 -> 1.8207587
C101: =TEXT(Forward_Year_2,"yyyy-mm-dd")&" "&C68 -> 2026-12-31 EV / EBITDA: | H101: =+G68 -> NM | M101: =+L68 -> 11.70442 | R101: =+Q68 -> 15.099559 | W101: =+V68 -> 4.3555446 | AB101: =+AA68 -> 8.3368081 | AG101: =+AF68 -> NM | AL101: =+AK68 -> 16.386828
C102: =TEXT(Forward_Year_2,"yyyy-mm-dd")&" "&C69 -> 2026-12-31 P / E: | H102: =+G69 -> NM | M102: =+L69 -> 18.130894 | R102: =+Q69 -> 29.137962 | W102: =+V69 -> 9.0818269 | AB102: =+AA69 -> 5.7257299 | AG102: =+AF69 -> NM | AL102: =+AK69 -> NM
C104: Corporate Website:

Sheet MAComps
B2: Precedent Transactions – U.S.-Based Medical Device and Connected Health Acquisitions
B3: Announced Between January 1st, 2020 and December 31st, 2024
B4: ($ in Millions Except Per Share and Per Unit Data)
B6: =Company_Name&" - Comparable M&A Transactions" -> Butterfly Network, inc. - Comparable M&A Transactions | F6: Operating Metrics | H6: Valuation Multiples | K6: Share Prices | N6: Premiums Paid
E7: Transaction | H7: EV / | I7: EV /
E8: Enterprise | F8: LTM | G8: LTM | H8: LTM | I8: LTM | J8: Offer | K8: 1-Day | L8: 1-Week | M8: 1-Month | N8: 1-Day | O8: 1-Week | P8: 1-Month
B9: Acquirer Name | C9: Target Name | D9: Date | E9: Value | F9: Revenue | G9: EBITDA | H9: Revenue | I9: EBITDA | J9: Price | K9: Prior | L9: Prior | M9: Prior | N9: Prior | O9: Prior | P9: Prior
B11: Boston Scientific Corporation | C11: Axonics, Inc. | D11: 45299 | E11: 3355.63 | F11: 366.38 | G11: NM | H11: =IFERROR(IF(OR(+$E11/F11<0,+$E11/F11>=100),"NM",+$E11/F11),"N/A") -> 9.1588788 | I11: =IFERROR(IF(OR(+$E11/G11<0,+$E11/G11>=100),"NM",+$E11/G11),"N/A") -> N/A | J11: 71 | K11: 57.57 | L11: 62.23 | M11: 56.82 | N11: =IFERROR($J11/K11-1,"N/A") -> 0.23328122 | O11: =IFERROR($J11/L11-1,"N/A") -> 0.14092881 | P11: =IFERROR($J11/M11-1,"N/A") -> 0.24956001
B12: Philips Holding USA Inc. | C12: BioTelemetry, Inc. | D12: 44183 | E12: 2799.37 | F12: 414.8 | G12: 105.09 | H12: =IFERROR(IF(OR(+$E12/F12<0,+$E12/F12>=100),"NM",+$E12/F12),"N/A") -> 6.7487223 | I12: =IFERROR(IF(OR(+$E12/G12<0,+$E12/G12>=100),"NM",+$E12/G12),"N/A") -> 26.637834 | J12: 72 | K12: 61.78 | L12: 59.53 | M12: 47.41 | N12: =IFERROR($J12/K12-1,"N/A") -> 0.1654257 | O12: =IFERROR($J12/L12-1,"N/A") -> 0.20947421 | P12: =IFERROR($J12/M12-1,"N/A") -> 0.51866695
B13: Philips Holding USA Inc. | C13: Volcano Corporation | D13: 45643 | E13: 1190.66 | F13: 396.88667 | G13: 15.728666 | H13: =IFERROR(IF(OR(+$E13/F13<0,+$E13/F13>=100),"NM",+$E13/F13),"N/A") -> 3 | I13: =IFERROR(IF(OR(+$E13/G13<0,+$E13/G13>=100),"NM",+$E13/G13),"N/A") -> 75.7 | J13: 18 | K13: 11.49 | L13: 11.63 | M13: 11.08 | N13: =IFERROR($J13/K13-1,"N/A") -> 0.56657963 | O13: =IFERROR($J13/L13-1,"N/A") -> 0.54772141 | P13: =IFERROR($J13/M13-1,"N/A") -> 0.62454874
B14: Siemens Healthineers AG | C14: Varian Medical Systems, Inc. | D14: 44045 | E14: 16390.76 | F14: 3196.6 | G14: 585.83 | H14: =IFERROR(IF(OR(+$E14/F14<0,+$E14/F14>=100),"NM",+$E14/F14),"N/A") -> 5.1275605 | I14: =IFERROR(IF(OR(+$E14/G14<0,+$E14/G14>=100),"NM",+$E14/G14),"N/A") -> 27.978697 | J14: 177.5 | K14: 142.72 | L14: 127.16 | M14: 122.39 | N14: =IFERROR($J14/K14-1,"N/A") -> 0.24369395 | O14: =IFERROR($J14/L14-1,"N/A") -> 0.39587921 | P14: =IFERROR($J14/M14-1,"N/A") -> 0.45028189
B15: Baxter International Inc. | C15: Hill-Rom Holdings, Inc. | D15: 44441 | E15: 11996.27 | F15: 2926.1 | G15: 574.6 | H15: =IFERROR(IF(OR(+$E15/F15<0,+$E15/F15>=100),"NM",+$E15/F15),"N/A") -> 4.0997471 | I15: =IFERROR(IF(OR(+$E15/G15<0,+$E15/G15>=100),"NM",+$E15/G15),"N/A") -> 20.877602 | J15: 156 | K15: 145.06 | L15: 131.64 | M15: 138.73 | N15: =IFERROR($J15/K15-1,"N/A") -> 0.075417069 | O15: =IFERROR($J15/L15-1,"N/A") -> 0.18505014 | P15: =IFERROR($J15/M15-1,"N/A") -> 0.12448641
B16: Stryker Coporation | C16: Vocera Communications, Inc. | D16: 44567 | E16: 2987.7 | F16: 234.19 | G16: 13.26 | H16: =IFERROR(IF(OR(+$E16/F16<0,+$E16/F16>=100),"NM",+$E16/F16),"N/A") -> 12.75759 | I16: =IFERROR(IF(OR(+$E16/G16<0,+$E16/G16>=100),"NM",+$E16/G16),"N/A") -> NM | J16: 79.25 | K16: 62.52 | L16: 64 | M16: 57.7 | N16: =IFERROR($J16/K16-1,"N/A") -> 0.26759437 | O16: =IFERROR($J16/L16-1,"N/A") -> 0.23828125 | P16: =IFERROR($J16/M16-1,"N/A") -> 0.37348354
B18: Maximum | E18: =MAX(E11:E16) -> 16390.76 | F18: =MAX(F11:F16) -> 3196.6 | G18: =MAX(G11:G16) -> 585.83 | H18: =MAX(H11:H16) -> 12.75759 | I18: =MAX(I11:I16) -> 75.7 | N18: =MAX(N11:N16) -> 0.56657963 | O18: =MAX(O11:O16) -> 0.54772141 | P18: =MAX(P11:P16) -> 0.62454874
B19: 75th Percentile | E19: =QUARTILE(E11:E16,3) -> 9836.11 | F19: =QUARTILE(F11:F16,3) -> 2298.275 | G19: =QUARTILE(G11:G16,3) -> 574.6 | H19: =QUARTILE(H11:H16,3) -> 8.5563396 | I19: =QUARTILE(I11:I16,3) -> 39.909023 | N19: =QUARTILE(N11:N16,3) -> 0.26161926 | O19: =QUARTILE(O11:O16,3) -> 0.35647972 | P19: =QUARTILE(P11:P16,3) -> 0.50157068
B20: Median | E20: =MEDIAN(E11:E16) -> 3171.665 | F20: =MEDIAN(F11:F16) -> 405.84333 | G20: =MEDIAN(G11:G16) -> 105.09 | H20: =MEDIAN(H11:H16) -> 5.9381414 | I20: =MEDIAN(I11:I16) -> 27.308266 | N20: =MEDIAN(N11:N16) -> 0.23848758 | O20: =MEDIAN(O11:O16) -> 0.22387773 | P20: =MEDIAN(P11:P16) -> 0.41188271
B21: 25th Percentile | E21: =QUARTILE(E11:E16,1) -> 2846.4525 | F21: =QUARTILE(F11:F16,1) -> 374.00667 | G21: =QUARTILE(G11:G16,1) -> 15.728666 | H21: =QUARTILE(H11:H16,1) -> 4.3567005 | I21: =QUARTILE(I11:I16,1) -> 25.197776 | N21: =QUARTILE(N11:N16,1) -> 0.18238958 | O21: =QUARTILE(O11:O16,1) -> 0.19115616 | P21: =QUARTILE(P11:P16,1) -> 0.28054089
B22: Minimum | E22: =MIN(E11:E16) -> 1190.66 | F22: =MIN(F11:F16) -> 234.19 | G22: =MIN(G11:G16) -> 13.26 | H22: =MIN(H11:H16) -> 3 | I22: =MIN(I11:I16) -> 20.877602 | N22: =MIN(N11:N16) -> 0.075417069 | O22: =MIN(O11:O16) -> 0.14092881 | P22: =MIN(P11:P16) -> 0.12448641

Sheet Sample
B3: =Company_Name&" - Usage and Adoption Trends" -> Butterfly Network, inc. - Usage and Adoption Trends
B5: Institution | C5: Butterfly IQ+ | D5: Butterfly IQ3 | E5: Blueprint
B7: Mount Sinai
B8: STAR Center | C8: 5 | D8: 0 | E8: No
B9: CAMS
B11: Columbia

Sheet PPT
B3: Implied Share Price Matrix - DCF | F3: Key Stats
D4: Perpetuity | F4: Initiation Date | H4: 46076
C5: Multiples Method | D5: Growth Method | F5: Initiation Price | H5: 3.06
B6: Upside | C6: 9.5962138 | D6: 11.701936 | F6: Price | H6: 3.79
B7: Discount | C7: 1.5319825 | D7: 2.0875822 | F7: Price Target | H7: 6.97
B8: Base | C8: 5.9395976 | D8: 7.4818276 | F8: 52 Week High - Low | H8: $1.32 - $5.03
B9: Discount | C9: 0.56717615 | D9: 0.97409699 | F9: Shares Outstanding - Mil | H9: =Diluted -> 227.39
B10: Downside | C10: 3.5848166 | D10: 4.6960088 | F10: Market Cap - Mil | H10: 957
B11: Discount | C11: -0.054138088 | D11: 0.23905246 | F11: Book Value / Share | H11: 0.77
B12: Median | D12: =MEDIAN(C6:D6,C8:D8,C10:D10) -> 6.7107126 | F12: Cash per Share | H12: 0.59
F13: Dividend | H13: N/A
