Workbook
Name Bundle: DCF!$F$6
Name COGS: DCF!$E$121
Name Company_Name: Model!$H$7
Name Cost_of_Debt: WACC!$F$8
Name Cost_of_Preferred: WACC!$F$9
Name Diluted: Model!$H$10
Name Discount_Rate: DCF!$F$15
Name Equity_Risk_Premium: WACC!$F$7
Name Forward_Year_1: Model!$O$14
Name Forward_Year_2: Model!$O$15
Name Forward_Year_3: Model!$O$16
Name Hist_Year: Model!$O$7
Name LTM: Model!$O$13
Name Pub_Comps_Params: PubComps_Data!$C$3:$C$99
Name Pub_Comps_Range: PubComps_Data!$C$3:$AL$99
Name Pub_Comps_Tickers: PubComps_Data!$C$3:$AL$3
Name Risk_Free_Rate: WACC!$F$6
Name Scenario: DCF!$F$5
Name Share_Price: Model!$H$9
Name Tax_Rate: Model!$H$12
Name Terminal_Growth_Rate: DCF!$P$10
Name Ticker: Model!$H$8
Name Units: Model!$H$15
Name Uplift: DCF!$F$7
Name Valuation_Date: Model!$O$10

Sheet Cover
B2: =Company_Name&" - Operating Model and Valuation - Cover Page and Navigation" -> Ouster, Inc. - Operating Model and Valuation - Cover Page and Navigation
C12: Company Name: | D12: =Company_Name -> Ouster, Inc.
C13: Model Name: | D13: Operating Model and Valuation (5-Year Forecast)
C14: Author: | D14: Glenn Rentrop, Atlantic Walk Research
C16: File Name: | D16: =MID(CELL("filename"),SEARCH("[",CELL("filename"))+1, SEARCH("]",CELL("filename"))-SEARCH("[",CELL("filename"))-1) -> OUSTMODEL.xlsx
C17: Analysis Date: | D17: =Valuation_Date -> 46062
C19: Navigation, Summary, or Graph Worksheet:
C20: Financial Model Worksheet:
C21: Data and Back-End Calculation Worksheet:
B23: # | C23: Sheet Name | D23: Link to Sheet
B24: =_xlfn.SHEET(INDIRECT(D24&"!A1")) -> 2 | C24: Model and Valuation Summary | D24: Summary
B25: =_xlfn.SHEET(INDIRECT(D25&"!A1")) -> 3 | C25: Graphs | D25: Graphs
B26: =_xlfn.SHEET(INDIRECT(D26&"!A1")) -> 4 | C26: Quarterly figures & KPIs | D26: Q
B27: =_xlfn.SHEET(INDIRECT(D27&"!A1")) -> 5 | C27: Operating Scenarios and 3-Statement Model | D27: Model
B28: =_xlfn.SHEET(INDIRECT(D28&"!A1")) -> 6 | C28: Debt, Capex, D&A | D28: Drivers
B29: =_xlfn.SHEET(INDIRECT(D29&"!A1")) -> 7 | C29: Discounted Cash Flow Analysis and Sensitivities | D29: DCF
B30: =_xlfn.SHEET(INDIRECT(D30&"!A1")) -> 8 | C30: Weighted Average Cost of Capital (WACC) Calculations | D30: WACC
B31: =_xlfn.SHEET(INDIRECT(D31&"!A1")) -> 9 | C31: Comparable Public Companies - Output | D31: PubComps
B32: =_xlfn.SHEET(INDIRECT(D32&"!A1")) -> 10 | C32: Comparable Public Companies - Data and Calculations | D32: PubComps_Data
B33: =_xlfn.SHEET(INDIRECT(D33&"!A1")) -> 11 | C33: Precedent Transactions | D33: MAComps

Sheet Summary
C3: =Company_Name&" - Summary of Operating Model and Valuation - "&Scenario&" Case" -> Ouster, Inc. - Summary of Operating Model and Valuation - Base Case
C4: ($ in Thousands Except Per Share and Per Unit Data)
G6: Historical: | K6: Projected: | R6: Projected
C7: Summary of Operational Performance: | E7: Units: | G7: =[1]Model!H17 -> 44561 | H7: =[1]Model!I17 -> 44926 | I7: =[1]Model!J17 -> 45291 | J7: =[1]Model!K17 -> 45657 | K7: =[1]Model!L17 -> 46022 | L7: =[1]Model!M17 -> 46387 | M7: =[1]Model!N17 -> 46752 | N7: =[1]Model!O17 -> 47118 | O7: =[1]Model!P17 -> 47483 | P7: =EOMONTH(O7,12) -> 47848 | R7: CAGR:
C8: Company-Wide:
C10: Revenue | E10: $T | G10: =Drivers!F6 -> 33578 | H10: =Drivers!G6 -> 41029 | I10: =Drivers!H6 -> 83279 | J10: =Drivers!I6 -> 111101 | K10: =Drivers!J6 -> 169000 | L10: =Drivers!K6 -> 254788 | M10: =Drivers!L6 -> 365254.16 | N10: =Drivers!M6 -> 535307.84 | ... P10: =Drivers!O6 -> 912910.72 | R10: =(O10/J10)^(1/YEARFRAC(J$7,O$7,))-1 -> 0.45005662
C12: Sensors Shipped | E12: # | G12: =Drivers!F8 -> 6475 | H12: =Drivers!G8 -> 8650 | I12: =Drivers!H8 -> 13400 | J12: =Drivers!I8 -> 17300 | K12: =Drivers!J8 -> 25000 | L12: =Drivers!K8 -> 33750 | M12: =Drivers!L8 -> 47250 | N12: =Drivers!M8 -> 68512.5 | ... P12: =Drivers!O8 -> 120239.44
C15: Gross Profit: | E15: $T | G15: =Model!G72 -> 9086 | H15: =Model!H72 -> 10930 | I15: =Model!I72 -> 8314 | J15: =Model!J72 -> 40460 | K15: =Model!K72 -> 82810 | L15: =Model!L72 -> 101915.2 | M15: =Model!M72 -> 146101.67 | N15: =Model!N72 -> 214123.14 | ... P15: =Model!P72 -> 365164.29 | R15: =(O15/J15)^(1/YEARFRAC(J$7,O$7,))-1 -> 0.47752683
C16: Profit Margin: | E16: % | G16: =G15/G10 -> 0.27059384 | H16: =H15/H10 -> 0.26639694 | I16: =I15/I10 -> 0.099833091 | J16: =J15/J10 -> 0.36417314 | K16: =K15/K10 -> 0.49 | L16: =L15/L10 -> 0.4 | M16: =M15/M10 -> 0.4 | N16: =N15/N10 -> 0.4 | ... P16: =P15/P10 -> 0.4
C18: Total Operating Expenses | E18: $T | G18: =-Model!G79 -> 108796 | H18: =-Model!H79 -> 156353 | I18: =-Model!I79 -> 381506 | J18: =-Model!J79 -> 144637 | K18: =-Model!K79 -> 160207.64 | L18: =-Model!L79 -> 155000 | M18: =-Model!M79 -> 155000 | N18: =-Model!N79 -> 155000 | ... P18: =-Model!P79 -> 155000
C20: EBIT | E20: $T | G20: =Model!G81 -> -99710 | H20: =Model!H81 -> -145423 | I20: =Model!I81 -> -373192 | J20: =Model!J81 -> -104177 | K20: =Model!K81 -> -77397.642 | L20: =Model!L81 -> -53084.8 | M20: =Model!M81 -> -8898.3344 | N20: =Model!N81 -> 59123.137 | ... P20: =Model!P81 -> 210164.29
C22: Comprehensive Income: | E22: $T | G22: =Model!G95 -> -93987 | H22: =Model!H95 -> -138703 | I22: =Model!I95 -> -373769 | J22: =Model!J95 -> -98240 | K22: =Model!K95 -> -67208.942 | L22: =Model!L95 -> -41538.641 | M22: =Model!M95 -> -4046.9856 | N22: =Model!N95 -> 53089.667 | ... P22: =Model!P95 -> 182422.33 | R22: =(O22/J22)^(1/YEARFRAC(J$7,O$7,))-1 -> -2.0283012
C23: Basic Earnings per Share (EPS): | E23: $ as Stated | G23: =Model!G100 -> -0.7 | H23: =Model!H100 -> -0.78 | I23: =Model!I100 -> -10.1 | J23: =Model!J100 -> -2.08 | K23: =Model!K100 -> -1.273786 | L23: =Model!L100 -> -0.75907701 | M23: =Model!M100 -> -0.064737467 | N23: =Model!N100 -> 0.94055831 | ... P23: =Model!P100 -> 3.0455256
C25: Capital expenditures: | E25: $T | G25: =Model!G183 -> -4283 | H25: =Model!H183 -> -5422 | I25: =Model!I183 -> -3006 | J25: =Model!J183 -> -3756 | K25: =Model!K183 -> -4806.2293 | L25: =Model!L183 -> -4650 | M25: =Model!M183 -> -4650 | N25: =Model!N183 -> -4650 | ... P25: =Model!P183 -> -4650 | R25: =(O25/J25)^(1/YEARFRAC(J$7,O$7,))-1 -> 0.043627403
C26: % Revenue: | E26: %
C28: Cash Flow From Operations: | E28: $T | G28: =Model!G180 -> -71061 | H28: =Model!H180 -> -110690 | I28: =Model!I180 -> -137890 | J28: =Model!J180 -> -33694 | K28: =Model!K180 -> -51116.581 | L28: =Model!L180 -> -37652.437 | M28: =Model!M180 -> -2912.2802 | N28: =Model!N180 -> 54390.923 | ... P28: =Model!P180 -> 196538.15 | R28: =(O28/J28)^(1/YEARFRAC(J$7,O$7,))-1 -> -2.2942193
C29: Cash Flow From Investing: | E29: $T | G29: =Model!G187 -> -15229 | H29: =Model!H187 -> -5147 | I29: =Model!I187 -> 50601 | J29: =Model!J187 -> 14652 | K29: =Model!K187 -> 7818.7707 | L29: =Model!L187 -> -2661.9517 | M29: =Model!M187 -> 27862.011 | N29: =Model!N187 -> -24312.76 | ... P29: =Model!P187 -> -79568.676 | R29: =(O29/J29)^(1/YEARFRAC(J$7,O$7,))-1 -> -2.1410686
C30: Cash Flows From Financing Activities: | E30: $T | G30: =Model!G204 -> 258304 | H30: =Model!H204 -> 55602 | I30: =Model!I204 -> 15657 | J30: =Model!J204 -> 15393 | K30: =Model!K204 -> 94100 | L30: =Model!L204 -> 0 | M30: =Model!M204 -> 0 | N30: =Model!N204 -> 0 | ... P30: =Model!P204 -> 0 | R30: =(O30/J30)^(1/YEARFRAC(J$7,O$7,))-1 -> -1
C32: Total Assets: | E32: $T | G32: =Model!G121 -> 307702 | H32: =Model!H121 -> 256137 | I32: =Model!I121 -> 330743 | J32: =Model!J121 -> 276148 | K32: =Model!K121 -> 332134.86 | L32: =Model!L121 -> 316873.53 | M32: =Model!M121 -> 341705.37 | N32: =Model!N121 -> 435035.49 | ... P32: =Model!P121 -> 807978.68 | R32: =(O32/J32)^(1/YEARFRAC(J$7,O$7,))-1 -> 0.16296275
C33: Long-term Debt: | E33: $T | G33: =Model!G131 -> 0 | H33: =Model!H131 -> 39574 | I33: =Model!I131 -> 43975 | J33: =Model!J131 -> 0 | K33: =Model!K131 -> 0 | L33: =Model!L131 -> 0 | M33: =Model!M131 -> 0 | N33: =Model!N131 -> 0 | ... P33: =Model!P131 -> 0 | R33: =(O33/J33)^(1/YEARFRAC(J$7,O$7,))-1 -> #DIV/0!
C34: Cash and Cash Equivalents: | E34: $T | G34: =SUM(Model!G106:G108) -> 183621 | H34: =SUM(Model!H106:H108) -> 123189 | I34: =SUM(Model!I106:I108) -> 190701 | J34: =SUM(Model!J106:J108) -> 172744 | K34: =SUM(Model!K106:K108) -> 210565.69 | L34: =SUM(Model!L106:L108) -> 132850.13 | M34: =SUM(Model!M106:M108) -> 124987.19 | N34: =SUM(Model!N106:N108) -> 174281.54 | ... P34: =SUM(Model!P106:P108) -> 483102.52 | R34: =(O34/J34)^(1/YEARFRAC(J$7,O$7,))-1 -> 0.11039289
C36: EBITDA: | E36: $T | G36: =Model!G97 -> -94233 | H36: =Model!H97 -> -135967 | I36: =Model!I97 -> -356044 | J36: =Model!J97 -> -94341 | K36: =Model!K97 -> -75152.108 | L36: =Model!L97 -> -49884.908 | M36: =Model!M97 -> -4939.6756 | N36: =Model!N97 -> 63720.509 | ... P36: =Model!P97 -> 215814.4 | R36: =(O36/J36)^(1/YEARFRAC(J$7,O$7,))-1 -> -2.0743962
C37: EBITDA Margin: | E37: % | G37: =DCF!G64 -> -2.8063911 | H37: =DCF!H64 -> -3.3139243 | I37: =DCF!I64 -> -4.2753155 | J37: =DCF!J64 -> -0.84914627 | K37: =DCF!K64 -> -0.44468703 | L37: =DCF!L64 -> -0.19578987 | M37: =DCF!M64 -> -0.013523941 | N37: =DCF!N64 -> 0.11903526 | ... P37: =DCF!P64 -> 0.23640253

Sheet Graphs
J2: ="Revenue and Gross Profit" -> Revenue and Gross Profit | V2: Revenue and EBITDA
J18: ="Revenue and OpEx" -> Revenue and OpEx | V18: ="Revenue and EBIT" -> Revenue and EBIT
J33: ="Sensors Shipped and ASP - Annual" -> Sensors Shipped and ASP - Annual | V33: Sensors Shipped and ASP - Quarterly
J52: Revenue By Segment

Sheet Q
B2: =Company_Name&" - Q3 Financial Results" -> Ouster, Inc. - Q3 Financial Results
B3: ($ in Thousands Except Per Share and Per Unit Data)
B6: Reported Income Statement and Cash Flow Statement Figures from Q3: | H6: FY25- Q1 | I6: FY25- Q2 | J6: FY25- Q3 | K6: FY25- Q4
C8: Royalty Revenue: | H8: 0 | I8: 0 | J8: 0 | K8: 21000
C10: Product Revenue: | H10: 32632 | I10: 35049 | J10: 39525 | K10: 41000
C11: % Growth | I11: =I10/H10-1 -> 0.074068399 | J11: =J10/I10-1 -> 0.12770692 | K11: =K10/J10-1 -> 0.037318153
C13: Total Revenue: | H13: =SUM(H8,H10) -> 32632 | I13: =SUM(I8,I10) -> 35049 | J13: =SUM(J8,J10) -> 39525 | K13: =SUM(K8,K10) -> 62000
C15: Operating Income (EBIT): | H15: -23830 | I15: -26822 | J15: -24251
C16: Annual Operating Margin: | H16: =+H15/H10 -> -0.73026477 | I16: =+I15/I10 -> -0.76527148 | J16: =+J15/J10 -> -0.61356104
C18: Taxes, Excluding Effect of Interest: | H18: 195 | I18: -3616 | J18: 72
C20: Net Operating Profit After Tax (NOPAT): | H20: =SUM(H15,H18) -> -23635 | I20: =SUM(I15,I18) -> -30438 | J20: =SUM(J15,J18) -> -24179
C22: Adjustments for Non-Cash Charges:
C23: Depreciation & Amortization: | H23: 1795 | I23: 1859 | J23: 2053
C24: Deferred Income Taxes: | H24: 0 | I24: 0 | J24: 0
C25: Other Operating Activities: | H25: 9402 | I25: 15211 | J25: 12060
C26: Total Adjustments for Non-Cash Charges: | H26: =SUM(H23:H25) -> 11197 | I26: =SUM(I23:I25) -> 17070 | J26: =SUM(J23:J25) -> 14113
C28: Net Change in Working Capital:
C29: Accounts Receivable: | H29: 4137 | I29: 2334 | J29: -9401
C30: Inventories: | H30: 1051 | I30: 998 | J30: -1594
C31: Accounts Payable: | H31: 4120 | I31: 2305 | J31: 2791
C32: Other Liabilities: | H32: -3367 | I32: -3404 | J32: -2518
C33: Total Net Change in Working Capital: | H33: =SUM(H29:H32) -> 5941 | I33: =SUM(I29:I32) -> 2233 | J33: =SUM(J29:J32) -> -10722
C35: Capital Expenditures and Acquisitions: | H35: -552 | I35: -889 | J35: -1702
C37: Q3 Unlevered Free Cash Flow: | H37: =SUM(H20,H26,H33,H35) -> -7049 | I37: =SUM(I20,I26,I33,I35) -> -12024 | J37: =SUM(J20,J26,J33,J35) -> -22490
C39: Sensors Shipped | H39: 4700 | I39: 5500 | J39: 7200 | K39: 8100
C40: % change | I40: =I39/H39-1 -> 0.17021277 | J40: =J39/I39-1 -> 0.30909091 | K40: =K39/J39-1 -> 0.125
C42: ASP | H42: =H10/H39*Units -> 6942.9787 | I42: =I10/I39*Units -> 6372.5455 | J42: =J10/J39*Units -> 5489.5833 | K42: 6760
C43: % change | I43: =I42/H42-1 -> -0.082159732 | J43: =J42/I42-1 -> -0.13855721

Sheet Model
I4: Historical | O4: Projected:
B5: =Company_Name -> Ouster, Inc. | E5: Units: | G5: =EOMONTH(H5,-12) -> 44561 | H5: 44926 | I5: =EOMONTH(H5,12) -> 45291 | J5: =EOMONTH(I5,12) -> 45657 | K5: =EOMONTH(J5,12) -> 46022 | L5: =EOMONTH(K5,12) -> 46387 | M5: =EOMONTH(L5,12) -> 46752 | N5: =EOMONTH(M5,12) -> 47118 | O5: =EOMONTH(N5,12) -> 47483
C7: Company Name: | E7: Name | H7: Ouster, Inc. | L7: Last Fiscal Year: | O7: 45657
C8: Ticker: | E8: Name | H8: OUST | L8: Next Fiscal Year: | O8: =EOMONTH(O7,12) -> 46022
C9: Current Share Price: | E9: $ / Share | H9: 21.06 | L9: Most Recent Quarter End Date: | O9: 45608
C10: Diluted Shares Outstanding: | E10: M Shares | H10: 52.56 | L10: Valuation Date: | O10: 46062
C12: Effective Tax Rate: | E12: % | H12: 0.21
C13: Discount Rate (WACC): | E13: % | H13: =Discount_Rate -> 0.10836181 | L13: LTM Period: | O13: 45930
L14: Forward Year 1: | O14: =EOMONTH(O7,12) -> 46022
C15: Conversion Units: | E15: # | H15: 1000 | L15: Forward Year 2: | O15: =EOMONTH(O14,12) -> 46387
L16: Forward Year 3: | O16: =EOMONTH(O15,12) -> 46752
I18: Historical | N18: Projected:
B19: =Company_Name&" - Financial Drivers" -> Ouster, Inc. - Financial Drivers | E19: Units: | G19: =EOMONTH(H19,-12) -> 44561 | H19: 44926 | I19: =EOMONTH(H19,12) -> 45291 | J19: =EOMONTH(I19,12) -> 45657 | K19: =EOMONTH(J19,12) -> 46022 | L19: =EOMONTH(K19,12) -> 46387 | M19: =EOMONTH(L19,12) -> 46752 | N19: =EOMONTH(M19,12) -> 47118 | O19: =EOMONTH(N19,12) -> 47483 | P19: =EOMONTH(O19,12) -> 47848
C20: INCOME STATEMENT
C22: Cost of product % Revenue | E22: % | G22: =G71/-G69 -> 0.72940616 | H22: =H71/-H69 -> 0.73360306 | I22: =I71/-I69 -> 0.90016691 | J22: =J71/-J69 -> 0.63582686 | K22: =INDEX($K$23:$P$25,MATCH(Scenario,$C$23:$C$25,0),1) -> 0.51 | L22: =INDEX($K$23:$P$25,MATCH(Scenario,$C$23:$C$25,0),2) -> 0.6 | M22: =INDEX($K$23:$P$25,MATCH(Scenario,$C$23:$C$25,0),3) -> 0.6 | N22: =INDEX($K$23:$P$25,MATCH(Scenario,$C$23:$C$25,0),4) -> 0.6 | O22: =INDEX($K$23:$P$25,MATCH(Scenario,$C$23:$C$25,0),5) -> 0.6 | P22: =INDEX($K$23:$P$25,MATCH(Scenario,$C$23:$C$25,0),6) -> 0.6
C23: Upside | E23: % | K23: 0.6 | L23: 0.55 | M23: =L23-2% -> 0.53 | N23: 0.55 | O23: 0.55 | P23: 0.55
C24: Base | E24: % | K24: 0.51 | L24: 0.6 | M24: 0.6 | N24: 0.6 | O24: 0.6 | P24: 0.6
C25: Downside | E25: % | K25: 0.63 | L25: 0.65 | M25: 0.61 | N25: 0.62 | O25: 0.63 | P25: 0.64
C27: Research and development % Revenue | E27: % | G27: =G75/G$69 -> 1.0298112 | H27: =H75/H$69 -> 1.5675985 | I27: =I75/I$69 -> 1.0952341 | J27: =J75/J$69 -> 0.52280358 | K27: 0.45 | L27: 0.28 | M27: 0.22 | N27: 0.17 | O27: 0.13 | P27: 0.1
C28: Sales and marketing % Revenue | E28: % | G28: =G76/G$69 -> 0.6628745 | H28: =H76/H$69 -> 0.75149285 | I28: =I76/I$69 -> 0.499994 | J28: =J76/J$69 -> 0.25069081 | K28: 0.21 | L28: 0.13 | M28: 0.11 | N28: 0.09 | O28: 0.07 | P28: 0.05
C29: General and administrative % Revenue | E29: % | G29: =G77/G$69 -> 1.547412 | H29: =H77/H$69 -> 1.491701 | I29: =I77/I$69 -> 0.98442585 | J29: =J77/J$69 -> 0.52835708 | K29: 0.37 | L29: 0.25 | M29: 0.19 | N29: 0.15 | O29: 0.12 | P29: 0.09
C31: Interest income % Cash & Equivalents | E31: % | H31: =H83/SUM(G106:G108) -> 0.012024768 | I31: =I83/SUM(H106:H108) -> 0.07336694 | J31: =J83/SUM(I106:I108) -> 0.057262416 | K31: 0.05 | L31: 0.05 | M31: 0.04 | N31: 0.04 | O31: 0.03 | P31: 0.03
C33: Beginning NOLs Balance | E33: $T | G33: 0 | H33: =G36 -> 461681 | I33: =H36 -> 595299 | J33: =I36 -> 667823 | K33: =J36 -> 701611 | L33: =K36 -> 768561.19 | M33: =L36 -> 809596.9 | N33: =M36 -> 813193.71 | O33: =N36 -> 761882.09 | P33: =O36 -> 653106.83
C34: (+) NOLs Created | E34: $T | G34: 461681 | H34: 133618 | I34: 72524 | J34: 33788 | K34: =IF(K88<0,K88*-1,0) -> 66950.192 | L34: =IF(L88<0,L88*-1,0) -> 41035.703 | M34: =IF(M88<0,M88*-1,0) -> 3596.8137 | N34: =IF(N88<0,N88*-1,0) -> 0 | O34: =IF(O88<0,O88*-1,0) -> 0 | P34: =IF(P88<0,P88*-1,0) -> 0
C35: (-) NOLs Used | E35: $T | G35: 0 | H35: 0 | I35: 0 | J35: 0 | K35: =-MIN(+K33+K34,MAX(K88*K40,0)) -> 0 | L35: =-MIN(+L33+L34,MAX(L88*L40,0)) -> 0 | M35: =-MIN(+M33+M34,MAX(M88*M40,0)) -> 0 | N35: =-MIN(+N33+N34,MAX(N88*N40,0)) -> -51311.616 | O35: =-MIN(+O33+O34,MAX(O88*O40,0)) -> -108775.26 | P35: =-MIN(+P33+P34,MAX(P88*P40,0)) -> -175601.63
C36: Ending Balance | E36: $T | G36: =SUM(G33:G35) -> 461681 | H36: =SUM(H33:H35) -> 595299 | I36: =SUM(I33:I35) -> 667823 | J36: =SUM(J33:J35) -> 701611 | K36: =SUM(K33:K35) -> 768561.19 | L36: =SUM(L33:L35) -> 809596.9 | M36: =SUM(M33:M35) -> 813193.71 | N36: =SUM(N33:N35) -> 761882.09 | ... P36: =SUM(P33:P35) -> 477505.2
C38: Taxable Income After NOL | E38: $T | G38: - | H38: - | I38: - | J38: -33788 | K38: =-SUM(K119,K35) -> -1262.5 | L38: =-SUM(L119,L35) -> -1319.375 | M38: =-SUM(M119,M35) -> -1376.9688 | N38: =-SUM(N119,N35) -> 49863.155 | O38: =-SUM(O119,O35) -> 107423.43 | P38: =-SUM(P119,P35) -> 174227.47
C39: Cash Taxes Payable | E39: $T | G39: - | H39: - | I39: - | J39: - | K39: =IF(K38<0,0,K38*Tax_Rate) -> 0 | L39: =IF(L38<0,0,L38*Tax_Rate) -> 0 | M39: =IF(M38<0,0,M38*Tax_Rate) -> 0 | N39: =IF(N38<0,0,N38*Tax_Rate) -> 10471.262 | O39: =IF(O38<0,0,O38*Tax_Rate) -> 22558.921 | P39: =IF(P38<0,0,P38*Tax_Rate) -> 36587.769
C40: NOL Utilization Limit (% of EBT) | E40: % | G40: 0.8 | H40: 0.8 | I40: 0.8 | J40: 0.8 | K40: 0.8 | L40: 0.8 | M40: 0.8 | N40: 0.8 | O40: 0.8 | P40: 0.8
C42: BALANCE SHEET
C44: Short-term investments | E44: % | I44: =I108/H106 -> 1.1319917 | J44: =J108/I106 -> 2.4804377 | K44: 2.5 | L44: 0.8 | M44: 0.8 | N44: 0.8 | O44: 0.8 | P44: 0.8
C45: Days receivables outstanding | E45: Days | G45: =G109*(G$104-EOMONTH(G$104,-12))/G$69 -> 116.56129 | H45: =H109*(H$104-EOMONTH(H$104,-12))/H$69 -> 99.930415 | I45: =I109*(I$104-EOMONTH(I$104,-12))/I$69 -> 63.888916 | J45: =J109*(J$104-EOMONTH(J$104,-12))/J$69 -> 59.103032 | K45: 52 | L45: =K45-4 -> 48 | M45: =L45-4 -> 44 | N45: =M45-4 -> 40 | O45: =N45-4 -> 36 | P45: =O45-4 -> 32
C46: Days inventory outstanding | E46: Days | G46: =G110*(G$104-EOMONTH(G$104,-12))/G$69 -> 80.961344 | H46: =H110*(H$104-EOMONTH(H$104,-12))/H$69 -> 173.76843 | I46: =I110*(I$104-EOMONTH(I$104,-12))/I$69 -> 101.82255 | J46: =J110*(J$104-EOMONTH(J$104,-12))/J$69 -> 54.08252 | K46: 52 | L46: =K46-4 -> 48 | M46: =L46-4 -> 44 | N46: =M46-4 -> 40 | O46: =N46-4 -> 36 | P46: =O46-4 -> 32
C47: Prepaid expenses and other current assets % Revenue | E47: % | G47: =G111/G69 -> 0.1657633 | H47: =H111/H69 -> 0.20821858 | I47: =I111/I69 -> 0.41603525 | J47: =J111/J69 -> 0.11476044 | K47: 0.08 | L47: 0.07 | M47: 0.07 | N47: 0.06 | O47: 0.06 | P47: 0.05
C49: Operating lease, right-of-use assets % Operating lease liability | E49: % | G49: =G115/SUM(G126,G129) -> 0.7863035 | H49: =H115/SUM(H126,H129) -> 0.78196258 | I49: =I115/SUM(I126,I129) -> 0.71600509 | J49: =J115/SUM(J126,J129) -> 0.7065679 | K49: =AVERAGE(G49:J49) -> 0.74770977 | L49: =AVERAGE(H49:K49) -> 0.73806133 | M49: =AVERAGE(I49:L49) -> 0.72708602 | N49: =AVERAGE(J49:M49) -> 0.72985626 | O49: =AVERAGE(K49:N49) -> 0.73567835 | P49: =AVERAGE(L49:O49) -> 0.73267049
C50: Unbilled receivable, non-current portion % Revenue | E50: % | G50: =G116/G69 -> 0 | H50: =H116/H69 -> 0 | I50: =I116/I69 -> 0.12688673 | J50: =J116/J69 -> 0.0912053 | K50: 0.07 | L50: 0.06 | M50: 0.05 | N50: 0.05 | O50: 0.04 | P50: 0.04
C52: Days Payables Outstanding | E52: Days | G52: =G123*(G104-EOMONTH(G104,-12))/G69 -> 52.861844 | H52: =H123*(H104-EOMONTH(H104,-12))/H69 -> 78.268298 | I52: =I123*(I104-EOMONTH(I104,-12))/I69 -> 15.53723 | J52: =J123*(J104-EOMONTH(J104,-12))/J69 -> 20.714557 | K52: 22 | L52: =K52-2 -> 20 | M52: =L52-2 -> 18 | N52: =M52-2 -> 16 | O52: =N52-2 -> 14 | P52: =O52-2 -> 12
C53: Accrued and other current liabilities % Opex | E53: % | G53: =G124/-G79 -> 0.13027133 | H53: =H124/-H79 -> 0.11175353 | I53: =I124/-I79 -> 0.15246418 | J53: =J124/-J79 -> 0.2115019 | K53: 0.13 | L53: =K53-1% -> 0.12 | M53: =L53-1% -> 0.11 | N53: =M53-1% -> 0.1 | O53: =N53-1% -> 0.09 | P53: =O53-1% -> 0.08
C54: Contract liabilities, current % Revenue | E54: % | G54: =G125/G69 -> 0 | H54: =H125/H69 -> 0 | I54: =I125/I69 -> 0.15472088 | J54: =J125/J69 -> 0.30918714 | K54: =AVERAGE(I54:J54) -> 0.23195401 | L54: 0.15 | M54: =L54-4% -> 0.11 | N54: =M54-1% -> 0.1 | O54: 0.1 | P54: 0.1
C55: Operating lease liability, current portion | E55: % | H55: =G126/G129 -> 0.18922754 | I55: =H126/H129 -> 0.24037313 | J55: =I126/I129 -> 0.37690551 | K55: =J126/J129 -> 0.55124866 | L55: =AVERAGE(H55:K55) -> 0.33943871 | M55: =AVERAGE(I55:L55) -> 0.3769915 | N55: =AVERAGE(J55:M55) -> 0.4111461 | O55: =AVERAGE(K55:N55) -> 0.41970624 | P55: =AVERAGE(L55:O55) -> 0.38682064
C57: Operating lease liability, long-term portion, change | E57: % | H57: =(1-(H129/G129)) -> 0.17324778 | I57: =(1-(I129/H129)) -> -0.405 | J57: =(1-(J129/I129)) -> 0.30663409 | K57: =AVERAGE(H57:J57) -> 0.024960623
C58: Contract liabilities, long-term portion % Short -term portion | E58: % | I58: =I132/I125 -> 0.385487 | J58: =J132/J125 -> 0.073884312 | K58: 0.06 | L58: 0.06 | M58: 0.05 | N58: 0.05 | O58: 0.04 | P58: 0.04
C59: Other non-current liabilities % Revenue | E59: % | G59: =G133/G69 -> 0.031717196 | H59: =H133/H69 -> 0.045626264 | I59: =I133/I69 -> 0.019332605 | J59: =J133/J69 -> 0.010971998 | K59: 0.01 | L59: 0.01 | M59: 0.01 | N59: 0.01 | O59: 0.01 | P59: 0.01
C61: CASH FLOW STATEMENT
C63: Stock-based compensation % Opex | E63: % | G63: =G154/-G79 -> 0.23312438 | H63: =H154/-H79 -> 0.21311392 | I63: =I154/-I79 -> 0.15130824 | J63: =J154/-J79 -> 0.27972787 | K63: =AVERAGE(G63:J63) -> 0.2193186 | L63: 0.2 | M63: 0.18 | N63: 0.16 | O63: 0.14 | P63: 0.12
I66: Historical | N66: Projected:
B67: =Company_Name&" - Income Statement" -> Ouster, Inc. - Income Statement | E67: Units: | G67: =EOMONTH(H67,-12) -> 44561 | H67: 44926 | I67: =EOMONTH(H67,12) -> 45291 | J67: =EOMONTH(I67,12) -> 45657 | K67: =EOMONTH(J67,12) -> 46022 | L67: =EOMONTH(K67,12) -> 46387 | M67: =EOMONTH(L67,12) -> 46752 | N67: =EOMONTH(M67,12) -> 47118 | O67: =EOMONTH(N67,12) -> 47483 | P67: =EOMONTH(O67,12) -> 47848 | R67: Management Target
C69: Total revenue | G69: 33578 | H69: 41029 | I69: 83279 | J69: 111101 | K69: =Drivers!J6 -> 169000 | L69: =Drivers!K6 -> 254788 | M69: =Drivers!L6 -> 365254.16 | N69: =Drivers!M6 -> 535307.84 | O69: =Drivers!N6 -> 712266.9 | P69: =Drivers!O6 -> 912910.72
C71: Cost of product | G71: -24492 | H71: -30099 | I71: -74965 | J71: -70641 | K71: =-K69*K22 -> -86190 | L71: =-L69*L22 -> -152872.8 | M71: =-M69*M22 -> -219152.5 | N71: =-N69*N22 -> -321184.71 | O71: =-O69*O22 -> -427360.14 | P71: =-P69*P22 -> -547746.43
C72: Gross profit | G72: =SUM(G69,G71) -> 9086 | H72: =SUM(H69,H71) -> 10930 | I72: =SUM(I69,I71) -> 8314 | J72: =SUM(J69,J71) -> 40460 | K72: =SUM(K69,K71) -> 82810 | L72: =SUM(L69,L71) -> 101915.2 | M72: =SUM(M69,M71) -> 146101.67 | N72: =SUM(N69,N71) -> 214123.14 | ... P72: =SUM(P69,P71) -> 365164.29
C73: % Gross Margin | G73: =G72/G69 -> 0.27059384 | H73: =H72/H69 -> 0.26639694 | I73: =I72/I69 -> 0.099833091 | J73: =J72/J69 -> 0.36417314 | K73: =K72/K69 -> 0.49 | L73: =L72/L69 -> 0.4 | M73: =M72/M69 -> 0.4 | N73: =N72/N69 -> 0.4 | ... P73: =P72/P69 -> 0.4
C75: Research and development | G75: 34579 | H75: 64317 | I75: 91210 | J75: 58084 | K75: 69993.63 | L75: 66500 | M75: 66500 | N75: 66500 | O75: 66500 | P75: 66500 | R75: 66712
C76: Sales and marketing | G76: 22258 | H76: 30833 | I76: 41639 | J76: 27852 | K76: 32663.694 | L76: 31500 | M76: 31500 | N76: 31500 | O76: 31500 | P76: 31500 | R76: 31548
C77: General and administrative | G77: 51959 | H77: 61203 | I77: 81982 | J77: 58701 | K77: 57550.318 | L77: 57000 | M77: 57000 | N77: 57000 | O77: 57000 | P77: 57000 | R77: 57080
C78: Goodwill impairment charges | G78: 0 | H78: 0 | I78: 166675 | J78: 0 | K78: 0 | L78: 0 | M78: 0 | N78: 0 | O78: 0 | P78: 0
C79: Total operating expenses | G79: =-SUM(G75:G78) -> -108796 | H79: =-SUM(H75:H78) -> -156353 | I79: =-SUM(I75:I78) -> -381506 | J79: =-SUM(J75:J78) -> -144637 | K79: =-SUM(K75:K78) -> -160207.64 | L79: =-SUM(L75:L78) -> -155000 | M79: =-SUM(M75:M78) -> -155000 | N79: =-SUM(N75:N78) -> -155000 | ... P79: =-SUM(P75:P78) -> -155000
C81: EBIT | G81: =SUM(G72,G79) -> -99710 | H81: =SUM(H72,H79) -> -145423 | I81: =SUM(I72,I79) -> -373192 | J81: =SUM(J72,J79) -> -104177 | K81: =SUM(K72,K79) -> -77397.642 | L81: =SUM(L72,L79) -> -53084.8 | M81: =SUM(M72,M79) -> -8898.3344 | N81: =SUM(N72,N79) -> 59123.137 | ... P81: =SUM(P72,P79) -> 210164.29
C83: Interest income | G83: 471 | H83: 2208 | I83: 9038 | J83: 10920 | K83: =SUM(J106:J108)*K31 -> 8637.2 | L83: =SUM(K106:K108)*L31 -> 10528.284 | M83: =SUM(L106:L108)*M31 -> 5314.0051 | N83: =SUM(M106:M108)*N31 -> 4999.4876 | O83: =SUM(N106:N108)*O31 -> 5228.4463 | P83: =SUM(O106:O108)*P31 -> 8747.976
C84: Interest expense | G84: -504 | H84: -2694 | I84: -9303 | J84: 0 | K84: 0 | L84: 0 | M84: 0 | N84: 0 | O84: 0 | P84: 0
C85: Other income (expense), net | G85: 2968 | H85: 7654 | I85: -130 | J85: -3251 | K85: =AVERAGE(G85:J85) -> 1810.25 | L85: =AVERAGE(H85:K85) -> 1520.8125 | M85: =AVERAGE(I85:L85) -> -12.484375 | N85: =AVERAGE(J85:M85) -> 16.894531 | O85: =AVERAGE(K85:N85) -> 833.86816 | P85: =AVERAGE(L85:O85) -> 589.77271
C86: Total other income (expense), net | G86: =SUM(G83:G85) -> 2935 | H86: =SUM(H83:H85) -> 7168 | I86: =SUM(I83:I85) -> -395 | J86: =SUM(J83:J85) -> 7669 | K86: =SUM(K83:K85) -> 10447.45 | L86: =SUM(L83:L85) -> 12049.097 | M86: =SUM(M83:M85) -> 5301.5207 | N86: =SUM(N83:N85) -> 5016.3822 | ... P86: =SUM(P83:P85) -> 9337.7488
C88: Loss before income taxes | G88: =SUM(G81,G86) -> -96775 | H88: =SUM(H81,H86) -> -138255 | I88: =SUM(I81,I86) -> -373587 | J88: =SUM(J81,J86) -> -96508 | K88: =SUM(K81,K86) -> -66950.192 | L88: =SUM(L81,L86) -> -41035.703 | M88: =SUM(M81,M86) -> -3596.8137 | N88: =SUM(N81,N86) -> 64139.519 | ... P88: =SUM(P81,P86) -> 219502.04
C90: Provision for income tax expense | G90: 2794 | H90: -305 | I90: -523 | J90: -537 | K90: =-K39 -> 0 | L90: =-L39 -> 0 | M90: =-M39 -> 0 | N90: =-N39 -> -10471.262 | O90: =-O39 -> -22558.921 | P90: =-P39 -> -36587.769
C91: Net loss | G91: =SUM(G88,G90) -> -93981 | H91: =SUM(H88,H90) -> -138560 | I91: =SUM(I88,I90) -> -374110 | J91: =SUM(J88,J90) -> -97045 | K91: =SUM(K88,K90) -> -66950.192 | L91: =SUM(L88,L90) -> -41035.703 | M91: =SUM(M88,M90) -> -3596.8137 | N91: =SUM(N88,N90) -> 53668.257 | ... P91: =SUM(P88,P90) -> 182914.27
C93: Changes in unrealized (loss) gain on available for sale securities | G93: 0 | H93: 0 | I93: 354 | J93: -386 | K93: =AVERAGE(I93:J93) -> -16 | L93: =AVERAGE(J93:K93) -> -201 | M93: =AVERAGE(K93:L93) -> -108.5 | N93: =AVERAGE(L93:M93) -> -154.75 | O93: =AVERAGE(M93:N93) -> -131.625 | P93: =AVERAGE(N93:O93) -> -143.1875
C94: Foreign currency translation adjustments | G94: -6 | H94: -143 | I94: -13 | J94: -809 | K94: =AVERAGE(G94:J94) -> -242.75 | L94: =AVERAGE(H94:K94) -> -301.9375 | M94: =AVERAGE(I94:L94) -> -341.67188 | N94: =AVERAGE(J94:M94) -> -423.83984 | O94: =AVERAGE(K94:N94) -> -327.5498 | P94: =AVERAGE(L94:O94) -> -348.74976
C95: Total comprehensive loss | G95: =SUM(G91,G93:G94) -> -93987 | H95: =SUM(H91,H93:H94) -> -138703 | I95: =SUM(I91,I93:I94) -> -373769 | J95: =SUM(J91,J93:J94) -> -98240 | K95: =SUM(K91,K93:K94) -> -67208.942 | L95: =SUM(L91,L93:L94) -> -41538.641 | M95: =SUM(M91,M93:M94) -> -4046.9856 | N95: =SUM(N91,N93:N94) -> 53089.667 | ... P95: =SUM(P91,P93:P94) -> 182422.33
C97: EBITDA | G97: =G81+G151 -> -94233 | H97: =H81+H151 -> -135967 | I97: =I81+I151 -> -356044 | J97: =J81+J151 -> -94341 | K97: =K81+K151 -> -75152.108 | L97: =L81+L151 -> -49884.908 | M97: =M81+M151 -> -4939.6756 | N97: =N81+N151 -> 63720.509 | ... P97: =P81+P151 -> 215814.4
C98: margin
C100: Net loss per common share, basic and diluted | G100: -0.7 | H100: -0.78 | I100: -10.1 | J100: -2.08 | K100: =(K91*1000)/K101 -> -1.273786 | L100: =(L91*1000)/L101 -> -0.75907701 | M100: =(M91*1000)/M101 -> -0.064737467 | N100: =(N91*1000)/N101 -> 0.94055831 | O100: =(O91*1000)/O101 -> 1.9366488 | P100: =(P91*1000)/P101 -> 3.0455256
C101: Weighted-average shares used to compute basic and diluted net loss per share | G101: 133917571 | H101: 177923156 | I101: 37042081 | J101: 46584479 | K101: =Diluted*1000000 -> 52560000 | L101: =K101+1500000 -> 54060000 | M101: =L101+1500000 -> 55560000 | N101: =M101+1500000 -> 57060000 | O101: =N101+1500000 -> 58560000 | P101: =O101+1500000 -> 60060000
I103: Historical | O103: Projected: | P103: Projected:
B104: =Company_Name&" - Balance Sheet" -> Ouster, Inc. - Balance Sheet | E104: Units: | G104: =EOMONTH(H104,-12) -> 44561 | H104: 44926 | I104: =EOMONTH(H104,12) -> 45291 | J104: =EOMONTH(I104,12) -> 45657 | K104: =EOMONTH(J104,12) -> 46022 | L104: =EOMONTH(K104,12) -> 46387 | M104: =EOMONTH(L104,12) -> 46752 | N104: =EOMONTH(M104,12) -> 47118 | O104: =EOMONTH(N104,12) -> 47483 | P104: =EOMONTH(O104,12) -> 47848
C106: Cash and cash equivalents | G106: 182644 | H106: 122932 | I106: 50991 | J106: 45542 | K106: =K211 -> 96083.69 | L106: =L211 -> 55443.675 | M106: =M211 -> 80022.125 | N106: =N211 -> 109639.19 | O106: =O211 -> 203287.53 | P106: =P211 -> 319878.85 | Q106: =SUM(K106:K108) -> 210565.69
C107: Restricted cash, current | G107: 977 | H107: 257 | I107: 552 | J107: 722 | K107: =AVERAGE(G107:J107) -> 627 | L107: =AVERAGE(H107:K107) -> 539.5 | M107: =AVERAGE(I107:L107) -> 610.125 | N107: =AVERAGE(J107:M107) -> 624.65625 | O107: =AVERAGE(K107:N107) -> 600.32031 | P107: =AVERAGE(L107:O107) -> 593.65039
C108: Short-term investments | G108: 0 | H108: 0 | I108: 139158 | J108: 126480 | K108: =K44*J106 -> 113855 | L108: =L44*K106 -> 76866.952 | M108: =M44*L106 -> 44354.94 | N108: =N44*M106 -> 64017.7 | O108: =O44*N106 -> 87711.35 | P108: =P44*O106 -> 162630.03
C109: Accounts receivable, net | G109: 10723 | H109: 11233 | I109: 14577 | J109: 17941 | K109: =K45/(K$67-EOMONTH(K$67,-12))*K$69 -> 24076.712 | L109: =L45/(L$67-EOMONTH(L$67,-12))*L$69 -> 33506.367 | M109: =M45/(M$67-EOMONTH(M$67,-12))*M$69 -> 44030.639 | N109: =N45/(N$67-EOMONTH(N$67,-12))*N$69 -> 58503.589 | O109: =O45/(O$67-EOMONTH(O$67,-12))*O$69 -> 70250.982 | P109: =P45/(P$67-EOMONTH(P$67,-12))*P$69 -> 80036.008
C110: Inventory | G110: 7448 | H110: 19533 | I110: 23232 | J110: 16417 | K110: =K46/(K$67-EOMONTH(K$67,-12))*K$69 -> 24076.712 | L110: =L46/(L$67-EOMONTH(L$67,-12))*L$69 -> 33506.367 | M110: =M46/(M$67-EOMONTH(M$67,-12))*M$69 -> 44030.639 | N110: =N46/(N$67-EOMONTH(N$67,-12))*N$69 -> 58503.589 | O110: =O46/(O$67-EOMONTH(O$67,-12))*O$69 -> 70250.982 | P110: =P46/(P$67-EOMONTH(P$67,-12))*P$69 -> 80036.008
C111: Prepaid expenses and other current assets | G111: 5566 | H111: 8543 | I111: 34647 | J111: 12750 | K111: =K47*K69 -> 13520 | L111: =L47*L69 -> 17835.16 | M111: =M47*M69 -> 25567.791 | N111: =N47*N69 -> 32118.471 | O111: =O47*O69 -> 42736.014 | P111: =P47*P69 -> 45645.536
C112: Total current assets | G112: =SUM(G106:G111) -> 207358 | H112: =SUM(H106:H111) -> 162498 | I112: =SUM(I106:I111) -> 263157 | J112: =SUM(J106:J111) -> 219852 | K112: =SUM(K106:K111) -> 272239.11 | L112: =SUM(L106:L111) -> 217698.02 | M112: =SUM(M106:M111) -> 238616.26 | N112: =SUM(N106:N111) -> 323407.19 | ... P112: =SUM(P106:P111) -> 688820.08
C114: Property and equipment, net | G114: 10054 | H114: 9695 | I114: 10228 | J114: 10164 | K114: =Drivers!J55 -> 12724.695 | L114: =Drivers!K55 -> 14174.803 | M114: =Drivers!L55 -> 14866.144 | N114: =Drivers!M55 -> 14918.773 | O114: =Drivers!N55 -> 14416.773 | P114: =Drivers!O55 -> 13416.662
C115: Operating lease, right-of-use assets | G115: 15156 | H115: 12997 | I115: 18561 | J115: 14308 | K115: =K49*SUM(K126,K129) -> 14838.3 | L115: =L49*SUM(L126,L129) -> 12393.988 | M115: =M49*SUM(M126,M129) -> 12300.957 | N115: =N49*SUM(N126,N129) -> 12401.015 | O115: =O49*SUM(O126,O129) -> 12324.249 | P115: =P49*SUM(P126,P129) -> 11749.762
C116: Unbilled receivable, non-current portion | G116: 0 | H116: 0 | I116: 10567 | J116: 10133 | K116: =K50*K69 -> 11830 | L116: =L50*L69 -> 15287.28 | M116: =M50*M69 -> 18262.708 | N116: =N50*N69 -> 26765.392 | O116: =O50*O69 -> 28490.676 | P116: =P50*P69 -> 36516.429
C117: Goodwill | G117: 51076 | H117: 51152 | I117: 0 | J117: 0 | K117: 0 | L117: =+-L184+L217 -> 36500 | M117: 36500 | N117: 36500 | O117: 36500 | P117: 36500
C118: Intangible assets, net | G118: 22652 | H118: 18165 | I118: 24436 | J118: 17830 | K118: 17830 | L118: 17830 | M118: 17830 | N118: 17830 | O118: 17830 | P118: 17830
C119: Restricted cash, non-current | G119: 1035 | H119: 1089 | I119: 1091 | J119: 1835 | K119: =AVERAGE(G119:J119) -> 1262.5 | L119: =AVERAGE(H119:K119) -> 1319.375 | M119: =AVERAGE(I119:L119) -> 1376.9688 | N119: =AVERAGE(J119:M119) -> 1448.4609 | O119: =AVERAGE(K119:N119) -> 1351.8262 | P119: =AVERAGE(L119:O119) -> 1374.1577
C120: Other non-current assets | G120: 371 | H120: 541 | I120: 2703 | J120: 2026 | K120: =AVERAGE(G120:J120) -> 1410.25 | L120: =AVERAGE(H120:K120) -> 1670.0625 | M120: =AVERAGE(I120:L120) -> 1952.3281 | N120: =AVERAGE(J120:M120) -> 1764.6602 | O120: =AVERAGE(K120:N120) -> 1699.3252 | P120: =AVERAGE(L120:O120) -> 1771.594
C121: Total assets | G121: =SUM(G114:G120,G112) -> 307702 | H121: =SUM(H114:H120,H112) -> 256137 | I121: =SUM(I114:I120,I112) -> 330743 | J121: =SUM(J114:J120,J112) -> 276148 | K121: =SUM(K114:K120,K112) -> 332134.86 | L121: =SUM(L114:L120,L112) -> 316873.53 | M121: =SUM(M114:M120,M112) -> 341705.37 | N121: =SUM(N114:N120,N112) -> 435035.49 | ... P121: =SUM(P114:P120,P112) -> 807978.68
C123: Accounts payable | G123: 4863 | H123: 8798 | I123: 3545 | J123: 6288 | K123: =K52/(K67-EOMONTH(K67,-12))*K69 -> 10186.301 | L123: =L52/(L67-EOMONTH(L67,-12))*L69 -> 13960.986 | M123: =M52/(M67-EOMONTH(M67,-12))*M69 -> 18012.534 | N123: =N52/(N67-EOMONTH(N67,-12))*N69 -> 23401.436 | O123: =O52/(O67-EOMONTH(O67,-12))*O69 -> 27319.826 | P123: =P52/(P67-EOMONTH(P67,-12))*P69 -> 30013.503
C124: Accrued and other current liabilities | G124: 14173 | H124: 17473 | I124: 58166 | J124: 30591 | K124: =-K79*K53 -> 20826.993 | L124: =-L79*L53 -> 18600 | M124: =-M79*M53 -> 17050 | N124: =-N79*N53 -> 15500 | O124: =-O79*O53 -> 13950 | P124: =-P79*P53 -> 12400
C125: Contract liabilities, current | G125: 0 | H125: 0 | I125: 12885 | J125: 34351 | K125: =K69*K54 -> 39200.227 | L125: =L69*L54 -> 38218.2 | M125: =M69*M54 -> 40177.958 | N125: =N69*N54 -> 53530.784 | O125: =O69*O54 -> 71226.69 | P125: =P69*P54 -> 91291.072
C126: Operating lease liability, current portion | G126: 3067 | H126: 3221 | I126: 7096 | J126: 7196 | K126: =K129*K55 -> 7052.08 | L126: =L129*L55 -> 4255.564 | M126: =M129*M55 -> 4631.8384 | N126: =N129*N55 -> 4950.4432 | O126: =O129*O55 -> 4952.4422 | P126: =P129*P55 -> 4473.1112
C127: Total current liabilities | G127: =SUM(G123:G126) -> 22103 | H127: =SUM(H123:H126) -> 29492 | I127: =SUM(I123:I126) -> 81692 | J127: =SUM(J123:J126) -> 78426 | K127: =SUM(K123:K126) -> 77265.602 | L127: =SUM(L123:L126) -> 75034.75 | M127: =SUM(M123:M126) -> 79872.331 | N127: =SUM(N123:N126) -> 97382.663 | ... P127: =SUM(P123:P126) -> 138177.69
C129: Operating lease liability, long-term portion | G129: 16208 | H129: 13400 | I129: 18827 | J129: 13054 | K129: =J129*0.98 -> 12792.92 | L129: =K129*0.98 -> 12537.062 | M129: =L129*0.98 -> 12286.32 | N129: =M129*0.98 -> 12040.594 | O129: =N129*0.98 -> 11799.782 | P129: =O129*0.98 -> 11563.786
C130: Warrant liabilities | G130: 7626 | H130: 180 | I130: 0 | J130: 0 | K130: 0 | L130: 0 | M130: 0 | N130: 0 | O130: 0 | P130: 0
C131: Debt | G131: 0 | H131: 39574 | I131: 43975 | J131: 0 | K131: 0 | L131: 0 | M131: 0 | N131: 0 | O131: 0 | P131: 0
C132: Contract liabilities, long-term portion | G132: 0 | H132: 0 | I132: 4967 | J132: 2538 | K132: =K125*K58 -> 2352.0136 | L132: =L125*L58 -> 2293.092 | M132: =M125*M58 -> 2008.8979 | N132: =N125*N58 -> 2676.5392 | O132: =O125*O58 -> 2849.0676 | P132: =P125*P58 -> 3651.6429
C133: Other non-current liabilities | G133: 1065 | H133: 1872 | I133: 1610 | J133: 1219 | K133: =K69*K59 -> 1690 | L133: =L69*L59 -> 2547.88 | M133: =M69*M59 -> 3652.5416 | N133: =N69*N59 -> 5353.0784 | O133: =O69*O59 -> 7122.669 | P133: =P69*P59 -> 9129.1072
C134: Total liabilities | G134: =SUM(G129:G133,G127) -> 47002 | H134: =SUM(H129:H133,H127) -> 84518 | I134: =SUM(I129:I133,I127) -> 151071 | J134: =SUM(J129:J133,J127) -> 95237 | K134: =SUM(K129:K133,K127) -> 94100.536 | L134: =SUM(L129:L133,L127) -> 92412.784 | M134: =SUM(M129:M133,M127) -> 97820.09 | N134: =SUM(N129:N133,N127) -> 117452.87 | ... P134: =SUM(P129:P133,P127) -> 162522.22
C136: Common stock | G136: 17 | H136: 19 | I136: 42 | J136: 47 | K136: 47 | L136: 47 | M136: 47 | N136: 47 | O136: 47 | P136: 47
...

Sheet Drivers
H2: Historical | N2: Projected:
B3: =Company_Name&" - Revenue Drivers" -> Ouster, Inc. - Revenue Drivers | E3: Units: | F3: =EOMONTH(G3,-12) -> 44561 | G3: 44926 | H3: =EOMONTH(G3,12) -> 45291 | I3: =EOMONTH(H3,12) -> 45657 | J3: =EOMONTH(I3,12) -> 46022 | K3: =EOMONTH(J3,12) -> 46387 | L3: =EOMONTH(K3,12) -> 46752 | M3: =EOMONTH(L3,12) -> 47118 | N3: =EOMONTH(M3,12) -> 47483 | O3: =EOMONTH(N3,12) -> 47848
C6: Revenue | E6: $T | F6: {=Model!G69} -> 33578 | G6: {=Model!H69} -> 41029 | H6: {=Model!I69} -> 83279 | I6: {=Model!J69} -> 111101 | J6: 169000 | K6: =IF(Bundle="yes",(((K8-K22)*K14)+(K22*K24))/1000+K31,(K8*K14)/1000+K31) -> 254788 | L6: =IF(Bundle="yes",(((L8-L22)*L14)+(L22*L24))/1000+L31,(L8*L14)/1000+L31) -> 365254.16 | M6: =IF(Bundle="yes",(((M8-M22)*M14)+(M22*M24))/1000+M31,(M8*M14)/1000+M31) -> 535307.84 | N6: =IF(Bundle="yes",(((N8-N22)*N14)+(N22*N24))/1000+N31,(N8*N14)/1000+N31) -> 712266.9 | O6: =IF(Bundle="yes",(((O8-O22)*O14)+(O22*O24))/1000+O31,(O8*O14)/1000+O31) -> 912910.72
C8: Sensors shipped | E8: # | F8: 6475 | G8: 8650 | H8: 13400 | I8: 17300 | J8: 25000 | K8: =J8*(1+K9) -> 33750 | L8: =K8*(1+L9) -> 47250 | M8: =L8*(1+M9) -> 68512.5 | N8: =M8*(1+N9) -> 92491.875 | O8: =N8*(1+O9) -> 120239.44
C9: % Change | E9: % | G9: =G8/F8-1 -> 0.33590734 | H9: =H8/G8-1 -> 0.54913295 | I9: =I8/H8-1 -> 0.29104478 | J9: =J8/I8-1 -> 0.44508671 | K9: =INDEX($K$10:$O$12,MATCH(Scenario,$C$10:$C$12,0),1) -> 0.35 | L9: =INDEX($K$10:$O$12,MATCH(Scenario,$C$10:$C$12,0),2) -> 0.4 | M9: =INDEX($K$10:$O$12,MATCH(Scenario,$C$10:$C$12,0),3) -> 0.45 | N9: =INDEX($K$10:$O$12,MATCH(Scenario,$C$10:$C$12,0),4) -> 0.35 | O9: =INDEX($K$10:$O$12,MATCH(Scenario,$C$10:$C$12,0),5) -> 0.3
C10: Upside | E10: % | K10: =K11+5% -> 0.4 | L10: =L11+5% -> 0.45 | M10: =M11+5% -> 0.5 | N10: =N11+5% -> 0.4 | O10: =O11+5% -> 0.35
C11: Base | E11: % | K11: 0.35 | L11: 0.4 | M11: 0.45 | N11: 0.35 | O11: 0.3
C12: Downside | E12: % | K12: 0.2 | L12: 0.3 | M12: 0.4 | N12: 0.3 | O12: 0.25
C14: ASP | E14: $T | F14: =F6*1000/F8 -> 5185.7915 | G14: =G6*1000/G8 -> 4743.237 | H14: =H6*1000/H8 -> 6214.8507 | I14: =I6*1000/I8 -> 6422.0231 | J14: =J6/J8*Units -> 6760 | K14: =J14*(1+K15) -> 6895.2 | L14: =K14*(1+L15) -> 7033.104 | M14: =L14*(1+M15) -> 7103.435 | N14: =M14*(1+N15) -> 6961.3663 | O14: =N14*(1+O15) -> 6822.139
C15: % Change | G15: =G14/F14-1 -> -0.08533982 | H15: =H14/G14-1 -> 0.31025516 | I15: =I14/H14-1 -> 0.033335052 | J15: =J14/I14-1 -> 0.052627789 | K15: 0.02 | L15: 0.02 | M15: 0.01 | N15: -0.02 | O15: -0.02
C17: Attach Rate | E17: % | K17: =INDEX($K$18:$O$20,MATCH(Scenario,$C$18:$C$20,0),1) -> 0.15 | L17: =INDEX($K$18:$O$20,MATCH(Scenario,$C$18:$C$20,0),2) -> 0.2 | M17: =INDEX($K$18:$O$20,MATCH(Scenario,$C$18:$C$20,0),3) -> 0.25 | N17: =INDEX($K$18:$O$20,MATCH(Scenario,$C$18:$C$20,0),4) -> 0.3 | O17: =INDEX($K$18:$O$20,MATCH(Scenario,$C$18:$C$20,0),5) -> 0.35
C18: Upside | E18: % | K18: =K19+5% -> 0.2 | L18: =L19+5% -> 0.25 | M18: =M19+5% -> 0.3 | N18: =N19+5% -> 0.35 | O18: =O19+5% -> 0.4
C19: Base | E19: % | K19: 0.15 | L19: 0.2 | M19: 0.25 | N19: 0.3 | O19: 0.35
C20: Downside | E20: % | K20: 0.1 | L20: 0.15 | M20: 0.2 | N20: 0.2 | O20: 0.25
C22: Perception Systems shipped | E22: # | K22: =K8*K17 -> 5062.5 | L22: =L8*L17 -> 9450 | M22: =M8*M17 -> 17128.125 | N22: =N8*N17 -> 27747.562 | O22: =O8*O17 -> 42083.803
C24: Perception System ASP | E24: $T | K24: =K14+K26 -> 8095.2 | L24: =L14+L26 -> 8233.104 | M24: =M14+M26 -> 8303.435 | N24: =N14+N26 -> 8161.3663 | O24: =O14+O26 -> 8022.139
C26: Perception System uplift | E26: # | K26: =INDEX($K$27:$O$29,MATCH(Uplift,$C$27:$C$29,0),1) -> 1200 | L26: =INDEX($K$27:$O$29,MATCH(Uplift,$C$27:$C$29,0),2) -> 1200 | M26: =INDEX($K$27:$O$29,MATCH(Uplift,$C$27:$C$29,0),3) -> 1200 | N26: =INDEX($K$27:$O$29,MATCH(Uplift,$C$27:$C$29,0),4) -> 1200 | O26: =INDEX($K$27:$O$29,MATCH(Uplift,$C$27:$C$29,0),5) -> 1200
C27: Upside | E27: # | K27: 1500 | L27: 1500 | M27: 1500 | N27: 1500 | O27: 1500
C28: Base | E28: # | K28: 1200 | L28: 1200 | M28: 1200 | N28: 1200 | O28: 1200
C29: Downside | E29: # | K29: 900 | L29: 900 | M29: 900 | N29: 900 | O29: 900
C31: Stereolabs Revenue | E31: $T | K31: 16000 | L31: =K31*(1+L32) -> 21600 | M31: =L31*(1+M32) -> 28080 | N31: =M31*(1+N32) -> 35100 | O31: =N31*(1+O32) -> 42120
C32: % Change | E32: % | L32: =INDEX($L$33:$O$35,MATCH(Scenario,$C$33:$C$35,0),1) -> 0.35 | M32: =INDEX($L$33:$O$35,MATCH(Scenario,$C$33:$C$35,0),2) -> 0.3 | N32: =INDEX($L$33:$O$35,MATCH(Scenario,$C$33:$C$35,0),3) -> 0.25 | O32: =INDEX($L$33:$O$35,MATCH(Scenario,$C$33:$C$35,0),4) -> 0.2
C33: Upside | E33: % | L33: =L34+5% -> 0.4 | M33: =M34+5% -> 0.35 | N33: =N34+5% -> 0.3 | O33: =O34+5% -> 0.25
C34: Base | E34: % | L34: 0.35 | M34: 0.3 | N34: 0.25 | O34: 0.2
C35: Downside | E35: % | L35: =L34-5% -> 0.3 | M35: =M34-5% -> 0.25 | N35: =N34-5% -> 0.2 | O35: =O34-5% -> 0.15
C38: Software attached sensors | E38: # | I38: =I8*I39 -> 1297.5 | J38: =J8*J39 -> 3750
C39: % mix | E39: % | I39: =J39/2 -> 0.075 | J39: 0.15 | K39: 0.2
C41: Bloomberg estimate | E41: $T | J41: 148000 | K41: 202000 | L41: 278000 | M41: 392000 | N41: 514000
E42: % | J42: =J41/I6-1 -> 0.33212122 | K42: =K41/J41-1 -> 0.36486486 | L42: =L41/K41-1 -> 0.37623762 | M42: =M41/L41-1 -> 0.41007194 | N42: =N41/M41-1 -> 0.31122449
C44: Oppenheimer estimates | E44: $T | J44: 147900 | K44: 217500 | L44: 295300 | M44: 392400 | N44: 513900
E45: % | J45: =J44/I6-1 -> 0.33122114 | K45: =K44/J44-1 -> 0.47058824 | L45: =L44/K44-1 -> 0.35770115 | M45: =M44/L44-1 -> 0.32881815 | N45: =N44/M44-1 -> 0.30963303
H49: Historical | L49: Projected:
B50: ="CapEx & Depreciation - "&Company_Name -> CapEx & Depreciation - Ouster, Inc. | E50: Units: | F50: =F3 -> 44561 | G50: =G3 -> 44926 | H50: =H3 -> 45291 | I50: =I3 -> 45657 | J50: =J3 -> 46022 | K50: =K3 -> 46387 | L50: =L3 -> 46752 | M50: =M3 -> 47118 | ... O50: =O3 -> 47848
C52: CapEx: | E52: $T | F52: =-Model!G183 -> 4283 | G52: =-Model!H183 -> 5422 | H52: =-Model!I183 -> 3006 | I52: =-Model!J183 -> 3756 | J52: =-Model!K79*Drivers!J53 -> 4806.2293 | K52: =-Model!L79*Drivers!K53 -> 4650 | L52: =-Model!M79*Drivers!L53 -> 4650 | M52: =-Model!N79*Drivers!M53 -> 4650 | N52: =-Model!O79*Drivers!N53 -> 4650 | O52: =-Model!P79*Drivers!O53 -> 4650
C53: CapEx % OpEx (Cash only): | E53: % | F53: =-F52/Model!G79 -> 0.039367256 | G53: =-G52/Model!H79 -> 0.03467794 | H53: =-H52/Model!I79 -> 0.0078792994 | I53: =-I52/Model!J79 -> 0.025968459 | J53: 0.03 | K53: 0.03 | L53: 0.03 | M53: 0.03 | N53: 0.03 | O53: 0.03
C55: Property, Plant and Equipment, Net: | E55: $T | F55: =Model!G114 -> 10054 | G55: =Model!H114 -> 9695 | H55: =Model!I114 -> 10228 | I55: =Model!J114 -> 10164 | J55: =I55+J52-J67 -> 12724.695 | K55: =J55+K52-K67 -> 14174.803 | L55: =K55+L52-L67 -> 14866.144 | M55: =L55+M52-M67 -> 14918.773 | N55: =M55+N52-N67 -> 14416.773 | O55: =N55+O52-O67 -> 13416.662
C57: D&A of Existing Net PP&E and Intangibles: | E57: % | G57: =G60/G55 -> 0.97534812 | H57: =H60/H55 -> 1.6765741 | I57: =I60/I55 -> 0.96772924 | J57: 0.15 | K57: =J57-1% -> 0.14 | L57: =K57-1% -> 0.13 | M57: =L57-1% -> 0.12 | N57: =M57-1% -> 0.11 | O57: =N57-1% -> 0.1
C58: D&A of NEW CapEx & Intangible Purchases: | E58: % | J58: 0.15 | K58: 0.15 | L58: 0.15 | M58: 0.15 | N58: 0.15 | O58: 0.15
C60: D&A - Existing PP&E and Intangibles, Net: | E60: $T | F60: =Model!G151 -> 5477 | G60: =Model!H151 -> 9456 | H60: =Model!I151 -> 17148 | I60: =Model!J151 -> 9836 | J60: =I55*J57 -> 1524.6 | K60: =J55*K57 -> 1781.4573 | L60: =K55*L57 -> 1842.7244 | M60: =L55*M57 -> 1783.9373 | N60: =M55*N57 -> 1641.065 | O60: =N55*O57 -> 1441.6773
C61: D&A - Year 1 CapEx & Intangible Purchases: | E61: $T | J61: =$J$52*J58 -> 720.93439 | K61: =$J$52*K58 -> 720.93439 | L61: =$J$52*L58 -> 720.93439 | M61: =$J$52*M58 -> 720.93439 | N61: =$J$52*N58 -> 720.93439 | O61: =$J$52*O58 -> 720.93439
C62: D&A - Year 2 CapEx & Intangible Purchases: | E62: $T | K62: =$K$52*J58 -> 697.5 | L62: =$K$52*K58 -> 697.5 | M62: =$K$52*L58 -> 697.5 | N62: =$K$52*M58 -> 697.5 | O62: =$K$52*N58 -> 697.5
C63: D&A - Year 3 CapEx & Intangible Purchases: | E63: $T | L63: =$L$52*J58 -> 697.5 | M63: =$L$52*K58 -> 697.5 | N63: =$L$52*L58 -> 697.5 | O63: =$L$52*M58 -> 697.5
C64: D&A - Year 4 CapEx & Intangible Purchases: | E64: $T | M64: =$M$52*J58 -> 697.5 | N64: =$M$52*K58 -> 697.5 | O64: =$M$52*L58 -> 697.5
C65: D&A - Year 5 CapEx & Intangible Purchases: | E65: $T | N65: =$N$52*J58 -> 697.5 | O65: =$N$52*K58 -> 697.5
C66: D&A - Year 6 CapEx & Intangible Purchases: | E66: $T | O66: =$O$52*J58 -> 697.5
C67: Total Depreciation & Amortisation: | E67: $T | F67: =SUM(F60:F66) -> 5477 | G67: =SUM(G60:G66) -> 9456 | H67: =SUM(H60:H66) -> 17148 | I67: =SUM(I60:I66) -> 9836 | J67: =SUM(J60:J66) -> 2245.5344 | K67: =SUM(K60:K66) -> 3199.8917 | L67: =SUM(L60:L66) -> 3958.6588 | M67: =SUM(M60:M66) -> 4597.3717 | ... O67: =SUM(O60:O66) -> 5650.1117

Sheet DCF
I2: Historical | M2: Projected:
B3: =Company_Name&" - Discounted Cash Flow Analysis" -> Ouster, Inc. - Discounted Cash Flow Analysis | E3: Units: | H3: 44926 | I3: 45291 | J3: 45657 | K3: 46022 | L3: 46387 | M3: 46752 | N3: 47118 | O3: 47483 | P3: 47848
E5: Scenario: | F5: Base | H5: Terminal Value - Multiples Method: | M5: Terminal Value - Perpetuity Growth Method:
E6: Bundle: | F6: yes
E7: Uplift: | F7: Base | H7: Median LTM TEV / EBITDA of Comps: | K7: =PubComps!Q36 -> 17.459867 | M7: Expected Long-Term GDP Growth: | P7: 0.015
H8: Median LTM TEV / EBITDA of Target: | K8: =[2]PubComps!S40 -> NM
C9: Company Name: | E9: Name | F9: =Company_Name -> Ouster, Inc.
C10: Ticker: | E10: Name | F10: =Ticker -> OUST | H10: Baseline Terminal EBITDA Multiple: | K10: =INDEX(K11:K13,MATCH(Scenario,H11:H13,0),1) -> 15.5 | M10: Baseline Terminal FCF Growth Rate: | P10: =INDEX(P11:P13,MATCH(Scenario,M11:M13,0),1) -> 0.02
C11: Current Share Price: | E11: $ / Share | F11: =Share_Price -> 21.06 | H11: Upside | K11: 16.5 | M11: Upside | P11: 0.03
C12: Diluted Shares Outstanding: | E12: M Shares | F12: =Diluted -> 52.56 | H12: Base | K12: 15.5 | M12: Base | P12: 0.02
H13: Downside | K13: 14.5 | M13: Downside | P13: 0.01
C14: Effective Tax Rate: | E14: % | F14: =Tax_Rate -> 0.21
C15: Discount Rate (WACC): | E15: % | F15: =WACC!L40 -> 0.10836181
H16: Baseline Terminal Value: | K16: =K10*(P63/Units) -> 3345.1232 | M16: Baseline Terminal Value: | P16: =(+P61*(1+Terminal_Growth_Rate)/(Discount_Rate-P10)*(1+Discount_Rate)^0.5)/Units -> 2939.0093
H17: Implied Terminal FCF Growth Rate: | K17: =(N63*(1+Discount_Rate)^0.5*Discount_Rate - O16) / (N63*(1+Discount_Rate)^0.5 + O16) -> 0.10836181 | M17: Implied Terminal EBITDA Multiple: | P17: =P16/(P63/Units) -> 13.618226
H19: (+) Present Value of Terminal Value: | K19: =K16/((1+Discount_Rate)^5) -> 1999.8819 | M19: (+) Present Value of Terminal Value: | P19: =P16/((1+Discount_Rate)^5) -> 1757.0867
H20: (+) Present Value of UFCF: | K20: =NPV(Discount_Rate,L61:P61)/Units -> 325.44824 | M20: (+) Present Value of UFCF: | P20: =NPV(Discount_Rate,L61:P61)/Units -> 325.44824
H21: Implied Enterprise Value: | K21: =SUM(K19:K20) -> 2325.3301 | M21: Implied Enterprise Value: | P21: =SUM(P19:P20) -> 2082.5349
C22: Current Equity Value: | F22: =$F$11*$F$12 -> 1106.9136
C23: (-) Cash & Investments: | F23: =-SUM(Model!K106:K108)/Units -> -210.56569 | H23: % of implied TEV from Terminal Value: | K23: =K19/K21 -> 0.86004214 | M23: % of implied TEV from Terminal Value: | P23: =P19/P21 -> 0.84372496
C24: (-) Net Operating Losses: | F24: 0
C25: (+) Debt & Finance Leases: | F25: 0 | H25: (+) Cash and Investments: | K25: =-F23 -> 210.56569 | M25: (+) Cash and Investments: | P25: =K25 -> 210.56569
C26: (+) Preferred Stock: | F26: 0 | H26: (+) Net Operating Losses: | K26: =-F24 -> 0 | M26: (+) Net Operating Losses: | P26: =K26 -> 0
C27: (+) Operating Leases: | F27: 0 | H27: (-)Debt and Finance Leases: | K27: =-F25 -> 0 | M27: (-)Debt and Finance Leases: | P27: =K27 -> 0
C28: (+) Noncontrolling Interests: | F28: 0 | H28: (-)Preferred Stock: | K28: =-F26 -> 0 | M28: (-)Preferred Stock: | P28: =K28 -> 0
C29: (+) Unfunded Pensions: | F29: 0 | H29: (-) Operating Leases: | K29: =-F27 -> 0 | M29: (-) Operating Leases: | P29: =K29 -> 0
C30: Current Enterprise Value: | F30: =SUM($F$22:$F$29) -> 896.34791 | H30: (-) Noncontrolling Interests: | K30: =-F28 -> 0 | M30: (-) Noncontrolling Interests: | P30: =K30 -> 0
H31: (-)Unfunded Pensions: | K31: =-F29 -> 0 | M31: (-)Unfunded Pensions: | P31: =K31 -> 0
H33: Implied Equity Value: | K33: =K21+SUM(K25:K31) -> 2535.8958 | M33: Implied Equity Value: | P33: =SUM(P21:P32) -> 2293.9443
H35: Diluted Shares Outstanding: | K35: =_xlfn.SINGLE(Diluted) -> 52.56 | M35: Diluted Shares Outstanding: | P35: =_xlfn.SINGLE(Diluted) -> 52.56
H37: Implied Share Price from DCF: | K37: =K33/K35 -> 48.247637 | M37: Implied Share Price from DCF: | P37: =P33/P35 -> 43.644299
H38: Premium / (Discount) to Current: | K38: =K37/F11-1 -> 1.2909609 | M38: Premium / (Discount) to Current: | P38: =P37/F11-1 -> 1.0723789
I40: Historical | M40: Projected:
B41: =Company_Name&" - Free Cash Flow Calculation" -> Ouster, Inc. - Free Cash Flow Calculation | E41: Units: | H41: 44926 | I41: 45291 | J41: 45657 | K41: 46022 | L41: 46387 | M41: 46752 | N41: 47118 | O41: 47483 | P41: 47848
C43: Revenue | E43: $T | G43: =Drivers!F6 -> 33578 | H43: =Drivers!G6 -> 41029 | I43: =Drivers!H6 -> 83279 | J43: =Drivers!I6 -> 111101 | K43: =Drivers!J6 -> 169000 | L43: =Drivers!K6 -> 254788 | M43: =Drivers!L6 -> 365254.16 | N43: =Drivers!M6 -> 535307.84 | ... P43: =Drivers!O6 -> 912910.72
C44: % Change | G44: 0 | H44: =H43/G43-1 -> 0.22190124 | I44: =I43/H43-1 -> 1.0297594 | J44: =J43/I43-1 -> 0.33408182 | K44: =K43/J43-1 -> 0.52113842 | L44: =L43/K43-1 -> 0.5076213 | M44: =M43/L43-1 -> 0.43356109 | N44: =N43/M43-1 -> 0.46557629 | O44: =O43/N43-1 -> 0.33057438 | P44: =P43/O43-1 -> 0.28169752
C46: Operating Expenses | E46: $T | G46: =Model!G79 -> -108796 | H46: =Model!H79 -> -156353 | I46: =Model!I79 -> -381506 | J46: =Model!J79 -> -144637 | K46: =Model!K79 -> -160207.64 | L46: =Model!L79 -> -155000 | M46: =Model!M79 -> -155000 | N46: =Model!N79 -> -155000 | ... P46: =Model!P79 -> -155000
C48: Operating Income (EBIT) | E48: $T | G48: =Model!G81 -> -99710 | H48: =Model!H81 -> -145423 | I48: =Model!I81 -> -373192 | J48: =Model!J81 -> -104177 | K48: =Model!K81 -> -77397.642 | L48: =Model!L81 -> -53084.8 | M48: =Model!M81 -> -8898.3344 | N48: =Model!N81 -> 59123.137 | ... P48: =Model!P81 -> 210164.29
C50: (-) Taxes, Excluding Effect of Interest | E50: $T | G50: 0 | H50: 0 | I50: 0 | J50: 0 | K50: =Model!K39 -> 0 | L50: =Model!L39 -> 0 | M50: =Model!M39 -> 0 | N50: =Model!N39 -> 10471.262 | O50: =Model!O39 -> 22558.921 | P50: =Model!P39 -> 36587.769
C52: Net Operating Profit After Taxes (NOPAT) | E52: $T | G52: =Model!G88 -> -96775 | H52: =Model!H88 -> -138255 | I52: =Model!I88 -> -373587 | J52: =Model!J88 -> -96508 | K52: =Model!K88 -> -66950.192 | L52: =Model!L88 -> -41035.703 | M52: =Model!M88 -> -3596.8137 | N52: =Model!N88 -> 64139.519 | ... P52: =Model!P88 -> 219502.04
C54: Depreciation and amortization: | E54: $T | G54: =Model!G151 -> 5477 | H54: =Model!H151 -> 9456 | I54: =Model!I151 -> 17148 | J54: =Model!J151 -> 9836 | K54: =Model!K151 -> 2245.5344 | L54: =Model!L151 -> 3199.8917 | M54: =Model!M151 -> 3958.6588 | N54: =Model!N151 -> 4597.3717 | ... P54: =Model!P151 -> 5650.1117
C56: Operating Net Working Capital | E56: $T | G56: =SUM(Model!G109:G111)-SUM(Model!G123:G124) -> 4701 | H56: =SUM(Model!H109:H111)-SUM(Model!H123:H124) -> 13038 | I56: =SUM(Model!I109:I111)-SUM(Model!I123:I124) -> 10745 | J56: =SUM(Model!J109:J111)-SUM(Model!J123:J124) -> 10229 | K56: =SUM(Model!K109:K111)-SUM(Model!K123:K124) -> 30660.13 | L56: =SUM(Model!L109:L111)-SUM(Model!L123:L124) -> 52286.908 | M56: =SUM(Model!M109:M111)-SUM(Model!M123:M124) -> 78566.535 | N56: =SUM(Model!N109:N111)-SUM(Model!N123:N124) -> 110224.21 | ... P56: =SUM(Model!P109:P111)-SUM(Model!P123:P124) -> 163304.05
C57: Change in Working Capital | E57: $T | G57: 0 | H57: =H56-G56 -> 8337 | I57: =I56-H56 -> -2293 | J57: =J56-I56 -> -516 | K57: =K56-J56 -> 20431.13 | L57: =L56-K56 -> 21626.778 | M57: =M56-L56 -> 26279.627 | N57: =N56-M56 -> 31657.678 | O57: =O56-N56 -> 31743.938 | P57: =P56-O56 -> 21335.898
C59: Capital Expenditures: | E59: $T | G59: =-Drivers!F52 -> -4283 | H59: =-Drivers!G52 -> -5422 | I59: =-Drivers!H52 -> -3006 | J59: =-Drivers!I52 -> -3756 | K59: =-Drivers!J52 -> -4806.2293 | L59: =-Drivers!K52 -> -4650 | M59: =-Drivers!L52 -> -4650 | N59: =-Drivers!M52 -> -4650 | ... P59: =-Drivers!O52 -> -4650
C61: Unlevered Free Cash Flow | E61: $T | G61: =SUM(G52,G54,G57,G59) -> -95581 | H61: =SUM(H52,H54,H57,H59) -> -125884 | I61: =SUM(I52,I54,I57,I59) -> -361738 | J61: =SUM(J52,J54,J57,J59) -> -90944 | K61: =SUM(K52,K54,K57,K59) -> -49079.757 | L61: =SUM(L52,L54,L57,L59) -> -20859.033 | M61: =SUM(M52,M54,M57,M59) -> 21991.472 | N61: =SUM(N52,N54,N57,N59) -> 95744.57 | ... P61: =SUM(P52,P54,P57,P59) -> 241838.05
C63: EBITDA | E63: $T | G63: =Model!G97 -> -94233 | H63: =Model!H97 -> -135967 | I63: =Model!I97 -> -356044 | J63: =Model!J97 -> -94341 | K63: =Model!K97 -> -75152.108 | L63: =Model!L97 -> -49884.908 | M63: =Model!M97 -> -4939.6756 | N63: =Model!N97 -> 63720.509 | ... P63: =Model!P97 -> 215814.4
C64: EBITDA Margin | E64: % | G64: =G63/G43 -> -2.8063911 | H64: =H63/H43 -> -3.3139243 | I64: =I63/I43 -> -4.2753155 | J64: =J63/J43 -> -0.84914627 | K64: =K63/K43 -> -0.44468703 | L64: =L63/L43 -> -0.19578987 | M64: =M63/M43 -> -0.013523941 | N64: =N63/N43 -> 0.11903526 | ... P64: =P63/P43 -> 0.23640253
B66: Sensitivity Analyses
K69: Discount Rate: (WACC)
E70: =K37 -> 48.247637 | F70: 0.103 | G70: =F70+0.001 -> 0.104 | H70: =G70+0.001 -> 0.105 | I70: =H70+0.001 -> 0.106 | J70: =I70+0.001 -> 0.107 | K70: =J70+0.001 -> 0.108 | L70: =K70+0.001 -> 0.109 | M70: =L70+0.001 -> 0.11 | N70: =M70+0.001 -> 0.111 | ... P70: =O70+0.001 -> 0.113
E71: 19 | F71: 58.114416 | G71: 57.873839 | H71: 57.634551 | I71: 57.396545 | J71: 57.159812 | K71: 56.924345 | L71: 56.690136 | M71: 56.457177 | N71: 56.225459 | O71: 55.994976 | P71: 55.76572
E72: =E71-0.2 -> 18.8 | F72: 57.611405 | G72: 57.373102 | H72: 57.136076 | I72: 56.900319 | J72: 56.665823 | K72: 56.432582 | L72: 56.200586 | M72: 55.969827 | N72: 55.740299 | O72: 55.511994 | P72: 55.284903
D73: TEV / | E73: =E72-0.2 -> 18.6 | F73: 57.108394 | G73: 56.872365 | H73: 56.6376 | I73: 56.404093 | J73: 56.171835 | K73: 55.940818 | L73: 55.711035 | M73: 55.482478 | N73: 55.25514 | O73: 55.029012 | P73: 54.804087
D74: EBITDA | E74: =E73-0.2 -> 18.4 | F74: 56.605383 | G74: 56.371628 | H74: 56.139125 | I74: 55.907867 | J74: 55.677846 | K74: 55.449055 | L74: 55.221485 | M74: 54.995129 | N74: 54.76998 | O74: 54.54603 | P74: 54.323271
D75: Multiple | E75: =E74-0.2 -> 18.2 | F75: 56.102372 | G75: 55.870891 | H75: 55.64065 | I75: 55.411641 | J75: 55.183858 | K75: 54.957291 | L75: 54.731935 | M75: 54.50778 | N75: 54.28482 | O75: 54.063047 | P75: 53.842454
E76: =E75-0.2 -> 18 | F76: 55.599361 | G76: 55.370154 | H76: 55.142174 | I76: 54.915415 | J76: 54.689869 | K76: 54.465528 | L76: 54.242384 | M76: 54.020431 | N76: 53.79966 | O76: 53.580065 | P76: 53.361638
E77: =E76-0.2 -> 17.8 | F77: 55.09635 | G77: 54.869417 | H77: 54.643699 | I77: 54.419189 | J77: 54.19588 | K77: 53.973764 | L77: 53.752834 | M77: 53.533082 | N77: 53.314501 | O77: 53.097083 | P77: 52.880822
E78: =E77-0.2 -> 17.6 | F78: 54.593339 | G78: 54.36868 | H78: 54.145224 | I78: 53.922963 | J78: 53.701892 | K78: 53.482001 | L78: 53.263284 | M78: 53.045733 | N78: 52.829341 | O78: 52.614101 | P78: 52.400005
E79: =E78-0.2 -> 17.4 | F79: 54.090328 | G79: 53.867943 | H79: 53.646748 | I79: 53.426738 | J79: 53.207903 | K79: 52.990237 | L79: 52.773733 | M79: 52.558384 | N79: 52.344181 | O79: 52.131119 | P79: 51.919189
E80: =E79-0.2 -> 17.2 | F80: 53.587317 | G80: 53.367206 | H80: 53.148273 | I80: 52.930512 | J80: 52.713914 | K80: 52.498474 | L80: 52.284183 | M80: 52.071035 | N80: 51.859021 | O80: 51.648136 | P80: 51.438373
E81: =E80-0.2 -> 17 | F81: 53.084306 | G81: 52.866469 | H81: 52.649798 | I81: 52.434286 | J81: 52.219926 | K81: 52.006711 | L81: 51.794633 | M81: 51.583686 | N81: 51.373862 | O81: 51.165154 | P81: 50.957556
K84: Discount Rate: (WACC)
E85: =P37 -> 43.644299 | F85: 0.103 | G85: =F85+0.001 -> 0.104 | H85: =G85+0.001 -> 0.105 | I85: =H85+0.001 -> 0.106 | J85: =I85+0.001 -> 0.107 | K85: =J85+0.001 -> 0.108 | L85: =K85+0.001 -> 0.109 | M85: =L85+0.001 -> 0.11 | N85: =M85+0.001 -> 0.111 | ... P85: =O85+0.001 -> 0.113
E86: 0.035 | F86: 55.396725 | G86: 54.538538 | H86: 53.705173 | I86: 52.895579 | J86: 52.108767 | K86: 51.343797 | L86: 50.599785 | M86: 49.875892 | N86: 49.171321 | O86: 48.485321 | P86: 47.817176
D87: Terminal | E87: =E86-0.2% -> 0.033 | F87: 54.024901 | G87: 53.209856 | H87: 52.417747 | I87: 51.647629 | J87: 50.898611 | K87: 50.169848 | L87: 49.460539 | M87: 48.769926 | N87: 48.097289 | O87: 47.441945 | P87: 46.803244
D88: FCF | E88: =E87-0.2% -> 0.031 | F88: 52.729286 | G88: 51.953976 | H88: 51.199908 | I88: 50.466233 | J88: 49.752145 | K88: 49.056879 | L88: 48.379712 | M88: 47.719956 | N88: 47.076956 | O88: 46.450091 | P88: 45.838771
D89: Growth | E89: =E88-0.2% -> 0.029 | F89: 51.503702 | G89: 50.765072 | H89: 50.046163 | I89: 49.346205 | J89: 48.664469 | K89: 48.000261 | L89: 47.352924 | M89: 46.721833 | N89: 46.106392 | O89: 45.506034 | P89: 44.920221
D90: Rates | E90: =E89-0.2% -> 0.027 | F90: 50.342618 | G90: 49.637927 | H90: 48.951581 | I90: 48.282884 | J90: 47.631173 | K90: 46.995819 | L90: 46.376221 | M90: 45.77181 | N90: 45.182042 | O90: 44.606401 | P90: 44.044393
E91: =E90-0.2% -> 0.025 | F91: 49.241075 | G91: 48.567849 | H91: 47.911726 | I91: 47.272071 | J91: 46.64828 | K91: 46.03978 | L91: 45.446024 | M91: 44.866491 | N91: 44.300683 | O91: 43.748128 | P91: 43.208372
E92: =E91-0.2% -> 0.023 | F92: 48.194605 | G92: 47.550612 | H92: 46.922592 | I92: 46.309968 | J92: 45.712188 | K92: 45.128729 | L92: 44.55909 | M92: 44.002793 | N92: 43.459383 | O92: 42.928426 | P92: 42.409505
E93: =E92-0.2% -> 0.021 | F93: 47.19918 | G93: 46.582396 | H93: 45.980557 | I93: 45.393138 | J93: 44.819633 | K93: 44.259563 | L93: 43.712468 | M93: 43.17791 | N93: 42.655472 | O93: 42.144753 | P93: 41.645369
E94: =E93-0.2% -> 0.019 | F94: 46.251154 | G94: 45.659739 | H94: 45.082336 | I94: 44.518458 | J94: 43.967646 | K94: 43.429457 | L94: 42.903471 | M94: 42.389284 | N94: 41.886511 | O94: 41.394783 | P94: 40.913747
E95: =E94-0.2% -> 0.017 | F95: 45.347219 | G95: 44.779502 | H95: 44.224939 | I95: 43.683088 | J95: 43.153522 | K95: 42.635838 | L95: 42.129646 | M95: 41.634575 | N95: 41.150269 | O95: 40.676389 | P95: 40.212607
E96: =E95-0.2% -> 0.015 | F96: 44.484369 | G96: 43.938823 | H96: 43.405647 | I96: 42.884434 | J96: 42.374793 | K96: 41.87635 | L96: 41.388747 | M96: 40.91164 | N96: 40.444702 | O96: 39.987617 | P96: 39.540083
K99: Discount Rate: (WACC)
E100: =F176 -> 36.426274 | F100: 0.103 | G100: =F100+0.001 -> 0.104 | H100: =G100+0.001 -> 0.105 | I100: =H100+0.001 -> 0.106 | J100: =I100+0.001 -> 0.107 | K100: =J100+0.001 -> 0.108 | L100: =K100+0.001 -> 0.109 | M100: =L100+0.001 -> 0.11 | N100: =M100+0.001 -> 0.111 | ... P100: =O100+0.001 -> 0.113
E101: 0.55 | F101: 45.871788 | G101: 45.684376 | H101: 45.497969 | I101: 45.312561 | J101: 45.128145 | K101: 44.944715 | L101: 44.762266 | M101: 44.58079 | N101: 44.400282 | O101: 44.220735 | P101: 44.042145
E102: =E101+1% -> 0.56 | F102: 44.142331 | G102: 43.962276 | H102: 43.783187 | I102: 43.605058 | J102: 43.427883 | K102: 43.251656 | L102: 43.07637 | M102: 42.902021 | N102: 42.728603 | O102: 42.556108 | P102: 42.384533
E103: =E102+1% -> 0.57 | F103: 42.412874 | G103: 42.240176 | H103: 42.068405 | I103: 41.897555 | J103: 41.72762 | K103: 41.558596 | L103: 41.390475 | M103: 41.223253 | N103: 41.056923 | O103: 40.891481 | P103: 40.726921
E104: =E103+1% -> 0.58 | F104: 40.683418 | G104: 40.518076 | H104: 40.353623 | I104: 40.190052 | J104: 40.027358 | K104: 39.865536 | L104: 39.70458 | M104: 39.544484 | N104: 39.385244 | O104: 39.226854 | P104: 39.069308
E105: =E104+1% -> 0.59 | F105: 38.953961 | G105: 38.795976 | H105: 38.63884 | I105: 38.482549 | J105: 38.327096 | K105: 38.172476 | L105: 38.018684 | M105: 37.865716 | N105: 37.713565 | O105: 37.562227 | P105: 37.411696
D106: COGS | E106: =E105+1% -> 0.6 | F106: 37.224504 | G106: 37.073876 | H106: 36.924058 | I106: 36.775046 | J106: 36.626833 | K106: 36.479416 | L106: 36.332789 | M106: 36.186947 | N106: 36.041886 | O106: 35.8976 | P106: 35.754084
E107: =E106+1% -> 0.61 | F107: 35.495047 | G107: 35.351776 | H107: 35.209276 | I107: 35.067543 | J107: 34.926571 | K107: 34.786356 | L107: 34.646894 | M107: 34.508179 | N107: 34.370206 | O107: 34.232972 | P107: 34.096472
E108: =E107+1% -> 0.62 | F108: 33.76559 | G108: 33.629676 | H108: 33.494494 | I108: 33.36004 | J108: 33.226309 | K108: 33.093297 | L108: 32.960998 | M108: 32.82941 | N108: 32.698527 | O108: 32.568345 | P108: 32.43886
E109: =E108+1% -> 0.63 | F109: 32.036133 | G109: 31.907576 | H109: 31.779712 | I109: 31.652537 | J109: 31.526046 | K109: 31.400237 | L109: 31.275103 | M109: 31.150642 | N109: 31.026848 | O109: 30.903718 | P109: 30.781247
E110: =E109+1% -> 0.64 | F110: 30.306676 | G110: 30.185476 | H110: 30.064929 | I110: 29.945034 | J110: 29.825784 | K110: 29.707177 | L110: 29.589208 | M110: 29.471873 | N110: 29.355169 | O110: 29.239091 | P110: 29.123635
E111: =E110+1% -> 0.65 | F111: 28.57722 | G111: 28.463376 | H111: 28.350147 | I111: 28.23753 | J111: 28.125522 | K111: 28.014117 | L111: 27.903313 | M111: 27.793105 | N111: 27.68349 | O111: 27.574464 | P111: 27.466023
I115: Historical | M115: Projected:
B116: Ouster, Inc. - COGS Sensitivity | E116: Units: | H116: 44926 | I116: 45291 | J116: 45657 | K116: 46022 | L116: 46387 | M116: 46752 | N116: 47118 | O116: 47483 | P116: 47848
C118: Revenue | E118: $T | G118: 33578 | H118: 41029 | I118: 83279 | J118: 111101 | K118: 161096.45 | L118: 226251.22 | M118: 313168.86 | N118: 458122.67 | O118: 608749.07 | P118: 779173.47
C119: % Change | G119: 0 | H119: 0.22190124 | I119: 1.0297594 | J119: 0.33408182 | K119: 0.45 | L119: 0.40444575 | M119: 0.38416427 | N119: 0.46286151 | O119: 0.32879054 | P119: 0.27995837
C121: COGS | D121: COGS | E121: 0.6 | G121: =Model!G71 -> -24492 | H121: =Model!H71 -> -30099 | I121: =Model!I71 -> -74965 | J121: =Model!J71 -> -70641 | K121: =-K118*COGS -> -96657.87 | L121: =-L118*COGS -> -135750.73 | M121: =-M118*COGS -> -187901.32 | N121: =-N118*COGS -> -274873.6 | O121: =-O118*COGS -> -365249.44 | P121: =-P118*COGS -> -467504.08
C123: Operating Expenses | E123: $T | G123: =Model!G79 -> -108796 | H123: =Model!H79 -> -156353 | I123: =Model!I79 -> -381506 | J123: =Model!J79 -> -144637 | K123: =Model!K79 -> -160207.64 | L123: =Model!L79 -> -155000 | M123: =Model!M79 -> -155000 | N123: =Model!N79 -> -155000 | ... P123: =Model!P79 -> -155000
C125: Operating Income (EBIT) | E125: $T | G125: =SUM(G118,G121,G123) -> -99710 | H125: =SUM(H118,H121,H123) -> -145423 | I125: =SUM(I118,I121,I123) -> -373192 | J125: =SUM(J118,J121,J123) -> -104177 | K125: =SUM(K118,K121,K123) -> -95769.062 | L125: =SUM(L118,L121,L123) -> -64499.511 | M125: =SUM(M118,M121,M123) -> -29732.456 | N125: =SUM(N118,N121,N123) -> 28249.068 | ... P125: =SUM(P118,P121,P123) -> 156669.39
C127: (-) Taxes, Excluding Effect of Interest | E127: $T | G127: 0 | H127: 0 | I127: 0 | J127: 0 | K127: 0 | L127: 0 | M127: 0 | N127: 4996.6514 | O127: 15267.23 | P127: 27092.854
C129: Net Operating Profit After Taxes (NOPAT) | E129: $T | G129: =SUM(G125,G127) -> -99710 | H129: =SUM(H125,H127) -> -145423 | I129: =SUM(I125,I127) -> -373192 | J129: =SUM(J125,J127) -> -104177 | K129: =SUM(K125,K127) -> -95769.062 | L129: =SUM(L125,L127) -> -64499.511 | M129: =SUM(M125,M127) -> -29732.456 | N129: =SUM(N125,N127) -> 33245.72 | ... P129: =SUM(P125,P127) -> 183762.24
C131: Depreciation and amortization: | E131: $T | G131: 5477 | H131: 9456 | I131: 17148 | J131: 9836 | K131: 2245.5344 | L131: 3199.8917 | M131: 3958.6588 | N131: 4597.3717 | O131: 5151.9994 | P131: 5650.1117
C133: Change in Working Capital | E133: $T | G133: 0 | H133: 8337 | I133: -2293 | J133: -516 | K133: 18023.254 | L133: 16095.176 | M133: 20584.172 | N133: 27164.641 | O133: 27211.431 | P133: 18256.536
C135: Capital Expenditures: | E135: $T | G135: -4283 | H135: -5422 | I135: -3006 | J135: -3756 | K135: -4806.2293 | L135: -4650 | M135: -4650 | N135: -4650 | O135: -4650 | P135: -4650
C137: Unlevered Free Cash Flow | E137: $T | G137: =SUM(G129,G131,G133,G135) -> -98516 | H137: =SUM(H129,H131,H133,H135) -> -133052 | I137: =SUM(I129,I131,I133,I135) -> -361343 | J137: =SUM(J129,J131,J133,J135) -> -98613 | K137: =SUM(K129,K131,K133,K135) -> -80306.503 | L137: =SUM(L129,L131,L133,L135) -> -49854.443 | M137: =SUM(M129,M131,M133,M135) -> -9839.6252 | N137: =SUM(N129,N131,N133,N135) -> 60357.733 | ... P137: =SUM(P129,P131,P133,P135) -> 203018.89
...

Sheet WACC
B2: ="WACC Analysis - "&_xlfn.SINGLE(Company_Name) -> WACC Analysis - Ouster, Inc.
B3: ($ USD in Millions Except Per Share Amounts in USD as Stated)
B5: Discount Rate Calculations - Assumptions:
B6: Risk-Free Rate: | F6: 0.045
B7: Equity Risk Premium: | F7: 0.035
B8: Pre-Tax Cost of Debt: | F8: =[1]Drivers!K76 -> 0.03933665
B9: Cost of Preferred Stock: | F9: 0
B11: Company Name: | C11: Ticker: | D11: Levered Beta: | E11: (+) Debt & Capital Leases: | G11: (+) Preferred Stock: | I11: Equity Value: | K11: Effective Tax Rate:
B12: Comparable Companies - Unlevered Beta Calculation:
D13: Levered | G13: Preferred | I13: Equity | L13: Unlevered
B14: Name | C14: Ticker | D14: Beta | E14: Debt | F14: % Debt | G14: Stock | H14: % Preferred | I14: Value | J14: % Equity | K14: Tax Rate | L14: Beta
B15: =INDEX(Pub_Comps_Range,MATCH(B$11,Pub_Comps_Params,0),MATCH($C15,Pub_Comps_Tickers,0)) -> Hesai Group | C15: HSAI | D15: =INDEX(Pub_Comps_Range,MATCH(D$11,Pub_Comps_Params,0),MATCH($C15,Pub_Comps_Tickers,0)) -> 1.15 | E15: =INDEX(Pub_Comps_Range,MATCH(E$11,Pub_Comps_Params,0),MATCH($C15,Pub_Comps_Tickers,0)) -> 120.1 | F15: =E15/(E15+G15+I15) -> 0.029003357 | G15: =INDEX(Pub_Comps_Range,MATCH(G$11,Pub_Comps_Params,0),MATCH($C15,Pub_Comps_Tickers,0)) -> 0 | H15: =G15/(E15+G15+I15) -> 0 | I15: =INDEX(Pub_Comps_Range,MATCH(I$11,Pub_Comps_Params,0),MATCH($C15,Pub_Comps_Tickers,0)) -> 4020.8 | J15: =$I15/($E15+$G15+$I15) -> 0.97099664 | K15: =INDEX(Pub_Comps_Range,MATCH(K$11,Pub_Comps_Params,0),MATCH($C15,Pub_Comps_Tickers,0)) -> 0.061 | L15: =IFERROR(D15/(1+(E15/I15)*(1-K15)+G15/I15),"N/A") -> 1.1186252
B16: =INDEX(Pub_Comps_Range,MATCH(B$11,Pub_Comps_Params,0),MATCH($C16,Pub_Comps_Tickers,0)) -> Innoviz Technologies, Ltd. | C16: INVZ | D16: =INDEX(Pub_Comps_Range,MATCH(D$11,Pub_Comps_Params,0),MATCH($C16,Pub_Comps_Tickers,0)) -> 1.34 | E16: =INDEX(Pub_Comps_Range,MATCH(E$11,Pub_Comps_Params,0),MATCH($C16,Pub_Comps_Tickers,0)) -> 34.9 | F16: =E16/(E16+G16+I16) -> 0.13861105 | G16: =INDEX(Pub_Comps_Range,MATCH(G$11,Pub_Comps_Params,0),MATCH($C16,Pub_Comps_Tickers,0)) -> 0 | H16: =G16/(E16+G16+I16) -> 0 | I16: =INDEX(Pub_Comps_Range,MATCH(I$11,Pub_Comps_Params,0),MATCH($C16,Pub_Comps_Tickers,0)) -> 216.88368 | J16: =$I16/($E16+$G16+$I16) -> 0.86138895 | K16: =INDEX(Pub_Comps_Range,MATCH(K$11,Pub_Comps_Params,0),MATCH($C16,Pub_Comps_Tickers,0)) -> 0 | L16: =IFERROR(D16/(1+(E16/I16)*(1-K16)+G16/I16),"N/A") -> 1.1542612
B17: =INDEX(Pub_Comps_Range,MATCH(B$11,Pub_Comps_Params,0),MATCH($C17,Pub_Comps_Tickers,0)) -> Aeva Technologies, Inc. | C17: AEVA | D17: =INDEX(Pub_Comps_Range,MATCH(D$11,Pub_Comps_Params,0),MATCH($C17,Pub_Comps_Tickers,0)) -> 2.08 | E17: =INDEX(Pub_Comps_Range,MATCH(E$11,Pub_Comps_Params,0),MATCH($C17,Pub_Comps_Tickers,0)) -> 6.124 | F17: =E17/(E17+G17+I17) -> 0.0066345105 | G17: =INDEX(Pub_Comps_Range,MATCH(G$11,Pub_Comps_Params,0),MATCH($C17,Pub_Comps_Tickers,0)) -> 0 | H17: =G17/(E17+G17+I17) -> 0 | I17: =INDEX(Pub_Comps_Range,MATCH(I$11,Pub_Comps_Params,0),MATCH($C17,Pub_Comps_Tickers,0)) -> 916.92828 | J17: =$I17/($E17+$G17+$I17) -> 0.99336549 | K17: =INDEX(Pub_Comps_Range,MATCH(K$11,Pub_Comps_Params,0),MATCH($C17,Pub_Comps_Tickers,0)) -> 0.2 | L17: =IFERROR(D17/(1+(E17/I17)*(1-K17)+G17/I17),"N/A") -> 2.0689455
B18: =INDEX(Pub_Comps_Range,MATCH(B$11,Pub_Comps_Params,0),MATCH($C18,Pub_Comps_Tickers,0)) -> Luminar Technologies, Inc. | C18: LAZR | D18: =INDEX(Pub_Comps_Range,MATCH(D$11,Pub_Comps_Params,0),MATCH($C18,Pub_Comps_Tickers,0)) -> 1.36 | E18: =INDEX(Pub_Comps_Range,MATCH(E$11,Pub_Comps_Params,0),MATCH($C18,Pub_Comps_Tickers,0)) -> 449 | F18: =E18/(E18+G18+I18) -> 0.97567737 | G18: =INDEX(Pub_Comps_Range,MATCH(G$11,Pub_Comps_Params,0),MATCH($C18,Pub_Comps_Tickers,0)) -> 0 | H18: =G18/(E18+G18+I18) -> 0 | I18: =INDEX(Pub_Comps_Range,MATCH(I$11,Pub_Comps_Params,0),MATCH($C18,Pub_Comps_Tickers,0)) -> 11.193109 | J18: =$I18/($E18+$G18+$I18) -> 0.024322635 | K18: =INDEX(Pub_Comps_Range,MATCH(K$11,Pub_Comps_Params,0),MATCH($C18,Pub_Comps_Tickers,0)) -> 0 | L18: =IFERROR(D18/(1+(E18/I18)*(1-K18)+G18/I18),"N/A") -> 0.033078784
B19: =INDEX(Pub_Comps_Range,MATCH(B$11,Pub_Comps_Params,0),MATCH($C19,Pub_Comps_Tickers,0)) -> MicroVision, Inc. | C19: MVIS | D19: =INDEX(Pub_Comps_Range,MATCH(D$11,Pub_Comps_Params,0),MATCH($C19,Pub_Comps_Tickers,0)) -> 1.27 | E19: =INDEX(Pub_Comps_Range,MATCH(E$11,Pub_Comps_Params,0),MATCH($C19,Pub_Comps_Tickers,0)) -> 46 | F19: =E19/(E19+G19+I19) -> 0.142671 | G19: =INDEX(Pub_Comps_Range,MATCH(G$11,Pub_Comps_Params,0),MATCH($C19,Pub_Comps_Tickers,0)) -> 0 | H19: =G19/(E19+G19+I19) -> 0 | I19: =INDEX(Pub_Comps_Range,MATCH(I$11,Pub_Comps_Params,0),MATCH($C19,Pub_Comps_Tickers,0)) -> 276.4201 | J19: =$I19/($E19+$G19+$I19) -> 0.857329 | K19: =INDEX(Pub_Comps_Range,MATCH(K$11,Pub_Comps_Params,0),MATCH($C19,Pub_Comps_Tickers,0)) -> 0 | L19: =IFERROR(D19/(1+(E19/I19)*(1-K19)+G19/I19),"N/A") -> 1.0888078
B20: =INDEX(Pub_Comps_Range,MATCH(B$11,Pub_Comps_Params,0),MATCH($C20,Pub_Comps_Tickers,0)) -> Aeye, Inc. | C20: LIDR | D20: =INDEX(Pub_Comps_Range,MATCH(D$11,Pub_Comps_Params,0),MATCH($C20,Pub_Comps_Tickers,0)) -> 2.98 | E20: =INDEX(Pub_Comps_Range,MATCH(E$11,Pub_Comps_Params,0),MATCH($C20,Pub_Comps_Tickers,0)) -> 0.824 | F20: =E20/(E20+G20+I20) -> 0.0097890426 | G20: =INDEX(Pub_Comps_Range,MATCH(G$11,Pub_Comps_Params,0),MATCH($C20,Pub_Comps_Tickers,0)) -> 0 | H20: =G20/(E20+G20+I20) -> 0 | I20: =INDEX(Pub_Comps_Range,MATCH(I$11,Pub_Comps_Params,0),MATCH($C20,Pub_Comps_Tickers,0)) -> 83.35175 | J20: =$I20/($E20+$G20+$I20) -> 0.99021096 | K20: =INDEX(Pub_Comps_Range,MATCH(K$11,Pub_Comps_Params,0),MATCH($C20,Pub_Comps_Tickers,0)) -> 0 | L20: =IFERROR(D20/(1+(E20/I20)*(1-K20)+G20/I20),"N/A") -> 2.9508287
B22: Median: | D22: =MEDIAN(D15:D19) -> 1.34 | E22: =MEDIAN(E15:E19) -> 46 | F22: =MEDIAN(F15:F19) -> 0.13861105 | G22: =MEDIAN(G15:G19) -> 0 | H22: =MEDIAN(H15:H19) -> 0 | I22: =MEDIAN(I15:I19) -> 276.4201 | J22: =MEDIAN(J15:J19) -> 0.86138895 | K22: =MEDIAN(K15:K19) -> 0 | L22: =MEDIAN(L15:L19) -> 1.1186252
B24: =Company_Name -> Ouster, Inc. | C24: =Ticker -> OUST | D24: =INDEX(Pub_Comps_Range,MATCH(D$11,Pub_Comps_Params,0),MATCH($C24,Pub_Comps_Tickers,0)) -> 2.24 | E24: =INDEX(Pub_Comps_Range,MATCH(E$11,Pub_Comps_Params,0),MATCH($C24,Pub_Comps_Tickers,0)) -> 0 | F24: =E24/($E24+$G24+$I24) -> 0 | G24: =INDEX(Pub_Comps_Range,MATCH(G$11,Pub_Comps_Params,0),MATCH($C24,Pub_Comps_Tickers,0)) -> 0 | H24: =G24/($E24+$G24+$I24) -> 0 | I24: =INDEX(Pub_Comps_Range,MATCH(I$11,Pub_Comps_Params,0),MATCH($C24,Pub_Comps_Tickers,0)) -> 1119.2969 | J24: =I24/($E24+$G24+$I24) -> 1 | K24: 0.132 | L24: =IFERROR(D24/(1+(E24/I24)*(1-K24)+G24/I24),"N/A") -> 2.24
B26: =TEXT(Company_Name,"")& " - Levered Beta & WACC Calculation:" -> Ouster, Inc. - Levered Beta & WACC Calculation:
D27: Unlevered | G27: Preferred | I27: Equity | L27: Levered
C28: Ticker | D28: Beta | E28: Debt | F28: % Debt | G28: Stock | H28: % Preferred | I28: Value | J28: % Equity | K28: Tax Rate | L28: Beta
B29: Current Capital Structure: | C29: =C24 -> OUST | D29: =L24 -> 2.24 | E29: 5461 | F29: 0.033001557 | G29: 0 | H29: 0 | I29: 160016.04 | J29: 0.96699844 | K29: 0.132 | L29: =D29*(1+E29/I29*(1-K29)+G29/I29) -> 2.3063554
B30: "Optimal" Capital Structure: | D30: =L22 -> 1.1186252 | E30: =(E29+I29)*F30 -> 22936.946 | F30: =F22 -> 0.13861105 | G30: 0 | H30: 0 | I30: =(I29+E29)*J30 -> 142540.09 | J30: =J22 -> 0.86138895 | K30: 0.132 | L30: =D30*(1+E30/I30*(1-K30)+G30/I30) -> 1.274869
B32: Cost of Equity Based on Comparables, Current Capital Structure: | L32: =Risk_Free_Rate+Equity_Risk_Premium*L29 -> 0.12572244
B33: Cost of Equity Based on Comparables, "Optimal" Capital Structure: | L33: =Risk_Free_Rate+Equity_Risk_Premium*L30 -> 0.089620417
B34: Cost of Equity Based on Historical Beta: | L34: =Risk_Free_Rate+Equity_Risk_Premium*D24 -> 0.1234
B36: WACC, Current Capital Structure: | L36: =L32*J29+Cost_of_Debt*(1-K29)*F29+Cost_of_Preferred*H29 -> 0.12270022
B37: WACC, "Optimal" Capital Structure: | L37: =L33*J30+Cost_of_Debt*(1-K30)*F30+Cost_of_Preferred*H30 -> 0.081930802
B38: WACC, Current Capital Structure and Historical Cost of Equity: | L38: =L34*J29+Cost_of_Debt*(1-K29)*F29+Cost_of_Preferred*H29 -> 0.12045442
B40: Average WACC Produced by All Methods: | L40: =AVERAGE(L36:L38) -> 0.10836181

Sheet PubComps
B2: Comparable Companies - Semiconductor Manufacturing Equipment Provisions and Servicing
B3: ($ USD in Millions Except Per Share Amounts in USD as Stated)
B5: Company Name: | C5: Ticker: | D5: Share Price: | E5: Total Diluted Shares: | F5: Equity Value: | G5: Levered Beta: | H5: Effective Tax Rate: | I5: (-) Cash & Cash-Equivalents: | J5: (+) Debt & Capital Leases: | K5: (+) Preferred Stock: | L5: (+) Noncontrolling Interests: | M5: Enterprise Value: | N5: LTM Revenue: | O5: 2025-12-31 Revenue: | P5: 2026-12-31 Revenue: | Q5: 2025-12-31 Gross Profit: | R5: 2026-12-31 Gross Profit: | S5: 2027-12-31 Gross Profit: | T5: LTM Reported Net Income: | U5: 2025-12-31 Reported Net Income: | V5: 2026-12-31 Reported Net Income: | W5: Year 1 Projected Revenue Growth: | X5: Year 1 Projected EBITDA Growth: | Y5: LTM EBITDA Margin: | Z5: 2025-12-31 EBITDA Margin: | AA5: 2026-12-31 EBITDA Margin:
B6: Operating Statistics: | F6: Capitalization | W6: Projected | X6: Projected
D7: Share | E7: Diluted | F7: Equity | L7: Other & | M7: Enterprise | N7: Revenue | Q7: EBITDA | T7: Net Income | W7: Revenue | X7: EBITDA | Y7: EBITDA Margin | AF7: Ticker: | AK7: =Ticker -> OUST | AP7: ONTO | AU7: ACLS | AZ7: FORM | BE7: UCTT | BJ7: VECO | BO7: ENTG
B8: Company Name | C8: Ticker | D8: Price | E8: Shares | F8: Value | G8: Beta | H8: Tax Rate | I8: Cash | J8: Debt | K8: Preferred | L8: NCI | M8: Value | N8: LTM | O8: 46022 | P8: =EOMONTH(O8,12) -> 46387 | Q8: =$N$8 -> LTM | R8: =+$O$8 -> 46022 | S8: =+$P$8 -> 46387 | T8: =$N$8 -> LTM | U8: =+$O$8 -> 46022 | V8: =+$P$8 -> 46387 | W8: Growth | X8: Growth | Y8: =$N$8 -> LTM | Z8: =+$O$8 -> 46022 | AA8: =+$P$8 -> 46387
B9: =INDEX(Pub_Comps_Range,MATCH(B$5,Pub_Comps_Params,0),MATCH($C9,Pub_Comps_Tickers,0)) -> Hesai Group | C9: HSAI | D9: =INDEX(Pub_Comps_Range,MATCH(D$5,Pub_Comps_Params,0),MATCH($C9,Pub_Comps_Tickers,0)) -> 25.13 | E9: =INDEX(Pub_Comps_Range,MATCH(E$5,Pub_Comps_Params,0),MATCH($C9,Pub_Comps_Tickers,0)) -> 160 | F9: =INDEX(Pub_Comps_Range,MATCH(F$5,Pub_Comps_Params,0),MATCH($C9,Pub_Comps_Tickers,0)) -> 4020.8 | G9: =INDEX(Pub_Comps_Range,MATCH(G$5,Pub_Comps_Params,0),MATCH($C9,Pub_Comps_Tickers,0)) -> 1.15 | H9: =INDEX(Pub_Comps_Range,MATCH(H$5,Pub_Comps_Params,0),MATCH($C9,Pub_Comps_Tickers,0)) -> 0.061 | I9: =INDEX(Pub_Comps_Range,MATCH(I$5,Pub_Comps_Params,0),MATCH($C9,Pub_Comps_Tickers,0)) -> -1059 | J9: =INDEX(Pub_Comps_Range,MATCH(J$5,Pub_Comps_Params,0),MATCH($C9,Pub_Comps_Tickers,0)) -> 120.1 | K9: =INDEX(Pub_Comps_Range,MATCH(K$5,Pub_Comps_Params,0),MATCH($C9,Pub_Comps_Tickers,0)) -> 0 | ... AA9: =INDEX(Pub_Comps_Range,MATCH(AA$5,Pub_Comps_Params,0),MATCH($C9,Pub_Comps_Tickers,0)) -> 0.40880503
B10: =INDEX(Pub_Comps_Range,MATCH(B$5,Pub_Comps_Params,0),MATCH($C10,Pub_Comps_Tickers,0)) -> Innoviz Technologies, Ltd. | C10: INVZ | D10: =INDEX(Pub_Comps_Range,MATCH(D$5,Pub_Comps_Params,0),MATCH($C10,Pub_Comps_Tickers,0)) -> 1.04 | E10: =INDEX(Pub_Comps_Range,MATCH(E$5,Pub_Comps_Params,0),MATCH($C10,Pub_Comps_Tickers,0)) -> 208.542 | F10: =INDEX(Pub_Comps_Range,MATCH(F$5,Pub_Comps_Params,0),MATCH($C10,Pub_Comps_Tickers,0)) -> 216.88368 | G10: =INDEX(Pub_Comps_Range,MATCH(G$5,Pub_Comps_Params,0),MATCH($C10,Pub_Comps_Tickers,0)) -> 1.34 | H10: =INDEX(Pub_Comps_Range,MATCH(H$5,Pub_Comps_Params,0),MATCH($C10,Pub_Comps_Tickers,0)) -> 0 | I10: =INDEX(Pub_Comps_Range,MATCH(I$5,Pub_Comps_Params,0),MATCH($C10,Pub_Comps_Tickers,0)) -> -74.3 | J10: =INDEX(Pub_Comps_Range,MATCH(J$5,Pub_Comps_Params,0),MATCH($C10,Pub_Comps_Tickers,0)) -> 34.9 | K10: =INDEX(Pub_Comps_Range,MATCH(K$5,Pub_Comps_Params,0),MATCH($C10,Pub_Comps_Tickers,0)) -> 0 | ... AA10: =INDEX(Pub_Comps_Range,MATCH(AA$5,Pub_Comps_Params,0),MATCH($C10,Pub_Comps_Tickers,0)) -> 0.1686747
B11: =INDEX(Pub_Comps_Range,MATCH(B$5,Pub_Comps_Params,0),MATCH($C11,Pub_Comps_Tickers,0)) -> Aeva Technologies, Inc. | C11: AEVA | D11: =INDEX(Pub_Comps_Range,MATCH(D$5,Pub_Comps_Params,0),MATCH($C11,Pub_Comps_Tickers,0)) -> 14.34 | E11: =INDEX(Pub_Comps_Range,MATCH(E$5,Pub_Comps_Params,0),MATCH($C11,Pub_Comps_Tickers,0)) -> 63.942 | F11: =INDEX(Pub_Comps_Range,MATCH(F$5,Pub_Comps_Params,0),MATCH($C11,Pub_Comps_Tickers,0)) -> 916.92828 | G11: =INDEX(Pub_Comps_Range,MATCH(G$5,Pub_Comps_Params,0),MATCH($C11,Pub_Comps_Tickers,0)) -> 2.08 | H11: =INDEX(Pub_Comps_Range,MATCH(H$5,Pub_Comps_Params,0),MATCH($C11,Pub_Comps_Tickers,0)) -> 0.2 | I11: =INDEX(Pub_Comps_Range,MATCH(I$5,Pub_Comps_Params,0),MATCH($C11,Pub_Comps_Tickers,0)) -> -48.8 | J11: =INDEX(Pub_Comps_Range,MATCH(J$5,Pub_Comps_Params,0),MATCH($C11,Pub_Comps_Tickers,0)) -> 6.124 | K11: =INDEX(Pub_Comps_Range,MATCH(K$5,Pub_Comps_Params,0),MATCH($C11,Pub_Comps_Tickers,0)) -> 0 | ... AA11: =INDEX(Pub_Comps_Range,MATCH(AA$5,Pub_Comps_Params,0),MATCH($C11,Pub_Comps_Tickers,0)) -> 0
B12: =INDEX(Pub_Comps_Range,MATCH(B$5,Pub_Comps_Params,0),MATCH($C12,Pub_Comps_Tickers,0)) -> Luminar Technologies, Inc. | C12: LAZR | D12: =INDEX(Pub_Comps_Range,MATCH(D$5,Pub_Comps_Params,0),MATCH($C12,Pub_Comps_Tickers,0)) -> 0.08 | E12: =INDEX(Pub_Comps_Range,MATCH(E$5,Pub_Comps_Params,0),MATCH($C12,Pub_Comps_Tickers,0)) -> 139.91386 | F12: =INDEX(Pub_Comps_Range,MATCH(F$5,Pub_Comps_Params,0),MATCH($C12,Pub_Comps_Tickers,0)) -> 11.193109 | G12: =INDEX(Pub_Comps_Range,MATCH(G$5,Pub_Comps_Params,0),MATCH($C12,Pub_Comps_Tickers,0)) -> 1.36 | H12: =INDEX(Pub_Comps_Range,MATCH(H$5,Pub_Comps_Params,0),MATCH($C12,Pub_Comps_Tickers,0)) -> 0 | I12: =INDEX(Pub_Comps_Range,MATCH(I$5,Pub_Comps_Params,0),MATCH($C12,Pub_Comps_Tickers,0)) -> -6.3 | J12: =INDEX(Pub_Comps_Range,MATCH(J$5,Pub_Comps_Params,0),MATCH($C12,Pub_Comps_Tickers,0)) -> 449 | K12: =INDEX(Pub_Comps_Range,MATCH(K$5,Pub_Comps_Params,0),MATCH($C12,Pub_Comps_Tickers,0)) -> 0 | ... AA12: =INDEX(Pub_Comps_Range,MATCH(AA$5,Pub_Comps_Params,0),MATCH($C12,Pub_Comps_Tickers,0)) -> N/A
B13: =INDEX(Pub_Comps_Range,MATCH(B$5,Pub_Comps_Params,0),MATCH($C13,Pub_Comps_Tickers,0)) -> MicroVision, Inc. | C13: MVIS | D13: =INDEX(Pub_Comps_Range,MATCH(D$5,Pub_Comps_Params,0),MATCH($C13,Pub_Comps_Tickers,0)) -> 0.85 | E13: =INDEX(Pub_Comps_Range,MATCH(E$5,Pub_Comps_Params,0),MATCH($C13,Pub_Comps_Tickers,0)) -> 325.20012 | F13: =INDEX(Pub_Comps_Range,MATCH(F$5,Pub_Comps_Params,0),MATCH($C13,Pub_Comps_Tickers,0)) -> 276.4201 | G13: =INDEX(Pub_Comps_Range,MATCH(G$5,Pub_Comps_Params,0),MATCH($C13,Pub_Comps_Tickers,0)) -> 1.27 | H13: =INDEX(Pub_Comps_Range,MATCH(H$5,Pub_Comps_Params,0),MATCH($C13,Pub_Comps_Tickers,0)) -> 0 | I13: =INDEX(Pub_Comps_Range,MATCH(I$5,Pub_Comps_Params,0),MATCH($C13,Pub_Comps_Tickers,0)) -> -99 | J13: =INDEX(Pub_Comps_Range,MATCH(J$5,Pub_Comps_Params,0),MATCH($C13,Pub_Comps_Tickers,0)) -> 46 | K13: =INDEX(Pub_Comps_Range,MATCH(K$5,Pub_Comps_Params,0),MATCH($C13,Pub_Comps_Tickers,0)) -> 0 | ... AA13: =INDEX(Pub_Comps_Range,MATCH(AA$5,Pub_Comps_Params,0),MATCH($C13,Pub_Comps_Tickers,0)) -> 0.225 | AF13: ACMR
B14: =INDEX(Pub_Comps_Range,MATCH(B$5,Pub_Comps_Params,0),MATCH($C14,Pub_Comps_Tickers,0)) -> Aeye, Inc. | C14: LIDR | D14: =INDEX(Pub_Comps_Range,MATCH(D$5,Pub_Comps_Params,0),MATCH($C14,Pub_Comps_Tickers,0)) -> 1.85 | E14: =INDEX(Pub_Comps_Range,MATCH(E$5,Pub_Comps_Params,0),MATCH($C14,Pub_Comps_Tickers,0)) -> 45.055 | F14: =INDEX(Pub_Comps_Range,MATCH(F$5,Pub_Comps_Params,0),MATCH($C14,Pub_Comps_Tickers,0)) -> 83.35175 | G14: =INDEX(Pub_Comps_Range,MATCH(G$5,Pub_Comps_Params,0),MATCH($C14,Pub_Comps_Tickers,0)) -> 2.98 | H14: =INDEX(Pub_Comps_Range,MATCH(H$5,Pub_Comps_Params,0),MATCH($C14,Pub_Comps_Tickers,0)) -> 0 | I14: =INDEX(Pub_Comps_Range,MATCH(I$5,Pub_Comps_Params,0),MATCH($C14,Pub_Comps_Tickers,0)) -> -84.333 | J14: =INDEX(Pub_Comps_Range,MATCH(J$5,Pub_Comps_Params,0),MATCH($C14,Pub_Comps_Tickers,0)) -> 0.824 | K14: =INDEX(Pub_Comps_Range,MATCH(K$5,Pub_Comps_Params,0),MATCH($C14,Pub_Comps_Tickers,0)) -> 0 | ... AA14: =INDEX(Pub_Comps_Range,MATCH(AA$5,Pub_Comps_Params,0),MATCH($C14,Pub_Comps_Tickers,0)) -> 0.158
B15: Maximum | D15: =MAX(D9:D13) -> 25.13 | F15: =MAX(F9:F13) -> 4020.8 | M15: =MAX(M9:M13) -> 3081.9 | N15: =MAX(N9:N13) -> 385 | O15: =MAX(O9:O13) -> 445 | P15: =MAX(P9:P13) -> 636 | Q15: =MAX(Q9:Q13) -> 187 | R15: =MAX(R9:R13) -> 260 | S15: =MAX(S9:S13) -> 346 | T15: =MAX(T9:T13) -> 60.4 | ... AA15: =MAX(AA9:AA13) -> 0.40880503
B16: 75th Percentile | D16: =QUARTILE(D9:D13,3) -> 14.34 | F16: =QUARTILE(F9:F13,3) -> 916.92828 | M16: =QUARTILE(M9:M13,3) -> 874.25228 | N16: =QUARTILE(N9:N13,3) -> 75.77 | O16: =QUARTILE(O9:O13,3) -> 58 | P16: =QUARTILE(P9:P13,3) -> 83 | Q16: =QUARTILE(Q9:Q13,3) -> 13 | R16: =QUARTILE(R9:R13,3) -> 14 | S16: =QUARTILE(S9:S13,3) -> 28 | T16: =QUARTILE(T9:T13,3) -> -65.136 | ... AA16: =QUARTILE(AA9:AA13,3) -> 0.27095126
B17: Median | D17: =MEDIAN(D9:D13) -> 1.04 | F17: =MEDIAN(F9:F13) -> 276.4201 | M17: =MEDIAN(M9:M13) -> 453.89311 | N17: =MEDIAN(N9:N13) -> 48.442 | O17: =MEDIAN(O9:O13) -> 17 | P17: =MEDIAN(P9:P13) -> 28 | Q17: =MEDIAN(Q9:Q13) -> 0 | R17: =MEDIAN(R9:R13) -> 3.375 | S17: =MEDIAN(S9:S13) -> 13 | T17: =MEDIAN(T9:T13) -> -88 | ... AA17: =MEDIAN(AA9:AA13) -> 0.19683735
B18: 25th Percentile | D18: =QUARTILE(D9:D13,1) -> 0.85 | F18: =QUARTILE(F9:F13,1) -> 216.88368 | M18: =QUARTILE(M9:M13,1) -> 223.4201 | N18: =QUARTILE(N9:N13,1) -> 15.154 | O18: =QUARTILE(O9:O13,1) -> 3 | P18: =QUARTILE(P9:P13,1) -> 15 | Q18: =QUARTILE(Q9:Q13,1) -> -1 | R18: =QUARTILE(R9:R13,1) -> 0 | S18: =QUARTILE(S9:S13,1) -> 9.72 | T18: =QUARTILE(T9:T13,1) -> -156 | ... AA18: =QUARTILE(AA9:AA13,1) -> 0.12650602
B19: Minimum | D19: =MIN(D9:D13) -> 0.08 | F19: =MIN(F9:F13) -> 11.193109 | M19: =MIN(M9:M13) -> 177.48368 | N19: =MIN(N9:N13) -> 2.636 | O19: =MIN(O9:O13) -> 0 | P19: =MIN(P9:P13) -> 0 | Q19: =MIN(Q9:Q13) -> -1.89 | R19: =MIN(R9:R13) -> 0 | S19: =MIN(S9:S13) -> 0 | T19: =MIN(T9:T13) -> -234 | ... AA19: =MIN(AA9:AA13) -> 0
B21: =INDEX(Pub_Comps_Range,MATCH(B$5,Pub_Comps_Params,0),MATCH($C21,Pub_Comps_Tickers,0)) -> Ouster, Inc. | C21: =Ticker -> OUST | D21: =Share_Price -> 21.06 | E21: =INDEX(Pub_Comps_Range,MATCH(E$5,Pub_Comps_Params,0),MATCH($C21,Pub_Comps_Tickers,0)) -> 53.148 | F21: =INDEX(Pub_Comps_Range,MATCH(F$5,Pub_Comps_Params,0),MATCH($C21,Pub_Comps_Tickers,0)) -> 1119.2969 | G21: =INDEX(Pub_Comps_Range,MATCH(G$5,Pub_Comps_Params,0),MATCH($C21,Pub_Comps_Tickers,0)) -> 2.24 | H21: =INDEX(Pub_Comps_Range,MATCH(H$5,Pub_Comps_Params,0),MATCH($C21,Pub_Comps_Tickers,0)) -> 0.21 | I21: =INDEX(Pub_Comps_Range,MATCH(I$5,Pub_Comps_Params,0),MATCH($C21,Pub_Comps_Tickers,0)) -> -210.56569 | J21: =INDEX(Pub_Comps_Range,MATCH(J$5,Pub_Comps_Params,0),MATCH($C21,Pub_Comps_Tickers,0)) -> 0 | K21: =INDEX(Pub_Comps_Range,MATCH(K$5,Pub_Comps_Params,0),MATCH($C21,Pub_Comps_Tickers,0)) -> 0 | L21: =INDEX(Pub_Comps_Range,MATCH(L$5,Pub_Comps_Params,0),MATCH($C21,Pub_Comps_Tickers,0)) -> 773.0331 | ... V21: =INDEX(Pub_Comps_Range,MATCH(V$5,Pub_Comps_Params,0),MATCH($C21,Pub_Comps_Tickers,0)) -> -41.035703 | W21: =MIN(W10:W15) -> 0.43103448 | X21: =MIN(X10:X15) -> -2.7857143 | Y21: =MIN(Y10:Y15) -> -1.4036419 | Z21: =MIN(Z10:Z15) -> -0.63 | AA21: =MIN(AA10:AA15) -> 0
B23: Company Name: | C23: Ticker: | D23: Share Price: | F23: Equity Value: | M23: Enterprise Value: | N23: LTM EV / Revenue: | O23: 2025-12-31 EV / Revenue: | P23: 2026-12-31 EV / Revenue: | Q23: LTM EV / Gross Profit: | R23: 2025-12-31 EV / Gross Profit: | S23: 2026-12-31 EV / Gross Profit: | T23: LTM P / E: | U23: 2025-12-31 P / E: | V23: 2026-12-31 P / E:
B24: Valuation Statistics: | F24: Capitalization | N24: Enterprise Value / | Q24: Enterprise Value /
F25: Equity | M25: Enterprise | N25: Revenue | Q25: EBITDA | T25: P / E Multiple
B26: Company Name | C26: Ticker | D26: Share Price | F26: Value | M26: Value | N26: =$N$8 -> LTM | O26: =+$O$8 -> 46022 | P26: =+$P$8 -> 46387 | Q26: =$N$8 -> LTM | R26: =+$O$8 -> 46022 | S26: =+$P$8 -> 46387 | T26: =$N$8 -> LTM | U26: =+$O$8 -> 46022 | V26: =+$P$8 -> 46387
B27: =INDEX(Pub_Comps_Range,MATCH(B$23,Pub_Comps_Params,0),MATCH($C27,Pub_Comps_Tickers,0)) -> Hesai Group | C27: HSAI | D27: =INDEX(Pub_Comps_Range,MATCH(D$23,Pub_Comps_Params,0),MATCH($C27,Pub_Comps_Tickers,0)) -> 25.13 | F27: =INDEX(Pub_Comps_Range,MATCH(F$23,Pub_Comps_Params,0),MATCH($C27,Pub_Comps_Tickers,0)) -> 4020.8 | M27: =INDEX(Pub_Comps_Range,MATCH(M$23,Pub_Comps_Params,0),MATCH($C27,Pub_Comps_Tickers,0)) -> 3081.9 | N27: =INDEX(Pub_Comps_Range,MATCH(N$23,Pub_Comps_Params,0),MATCH($C27,Pub_Comps_Tickers,0)) -> 8.0049351 | O27: =INDEX(Pub_Comps_Range,MATCH(O$23,Pub_Comps_Params,0),MATCH($C27,Pub_Comps_Tickers,0)) -> 6.925618 | P27: =INDEX(Pub_Comps_Range,MATCH(P$23,Pub_Comps_Params,0),MATCH($C27,Pub_Comps_Tickers,0)) -> 4.8457547 | Q27: =INDEX(Pub_Comps_Range,MATCH(Q$23,Pub_Comps_Params,0),MATCH($C27,Pub_Comps_Tickers,0)) -> 19.322257 | R27: =INDEX(Pub_Comps_Range,MATCH(R$23,Pub_Comps_Params,0),MATCH($C27,Pub_Comps_Tickers,0)) -> 16.480749 | S27: =INDEX(Pub_Comps_Range,MATCH(S$23,Pub_Comps_Params,0),MATCH($C27,Pub_Comps_Tickers,0)) -> 11.853462 | T27: =INDEX(Pub_Comps_Range,MATCH(T$23,Pub_Comps_Params,0),MATCH($C27,Pub_Comps_Tickers,0)) -> 66.569536 | ... V27: =INDEX(Pub_Comps_Range,MATCH(V$23,Pub_Comps_Params,0),MATCH($C27,Pub_Comps_Tickers,0)) -> 44.675556
B28: =INDEX(Pub_Comps_Range,MATCH(B$23,Pub_Comps_Params,0),MATCH($C28,Pub_Comps_Tickers,0)) -> Innoviz Technologies, Ltd. | C28: INVZ | D28: =INDEX(Pub_Comps_Range,MATCH(D$23,Pub_Comps_Params,0),MATCH($C28,Pub_Comps_Tickers,0)) -> 1.04 | F28: =INDEX(Pub_Comps_Range,MATCH(F$23,Pub_Comps_Params,0),MATCH($C28,Pub_Comps_Tickers,0)) -> 216.88368 | M28: =INDEX(Pub_Comps_Range,MATCH(M$23,Pub_Comps_Params,0),MATCH($C28,Pub_Comps_Tickers,0)) -> 177.48368 | N28: =INDEX(Pub_Comps_Range,MATCH(N$23,Pub_Comps_Params,0),MATCH($C28,Pub_Comps_Tickers,0)) -> 3.6638388 | O28: =INDEX(Pub_Comps_Range,MATCH(O$23,Pub_Comps_Params,0),MATCH($C28,Pub_Comps_Tickers,0)) -> 3.0600634 | P28: =INDEX(Pub_Comps_Range,MATCH(P$23,Pub_Comps_Params,0),MATCH($C28,Pub_Comps_Tickers,0)) -> 2.1383576 | Q28: =INDEX(Pub_Comps_Range,MATCH(Q$23,Pub_Comps_Params,0),MATCH($C28,Pub_Comps_Tickers,0)) -> 15.597476 | R28: =INDEX(Pub_Comps_Range,MATCH(R$23,Pub_Comps_Params,0),MATCH($C28,Pub_Comps_Tickers,0)) -> 13.652591 | S28: =INDEX(Pub_Comps_Range,MATCH(S$23,Pub_Comps_Params,0),MATCH($C28,Pub_Comps_Tickers,0)) -> 12.677406 | T28: =INDEX(Pub_Comps_Range,MATCH(T$23,Pub_Comps_Params,0),MATCH($C28,Pub_Comps_Tickers,0)) -> NM | ... V28: =INDEX(Pub_Comps_Range,MATCH(V$23,Pub_Comps_Params,0),MATCH($C28,Pub_Comps_Tickers,0)) -> NM
B29: =INDEX(Pub_Comps_Range,MATCH(B$23,Pub_Comps_Params,0),MATCH($C29,Pub_Comps_Tickers,0)) -> Aeva Technologies, Inc. | C29: AEVA | D29: =INDEX(Pub_Comps_Range,MATCH(D$23,Pub_Comps_Params,0),MATCH($C29,Pub_Comps_Tickers,0)) -> 14.34 | F29: =INDEX(Pub_Comps_Range,MATCH(F$23,Pub_Comps_Params,0),MATCH($C29,Pub_Comps_Tickers,0)) -> 916.92828 | M29: =INDEX(Pub_Comps_Range,MATCH(M$23,Pub_Comps_Params,0),MATCH($C29,Pub_Comps_Tickers,0)) -> 874.25228 | N29: =INDEX(Pub_Comps_Range,MATCH(N$23,Pub_Comps_Params,0),MATCH($C29,Pub_Comps_Tickers,0)) -> 57.691189 | O29: =INDEX(Pub_Comps_Range,MATCH(O$23,Pub_Comps_Params,0),MATCH($C29,Pub_Comps_Tickers,0)) -> 51.426605 | P29: =INDEX(Pub_Comps_Range,MATCH(P$23,Pub_Comps_Params,0),MATCH($C29,Pub_Comps_Tickers,0)) -> 31.223296 | Q29: =INDEX(Pub_Comps_Range,MATCH(Q$23,Pub_Comps_Params,0),MATCH($C29,Pub_Comps_Tickers,0)) -> NM | R29: =INDEX(Pub_Comps_Range,MATCH(R$23,Pub_Comps_Params,0),MATCH($C29,Pub_Comps_Tickers,0)) -> NM | S29: =INDEX(Pub_Comps_Range,MATCH(S$23,Pub_Comps_Params,0),MATCH($C29,Pub_Comps_Tickers,0)) -> N/A | T29: =INDEX(Pub_Comps_Range,MATCH(T$23,Pub_Comps_Params,0),MATCH($C29,Pub_Comps_Tickers,0)) -> NM | ... V29: =INDEX(Pub_Comps_Range,MATCH(V$23,Pub_Comps_Params,0),MATCH($C29,Pub_Comps_Tickers,0)) -> NM
B30: =INDEX(Pub_Comps_Range,MATCH(B$23,Pub_Comps_Params,0),MATCH($C30,Pub_Comps_Tickers,0)) -> Luminar Technologies, Inc. | C30: LAZR | D30: =INDEX(Pub_Comps_Range,MATCH(D$23,Pub_Comps_Params,0),MATCH($C30,Pub_Comps_Tickers,0)) -> 0.08 | F30: =INDEX(Pub_Comps_Range,MATCH(F$23,Pub_Comps_Params,0),MATCH($C30,Pub_Comps_Tickers,0)) -> 11.193109 | M30: =INDEX(Pub_Comps_Range,MATCH(M$23,Pub_Comps_Params,0),MATCH($C30,Pub_Comps_Tickers,0)) -> 453.89311 | N30: =INDEX(Pub_Comps_Range,MATCH(N$23,Pub_Comps_Params,0),MATCH($C30,Pub_Comps_Tickers,0)) -> 5.9904066 | O30: =INDEX(Pub_Comps_Range,MATCH(O$23,Pub_Comps_Params,0),MATCH($C30,Pub_Comps_Tickers,0)) -> N/A | P30: =INDEX(Pub_Comps_Range,MATCH(P$23,Pub_Comps_Params,0),MATCH($C30,Pub_Comps_Tickers,0)) -> N/A | Q30: =INDEX(Pub_Comps_Range,MATCH(Q$23,Pub_Comps_Params,0),MATCH($C30,Pub_Comps_Tickers,0)) -> NM | R30: =INDEX(Pub_Comps_Range,MATCH(R$23,Pub_Comps_Params,0),MATCH($C30,Pub_Comps_Tickers,0)) -> N/A | S30: =INDEX(Pub_Comps_Range,MATCH(S$23,Pub_Comps_Params,0),MATCH($C30,Pub_Comps_Tickers,0)) -> N/A | T30: =INDEX(Pub_Comps_Range,MATCH(T$23,Pub_Comps_Params,0),MATCH($C30,Pub_Comps_Tickers,0)) -> NM | ... V30: =INDEX(Pub_Comps_Range,MATCH(V$23,Pub_Comps_Params,0),MATCH($C30,Pub_Comps_Tickers,0)) -> N/A
B31: =INDEX(Pub_Comps_Range,MATCH(B$23,Pub_Comps_Params,0),MATCH($C31,Pub_Comps_Tickers,0)) -> MicroVision, Inc. | C31: MVIS | D31: =INDEX(Pub_Comps_Range,MATCH(D$23,Pub_Comps_Params,0),MATCH($C31,Pub_Comps_Tickers,0)) -> 0.85 | F31: =INDEX(Pub_Comps_Range,MATCH(F$23,Pub_Comps_Params,0),MATCH($C31,Pub_Comps_Tickers,0)) -> 276.4201 | M31: =INDEX(Pub_Comps_Range,MATCH(M$23,Pub_Comps_Params,0),MATCH($C31,Pub_Comps_Tickers,0)) -> 223.4201 | N31: =INDEX(Pub_Comps_Range,MATCH(N$23,Pub_Comps_Params,0),MATCH($C31,Pub_Comps_Tickers,0)) -> 84.757248 | O31: =INDEX(Pub_Comps_Range,MATCH(O$23,Pub_Comps_Params,0),MATCH($C31,Pub_Comps_Tickers,0)) -> 74.473368 | P31: =INDEX(Pub_Comps_Range,MATCH(P$23,Pub_Comps_Params,0),MATCH($C31,Pub_Comps_Tickers,0)) -> 14.894674 | Q31: =INDEX(Pub_Comps_Range,MATCH(Q$23,Pub_Comps_Params,0),MATCH($C31,Pub_Comps_Tickers,0)) -> NM | R31: =INDEX(Pub_Comps_Range,MATCH(R$23,Pub_Comps_Params,0),MATCH($C31,Pub_Comps_Tickers,0)) -> NM | S31: =INDEX(Pub_Comps_Range,MATCH(S$23,Pub_Comps_Params,0),MATCH($C31,Pub_Comps_Tickers,0)) -> 66.19855 | T31: =INDEX(Pub_Comps_Range,MATCH(T$23,Pub_Comps_Params,0),MATCH($C31,Pub_Comps_Tickers,0)) -> NM | ... V31: =INDEX(Pub_Comps_Range,MATCH(V$23,Pub_Comps_Params,0),MATCH($C31,Pub_Comps_Tickers,0)) -> NM
B32: =INDEX(Pub_Comps_Range,MATCH(B$23,Pub_Comps_Params,0),MATCH($C32,Pub_Comps_Tickers,0)) -> Aeye, Inc. | C32: LIDR | D32: =INDEX(Pub_Comps_Range,MATCH(D$23,Pub_Comps_Params,0),MATCH($C32,Pub_Comps_Tickers,0)) -> 1.85 | F32: =INDEX(Pub_Comps_Range,MATCH(F$23,Pub_Comps_Params,0),MATCH($C32,Pub_Comps_Tickers,0)) -> 83.35175 | M32: =INDEX(Pub_Comps_Range,MATCH(M$23,Pub_Comps_Params,0),MATCH($C32,Pub_Comps_Tickers,0)) -> -0.15725 | N32: =INDEX(Pub_Comps_Range,MATCH(N$23,Pub_Comps_Params,0),MATCH($C32,Pub_Comps_Tickers,0)) -> NM | O32: =INDEX(Pub_Comps_Range,MATCH(O$23,Pub_Comps_Params,0),MATCH($C32,Pub_Comps_Tickers,0)) -> N/A | P32: =INDEX(Pub_Comps_Range,MATCH(P$23,Pub_Comps_Params,0),MATCH($C32,Pub_Comps_Tickers,0)) -> 37.236684 | Q32: =INDEX(Pub_Comps_Range,MATCH(Q$23,Pub_Comps_Params,0),MATCH($C32,Pub_Comps_Tickers,0)) -> NM | R32: =INDEX(Pub_Comps_Range,MATCH(R$23,Pub_Comps_Params,0),MATCH($C32,Pub_Comps_Tickers,0)) -> 7.4473368 | S32: =INDEX(Pub_Comps_Range,MATCH(S$23,Pub_Comps_Params,0),MATCH($C32,Pub_Comps_Tickers,0)) -> NM | T32: =INDEX(Pub_Comps_Range,MATCH(T$23,Pub_Comps_Params,0),MATCH($C32,Pub_Comps_Tickers,0)) -> NM | ... V32: =INDEX(Pub_Comps_Range,MATCH(V$23,Pub_Comps_Params,0),MATCH($C32,Pub_Comps_Tickers,0)) -> NM
B34: Maximum | F34: =MAX(F27:F32) -> 4020.8 | M34: =MAX(M27:M32) -> 3081.9 | N34: =MAX(N27:N32) -> 84.757248 | O34: =MAX(O27:O32) -> 74.473368 | P34: =MAX(P27:P32) -> 37.236684 | Q34: =MAX(Q27:Q32) -> 19.322257 | R34: =MAX(R27:R32) -> 16.480749 | S34: =MAX(S27:S32) -> 66.19855 | T34: =MAX(T27:T32) -> 66.569536 | ... V34: =MAX(V27:V32) -> 44.675556
B35: 75th Percentile | F35: =QUARTILE(F27:F32,3) -> 756.80124 | M35: =QUARTILE(M27:M32,3) -> 769.16249 | N35: =QUARTILE(N27:N32,3) -> 57.691189 | O35: =QUARTILE(O27:O32,3) -> 57.188296 | P35: =QUARTILE(P27:P32,3) -> 31.223296 | Q35: =QUARTILE(Q27:Q32,3) -> 18.391062 | R35: =QUARTILE(R27:R32,3) -> 15.06667 | S35: =QUARTILE(S27:S32,3) -> 39.437978 | T35: =QUARTILE(T27:T32,3) -> 66.569536 | ... V35: =QUARTILE(V27:V32,3) -> 44.675556
B36: Median | F36: =MEDIAN(F27:F32) -> 246.65189 | M36: =MEDIAN(M27:M32) -> 338.65661 | N36: =MEDIAN(N27:N32) -> 8.0049351 | O36: =MEDIAN(O27:O32) -> 29.176111 | P36: =MEDIAN(P27:P32) -> 14.894674 | Q36: =MEDIAN(Q27:Q32) -> 17.459867 | R36: =MEDIAN(R27:R32) -> 13.652591 | S36: =MEDIAN(S27:S32) -> 12.677406 | T36: =MEDIAN(T27:T32) -> 66.569536 | ... V36: =MEDIAN(V27:V32) -> 44.675556
B37: 25th Percentile | F37: =QUARTILE(F27:F32,1) -> 116.73473 | M37: =QUARTILE(M27:M32,1) -> 188.96779 | N37: =QUARTILE(N27:N32,1) -> 5.9904066 | O37: =QUARTILE(O27:O32,1) -> 5.9592293 | P37: =QUARTILE(P27:P32,1) -> 4.8457547 | Q37: =QUARTILE(Q27:Q32,1) -> 16.528671 | R37: =QUARTILE(R27:R32,1) -> 10.549964 | S37: =QUARTILE(S27:S32,1) -> 12.265434 | T37: =QUARTILE(T27:T32,1) -> 66.569536 | ... V37: =QUARTILE(V27:V32,1) -> 44.675556
B38: Minimum | F38: =MIN(F27:F32) -> 11.193109 | M38: =MIN(M27:M32) -> -0.15725 | N38: =MIN(N27:N32) -> 3.6638388 | O38: =MIN(O27:O32) -> 3.0600634 | P38: =MIN(P27:P32) -> 2.1383576 | Q38: =MIN(Q27:Q32) -> 15.597476 | R38: =MIN(R27:R32) -> 7.4473368 | S38: =MIN(S27:S32) -> 11.853462 | T38: =MIN(T27:T32) -> 66.569536 | ... V38: =MIN(V27:V32) -> 44.675556
B40: =INDEX(Pub_Comps_Range,MATCH(B$23,Pub_Comps_Params,0),MATCH($C40,Pub_Comps_Tickers,0)) -> Ouster, Inc. | C40: =Ticker -> OUST | F40: =INDEX(Pub_Comps_Range,MATCH(F$23,Pub_Comps_Params,0),MATCH($C40,Pub_Comps_Tickers,0)) -> 1119.2969 | M40: =INDEX(Pub_Comps_Range,MATCH(M$23,Pub_Comps_Params,0),MATCH($C40,Pub_Comps_Tickers,0)) -> 1681.7643 | N40: =INDEX(Pub_Comps_Range,MATCH(N$23,Pub_Comps_Params,0),MATCH($C40,Pub_Comps_Tickers,0)) -> 15.137256 | O40: =INDEX(Pub_Comps_Range,MATCH(O$23,Pub_Comps_Params,0),MATCH($C40,Pub_Comps_Tickers,0)) -> 9.951268 | P40: =INDEX(Pub_Comps_Range,MATCH(P$23,Pub_Comps_Params,0),MATCH($C40,Pub_Comps_Tickers,0)) -> 6.6006417 | Q40: =INDEX(Pub_Comps_Range,MATCH(Q$23,Pub_Comps_Params,0),MATCH($C40,Pub_Comps_Tickers,0)) -> 41.566097 | R40: =INDEX(Pub_Comps_Range,MATCH(R$23,Pub_Comps_Params,0),MATCH($C40,Pub_Comps_Tickers,0)) -> 20.30871 | S40: =INDEX(Pub_Comps_Range,MATCH(S$23,Pub_Comps_Params,0),MATCH($C40,Pub_Comps_Tickers,0)) -> 16.501604 | T40: =INDEX(Pub_Comps_Range,MATCH(T$23,Pub_Comps_Params,0),MATCH($C40,Pub_Comps_Tickers,0)) -> NM | ... V40: =INDEX(Pub_Comps_Range,MATCH(V$23,Pub_Comps_Params,0),MATCH($C40,Pub_Comps_Tickers,0)) -> NM

Sheet PubComps_Data
C3: Ticker: | H3: =Ticker -> OUST | M3: HSAI | R3: INVZ | W3: AEVA | AB3: LAZR | AG3: MVIS | AL3: LIDR
C4: Company Name: | H4: =Company_Name -> Ouster, Inc. | M4: Hesai Group | R4: Innoviz Technologies, Ltd. | W4: Aeva Technologies, Inc. | AB4: Luminar Technologies, Inc. | AG4: MicroVision, Inc. | AL4: Aeye, Inc.
E5: Calendarization: | J5: Calendarization: | O5: Calendarization: | T5: Calendarization: | Y5: Calendarization: | AD5: Calendarization: | AI5: Calendarization: | AN5: OUST
E6: N/A | F6: N/A | G6: =Hist_Year -> 45657 | H6: =Hist_Year -> 45657 | J6: 45565 | K6: 45930 | L6: 45657 | M6: 45930 | O6: 45472 | P6: 45836 | Q6: 45654 | R6: 45836 | T6: 45473 | U6: 45838 | V6: 45657 | W6: 45838 | Y6: 45565 | Z6: 45930 | AA6: 45657 | AB6: 45930 | AD6: 45565 | AE6: 45930 | AF6: 45657 | AG6: 45930 | AI6: 45473 | AJ6: 45838 | AK6: 45657 | AL6: 45838
E7: Old Partial | F7: New Partial | G7: FY | H7: LTM | J7: Old Partial | K7: New Partial | L7: FY | M7: LTM | O7: Old Partial | P7: New Partial | Q7: FY | R7: LTM | T7: Old Partial | U7: New Partial | V7: FY | W7: LTM | Y7: Old Partial | Z7: New Partial | AA7: FY | AB7: LTM | AD7: Old Partial | AE7: New Partial | AF7: FY | AG7: LTM | AI7: Old Partial | AJ7: New Partial | AK7: FY | AL7: LTM
C8: LTM Revenue: | G8: =Model!J69/Units -> 111.101 | H8: =G8+F8-E8 -> 111.101 | M8: 385 | O8: 18.241 | P8: 42.415 | Q8: 24.268 | R8: =+Q8+P8-O8 -> 48.442 | T8: 6.369 | U8: 12.458 | V8: 9.065 | W8: =+V8+U8-T8 -> 15.154 | Y8: 52.9 | Z8: 53.27 | AA8: 75.4 | AB8: =+AA8+Z8-Y8 -> 75.77 | AD8: 3.04 | AE8: 0.98 | AF8: 4.696 | AG8: =+AF8+AE8-AD8 -> 2.636 | AI8: 0.156 | AJ8: 0.136 | AK8: 0.202 | AL8: =+AK8+AJ8-AI8 -> 0.182
C9: LTM Reported Net Income: | G9: =Model!J91/Units -> -97.045 | H9: =G9+F9-E9 -> -97.045 | M9: 60.4 | O9: -76.161 | P9: -46.54 | Q9: -94.757 | R9: =+Q9+P9-O9 -> -65.136 | T9: -116 | U9: -120 | V9: -152 | W9: =+V9+U9-T9 -> -156 | Y9: -228 | Z9: -189 | AA9: -273 | AB9: =+AA9+Z9-Y9 -> -234 | AD9: -65 | AE9: -57 | AF9: -96 | AG9: =+AF9+AE9-AD9 -> -88 | AI9: -27 | AJ9: -26 | AK9: -35 | AL9: =+AK9+AJ9-AI9 -> -34
C11: LTM Gross Profit: | G11: =Model!J72/Units -> 40.46 | H11: =G11+F11-E11 -> 40.46 | M11: 159.5 | O11: -1.7 | P11: 10.84 | Q11: -1.161 | R11: =+Q11+P11-O11 -> 11.379 | T11: -3 | U11: -2 | V11: -3 | W11: =+V11+U11-T11 -> -2 | Y11: -38 | Z11: -28 | AA11: -21.29 | AB11: =+AA11+Z11-Y11 -> -11.29 | AD11: -0.3 | AE11: -1.2 | AF11: -2.8 | AG11: =+AF11+AE11-AD11 -> -3.7 | AI11: 0.573 | AJ11: 0.171 | AK11: 0.471 | AL11: =+AK11+AJ11-AI11 -> 0.069
C13: Effective Tax Rate: | H13: =Tax_Rate -> 0.21 | M13: 0.061 | R13: 0 | W13: 0.2 | AB13: 0 | AG13: 0 | AL13: 0
E15: Balance Sheet Data: | J15: Balance Sheet Data: | O15: Balance Sheet Data: | T15: Balance Sheet Data: | Y15: Balance Sheet Data: | AD15: Balance Sheet Data: | AI15: Balance Sheet Data:
C16: (-) Cash & Cash-Equivalents: | H16: =DCF!F23 -> -210.56569 | M16: -1059 | R16: -74.3 | W16: -48.8 | AB16: -6.3 | AG16: -99 | AL16: -84.333
C17: (-) Equity Investments: | H17: =[2]DCF!G23 -> 0 | M17: 0 | R17: 0 | W17: 0 | AB17: 0 | AG17: 0 | AL17: 0
C18: (-) Other Non-Core Assets, Net: | H18: =[2]DCF!G24 -> 0 | M18: 0 | R18: 0 | W18: 0 | AB18: 0 | AG18: 0 | AL18: 0
C19: (-) Net Operating Losses: | H19: =[2]DCF!G25 -> 0 | M19: 0 | R19: 0 | W19: 0 | AB19: 0 | AG19: 0 | AL19: 0
C20: (+) Debt & Capital Leases: | H20: =[2]DCF!G26 -> 0 | M20: 120.1 | R20: 34.9 | W20: 6.124 | AB20: 449 | AG20: 46 | AL20: 0.824
C21: (+) Preferred Stock: | H21: =[2]DCF!G27 -> 0 | M21: 0 | R21: 0 | W21: 0 | AB21: 0 | AG21: 0 | AL21: 0
C22: (+) Noncontrolling Interests: | H22: =[2]DCF!G28 -> 773.0331 | M22: 0 | R22: 0 | W22: 0 | AB22: 0 | AG22: 0 | AL22: 0
C23: (+) Unfunded Pension Obligations: | H23: 0 | M23: 0 | R23: 0 | W23: 0 | AB23: 0 | AG23: 0 | AL23: 0
C24: (+) Restructuring & Other Liabilities: | H24: =[2]DCF!G30 -> 0 | M24: 0 | R24: 0 | AB24: 0 | AG24: 0
E26: Projected Financials: | J26: Projected Financials: | O26: Projected Financials: | T26: Projected Financials: | Y26: Projected Financials: | AD26: Projected Financials: | AI26: Projected Financials:
E27: =Forward_Year_1 -> 46022 | F27: =Forward_Year_2 -> 46387 | G27: =Forward_Year_3 -> 46752 | J27: =Forward_Year_1 -> 46022 | K27: =Forward_Year_2 -> 46387 | L27: =Forward_Year_3 -> 46752 | O27: =Forward_Year_1 -> 46022 | P27: =Forward_Year_2 -> 46387 | Q27: =Forward_Year_3 -> 46752 | T27: =Forward_Year_1 -> 46022 | U27: =Forward_Year_2 -> 46387 | V27: =Forward_Year_3 -> 46752 | Y27: =Forward_Year_1 -> 46022 | Z27: =Forward_Year_2 -> 46387 | AA27: =Forward_Year_3 -> 46752 | AD27: =Forward_Year_1 -> 46022 | AE27: =Forward_Year_2 -> 46387 | AF27: =Forward_Year_3 -> 46752 | AI27: =Forward_Year_1 -> 46022 | AJ27: =Forward_Year_2 -> 46387 | AK27: =Forward_Year_3 -> 46752
C28: Revenue: | E28: =Model!K69/Units -> 169 | F28: =Model!L69/Units -> 254.788 | G28: =Model!M69/Units -> 365.25416 | J28: 445 | K28: 636 | L28: 893 | O28: 58 | P28: 83 | Q28: 126 | T28: 17 | U28: 28 | V28: 76 | AD28: 3 | AE28: 15 | AF28: 36 | AI28: 0 | AJ28: 6 | AK28: 35
C29: Gross Profit: | E29: =Model!K72/Units -> 82.81 | F29: =Model!L72/Units -> 101.9152 | G29: =Model!M72/Units -> 146.10167 | J29: 187 | K29: 260 | L29: 346 | O29: 13 | P29: 14 | Q29: 28 | T29: -1 | U29: 0 | V29: 13 | AD29: =AD28*-0.63 -> -1.89 | AE29: =AE28*0.225 -> 3.375 | AF29: =AF28*0.27 -> 9.72 | AI29: 30 | AJ29: =AJ28*0.158 -> 0.948 | AK29: =AK28*0.25 -> 8.75
C30: Reported Net Income: | E30: =Model!K91/Units -> -66.950192 | F30: =Model!L91/Units -> -41.035703 | G30: =Model!M91/Units -> -3.5968137 | J30: 57 | K30: 90 | L30: 142 | O30: -62 | P30: -67 | Q30: -68 | T30: -152 | U30: -137 | V30: -137 | AD30: -73 | AE30: -54 | AF30: -42 | AI30: -35 | AJ30: -33 | AK30: -27
E32: Diluted Shares Calculations: | J32: Diluted Shares Calculations: | O32: Diluted Shares Calculations: | T32: Diluted Shares Calculations: | Y32: Diluted Shares Calculations: | AD32: Diluted Shares Calculations: | AI32: Diluted Shares Calculations:
C33: Share Price: | H33: =Share_Price -> 21.06 | M33: 25.13 | R33: 1.04 | W33: 14.34 | AB33: 0.08 | AG33: 0.85 | AL33: 1.85
C34: Common Shares Outstanding: | H34: =Diluted -> 52.56 | M34: 160 | R34: 208.542 | W34: 61.942 | AB34: 77.9 | AG34: 311 | AL34: 45.055
C35: Options and Warrants:
F36: Total | G36: Strike | H36: Dilution | K36: Total | L36: Strike | M36: Dilution | P36: Total | Q36: Strike | R36: Dilution | U36: Total | V36: Strike | W36: Dilution | Z36: Total | AA36: Strike | AB36: Dilution | AE36: Total | AF36: Strike | AG36: Dilution | AJ36: Total | AK36: Strike | AL36: Dilution
H37: =IF(G37<H$32,F37-((F37*G37)/H$32),0) -> 0 | M37: =IF(L37<M$32,K37-((K37*L37)/M$32),0) -> 0 | R37: =IF(Q37<R$32,P37-((P37*Q37)/R$32),0) -> 0 | W37: =IF(V37<W$32,U37-((U37*V37)/W$32),0) -> 0 | AB37: =IF(AA37<AB$32,Z37-((Z37*AA37)/AB$32),0) -> 0 | AG37: =IF(AF37<AG$32,AE37-((AE37*AF37)/AG$32),0) -> 0 | AL37: =IF(AK37<AL$32,AJ37-((AJ37*AK37)/AL$32),0) -> 0
H38: =IF(G38<H$32,F38-((F38*G38)/H$32),0) -> 0 | M38: =IF(L38<M$32,K38-((K38*L38)/M$32),0) -> 0 | R38: =IF(Q38<R$32,P38-((P38*Q38)/R$32),0) -> 0 | W38: =IF(V38<W$32,U38-((U38*V38)/W$32),0) -> 0 | AB38: =IF(AA38<AB$32,Z38-((Z38*AA38)/AB$32),0) -> 0 | AG38: =IF(AF38<AG$32,AE38-((AE38*AF38)/AG$32),0) -> 0 | AL38: =IF(AK38<AL$32,AJ38-((AJ38*AK38)/AL$32),0) -> 0
H39: =IF(G39<H$32,F39-((F39*G39)/H$32),0) -> 0 | M39: =IF(L39<M$32,K39-((K39*L39)/M$32),0) -> 0 | R39: =IF(Q39<R$32,P39-((P39*Q39)/R$32),0) -> 0 | W39: =IF(V39<W$32,U39-((U39*V39)/W$32),0) -> 0 | AB39: =IF(AA39<AB$32,Z39-((Z39*AA39)/AB$32),0) -> 0 | AG39: =IF(AF39<AG$32,AE39-((AE39*AF39)/AG$32),0) -> 0 | AL39: =IF(AK39<AL$32,AJ39-((AJ39*AK39)/AL$32),0) -> 0
H40: =IF(G40<H$32,F40-((F40*G40)/H$32),0) -> 0 | M40: =IF(L40<M$32,K40-((K40*L40)/M$32),0) -> 0 | R40: =IF(Q40<R$32,P40-((P40*Q40)/R$32),0) -> 0 | W40: =IF(V40<W$32,U40-((U40*V40)/W$32),0) -> 0 | AB40: =IF(AA40<AB$32,Z40-((Z40*AA40)/AB$32),0) -> 0 | AG40: =IF(AF40<AG$32,AE40-((AE40*AF40)/AG$32),0) -> 0 | AL40: =IF(AK40<AL$32,AJ40-((AJ40*AK40)/AL$32),0) -> 0
H41: =IF(G41<H$32,F41-((F41*G41)/H$32),0) -> 0 | M41: =IF(L41<M$32,K41-((K41*L41)/M$32),0) -> 0 | R41: =IF(Q41<R$32,P41-((P41*Q41)/R$32),0) -> 0 | W41: =IF(V41<W$32,U41-((U41*V41)/W$32),0) -> 0 | AB41: =IF(AA41<AB$32,Z41-((Z41*AA41)/AB$32),0) -> 0 | AG41: =IF(AF41<AG$32,AE41-((AE41*AF41)/AG$32),0) -> 0 | AL41: =IF(AK41<AL$32,AJ41-((AJ41*AK41)/AL$32),0) -> 0
H42: =IF(G42<H$32,F42-((F42*G42)/H$32),0) -> 0 | M42: =IF(L42<M$32,K42-((K42*L42)/M$32),0) -> 0 | R42: =IF(Q42<R$32,P42-((P42*Q42)/R$32),0) -> 0 | W42: =IF(V42<W$32,U42-((U42*V42)/W$32),0) -> 0 | AB42: =IF(AA42<AB$32,Z42-((Z42*AA42)/AB$32),0) -> 0 | AG42: =IF(AF42<AG$32,AE42-((AE42*AF42)/AG$32),0) -> 0 | AL42: =IF(AK42<AL$32,AJ42-((AJ42*AK42)/AL$32),0) -> 0
H43: =IF(G43<H$32,F43-((F43*G43)/H$32),0) -> 0 | M43: =IF(L43<M$32,K43-((K43*L43)/M$32),0) -> 0 | R43: =IF(Q43<R$32,P43-((P43*Q43)/R$32),0) -> 0 | W43: =IF(V43<W$32,U43-((U43*V43)/W$32),0) -> 0 | AB43: =IF(AA43<AB$32,Z43-((Z43*AA43)/AB$32),0) -> 0 | AG43: =IF(AF43<AG$32,AE43-((AE43*AF43)/AG$32),0) -> 0 | AL43: =IF(AK43<AL$32,AJ43-((AJ43*AK43)/AL$32),0) -> 0
H44: =IF(G44<H$32,F44-((F44*G44)/H$32),0) -> 0 | M44: =IF(L44<M$32,K44-((K44*L44)/M$32),0) -> 0 | R44: =IF(Q44<R$32,P44-((P44*Q44)/R$32),0) -> 0 | W44: =IF(V44<W$32,U44-((U44*V44)/W$32),0) -> 0 | AB44: =IF(AA44<AB$32,Z44-((Z44*AA44)/AB$32),0) -> 0 | AG44: =IF(AF44<AG$32,AE44-((AE44*AF44)/AG$32),0) -> 0 | AL44: =IF(AK44<AL$32,AJ44-((AJ44*AK44)/AL$32),0) -> 0
H45: =IF(G45<H$32,F45-((F45*G45)/H$32),0) -> 0 | M45: =IF(L45<M$32,K45-((K45*L45)/M$32),0) -> 0 | R45: =IF(Q45<R$32,P45-((P45*Q45)/R$32),0) -> 0 | W45: =IF(V45<W$32,U45-((U45*V45)/W$32),0) -> 0 | AB45: =IF(AA45<AB$32,Z45-((Z45*AA45)/AB$32),0) -> 0 | AG45: =IF(AF45<AG$32,AE45-((AE45*AF45)/AG$32),0) -> 0 | AL45: =IF(AK45<AL$32,AJ45-((AJ45*AK45)/AL$32),0) -> 0
C47: Convertible Bonds: | E47: $ Amount | F47: Par Value | G47: Conv. Price | H47: Dilution | J47: $ Amount | K47: Par Value | L47: Conv. Price | M47: Dilution | O47: $ Amount | P47: Par Value | Q47: Conv. Price | R47: Dilution | T47: $ Amount | U47: Par Value | V47: Conv. Price | W47: Dilution | Y47: $ Amount | Z47: Par Value | AA47: Conv. Price | AB47: Dilution | AD47: $ Amount | AE47: Par Value | AF47: Conv. Price | AG47: Dilution | AI47: $ Amount | AJ47: Par Value | AK47: Conv. Price | AL47: Dilution
H48: =IFERROR(IF(G48>H$32,0,(+F48/G48)*E48/F48), 0) -> 0 | M48: =IFERROR(IF(L48>M$32,0,(+K48/L48)*J48/K48),0) -> 0 | R48: =IFERROR(IF(Q48>R$32,0,(+P48/Q48)*O48/P48),0) -> 0 | W48: =IFERROR(IF(V48>W$32,0,(+U48/V48)*T48/U48),0) -> 0 | AB48: =IFERROR(IF(AA48>AB$32,0,+Y48/AA48-(AB$32*(Y48/AA48)-Y48)*0.5/AB$32),0) -> 0 | AG48: =IFERROR(IF(AF48>AG$32,0,+AD48/AF48-(AG$32*(AD48/AF48)-AD48)*0.5/AG$32),0) -> 0 | AL48: =IFERROR(IF(AK48>AL$32,0,+AI48/AK48-(AL$32*(AI48/AK48)-AI48)*0.5/AL$32),0) -> 0
H49: =IFERROR(IF(G49>H$32,0,(+F49/G49)*E49/F49),0) -> 0 | M49: =IFERROR(IF(L49>M$32,0,(+K49/L49)*J49/K49),0) -> 0 | R49: =IFERROR(IF(Q49>R$32,0,(+P49/Q49)*O49/P49),0) -> 0 | W49: =IFERROR(IF(V49>W$32,0,(+U49/V49)*T49/U49),0) -> 0 | AB49: =IFERROR(IF(AA49>AB$32,0,(+Z49/AA49)*Y49/Z49),0) -> 0 | AG49: =IFERROR(IF(AF49>AG$32,0,(+AE49/AF49)*AD49/AE49),0) -> 0 | AL49: =IFERROR(IF(AK49>AL$32,0,(+AJ49/AK49)*AI49/AJ49),0) -> 0
G51: # RSUs | H51: Dilution | L51: # RSUs | M51: Dilution | Q51: # RSUs | R51: Dilution | V51: # RSUs | W51: Dilution | AA51: # RSUs | AB51: Dilution | AF51: # RSUs | AG51: Dilution | AK51: # RSUs | AL51: Dilution
C52: Restricted Stock Units (RSUs): | G52: =(321+105+91+71)/Units -> 0.588 | H52: =+G52 -> 0.588 | L52: 0 | M52: =+L52 -> 0 | Q52: 0 | R52: =+Q52 -> 0 | V52: 2 | W52: =+V52 -> 2 | AA52: =(3470929+976862+513318)/AB33/1000000 -> 62.013863 | AB52: =+AA52 -> 62.013863 | AF52: =(8164661+1555793+809887+769882+769882)/AG33/1000000 -> 14.200124 | AG52: =+AF52 -> 14.200124 | AK52: 0 | AL52: =+AK52 -> 0
C54: Total Diluted Shares: | H54: =+H52+SUM(H37:H45)+SUM(H48:H49)+H34 -> 53.148 | M54: =+M52+SUM(M37:M45)+SUM(M48:M49)+M34 -> 160 | R54: =+R52+SUM(R37:R45)+SUM(R48:R49)+R34 -> 208.542 | W54: =+W52+SUM(W37:W45)+SUM(W48:W49)+W34 -> 63.942 | AB54: =+AB52+SUM(AB37:AB45)+SUM(AB48:AB49)+AB34 -> 139.91386 | AG54: =+AG52+SUM(AG37:AG45)+SUM(AG48:AG49)+AG34 -> 325.20012 | AL54: =+AL52+SUM(AL37:AL45)+SUM(AL48:AL49)+AL34 -> 45.055
E56: Valuation Metrics: | J56: Valuation Metrics: | O56: Valuation Metrics: | T56: Valuation Metrics: | Y56: Valuation Metrics: | AD56: Valuation Metrics: | AI56: Valuation Metrics:
C58: Equity Value: | H58: =+H54*H33 -> 1119.2969 | M58: =+M54*M33 -> 4020.8 | R58: =+R54*R33 -> 216.88368 | W58: =+W54*W33 -> 916.92828 | AB58: =+AB54*AB33 -> 11.193109 | AG58: =+AG54*AG33 -> 276.4201 | AL58: =+AL54*AL33 -> 83.35175
C59: Enterprise Value: | H59: =+H58+SUM(H16:H24) -> 1681.7643 | M59: =+M58+SUM(M16:M24) -> 3081.9 | R59: =+R58+SUM(R16:R24) -> 177.48368 | W59: =+W58+SUM(W16:W24) -> 874.25228 | AB59: =+AB58+SUM(AB16:AB24) -> 453.89311 | AG59: =+AG58+SUM(AG16:AG24) -> 223.4201 | AL59: =+AL58+SUM(AL16:AL24) -> -0.15725
C60: Levered Beta: | H60: 2.24 | M60: 1.15 | R60: 1.34 | W60: 2.08 | AB60: 1.36 | AG60: 1.27 | AL60: 2.98
E62: Valuation Multiples: | J62: Valuation Multiples: | O62: Valuation Multiples: | T62: Valuation Multiples: | Y62: Valuation Multiples: | AD62: Valuation Multiples: | AI62: Valuation Multiples:
E63: =H7 -> LTM | F63: =E27 -> 46022 | G63: =F27 -> 46387 | H63: =G27 -> 46752 | J63: =M7 -> LTM | K63: =J27 -> 46022 | L63: =K27 -> 46387 | M63: =L27 -> 46752 | O63: =R7 -> LTM | P63: =O27 -> 46022 | Q63: =P27 -> 46387 | R63: =Q27 -> 46752 | T63: =W7 -> LTM | U63: =T27 -> 46022 | V63: =U27 -> 46387 | W63: =V27 -> 46752 | Y63: =AB7 -> LTM | Z63: =Y27 -> 46022 | AA63: =Z27 -> 46387 | AB63: =AA27 -> 46752 | AD63: =AG7 -> LTM | AE63: =AD27 -> 46022 | AF63: =AE27 -> 46387 | AG63: =AF27 -> 46752 | AI63: =AL7 -> LTM | AJ63: =AI27 -> 46022 | AK63: =AJ27 -> 46387 | AL63: =AK27 -> 46752
C64: EV / Revenue: | E64: =IFERROR(IF(OR(+H$59/H8<0,+H$59/H8>=100),"NM",+H$59/H8), "N/A") -> 15.137256 | F64: =IFERROR(IF(OR(+H59/E28<0,+H59/E28>=100),"NM",+H59/E28), "N/A") -> 9.951268 | G64: =IFERROR(IF(OR(+$H$59/F28<0,+$H$59/F28>=100),"NM",+$H$59/F28), "N/A") -> 6.6006417 | H64: =IFERROR(IF(OR(+$H$59/G28<0,+$H$59/G28>=100),"NM",+$H$59/G28), "N/A") -> 4.6043672 | J64: =IFERROR(IF(OR(+M$59/M8<0,+M$59/M8>=100),"NM",+M$59/M8),"N/A") -> 8.0049351 | K64: =IFERROR(IF(OR(+$M$59/J28<0,+$M$59/J28>=100),"NM",+$M$59/J28), "N/A") -> 6.925618 | L64: =IFERROR(IF(OR(+$M$59/K28<0,+$M$59/K28>=100),"NM",+$M$59/K28), "N/A") -> 4.8457547 | M64: =IFERROR(IF(OR(+$M$59/L28<0,+$M$59/L28>=100),"NM",+$M$59/L28), "N/A") -> 3.4511758 | O64: =IFERROR(IF(OR(+R$59/R8<0,+R$59/R8>=100),"NM",+R$59/R8),"N/A") -> 3.6638388 | P64: =IFERROR(IF(OR(+$R$59/O28<0,+$R$59/O28>=100),"NM",+$R$59/O28), "N/A") -> 3.0600634 | Q64: =IFERROR(IF(OR(+R59/P28<0,+R59/P28>=100),"NM",+R59/P28), "N/A") -> 2.1383576 | R64: =IFERROR(IF(OR(+R59/Q28<0,+R59/Q28>=100),"NM",+R59/Q28), "N/A") -> 1.4086006 | T64: =IFERROR(IF(OR(+W$59/W8<0,+W$59/W8>=100),"NM",+W$59/W8),"N/A") -> 57.691189 | U64: =IFERROR(IF(OR(+$W$59/T28<0,+$W$59/T28>=100),"NM",+$W$59/T28), "N/A") -> 51.426605 | V64: =IFERROR(IF(OR(+$W$59/U28<0,+$W$59/U28>=100),"NM",+$W$59/U28), "N/A") -> 31.223296 | W64: =IFERROR(IF(OR(+$W$59/V28<0,+$W$59/V28>=100),"NM",+$W$59/V28), "N/A") -> 11.503319 | Y64: =IFERROR(IF(OR(+AB$59/AB8<0,+AB$59/AB8>=100),"NM",+AB$59/AB8),"N/A") -> 5.9904066 | Z64: =IFERROR(IF(OR(+$AB$59/Y28<0,+$AB$59/Y28>=100),"NM",+$AB$59/Y28), "N/A") -> N/A | AA64: =IFERROR(IF(OR(+$AB$59/Z28<0,+$AB$59/Z28>=100),"NM",+$AB$59/Z28), "N/A") -> N/A | AB64: =IFERROR(IF(OR(+$AB$59/AA28<0,+$AB$59/AA28>=100),"NM",+$AB$59/AA28), "N/A") -> N/A | AD64: =IFERROR(IF(OR(+AG$59/AG8<0,+AG$59/AG8>=100),"NM",+AG$59/AG8),"N/A") -> 84.757248 | AE64: =IFERROR(IF(OR(+$AG$59/AD28<0,+$AG$59/AD28>=100),"NM",+$AG$59/AD28), "N/A") -> 74.473368 | AF64: =IFERROR(IF(OR(+$AG$59/AE28<0,+$AG$59/AE28>=100),"NM",+$AG$59/AE28), "N/A") -> 14.894674 | AG64: =IFERROR(IF(OR(+$AG$59/AF28<0,+$AG$59/AF28>=100),"NM",+$AG$59/AF28), "N/A") -> 6.206114 | AI64: =IFERROR(IF(OR(+AL$59/AL8<0,+AL$59/AL8>=100),"NM",+AL$59/AL8),"N/A") -> NM | AJ64: =IFERROR(IF(OR(+$AG$59/AI28<0,+$AG$59/AI28>=100),"NM",+$AG$59/AI28), "N/A") -> N/A | AK64: =IFERROR(IF(OR(+$AG$59/AJ28<0,+$AG$59/AJ28>=100),"NM",+$AG$59/AJ28), "N/A") -> 37.236684 | AL64: =IFERROR(IF(OR(+$AG$59/AK28<0,+$AG$59/AK28>=100),"NM",+$AG$59/AK28), "N/A") -> 6.3834316
C65: EV / Gross Profit: | E65: =IFERROR(IF(OR(+H$59/H11<0,+H$59/H11>=100),"NM",+H$59/H11), "N/A") -> 41.566097 | F65: =IFERROR(IF(OR(+$H$59/E29<0,+$H$59/E29>=100),"NM",+$H$59/E29), "N/A") -> 20.30871 | G65: =IFERROR(IF(OR(+$H$59/F29<0,+$H$59/F29>=100),"NM",+$H$59/F29), "N/A") -> 16.501604 | H65: =IFERROR(IF(OR(+$H$59/G29<0,+$H$59/G29>=100),"NM",+$H$59/G29), "N/A") -> 11.510918 | J65: =IFERROR(IF(OR(+M$59/M11<0,+M$59/M11>=100),"NM",+M$59/M11),"N/A") -> 19.322257 | K65: =IFERROR(IF(OR(+$M$59/J29<0,+$M$59/J29>=100),"NM",+$M$59/J29),"N/A") -> 16.480749 | L65: =IFERROR(IF(OR(+$M$59/K29<0,+$M$59/K29>=100),"NM",+$M$59/K29),"N/A") -> 11.853462 | M65: =IFERROR(IF(OR(+$M$59/L29<0,+$M$59/L29>=100),"NM",+$M$59/L29),"N/A") -> 8.9072254 | O65: =IFERROR(IF(OR(+$R$59/R11<0,+$R$59/R11>=100),"NM",+$R$59/R11),"N/A") -> 15.597476 | P65: =IFERROR(IF(OR(+$R$59/O29<0,+$R$59/O29>=100),"NM",+$R$59/O29),"N/A") -> 13.652591 | Q65: =IFERROR(IF(OR(+$R$59/P29<0,+$R$59/P29>=100),"NM",+$R$59/P29),"N/A") -> 12.677406 | R65: =IFERROR(IF(OR(+$R$59/Q29<0,+$R$59/Q29>=100),"NM",+$R$59/Q29),"N/A") -> 6.3387029 | T65: =IFERROR(IF(OR(+W$59/W11<0,+W$59/W11>=100),"NM",+W$59/W11),"N/A") -> NM | U65: =IFERROR(IF(OR(+$W$59/T29<0,+$W$59/T29>=100),"NM",+$W$59/T29), "N/A") -> NM | V65: =IFERROR(IF(OR(+$W$59/U29<0,+$W$59/U29>=100),"NM",+$W$59/U29), "N/A") -> N/A | W65: =IFERROR(IF(OR(+$W$59/V29<0,+$W$59/V29>=100),"NM",+$W$59/V29), "N/A") -> 67.250175 | Y65: =IFERROR(IF(OR(+AB$59/AB11<0,+AB$59/AB11>=100),"NM",+AB$59/AB11),"N/A") -> NM | Z65: =IFERROR(IF(OR(+$AB$59/Y29<0,+$AB$59/Y29>=100),"NM",+$AB$59/Y29),"N/A") -> N/A | AA65: =IFERROR(IF(OR(+$AB$59/Z29<0,+$AB$59/Z29>=100),"NM",+$AB$59/Z29),"N/A") -> N/A | AB65: =IFERROR(IF(OR(+$AB$59/AA29<0,+$AB$59/AA29>=100),"NM",+$AB$59/AA29),"N/A") -> N/A | AD65: =IFERROR(IF(OR(+AG$59/AG11<0,+AG$59/AG11>=100),"NM",+AG$59/AG11),"N/A") -> NM | AE65: =IFERROR(IF(OR(+$AG$59/AD29<0,+$AG$59/AD29>=100),"NM",+$AG$59/AD29),"N/A") -> NM | AF65: =IFERROR(IF(OR(+$AG$59/AE29<0,+$AG$59/AE29>=100),"NM",+$AG$59/AE29),"N/A") -> 66.19855 | AG65: =IFERROR(IF(OR(+$AG$59/AF29<0,+$AG$59/AF29>=100),"NM",+$AG$59/AF29),"N/A") -> 22.985608 | AI65: =IFERROR(IF(OR(+AL$59/AL11<0,+AL$59/AL11>=100),"NM",+AL$59/AL11),"N/A") -> NM | AJ65: =IFERROR(IF(OR(+$AG$59/AI29<0,+$AG$59/AI29>=100),"NM",+$AG$59/AI29),"N/A") -> 7.4473368 | AK65: =IFERROR(IF(OR(+$AG$59/AJ29<0,+$AG$59/AJ29>=100),"NM",+$AG$59/AJ29),"N/A") -> NM | AL65: =IFERROR(IF(OR(+$AG$59/AK29<0,+$AG$59/AK29>=100),"NM",+$AG$59/AK29),"N/A") -> 25.533726
C66: P / E: | E66: =IFERROR(IF(OR(+H$58/H9<0,+H$58/H9>=100),"NM",+H$58/H9), "N/A") -> NM | F66: =IFERROR(IF(OR($H$58/E$30<0,+$H$58/E$30>=100),"NM",+$H$58/E$30), "N/A") -> NM | G66: =IFERROR(IF(OR(H58/F$30<0,+H58/F$30>=100),"NM",+H58/F$30), "N/A") -> NM | H66: =IFERROR(IF(OR(H58/G$30<0,+H58/G$30>=100),"NM",+H58/G$30), "N/A") -> NM | J66: =IFERROR(IF(OR(+M$58/M9<0,+M$58/M9>=100),"NM",+M$58/M9), "N/A") -> 66.569536 | K66: =IFERROR(IF(OR($M$58/J$30<0,+$M$58/J$30>=100),"NM",+$M$58/J$30), "N/A") -> 70.540351 | L66: =IFERROR(IF(OR(M58/K$30<0,+M58/K$30>=100),"NM",+M58/K$30), "N/A") -> 44.675556 | M66: =IFERROR(IF(OR(M58/L$30<0,+M58/L$30>=100),"NM",+M58/L$30), "N/A") -> 28.315493 | O66: =IFERROR(IF(OR(+R$58/R9<0,+R$58/R9>=100),"NM",+R$58/R9), "N/A") -> NM | P66: =IFERROR(IF(OR($R$58/O$30<0,+$R$58/O$30>=100),"NM",+$R$58/O$30), "N/A") -> NM | Q66: =IFERROR(IF(OR(R58/P$30<0,+R58/P$30>=100),"NM",+R58/P$30), "N/A") -> NM | R66: =IFERROR(IF(OR(R58/Q$30<0,+R58/Q$30>=100),"NM",+R58/Q$30), "N/A") -> NM | T66: =IFERROR(IF(OR(+W$58/W9<0,+W$58/W9>=100),"NM",+W$58/W9),"N/A") -> NM | U66: =IFERROR(IF(OR(+W$58/T30<0,+W$58/T30>=100),"NM",+W$58/T30),"N/A") -> NM | V66: =IFERROR(IF(OR(+W$58/U30<0,+W$58/U30>=100),"NM",+W$58/U30),"N/A") -> NM | W66: =IFERROR(IF(OR(+W$58/V30<0,+W$58/V30>=100),"NM",+W$58/V30),"N/A") -> NM | Y66: =IFERROR(IF(OR(+AB$58/AB9<0,+AB$58/AB9>=100),"NM",+AB$58/AB9),"N/A") -> NM | Z66: =IFERROR(IF(OR(+$AB$58/Y30<0,+$AB$58/Y30>=100),"NM",+$AB$58/Y30),"N/A") -> N/A | AA66: =IFERROR(IF(OR(+$AB$58/Z30<0,+$AB$58/Z30>=100),"NM",+$AB$58/Z30),"N/A") -> N/A | AB66: =IFERROR(IF(OR(+$AB$58/AA30<0,+$AB$58/AA30>=100),"NM",+$AB$58/AA30),"N/A") -> N/A | AD66: =IFERROR(IF(OR(+AG$58/AG9<0,+AG$58/AG9>=100),"NM",+AG$58/AG9),"N/A") -> NM | AE66: =IFERROR(IF(OR(+$AG$58/AD30<0,+$AG$58/AD30>=100),"NM",+$AG$58/AD30),"N/A") -> NM | AF66: =IFERROR(IF(OR(+$AG$58/AE30<0,+$AG$58/AE30>=100),"NM",+$AG$58/AE30),"N/A") -> NM | AG66: =IFERROR(IF(OR(+$AG$58/AF30<0,+$AG$58/AF30>=100),"NM",+$AG$58/AF30),"N/A") -> NM | AI66: =IFERROR(IF(OR(+AL$58/AL9<0,+AL$58/AL9>=100),"NM",+AL$58/AL9),"N/A") -> NM | AJ66: =IFERROR(IF(OR(+$AG$58/AI30<0,+$AG$58/AI30>=100),"NM",+$AG$58/AI30),"N/A") -> NM | AK66: =IFERROR(IF(OR(+$AG$58/AJ30<0,+$AG$58/AJ30>=100),"NM",+$AG$58/AJ30),"N/A") -> NM | AL66: =IFERROR(IF(OR(+$AG$58/AK30<0,+$AG$58/AK30>=100),"NM",+$AG$58/AK30),"N/A") -> NM
E68: Lookup Variables: | J68: Lookup Variables: | O68: Lookup Variables: | T68: Lookup Variables: | Y68: Lookup Variables: | AD68: Lookup Variables: | AI68: Lookup Variables:
C70: =TEXT(Forward_Year_1,"yyyy-mm-dd")&" "&C28 -> 2025-12-31 Revenue: | H70: =+E28 -> 169 | M70: =+J28 -> 445 | R70: =+O28 -> 58 | W70: =+T28 -> 17 | AB70: =+Y28 -> 0 | AG70: =+AD28 -> 3 | AL70: =+AI28 -> 0
C71: =TEXT(Forward_Year_1,"yyyy-mm-dd")&" "&C29 -> 2025-12-31 Gross Profit: | H71: =+E29 -> 82.81 | M71: =+J29 -> 187 | R71: =+O29 -> 13 | W71: =+T29 -> -1 | AB71: =+Y29 -> 0 | AG71: =+AD29 -> -1.89 | AL71: =+AI29 -> 30
C72: =TEXT(Forward_Year_1,"yyyy-mm-dd")&" "&C30 -> 2025-12-31 Reported Net Income: | H72: =+E30 -> -66.950192 | M72: =+J30 -> 57 | R72: =+O30 -> -62 | W72: =+T30 -> -152 | AB72: =+Y30 -> 0 | AG72: =+AD30 -> -73 | AL72: =+AI30 -> -35
C74: =TEXT(Forward_Year_2,"yyyy-mm-dd")&" "&C28 -> 2026-12-31 Revenue: | H74: =+F28 -> 254.788 | M74: =+K28 -> 636 | R74: =+P28 -> 83 | W74: =+U28 -> 28 | AB74: =+Z28 -> 0 | AG74: =+AE28 -> 15 | AL74: =+AJ28 -> 6
C75: =TEXT(Forward_Year_2,"yyyy-mm-dd")&" "&C29 -> 2026-12-31 Gross Profit: | H75: =+F29 -> 101.9152 | M75: =+K29 -> 260 | R75: =+P29 -> 14 | W75: =+U29 -> 0 | AB75: =+Z29 -> 0 | AG75: =+AE29 -> 3.375 | AL75: =+AJ29 -> 0.948
C76: =TEXT(Forward_Year_2,"yyyy-mm-dd")&" "&C30 -> 2026-12-31 Reported Net Income: | H76: =+F30 -> -41.035703 | M76: =+K30 -> 90 | R76: =+P30 -> -67 | W76: =+U30 -> -137 | AB76: =+Z30 -> 0 | AG76: =+AE30 -> -54 | AL76: =+AJ30 -> -33
C78: =TEXT(Forward_Year_3,"yyyy-mm-dd")&" "&C28 -> 2027-12-31 Revenue: | H78: =+G28 -> 365.25416 | M78: =+L28 -> 893 | R78: =+Q28 -> 126 | W78: =+V28 -> 76 | AB78: =+AA28 -> 0 | AG78: =+AF28 -> 36 | AL78: =+AK28 -> 35
C79: =TEXT(Forward_Year_3,"yyyy-mm-dd")&" "&C29 -> 2027-12-31 Gross Profit: | H79: =+G29 -> 146.10167 | M79: =+L29 -> 346 | R79: =+Q29 -> 28 | W79: =+V29 -> 13 | AB79: =+AA29 -> 0 | AG79: =+AF29 -> 9.72 | AL79: =+AK29 -> 8.75
C80: =TEXT(Forward_Year_3,"yyyy-mm-dd")&" "&C30 -> 2027-12-31 Reported Net Income: | H80: =+G30 -> -3.5968137 | M80: =+L30 -> 142 | R80: =+Q30 -> -68 | W80: =+V30 -> -137 | AB80: =+AA30 -> 0 | AG80: =+AF30 -> -42 | AL80: =+AK30 -> -27
C82: Year 1 Projected Revenue Growth: | H82: =IFERROR(+H74/H70-1,"N/A") -> 0.5076213 | M82: =IFERROR(+M74/M70-1,"N/A") -> 0.42921348 | R82: =IFERROR(+R74/R70-1,"N/A") -> 0.43103448 | W82: =IFERROR(+W74/W70-1,"N/A") -> 0.64705882 | AB82: =IFERROR(+AB74/AB70-1,"N/A") -> N/A | AG82: =IFERROR(+AG74/AG70-1,"N/A") -> 4 | AL82: =IFERROR(+AL74/AL70-1,"N/A") -> N/A
C83: Year 1 Projected EBITDA Growth: | H83: =IFERROR(+H75/H71-1,"N/A") -> 0.23071127 | M83: =IFERROR(+M75/M71-1,"N/A") -> 0.39037433 | R83: =IFERROR(+R75/R71-1,"N/A") -> 0.076923077 | W83: =IFERROR(+W75/W71-1,"N/A") -> -1 | AB83: =IFERROR(+AB75/AB71-1,"N/A") -> N/A | AG83: =IFERROR(+AG75/AG71-1,"N/A") -> -2.7857143 | AL83: =IFERROR(+AL75/AL71-1,"N/A") -> -0.9684
C85: LTM EBITDA Margin: | H85: =IFERROR(+H11/H8,"N/A") -> 0.36417314 | M85: =IFERROR(+M11/M8,"N/A") -> 0.41428571 | R85: =IFERROR(+R11/R8,"N/A") -> 0.23489947 | W85: =IFERROR(+W11/W8,"N/A") -> -0.13197836 | AB85: =IFERROR(+AB11/AB8,"N/A") -> -0.14900356 | AG85: =IFERROR(+AG11/AG8,"N/A") -> -1.4036419 | AL85: =IFERROR(+AL11/AL8,"N/A") -> 0.37912088
C86: =TEXT(Forward_Year_1,"yyyy-mm-dd")&" EBITDA Margin:" -> 2025-12-31 EBITDA Margin: | H86: =IFERROR(+H71/H70,"N/A") -> 0.49 | M86: =IFERROR(+M71/M70,"N/A") -> 0.42022472 | R86: =IFERROR(+R71/R70,"N/A") -> 0.22413793 | W86: =IFERROR(+W71/W70,"N/A") -> -0.058823529 | AB86: =IFERROR(+AB71/AB70,"N/A") -> N/A | AG86: =IFERROR(+AG71/AG70,"N/A") -> -0.63 | AL86: =IFERROR(+AL71/AL70,"N/A") -> N/A
C87: =TEXT(Forward_Year_2,"yyyy-mm-dd")&" EBITDA Margin:" -> 2026-12-31 EBITDA Margin: | H87: =IFERROR(+H75/H74,"N/A") -> 0.4 | M87: =IFERROR(+M75/M74,"N/A") -> 0.40880503 | R87: =IFERROR(+R75/R74,"N/A") -> 0.1686747 | W87: =IFERROR(+W75/W74,"N/A") -> 0 | AB87: =IFERROR(+AB75/AB74,"N/A") -> N/A | AG87: =IFERROR(+AG75/AG74,"N/A") -> 0.225 | AL87: =IFERROR(+AL75/AL74,"N/A") -> 0.158
C89: =TEXT(E63,"mm/dd/yyyy")&" "&C64 -> LTM EV / Revenue: | H89: =+E64 -> 15.137256 | M89: =+J64 -> 8.0049351 | R89: =+O64 -> 3.6638388 | W89: =+T64 -> 57.691189 | AB89: =+Y64 -> 5.9904066 | AG89: =+AD64 -> 84.757248 | AL89: =+AI64 -> NM
C90: =TEXT(E63,"mm/dd/yyyy")&" "&C65 -> LTM EV / Gross Profit: | H90: =+E65 -> 41.566097 | M90: =+J65 -> 19.322257 | R90: =+O65 -> 15.597476 | W90: =+T65 -> NM | AB90: =+Y65 -> NM | AG90: =+AD65 -> NM | AL90: =+AI65 -> NM
C91: =TEXT(E63,"mm/dd/yyyy")&" "&C66 -> LTM P / E: | H91: =+E66 -> NM | M91: =+J66 -> 66.569536 | R91: =+O66 -> NM | W91: =+T66 -> NM | AB91: =+Y66 -> NM | AG91: =+AD66 -> NM | AL91: =+AI66 -> NM
C93: =TEXT(Forward_Year_1,"yyyy-mm-dd")&" "&C64 -> 2025-12-31 EV / Revenue: | H93: =+F64 -> 9.951268 | M93: =+K64 -> 6.925618 | R93: =+P64 -> 3.0600634 | W93: =+U64 -> 51.426605 | AB93: =+Z64 -> N/A | AG93: =+AE64 -> 74.473368 | AL93: =+AJ64 -> N/A
C94: =TEXT(Forward_Year_1,"yyyy-mm-dd")&" "&C65 -> 2025-12-31 EV / Gross Profit: | H94: =+F65 -> 20.30871 | M94: =+K65 -> 16.480749 | R94: =+P65 -> 13.652591 | W94: =+U65 -> NM | AB94: =+Z65 -> N/A | AG94: =+AE65 -> NM | AL94: =+AJ65 -> 7.4473368
C95: =TEXT(Forward_Year_1,"yyyy-mm-dd")&" "&C66 -> 2025-12-31 P / E: | H95: =+F66 -> NM | M95: =+K66 -> 70.540351 | R95: =+P66 -> NM | W95: =+U66 -> NM | AB95: =+Z66 -> N/A | AG95: =+AE66 -> NM | AL95: =+AJ66 -> NM
C97: =TEXT(Forward_Year_2,"yyyy-mm-dd")&" "&C64 -> 2026-12-31 EV / Revenue: | H97: =+G64 -> 6.6006417 | M97: =+L64 -> 4.8457547 | R97: =+Q64 -> 2.1383576 | W97: =+V64 -> 31.223296 | AB97: =+AA64 -> N/A | AG97: =+AF64 -> 14.894674 | AL97: =+AK64 -> 37.236684
C98: =TEXT(Forward_Year_2,"yyyy-mm-dd")&" "&C65 -> 2026-12-31 EV / Gross Profit: | H98: =+G65 -> 16.501604 | M98: =+L65 -> 11.853462 | R98: =+Q65 -> 12.677406 | W98: =+V65 -> N/A | AB98: =+AA65 -> N/A | AG98: =+AF65 -> 66.19855 | AL98: =+AK65 -> NM
C99: =TEXT(Forward_Year_2,"yyyy-mm-dd")&" "&C66 -> 2026-12-31 P / E: | H99: =+G66 -> NM | M99: =+L66 -> 44.675556 | R99: =+Q66 -> NM | W99: =+V66 -> NM | AB99: =+AA66 -> N/A | AG99: =+AF66 -> NM | AL99: =+AK66 -> NM
C101: Corporate Website:

Sheet MAComps
B2: Precedent Transactions – International LIDAR manufacturing companies
B3: Announced Between July 31st, 2019 and December 31st, 2024
B4: ($ in Millions Except Per Share and Per Unit Data)
B6: =Company_Name&" - Comparable M&A Transactions" -> Ouster, Inc. - Comparable M&A Transactions | F6: Operating Metrics | H6: Valuation Multiples | K6: Share Prices | N6: Premiums Paid
E7: Transaction | H7: EV / | I7: EV /
E8: Enterprise | F8: LTM | G8: LTM | H8: LTM | I8: LTM | J8: Offer | K8: 1-Day | L8: 1-Week | M8: 1-Month | N8: 1-Day | O8: 1-Week | P8: 1-Month
B9: Acquirer Name | C9: Target Name | D9: Date | E9: Value | F9: Revenue | G9: EBITDA | H9: Revenue | I9: EBITDA | J9: Price | K9: Prior | L9: Prior | M9: Prior | N9: Prior | O9: Prior | P9: Prior
B11: Middleground Management, LP | C11: Stemmer Imaging AG | D11: 45495 | E11: 313.42 | F11: 135.25 | G11: 25.06 | H11: =IFERROR(IF(OR(+$E11/F11<0,+$E11/F11>=100),"NM",+$E11/F11),"N/A") -> 2.3173383 | I11: =IFERROR(IF(OR(+$E11/G11<0,+$E11/G11>=100),"NM",+$E11/G11),"N/A") -> 12.506784 | J11: 52.12 | K11: 34.39 | L11: 36.46 | M11: 38.53 | N11: =IFERROR($J11/K11-1,"N/A") -> 0.51555685 | O11: =IFERROR($J11/L11-1,"N/A") -> 0.42951179 | P11: =IFERROR($J11/M11-1,"N/A") -> 0.35271217
B12: Unknown | C12: SES-imagotag Societe Anonyme | D12: 44894 | E12: 1872.19 | F12: 552.46 | G12: 36 | H12: =IFERROR(IF(OR(+$E12/F12<0,+$E12/F12>=100),"NM",+$E12/F12),"N/A") -> 3.3888245 | I12: =IFERROR(IF(OR(+$E12/G12<0,+$E12/G12>=100),"NM",+$E12/G12),"N/A") -> 52.005278 | J12: 115.81 | K12: 132.15 | L12: 122.22 | M12: 118.71 | N12: =IFERROR($J12/K12-1,"N/A") -> -0.12364737 | O12: =IFERROR($J12/L12-1,"N/A") -> -0.052446408 | P12: =IFERROR($J12/M12-1,"N/A") -> -0.024429281
B13: Japan Industrial Partners, Inc. | C13: Nippon Avionics Co. Ltd. | D13: 43677 | E13: 51.7 | F13: 159.74 | G13: 4.96 | H13: =IFERROR(IF(OR(+$E13/F13<0,+$E13/F13>=100),"NM",+$E13/F13),"N/A") -> 0.32365093 | I13: =IFERROR(IF(OR(+$E13/G13<0,+$E13/G13>=100),"NM",+$E13/G13),"N/A") -> 10.423387 | J13: 10.06 | K13: 11.26 | L13: 11.73 | M13: 11.11 | N13: =IFERROR($J13/K13-1,"N/A") -> -0.10657194 | O13: =IFERROR($J13/L13-1,"N/A") -> -0.14236999 | P13: =IFERROR($J13/M13-1,"N/A") -> -0.094509451
B18: Maximum | E18: =MAX(E11:E16) -> 1872.19 | F18: =MAX(F11:F16) -> 552.46 | G18: =MAX(G11:G16) -> 36 | H18: =MAX(H11:H16) -> 3.3888245 | I18: =MAX(I11:I16) -> 52.005278 | N18: =MAX(N11:N16) -> 0.51555685 | O18: =MAX(O11:O16) -> 0.42951179 | P18: =MAX(P11:P16) -> 0.35271217
B19: 75th Percentile | E19: =QUARTILE(E11:E16,3) -> 1092.805 | F19: =QUARTILE(F11:F16,3) -> 356.1 | G19: =QUARTILE(G11:G16,3) -> 30.53 | H19: =QUARTILE(H11:H16,3) -> 2.8530814 | I19: =QUARTILE(I11:I16,3) -> 32.256031 | N19: =QUARTILE(N11:N16,3) -> 0.20449246 | O19: =QUARTILE(O11:O16,3) -> 0.18853269 | P19: =QUARTILE(P11:P16,3) -> 0.16414145
B20: Median | E20: =MEDIAN(E11:E16) -> 313.42 | F20: =MEDIAN(F11:F16) -> 159.74 | G20: =MEDIAN(G11:G16) -> 25.06 | H20: =MEDIAN(H11:H16) -> 2.3173383 | I20: =MEDIAN(I11:I16) -> 12.506784 | N20: =MEDIAN(N11:N16) -> -0.10657194 | O20: =MEDIAN(O11:O16) -> -0.052446408 | P20: =MEDIAN(P11:P16) -> -0.024429281
B21: 25th Percentile | E21: =QUARTILE(E11:E16,1) -> 182.56 | F21: =QUARTILE(F11:F16,1) -> 147.495 | G21: =QUARTILE(G11:G16,1) -> 15.01 | H21: =QUARTILE(H11:H16,1) -> 1.3204946 | I21: =QUARTILE(I11:I16,1) -> 11.465085 | N21: =QUARTILE(N11:N16,1) -> -0.11510965 | O21: =QUARTILE(O11:O16,1) -> -0.0974082 | P21: =QUARTILE(P11:P16,1) -> -0.059469366
B22: Minimum | E22: =MIN(E11:E16) -> 51.7 | F22: =MIN(F11:F16) -> 135.25 | G22: =MIN(G11:G16) -> 4.96 | H22: =MIN(H11:H16) -> 0.32365093 | I22: =MIN(I11:I16) -> 10.423387 | N22: =MIN(N11:N16) -> -0.12364737 | O22: =MIN(O11:O16) -> -0.14236999 | P22: =MIN(P11:P16) -> -0.094509451

Sheet PPT
B2: Valuation Statistics: | F2: Capitalization | H2: Enterprise Value / | K2: Enterprise Value /
F3: Equity | G3: Enterprise | H3: Revenue | K3: EBITDA | N3: P / E Multiple
B4: Company Name | C4: Ticker | D4: Share Price | F4: Value | G4: Value | H4: LTM | I4: 46022 | J4: 46387 | K4: LTM | L4: 46022 | M4: 46387 | N4: LTM | O4: 46022 | P4: 46387
B5: Hesai Group | C5: HSAI | D5: 25.13 | F5: 4020.8 | G5: 3081.9 | H5: 8.0049351 | I5: 6.925618 | J5: 4.8457547 | K5: 19.322257 | L5: 16.480749 | M5: 11.853462 | N5: 66.569536 | O5: 70.540351 | P5: 44.675556
B6: Innoviz Technologies, Ltd. | C6: INVZ | D6: 1.04 | F6: 216.88368 | G6: 177.48368 | H6: 3.6638388 | I6: 3.0600634 | J6: 2.1383576 | K6: 15.597476 | L6: 13.652591 | M6: 12.677406 | N6: NM | O6: NM | P6: NM
B7: Aeva Technologies, Inc. | C7: AEVA | D7: 14.34 | F7: 916.92828 | G7: 874.25228 | H7: 57.691189 | I7: 51.426605 | J7: 31.223296 | K7: NM | L7: NM | M7: N/A | N7: NM | O7: NM | P7: NM
B8: Luminar Technologies, Inc. | C8: LAZR | D8: 0.08 | F8: 11.193109 | G8: 453.89311 | H8: 5.9904066 | I8: N/A | J8: N/A | K8: NM | L8: N/A | M8: N/A | N8: NM | O8: N/A | P8: N/A
B9: MicroVision, Inc. | C9: MVIS | D9: 0.85 | F9: 276.4201 | G9: 223.4201 | H9: 84.757248 | I9: 74.473368 | J9: 14.894674 | K9: NM | L9: NM | M9: 66.19855 | N9: NM | O9: NM | P9: NM
B10: Aeye, Inc. | C10: LIDR | D10: 1.85 | F10: 83.35175 | G10: -0.15725 | H10: NM | I10: N/A | J10: 37.236684 | K10: NM | L10: 7.4473368 | M10: NM | N10: NM | O10: NM | P10: NM
B12: Maximum | F12: 4020.8 | G12: 3081.9 | H12: 84.757248 | I12: 74.473368 | J12: 37.236684 | K12: 19.322257 | L12: 16.480749 | M12: 66.19855 | N12: 66.569536 | O12: 70.540351 | P12: 44.675556
B13: 75th Percentile | F13: 756.80124 | G13: 769.16249 | H13: 57.691189 | I13: 57.188296 | J13: 31.223296 | K13: 18.391062 | L13: 15.06667 | M13: 39.437978 | N13: 66.569536 | O13: 70.540351 | P13: 44.675556
B14: Median | F14: 246.65189 | G14: 338.65661 | H14: 8.0049351 | I14: 29.176111 | J14: 14.894674 | K14: 17.459867 | L14: 13.652591 | M14: 12.677406 | N14: 66.569536 | O14: 70.540351 | P14: 44.675556
B15: 25th Percentile | F15: 116.73473 | G15: 188.96779 | H15: 5.9904066 | I15: 5.9592293 | J15: 4.8457547 | K15: 16.528671 | L15: 10.549964 | M15: 12.265434 | N15: 66.569536 | O15: 70.540351 | P15: 44.675556
B16: Minimum | F16: 11.193109 | G16: -0.15725 | H16: 3.6638388 | I16: 3.0600634 | J16: 2.1383576 | K16: 15.597476 | L16: 7.4473368 | M16: 11.853462 | N16: 66.569536 | O16: 70.540351 | P16: 44.675556
B18: Ouster, Inc. | C18: OUST | F18: 1119.2969 | G18: 1040.6458 | H18: 9.3666644 | I18: 6.4597685 | J18: 4.5995145 | K18: 25.72036 | L18: 16.149421 | M18: 11.498786 | N18: NM | O18: NM | P18: NM
D25: DCF - Implied Share Prices
E26: Multiples Method | F26: Perpetuity Growth Method
D27: Upside | E27: 62.723988 | F27: 63.198664
E28: 1.978347 | F28: 2.0008862
D29: Base | E29: 35.951374 | F29: 34.18386
E30: 0.70709279 | F30: 0.62316525
D31: Downside | E31: 17.583537 | F31: 16.134863
E32: -0.1650742 | F32: -0.23386217
D33: Median | F33: =MEDIAN(E27:F27,E29:F29,E31:F31) -> 35.067617
I37: Historical | O37: Projected:
C38: Ouster, Inc. - Net Operating Loss | F38: Units: | G38: 44561 | H38: 44926 | I38: 45291 | J38: 45657 | K38: 46022 | L38: 46387 | M38: 46752 | N38: 47118 | O38: 47483 | P38: 47848
D40: Beginning NOLs Balance | F40: $T | G40: 0 | H40: 461681 | I40: 595299 | J40: 667823 | K40: 701611 | L40: 786932.61 | M40: 840254.65 | N40: 864318.74 | O40: 837911.9 | P40: 762956.31
D41: (+) NOLs Created | F41: $T | G41: 461681 | H41: 133618 | I41: 72524 | J41: 33788 | K41: 85321.612 | L41: 53322.043 | M41: 24064.087 | N41: 0 | O41: 0 | P41: 0
D42: (-) NOLs Used | F42: $T | G42: 0 | H42: 0 | I42: 0 | J42: 0 | K42: 0 | L42: 0 | M42: 0 | N42: -26406.839 | O42: -74955.593 | P42: -131312.95
D43: Ending Balance | F43: $T | G43: 461681 | H43: 595299 | I43: 667823 | J43: 701611 | K43: 786932.61 | L43: 840254.65 | M43: 864318.74 | N43: 837911.9 | O43: 762956.31 | P43: 631643.36
D45: Taxable Income After NOL | F45: $T | G45: - | H45: - | I45: - | J45: -33788 | K45: -1262.5 | L45: -1319.375 | M45: -1376.9688 | N45: 24958.378 | O45: 73603.767 | P45: 129938.79
D46: Cash Taxes Payable | F46: $T | G46: - | H46: - | I46: - | J46: - | K46: 0 | L46: 0 | M46: 0 | N46: 5241.2594 | O46: 15456.791 | P46: 27287.147
D47: NOL Utilization Limit (% of EBT) | F47: % | G47: 0.8 | H47: 0.8 | I47: 0.8 | J47: 0.8 | K47: 0.8 | L47: 0.8 | M47: 0.8 | N47: 0.8 | O47: 0.8 | P47: 0.8
D53: Key Stats
D54: Initiation Date | F54: 46076
D55: Initiation Price | F55: 21.06
D56: Price | F56: 22.86
D57: Price Target | F57: 35.07
D58: 52 Week High - Low | F58: $6.34 - $41.65
D59: Shares Outstanding - Mil | F59: =Diluted -> 52.56
D60: Market Cap - Mil | F60: 1120
D61: Book Value / Share | F61: 4.18
D62: Cash per Share | F62: =191000/(Diluted*1000) -> 3.6339422
D63: Dividend | F63: N/A
