Workbook
Name COGS: rNPV!$D$45
Name Company_Name: Model!$F$5
Name Cost_of_Debt: WACC!$F$8
Name Cost_of_Preferred: WACC!$F$9
Name Diluted: Model!$F$8
Name Discount_Rate: rNPV!$G$19
Name Equity_Risk_Premium: WACC!$F$7
Name Forward_Year_1: Model!$L$12
Name Forward_Year_2: Model!$L$13
Name Forward_Year_3: Model!$L$14
Name Hist_Year: Model!$L$5
Name Legal: rNPV!$D$9
Name LTM: Model!$L$11
Name OpEx: rNPV!$D$5
Name Pub_Comps_Params: Pubcomps_Data!$C$3:$C$102
Name Pub_Comps_Range: Pubcomps_Data!$C$3:$AL$102
Name Pub_Comps_Tickers: Pubcomps_Data!$C$3:$AL$3
Name Risk_Free_Rate: WACC!$F$6
Name RoyaltyJ: rNPV!#REF!
Name Royaltyxw: rNPV!#REF!
Name Scenario: rNPV!$D$6
Name Share_Price: Model!$F$7
Name Tax_Rate: Model!$F$10
Name Terminal_Growth_Rate: rNPV!$Q$14
Name Ticker: Model!$F$6
Name Units: Model!$F$13
Name Vali: rNPV!$D$8
Name Valuation_Date: Model!$L$8

Sheet Cover
B2: =Company_Name&" - Operating Model and Valuation - Cover Page and Navigation" -> Ultragenyx Pharmaceutical Inc. - Operating Model and Valuation - Cover Page and Navigation
C12: Company Name: | D12: =Company_Name -> Ultragenyx Pharmaceutical Inc.
C13: Model Name: | D13: Operating Model and Valuation (5-Year Forecast)
C14: Author: | D14: Glenn Rentrop
C16: File Name: | D16: =MID(CELL("filename"),SEARCH("[",CELL("filename"))+1, SEARCH("]",CELL("filename"))-SEARCH("[",CELL("filename"))-1) -> IOVAMODEL.xlsx
C17: Analysis Date: | D17: =Valuation_Date -> 45677
C19: Navigation, Summary, or Graph Worksheet:
C20: Financial Model Worksheet:
C21: Data and Back-End Calculation Worksheet:
B23: # | C23: Sheet Name | D23: Link to Sheet
B24: =_xlfn.SHEET(INDIRECT(D24&"!A1")) -> 2 | C24: Model and Valuation Summary | D24: Summary
B25: =_xlfn.SHEET(INDIRECT(D25&"!A1")) -> 3 | C25: Graphs and Dashboard | D25: Graphs
B26: =_xlfn.SHEET(INDIRECT(D26&"!A1")) -> 4 | C26: Operating Scenarios and 3-Statement Model | D26: Model
B27: =_xlfn.SHEET(INDIRECT(D27&"!A1")) -> 5 | C27: Revenue Drivers, Scenario Analysis, Capex, D&A | D27: Drivers
B28: =_xlfn.SHEET(INDIRECT(D28&"!A1")) -> 6 | C28: Stub Period Results from Q1 | D28: Q3
B29: =_xlfn.SHEET(INDIRECT(D29&"!A1")) -> 7 | C29: DCF valuation, rNPV's by asset | D29: rNPV
B30: =_xlfn.SHEET(INDIRECT(D30&"!A1")) -> 8 | C30: Weighted Average Cost of Capital (WACC) Calculations | D30: WACC
B31: =_xlfn.SHEET(INDIRECT(D31&"!A1")) -> 9 | C31: Valuation Summary - Back-End Calculations | D31: ValSum
B32: =_xlfn.SHEET(INDIRECT(D32&"!A1")) -> #REF! | C32: Valuation "Football Field" Chart | D32: ValGraph
B33: =_xlfn.SHEET(INDIRECT(D33&"!A1")) -> 10 | C33: Comparable Public Companies - Output | D33: PubComps
B34: =_xlfn.SHEET(INDIRECT(D34&"!A1")) -> 11 | C34: Comparable Public Companies - Data and Calculations | D34: PubComps_Data

Sheet Summary
C3: =Company_Name&" - Summary of Operating Model and Valuation - "&Scenario&" Case" -> Ultragenyx Pharmaceutical Inc. - Summary of Operating Model and Valuation - Base Case
C4: ($ in Thousands Except Per Share and Per Unit Data)
H6: Historical | N6: Projected
C7: Summary of Operational Performance: | E7: Units: | G7: 44561 | H7: =EOMONTH(G7,12) -> 44926 | I7: =EOMONTH(H7,12) -> 45291 | J7: =EOMONTH(I7,12) -> 45657 | K7: =EOMONTH(J7,12) -> 46022 | L7: =EOMONTH(K7,12) -> 46387 | M7: =EOMONTH(L7,12) -> 46752 | N7: =EOMONTH(M7,12) -> 47118 | O7: =EOMONTH(N7,12) -> 47483 | P7: =EOMONTH(O7,12) -> 47848 | R7: CAGR:
C8: Segment-Level Statistics:
C10: Product Revenue | E10: $T | G10: =Model!G59 -> 77017 | H10: =Model!H59 -> 118927 | I10: =Model!I59 -> 180413 | J10: =Model!J59 -> 285415 | K10: =Model!K59 -> 375393.05 | L10: =Model!L59 -> 585021.11 | M10: =Model!M59 -> 864635.16 | N10: =Model!N59 -> 1245100.3 | ... P10: =Model!P59 -> 2089814.3 | R10: =(P10/G10)^(1/YEARFRAC(G$7,P$7,))-1 -> 0.44304583
E11: % | H11: =H10/G10-1 -> 0.54416557 | I11: =I10/H10-1 -> 0.51700623 | J11: =J10/I10-1 -> 0.58200906 | K11: =K10/J10-1 -> 0.3152534 | L11: =L10/K10-1 -> 0.55842287 | M11: =M10/L10-1 -> 0.47795548 | N11: =N10/M10-1 -> 0.44002963 | O11: =O10/N10-1 -> 0.32716972 | P11: =P10/O10-1 -> 0.26466914
C13: Royalty revenue | E13: $T | G13: =Model!G60 -> 0 | H13: =Model!H60 -> 21692 | I13: =Model!I60 -> 182652 | J13: =Model!J60 -> 274815 | K13: =Model!K60 -> 296122.5 | L13: =Model!L60 -> 316851.07 | M13: =Model!M60 -> 335862.14 | N13: =Model!N60 -> 352655.24 | ... P13: =Model!P60 -> 388802.41 | R13: =(P13/H13)^(1/YEARFRAC(H$7,P$7,))-1 -> 0.43442772
E14: % | I14: =I13/H13-1 -> 7.4202471 | J14: =J13/I13-1 -> 0.50458248 | K14: =K13/J13-1 -> 0.077533967 | L14: =L13/K13-1 -> 0.07 | M14: =M13/L13-1 -> 0.06 | N14: =N13/M13-1 -> 0.05 | O14: =O13/N13-1 -> 0.05 | P14: =P13/O13-1 -> 0.05
C16: Non-cash collaboration royalty revenue | E16: $T | G16: =Model!G61 -> 189149 | H16: =Model!H61 -> 236716 | I16: =Model!I61 -> 69705 | J16: =Model!J61 -> 0 | K16: =Model!K61 -> 0 | L16: =Model!L61 -> 0 | M16: =Model!M61 -> 0 | N16: =Model!N61 -> 0 | ... P16: =Model!P61 -> 0
C18: Company-Wide:
C20: Revenue: | E20: $T | G20: =Model!G62 -> 266166 | H20: =Model!H62 -> 377335 | I20: =Model!I62 -> 432770 | J20: =Model!J62 -> 560230 | K20: =Model!K62 -> 673000 | L20: =Model!L62 -> 745000 | M20: =Model!M62 -> 1200497.3 | N20: =Model!N62 -> 1597755.5 | ... P20: =Model!P62 -> 2478616.7 | R20: =(P20/G20)^(1/YEARFRAC(G$7,P$7,))-1 -> 0.28136536
C21: Revenue Growth: | E21: % | H21: =H20/G20-1 -> 0.41766792 | I21: =I20/H20-1 -> 0.1469119 | J21: =J20/I20-1 -> 0.29452134 | K21: =K20/J20-1 -> 0.20129233 | L21: =L20/K20-1 -> 0.10698366 | M21: =M20/L20-1 -> 0.61140577 | N21: =N20/M20-1 -> 0.33091136 | O21: =O20/N20-1 -> 0.26599305 | P21: =P20/O20-1 -> 0.22537139
C23: Gross Profit: | E23: $T | G23: =Model!G62-Model!G64 -> 250158 | H23: =Model!H62-Model!H64 -> 349015 | I23: =Model!I62-Model!I64 -> 387561 | J23: =Model!J62-Model!J64 -> 483502 | K23: =Model!K62-Model!K64 -> 564000 | L23: =Model!L62-Model!L64 -> 655824.55 | M23: =Model!M62-Model!M64 -> 1056799.5 | N23: =Model!N62-Model!N64 -> 1453957.5 | ... P23: =Model!P62-Model!P64 -> 2255541.2 | R23: =(P23/G23)^(1/YEARFRAC(G$7,P$7,))-1 -> 0.2767773
C24: Profit Margin: | E24: % | H24: =G23/H20 -> 0.66295997 | I24: =H23/I20 -> 0.80646764 | J24: =I23/J20 -> 0.69178909 | K24: =J23/K20 -> 0.71842793 | L24: =K23/L20 -> 0.75704698 | M24: =L23/M20 -> 0.54629406 | N24: =M23/N20 -> 0.66142752 | O24: =N23/O20 -> 0.71880331 | P24: =O23/P20 -> 0.74263199
C26: =[1]Model!C84 -> Total operating expenses | E26: $T | G26: =-Model!G67 -> 733143 | H26: =-Model!H67 -> 1012248 | I26: =-Model!I67 -> 1003457 | J26: =-Model!J67 -> 1096203 | K26: =-Model!K67 -> 1208000 | L26: =-Model!L67 -> 1133225.5 | M26: =-Model!M67 -> 900447.84 | N26: =-Model!N67 -> 707682.99 | ... P26: =-Model!P67 -> 831075.51 | R26: =(P26/G26)^(1/YEARFRAC(G$7,P$7,))-1 -> 0.014028588
C28: EBIT | G28: =Model!G69 -> -466977 | H28: =Model!H69 -> -634913 | I28: =Model!I69 -> -570687 | J28: =Model!J69 -> -535973 | K28: =Model!K69 -> -535000 | L28: =Model!L69 -> -388225.45 | M28: =Model!M69 -> 300049.46 | N28: =Model!N69 -> 890072.5 | ... P28: =Model!P69 -> 1647541.2 | R28: =(P28/G28)^(1/YEARFRAC(G$7,P$7,))-1 -> -2.1503708
C29: Ebit Margin: | H29: =H28/H20 -> -1.6826242 | I29: =I28/I20 -> -1.3186843 | J29: =J28/J20 -> -0.95670171 | K29: =K28/K20 -> -0.79494799 | L29: =L28/L20 -> -0.52110799 | M29: =M28/M20 -> 0.24993764 | N29: =N28/N20 -> 0.55707679 | O29: =O28/O20 -> 0.55404848
C31: Comprehensive Income: | E31: $T | G31: =Model!G78 -> -538221 | H31: =Model!H78 -> -687719 | I31: =Model!I78 -> -609943 | J31: =Model!J78 -> -567586 | K31: =Model!K78 -> -586936.59 | L31: =Model!L78 -> -451266.6 | M31: =Model!M78 -> 221576.01 | N31: =Model!N78 -> 822459.44 | ... P31: =Model!P78 -> 1651310.3 | R31: =(P31/G31)^(1/YEARFRAC(G$7,P$7,))-1 -> -2.1326519
C32: Basic Earnings per Share (EPS): | E32: $ as Stated | G32: =Model!G85 -> -6.7 | H32: =Model!H85 -> -10.12 | I32: =Model!I85 -> -8.25 | J32: =Model!J85 -> -6.29 | K32: =Model!K85 -> -5.2093264 | L32: =Model!L85 -> -3.7395413 | M32: =Model!M85 -> 3.2817712 | N32: =Model!N85 -> 9.2989039 | ... P32: =Model!P85 -> 17.016768
C34: Capital expenditures: | E34: $T | G34: =Model!G172 -> -73093 | H34: =Model!H172 -> -116123 | I34: =Model!I172 -> -44267 | J34: =Model!J172 -> -7491 | K34: =Model!K172 -> -6980 | L34: =Model!L172 -> -6631 | M34: =Model!M172 -> -3150 | N34: =Model!N172 -> -2900 | ... P34: =Model!P172 -> -3040 | R34: =(P34/G34)^(1/YEARFRAC(G$7,P$7,))-1 -> -0.29764721
C35: % Revenue: | E35: %
C37: Cash Flow From Operations: | E37: $T | G37: =Model!G168 -> -423935 | H37: =Model!H168 -> -366459 | I37: =Model!I168 -> -476285 | J37: =Model!J168 -> -414188 | K37: =Model!K168 -> -18419.914 | L37: =Model!L168 -> -352456.35 | M37: =Model!M168 -> 140716.03 | N37: =Model!N168 -> 737315.01 | ... P37: =Model!P168 -> 1501170.5
C38: Cash Flow From Investing: | E38: $T | G38: =Model!G179 -> -195372 | H38: =Model!H179 -> -291652 | I38: =Model!I179 -> 168000 | J38: =Model!J179 -> -17768 | K38: =Model!K179 -> -93799.998 | L38: =Model!L179 -> 6414.5169 | M38: =Model!M179 -> 68561.755 | N38: =Model!N179 -> -3289.6174 | ... P38: =Model!P179 -> 22101.977
C39: Cash Flows From Financing Activities: | E39: $T | G39: =Model!G192 -> 118552 | H39: =Model!H192 -> 501208 | I39: =Model!I192 -> 388142 | J39: =Model!J192 -> 399241 | K39: =Model!K192 -> 0 | L39: =Model!L192 -> 0 | M39: =Model!M192 -> 0 | N39: =Model!N192 -> 0 | ... P39: =Model!P192 -> 0
C41: Total Assets: | E41: $T | G41: =Model!G106 -> 1522397 | H41: =Model!H106 -> 1545444 | I41: =Model!I106 -> 1491013 | J41: =Model!J106 -> 1503456 | K41: =Model!K106 -> 1504434.2 | L41: =Model!L106 -> 1162273.4 | M41: =Model!M106 -> 1422569.4 | N41: =Model!N106 -> 2235992.1 | ... P41: =Model!P106 -> 4940679.9
C42: Cash and Cash Equivalents: | E42: $T | G42: =Model!G92 -> 307584 | H42: =Model!H92 -> 132944 | I42: =Model!I92 -> 213584 | J42: =Model!J92 -> 173729 | K42: =Model!K92 -> 60426.088 | L42: =Model!L92 -> -286670.99 | M42: =Model!M92 -> -78443.516 | N42: =Model!N92 -> 654153.48 | ... P42: =Model!P92 -> 3246576.5
C44: EBITDA: | E44: $T | G44: =Model!G83 -> -453738 | H44: =Model!H83 -> -616693 | I44: =Model!I83 -> -544681 | J44: =Model!J83 -> -500430 | K44: =Model!K83 -> -508221.88 | L44: =Model!L83 -> -364829.64 | M44: =Model!M83 -> 320169.6 | N44: =Model!N83 -> 907201.07 | ... P44: =Model!P83 -> 1660155.9 | R44: =(P44/G44)^(1/YEARFRAC(G$7,P$7,))-1 -> -2.1550313
C45: EBITDA Margin: | E45: % | H45: =H44/H20 -> -1.6343382 | I45: =I44/I20 -> -1.2585923 | J45: =J44/J20 -> -0.89325813 | K45: =K44/K20 -> -0.75515881 | L45: =L44/L20 -> -0.48970422 | M45: =M44/M20 -> 0.26669748 | N45: =N44/N20 -> 0.56779718 | O45: =O44/O20 -> 0.56130445 | P45: =P44/P20 -> 0.66979129
H47: LTM | J47: Projected:
C48: Summary of Valuation Multiples: | E48: Units: | I48: =K7 -> 46022 | J48: =L7 -> 46387
C49: EV / Revenue - Comparables: | E49: x | H49: {=PubComps!N36:P36} -> 3.4784195 | I49: 5.4271576 | J49: 3.268504
C50: ="EV / Revenue - "&Company_Name&":" -> EV / Revenue - Ultragenyx Pharmaceutical Inc.: | E50: x | H50: {=PubComps!N40:P40} -> 3.9865889 | I50: 3.3185835 | J50: 2.9978613
C51: Projected Revenue Growth - Comparables: | E51: % | J51: =PubComps!W17 -> 0.15154256
C52: ="Projected Revenue Growth - "&Company_Name&":" -> Projected Revenue Growth - Ultragenyx Pharmaceutical Inc.: | E52: % | J52: =PubComps!W21 -> 0.064013841
C54: EV / EBITDA - Comparables: | E54: x | H54: {=PubComps!Q36:S36} -> 10.759602 | I54: 15.526997 | J54: 13.125439
C55: ="EV / EBITDA - "&Company_Name&":" -> EV / EBITDA - Ultragenyx Pharmaceutical Inc.: | E55: x | H55: {=PubComps!Q40:S40} -> NM | I55: NM | J55: NM
C56: Projected EBITDA Growth - Comparables: | E56: % | J56: =PubComps!X17 -> 0.835457
C57: ="Projected EBITDA Growth - "&Company_Name&":" -> Projected EBITDA Growth - Ultragenyx Pharmaceutical Inc.: | E57: % | J57: =PubComps!X21 -> 0.2139738
C59: P / E - Comparables: | E59: x | H59: {=PubComps!T36:V36} -> 13.07005 | I59: 18.145034 | J59: 14.770238
C60: ="P / E - "&Company_Name&":" -> P / E - Ultragenyx Pharmaceutical Inc.: | E60: x | H60: {=PubComps!T40:V40} -> NM | I60: NM | J60: NM

Sheet Graphs
K3: ="Revenue by Segment" -> Revenue by Segment
K17: ="Revenue vs. OpEx" -> Revenue vs. OpEx
J33: ="OpEx breakout" -> OpEx breakout
J42: =Company_Name&" - Price Volume Graph" -> Ultragenyx Pharmaceutical Inc. - Price Volume Graph
K46: Date | L46: Close | M46: Volume
K47: 46042 | L47: 22.63 | M47: 2275800
K48: 46038 | L48: 22.49 | M48: 1900600
K49: 46037 | L49: 23.5 | M49: 1760800
K50: 46036 | L50: 24.07 | M50: 2264700
K51: 46035 | L51: 24.11 | M51: 3545100
K52: 46034 | L52: 24.37 | M52: 4596500
K53: 46031 | L53: 22.51 | M53: 2764700
K54: 46030 | L54: 23.21 | M54: 2681800
K55: 46029 | L55: 24.2 | M55: 4460400
K56: 46028 | L56: 22.54 | M56: 3744400
K57: 46027 | L57: 23.11 | M57: 3956400
K58: 46024 | L58: 23.6 | M58: 3639700
... K297: 45678 | L297: 41.28 | M297: 1164800

Sheet Model
I2: Historical | O2: Projected:
B3: =Company_Name -> Ultragenyx Pharmaceutical Inc. | E3: Units: | G3: 44561 | H3: =EOMONTH(G3,12) -> 44926 | I3: =EOMONTH(H3,12) -> 45291 | J3: =EOMONTH(I3,12) -> 45657 | K3: =EOMONTH(J3,12) -> 46022 | L3: =EOMONTH(K3,12) -> 46387 | M3: =EOMONTH(L3,12) -> 46752 | N3: =EOMONTH(M3,12) -> 47118 | O3: =EOMONTH(N3,12) -> 47483 | P3: =EOMONTH(O3,12) -> 47848
C5: Company Name: | E5: Name | F5: Ultragenyx Pharmaceutical Inc. | H5: Last Fiscal Year: | L5: 45657
C6: Ticker: | E6: Name | F6: RARE | H6: Next Fiscal Year: | L6: =EOMONTH(L5,12) -> 46022
C7: Current Share Price: | E7: $ / Share | F7: 23.66 | H7: Most Recent Quarter End Date: | L7: 45608
C8: Diluted Shares Outstanding: | E8: M Shares | F8: 97.56 | H8: Valuation Date: | L8: 45677
C10: Effective Tax Rate: | E10: % | F10: 0.21
C11: Discount Rate (WACC): | E11: % | F11: =Discount_Rate -> 0.1 | H11: LTM Period: | L11: 45565
H12: Forward Year 1: | L12: =EOMONTH(L5,12) -> 46022
C13: Conversion Units: | E13: # | F13: 1000 | H13: Forward Year 2: | L13: =EOMONTH(L12,12) -> 46387
H14: Forward Year 3: | L14: =EOMONTH(L13,12) -> 46752
I16: Historical | O16: Projected:
B17: =Company_Name&" - Model Drivers and Assumptions" -> Ultragenyx Pharmaceutical Inc. - Model Drivers and Assumptions | E17: Units: | G17: =G3 -> 44561 | H17: =EOMONTH(G17,12) -> 44926 | I17: =EOMONTH(H17,12) -> 45291 | J17: =EOMONTH(I17,12) -> 45657 | K17: =EOMONTH(J17,12) -> 46022 | L17: =EOMONTH(K17,12) -> 46387 | M17: =EOMONTH(L17,12) -> 46752 | N17: =EOMONTH(M17,12) -> 47118 | O17: =EOMONTH(N17,12) -> 47483 | P17: =EOMONTH(O17,12) -> 47848
C18: Income Statement
C20: Cost of sales % Revenue | E20: % | G20: =G64/G62 -> 0.060142918 | H20: =H64/H62 -> 0.075052672 | I20: =I64/I62 -> 0.10446427 | J20: =J64/J62 -> 0.13695804 | K20: =AVERAGE(G20:J20) -> 0.094154473
C21: Selling, general and administrative % Revenue | E21: % | G21: =G65/G62 -> 0.82648422 | H21: =H65/H62 -> 0.73711424 | I21: =I65/I62 -> 0.71585138 | J21: =J65/J62 -> 0.57406779 | K21: =AVERAGE(G21:J21) -> 0.71337941
C23: Interest income % cash | E23: % | H23: =H71/G92 -> 0.036003173 | I23: =I71/H92 -> 0.20074618 | J23: =J71/I92 -> 0.17092104 | K23: 0.04 | L23: 0.04 | M23: 0.04 | N23: 0.04 | O23: 0.04 | P23: 0.04
C25: Beginning Balance | E25: $T | G25: 0 | H25: =G29 -> 1862400 | I25: =H29 -> 1466600 | J25: =I29 -> 1664700 | K25: =J29 -> 1934900 | L25: =K29 -> 2521836.6 | M25: =L29 -> 2973103.2 | N25: =M29 -> 2795842.4 | O25: =N29 -> 2137874.8 | P25: =O29 -> 1271592.3
C26: (+) NOLs Created | E26: $T | G26: 0 | H26: 0 | I26: 198100 | J26: 270200 | K26: =IF(K78<0,-K78,0) -> 586936.59 | L26: =IF(L78<0,-L78,0) -> 451266.6 | M26: =IF(M78<0,-M78,0) -> 0 | N26: =IF(N78<0,-N78,0) -> 0 | O26: =IF(O78<0,-O78,0) -> 0 | P26: =IF(P78<0,-P78,0) -> 0
C27: (-) NOLs Used | E27: $T | G27: 0 | H27: -395800 | I27: 0 | J27: 0 | K27: =-MIN(+K25+K26,MAX(K78*K33,0)) -> 0 | L27: =-MIN(+L25+L26,MAX(L78*L33,0)) -> 0 | M27: =-MIN(+M25+M26,MAX(M78*M33,0)) -> -177260.81 | N27: =-MIN(+N25+N26,MAX(N78*N33,0)) -> -657967.55 | O27: =-MIN(+O25+O26,MAX(O78*O33,0)) -> -866282.49 | P27: =-MIN(+P25+P26,MAX(P78*P33,0)) -> -1271592.3
C28: Other NOL Adjustments | E28: $T | G28: 0 | H28: 0 | I28: 0 | J28: 0 | K28: 0 | L28: 0 | M28: 0 | N28: 0 | O28: 0 | P28: 0
C29: Ending Balance | E29: $T | G29: 1862400 | H29: =SUM(H25:H28) -> 1466600 | I29: =SUM(I25:I28) -> 1664700 | J29: =SUM(J25:J28) -> 1934900 | K29: =SUM(K25:K28) -> 2521836.6 | L29: =SUM(L25:L28) -> 2973103.2 | M29: =SUM(M25:M28) -> 2795842.4 | N29: =SUM(N25:N28) -> 2137874.8 | O29: =SUM(O25:O28) -> 1271592.3 | P29: =SUM(P25:P28) -> 0
C31: Taxable Income After NOL | E31: $T | G31: 0 | H31: 0 | I31: 0 | J31: 0 | K31: =IF(K27<0,SUM(K27,K78),0) -> 0 | L31: =IF(L27<0,SUM(L27,L78),0) -> 0 | M31: =IF(M27<0,SUM(M27,M78),0) -> 44315.202 | N31: =IF(N27<0,SUM(N27,N78),0) -> 164491.89 | O31: =IF(O27<0,SUM(O27,O78),0) -> 216570.62 | P31: =IF(P27<0,SUM(P27,P78),0) -> 379717.96
C32: Cash Taxes Payable | E32: $T | G32: 0 | H32: 0 | I32: 0 | J32: 0 | K32: =K31*Tax_Rate -> 0 | L32: =L31*Tax_Rate -> 0 | M32: =M31*Tax_Rate -> 9306.1925 | N32: =N31*Tax_Rate -> 34543.296 | O32: =O31*Tax_Rate -> 45479.831 | P32: =P31*Tax_Rate -> 79740.771
C33: NOL Utilization Limit (% of EBT) | E33: $T | G33: 0.8 | H33: 0.8 | I33: 0.8 | J33: 0.8 | K33: 0.8 | L33: 0.8 | M33: 0.8 | N33: 0.8 | O33: 0.8 | P33: 0.8
C35: Balance Sheet
C37: Days Recievables Outstanding | E37: Days | G37: =G94*(G57-EOMONTH(G57,-12))/G62 -> 38.989503 | H37: =H94*(H57-EOMONTH(H57,-12))/H62 -> 39.122862 | I37: =I94*(I57-EOMONTH(I57,-12))/I62 -> 61.897428 | J37: =J94*(J57-EOMONTH(J57,-12))/J62 -> 79.572972 | K37: 90 | L37: 100 | M37: 90 | N37: 80 | O37: 70 | P37: 65
C38: Days Inventory Outstanding | E38: Days | G38: =G95*(G57-EOMONTH(G57,-12))/G62 -> 22.257971 | H38: =H95*(H57-EOMONTH(H57,-12))/H62 -> 25.891025 | I38: =I95*(I57-EOMONTH(I57,-12))/I62 -> 28.649594 | J38: =J95*(J57-EOMONTH(J57,-12))/J62 -> 29.403213 | K38: =AVERAGE(G38:J38) -> 26.550451 | L38: =K38+2 -> 28.550451 | M38: =L38+2 -> 30.550451 | N38: =M38+2 -> 32.550451 | O38: =N38+2 -> 34.550451 | P38: =O38+2 -> 36.550451
C39: Prepaid expenses and other current assets % Revenue | E39: % | G39: =G96/G62 -> 0.26954983 | H39: =H96/H62 -> 0.18266527 | I39: =I96/I62 -> 0.11002611 | J39: =J96/J62 -> 0.071916891 | K39: 0.06 | L39: 0.05 | M39: 0.03 | N39: 0.02 | O39: 0.01 | P39: 0.01
C41: Marketable debt securities (non-current) % current | E41: % | G41: =G101/G93 -> 0.59853402 | H41: =H101/H93 -> 0.24229935 | I41: =I101/I93 -> 0.54974493 | J41: =J101/J93 -> 0.30943213 | K41: =AVERAGE(G41:J41) -> 0.42500261 | L41: =K41-5% -> 0.37500261 | M41: =L41-5% -> 0.32500261 | N41: =M41-5% -> 0.27500261 | O41: =N41-5% -> 0.22500261 | P41: =O41-5% -> 0.17500261
C42: Other assets % Revenue | E42: % | G42: =G105/G62 -> 0.077237513 | H42: =H105/H62 -> 0.044644679 | I42: =I105/I62 -> 0.13329251 | J42: =J105/J62 -> 0.11188262 | K42: =AVERAGE(G42:J42) -> 0.091764331 | L42: 0.07 | M42: 0.05 | N42: 0.04 | O42: 0.03 | P42: 0.02
C44: Days Payables Outstanding | E44: Days | G44: =G110*(G57-EOMONTH(G57,-12))/G62 -> 23.501762 | H44: =H110*(H57-EOMONTH(H57,-12))/H62 -> 41.859382 | I44: =I110*(I57-EOMONTH(I57,-12))/I62 -> 35.519121 | J44: =J110*(J57-EOMONTH(J57,-12))/J62 -> 25.319415 | K44: =AVERAGE(G44:J44) -> 31.54992 | L44: 28 | M44: 26 | N44: 24 | O44: 22 | P44: 20
C45: Accrued liabilities % Opex | E45: % | G45: =-G111/G67 -> 0.19853562 | H45: =-H111/H67 -> 0.20220144 | I45: =-I111/I67 -> 0.19580909 | J45: =-J111/J67 -> 0.21982516 | K45: =AVERAGE(G45:J45) -> 0.20409283 | L45: =K45-3% -> 0.17409283 | M45: =L45-3% -> 0.14409283 | N45: =M45-2% -> 0.12409283 | O45: =N45-2% -> 0.10409283 | P45: =O45-2% -> 0.084092826
C47: Other liabilities (current) | E47: % | G47: =G115/G122 -> 0 | H47: =H115/H122 -> 0 | I47: =I115/I122 -> 0 | J47: =J115/J122 -> 0.25055614 | K47: 0.25055614 | L47: 0.25055614 | M47: 0.25055614 | N47: 0.25055614 | O47: 0.25055614 | P47: 0.25055614
C49: Lease liabilities (non-current) % PPE | E49: % | G49: =G119/G99 -> 0.21879403 | H49: =H119/H99 -> 0.076288088 | I49: =I119/I99 -> 0.10522222 | J49: =J119/J99 -> 0.11297 | K49: =AVERAGE(H49:J49) -> 0.098160104 | L49: =AVERAGE(I49:K49) -> 0.10545078 | M49: =AVERAGE(J49:L49) -> 0.10552696 | N49: =AVERAGE(K49:M49) -> 0.10304595 | O49: =AVERAGE(L49:N49) -> 0.10467456 | P49: =AVERAGE(M49:O49) -> 0.10441582
C50: Other liabilities (non-current) | E50: % | G50: =G122/G65 -> 0.0045685556 | H50: =H122/H65 -> 0.017329465 | I50: =I122/I65 -> 0.039396512 | J50: =J122/J65 -> 0.05311402 | K50: =AVERAGE(G50:J50) -> 0.028602138 | L50: 0.03 | M50: 0.02 | N50: 0.02 | O50: 0.01 | P50: 0.01
C52: Cash Flow Statement
C54: Stock-based compensation % R&D | E54: % | G54: =G149/G66 -> 0.21110604 | H54: =H149/H66 -> 0.18472518 | I54: =I149/I66 -> 0.20853914 | J54: =J149/J66 -> 0.22644781 | K54: =AVERAGE(G54:J54) -> 0.20770454 | L54: =K54-2% -> 0.18770454 | M54: =L54-2% -> 0.16770454 | N54: =M54-2% -> 0.14770454 | O54: =N54-2% -> 0.12770454 | P54: =O54-2% -> 0.10770454
I56: Historical | O56: Projected:
B57: ="Income Statement - "&Company_Name -> Income Statement - Ultragenyx Pharmaceutical Inc. | E57: Units: | G57: =G3 -> 44561 | H57: =EOMONTH(G57,12) -> 44926 | I57: =EOMONTH(H57,12) -> 45291 | J57: =EOMONTH(I57,12) -> 45657 | K57: =EOMONTH(J57,12) -> 46022 | L57: =EOMONTH(K57,12) -> 46387 | M57: =EOMONTH(L57,12) -> 46752 | N57: =EOMONTH(M57,12) -> 47118 | O57: =EOMONTH(N57,12) -> 47483 | P57: =EOMONTH(O57,12) -> 47848
C59: Product sales | E59: $T | G59: 77017 | H59: 118927 | I59: 180413 | J59: 285415 | K59: =Drivers!K6 -> 375393.05 | L59: =Drivers!L6 -> 585021.11 | M59: =Drivers!M6 -> 864635.16 | N59: =Drivers!N6 -> 1245100.3 | O59: =Drivers!O6 -> 1652459.4 | P59: =Drivers!P6 -> 2089814.3
C60: Royalty revenue | E60: $T | G60: 0 | H60: 21692 | I60: 182652 | J60: 274815 | K60: =Drivers!K7 -> 296122.5 | L60: =Drivers!L7 -> 316851.07 | M60: =Drivers!M7 -> 335862.14 | N60: =Drivers!N7 -> 352655.24 | O60: =Drivers!O7 -> 370288.01 | P60: =Drivers!P7 -> 388802.41
C61: Non-cash collaboration royalty revenue | E61: $T | G61: 189149 | H61: 236716 | I61: 69705 | J61: 0 | K61: =Drivers!K8 -> 0 | L61: =Drivers!L8 -> 0 | M61: =Drivers!M8 -> 0 | N61: =Drivers!N8 -> 0 | O61: =Drivers!O8 -> 0 | P61: =Drivers!P8 -> 0
C62: Total revenues | E62: $T | G62: =SUM(G59:G61) -> 266166 | H62: =SUM(H59:H61) -> 377335 | I62: =SUM(I59:I61) -> 432770 | J62: =SUM(J59:J61) -> 560230 | K62: 673000 | L62: 745000 | M62: =Drivers!M9 -> 1200497.3 | N62: =Drivers!N9 -> 1597755.5 | O62: =Drivers!O9 -> 2022747.4 | P62: =Drivers!P9 -> 2478616.7
C64: Cost of sales | E64: $T | G64: 16008 | H64: 28320 | I64: 45209 | J64: 76728 | K64: 109000 | L64: 89175.452 | M64: 143697.84 | N64: 143797.99 | O64: 182047.26 | P64: =P62*0.09 -> 223075.51
C65: Selling, general and administrative | E65: $T | G65: 219982 | H65: 278139 | I65: 309799 | J65: 321610 | K65: 349000 | L65: 331550 | M65: 315000 | N65: 290000 | O65: 320000 | P65: =Drivers!P14 -> 304000
C66: Research and development | E66: $T | G66: 497153 | H66: 705789 | I66: 648449 | J66: 697865 | K66: 750000 | L66: 712500 | M66: 441750 | N66: 273885 | O66: 400000 | P66: =-rNPV!Q50 -> 304000
C67: Total operating expenses | E67: $T | G67: =-SUM(G64:G66) -> -733143 | H67: =-SUM(H64:H66) -> -1012248 | I67: =-SUM(I64:I66) -> -1003457 | J67: =-SUM(J64:J66) -> -1096203 | K67: =-SUM(K64:K66) -> -1208000 | L67: =-SUM(L64:L66) -> -1133225.5 | M67: =-SUM(M64:M66) -> -900447.84 | N67: =-SUM(N64:N66) -> -707682.99 | ... P67: =-SUM(P64:P66) -> -831075.51
C69: Loss from operations | E69: $T | G69: =SUM(G62,G67) -> -466977 | H69: =SUM(H62,H67) -> -634913 | I69: =SUM(I62,I67) -> -570687 | J69: =SUM(J62,J67) -> -535973 | K69: =SUM(K62,K67) -> -535000 | L69: =SUM(L62,L67) -> -388225.45 | M69: =SUM(M62,M67) -> 300049.46 | N69: =SUM(N62,N67) -> 890072.5 | ... P69: =SUM(P62,P67) -> 1647541.2
C71: Interest income | E71: $T | G71: 1928 | H71: 11074 | I71: 26688 | J71: 36506 | K71: =J92*K23 -> 6949.16 | L71: =K92*L23 -> 2417.0435 | M71: =L92*M23 -> -11466.84 | N71: =M92*N23 -> -3137.7407 | O71: =N92*O23 -> 26166.139 | P71: =O92*P23 -> 68979.041
C72: Change in fair value of equity investments | E72: $T | G72: -42063 | H72: -19299 | I72: 397 | J72: -1115 | K72: 0 | L72: 0 | M72: 0 | N72: 0 | O72: 0 | P72: 0
C73: Non-cash interest expense on liabilities for sales of future royalties | E73: $T | G73: -29422 | H73: -43015 | I73: -66004 | J73: -63041 | K73: =-Drivers!K42 -> -56735.75 | L73: =-Drivers!L42 -> -62401.688 | M73: =-Drivers!M42 -> -64403.359 | N73: =-Drivers!N42 -> -61645.449 | O73: =-Drivers!O42 -> -61296.562 | P73: =-Drivers!P42 -> -62436.764
C74: Other income (expense) | E74: $T | G74: -1687 | H74: -1566 | I74: 0 | J74: 0 | K74: 0 | L74: 0 | M74: 0 | N74: 0 | O74: 0 | P74: 0
C75: Other expense | E75: $T | G75: 0 | H75: 0 | I75: -337 | J75: -3963 | K75: =AVERAGE(I75:J75) -> -2150 | L75: =AVERAGE(J75:K75) -> -3056.5 | M75: =AVERAGE(K75:L75) -> -2603.25 | N75: =AVERAGE(L75:M75) -> -2829.875 | O75: =AVERAGE(M75:N75) -> -2716.5625 | P75: =AVERAGE(N75:O75) -> -2773.2188
C76: Other income (expense) | E76: $T | G76: =SUM(G71:G75) -> -71244 | H76: =SUM(H71:H75) -> -52806 | I76: =SUM(I71:I75) -> -39256 | J76: =SUM(J71:J75) -> -31613 | K76: =SUM(K71:K75) -> -51936.59 | L76: =SUM(L71:L75) -> -63041.144 | M76: =SUM(M71:M75) -> -78473.449 | N76: =SUM(N71:N75) -> -67613.065 | ... P76: =SUM(P71:P75) -> 3769.0581
C78: Loss before income taxes | E78: $T | G78: =SUM(G69,G76) -> -538221 | H78: =SUM(H69,H76) -> -687719 | I78: =SUM(I69,I76) -> -609943 | J78: =SUM(J69,J76) -> -567586 | K78: =SUM(K69,K76) -> -586936.59 | L78: =SUM(L69,L76) -> -451266.6 | M78: =SUM(M69,M76) -> 221576.01 | N78: =SUM(N69,N76) -> 822459.44 | ... P78: =SUM(P69,P76) -> 1651310.3
C80: Provision for income taxes | E80: $T | G80: -1044 | H80: -5696 | I80: 1825 | J80: -1597 | K80: =-K32 -> 0 | L80: =-L32 -> 0 | M80: =-M32 -> -9306.1925 | N80: =-N32 -> -34543.296 | O80: =-O32 -> -45479.831 | P80: =-P32 -> -79740.771
C81: Loss after income taxes | E81: $T | G81: =SUM(G78,G80) -> -539265 | H81: =SUM(H78,H80) -> -693415 | I81: =SUM(I78,I80) -> -608118 | J81: =SUM(J78,J80) -> -569183 | K81: =SUM(K78,K80) -> -586936.59 | L81: =SUM(L78,L80) -> -451266.6 | M81: =SUM(M78,M80) -> 212269.82 | N81: =SUM(N78,N80) -> 787916.14 | ... P81: =SUM(P78,P80) -> 1571569.5
C83: EBITDA | E83: $T | G83: =G69+G152 -> -453738 | H83: =H69+H152 -> -616693 | I83: =I69+I152 -> -544681 | J83: =J69+J152 -> -500430 | K83: =K69+K152 -> -508221.88 | L83: =L69+L152 -> -364829.64 | M83: =M69+M152 -> 320169.6 | N83: =N69+N152 -> 907201.07 | ... P83: =P69+P152 -> 1660155.9
C85: Net loss per share, basic and diluted | G85: -6.7 | H85: -10.12 | I85: -8.25 | J85: -6.29 | K85: =K83*Units/K86 -> -5.2093264 | L85: =L83*Units/L86 -> -3.7395413 | M85: =M83*Units/M86 -> 3.2817712 | N85: =N83*Units/N86 -> 9.2989039 | O85: =O83*Units/O86 -> 11.637732 | P85: =P83*Units/P86 -> 17.016768
C86: Shares used in computing net loss per share, basic and diluted | G86: 67795540 | H86: 69914225 | I86: 73543862 | J86: 90538118 | K86: =Diluted*Units*Units -> 97560000 | L86: =Diluted*Units*Units -> 97560000 | M86: =Diluted*Units*Units -> 97560000 | N86: =Diluted*Units*Units -> 97560000 | O86: =Diluted*Units*Units -> 97560000 | P86: =Diluted*Units*Units -> 97560000
I88: Historical | O88: Projected:
B89: ="Balance Sheet - "&Company_Name -> Balance Sheet - Ultragenyx Pharmaceutical Inc. | E89: Units: | G89: =G3 -> 44561 | H89: =H3 -> 44926 | I89: =I3 -> 45291 | J89: =J3 -> 45657 | K89: =K3 -> 46022 | L89: =L3 -> 46387 | M89: =M3 -> 46752 | N89: =N3 -> 47118 | ... P89: =P3 -> 47848
C90: ASSETS
C92: Cash and cash equivalents | E92: $T | G92: 307584 | H92: 132944 | I92: 213584 | J92: 173729 | K92: =K198 -> 60426.088 | L92: =L198 -> -286670.99 | M92: =M198 -> -78443.516 | N92: =N198 -> 654153.48 | O92: =O198 -> 1724476 | P92: =P198 -> 3246576.5
C93: Marketable debt securities (current) | E93: $T | G93: 432612 | H93: 614818 | I93: 363625 | J93: 436296 | K93: =AVERAGE(G93:J93) -> 461837.75 | L93: =AVERAGE(H93:K93) -> 469144.19 | M93: =AVERAGE(I93:L93) -> 432725.73 | N93: =AVERAGE(J93:M93) -> 450000.92 | O93: =AVERAGE(K93:N93) -> 453427.15 | P93: =AVERAGE(L93:O93) -> 451324.5
C94: Accounts receivable, net | E94: $T | G94: 28432 | H94: 40445 | I94: 73390 | J94: 121801 | K94: =K37/(K57-EOMONTH(K57,-12))*K62 -> 165945.21 | L94: =L37/(L57-EOMONTH(L57,-12))*L62 -> 204109.59 | M94: =M37/(M57-EOMONTH(M57,-12))*M62 -> 296013.03 | N94: =N37/(N57-EOMONTH(N57,-12))*N62 -> 349236.17 | O94: =O37/(O57-EOMONTH(O57,-12))*O62 -> 387924.15 | P94: =P37/(P57-EOMONTH(P57,-12))*P62 -> 441397.5
C95: Inventory | E95: $T | G95: 16231 | H95: 26766 | I95: 33969 | J95: 45007 | K95: =K38/(K57-EOMONTH(K57,-12))*K62 -> 48954.667 | L95: =L38/(L57-EOMONTH(L57,-12))*L62 -> 58274.208 | M95: =M38/(M57-EOMONTH(M57,-12))*M62 -> 100481.46 | N95: =N38/(N57-EOMONTH(N57,-12))*N62 -> 142097.44 | O95: =O38/(O57-EOMONTH(O57,-12))*O62 -> 191470.78 | P95: =P38/(P57-EOMONTH(P57,-12))*P62 -> 248204.27
C96: Prepaid expenses and other current assets | E96: $T | G96: 71745 | H96: 68926 | I96: 47616 | J96: 40290 | K96: =K39*K62 -> 40380 | L96: =L39*L62 -> 37250 | M96: =M39*M62 -> 36014.919 | N96: =N39*N62 -> 31955.11 | O96: =O39*O62 -> 20227.474 | P96: =P39*P62 -> 24786.167
C97: Total current assets | E97: $T | G97: =SUM(G92:G96) -> 856604 | H97: =SUM(H92:H96) -> 883899 | I97: =SUM(I92:I96) -> 732184 | J97: =SUM(J92:J96) -> 817123 | K97: =SUM(K92:K96) -> 777543.71 | L97: =SUM(L92:L96) -> 482106.99 | M97: =SUM(M92:M96) -> 786791.63 | N97: =SUM(N92:N96) -> 1627443.1 | ... P97: =SUM(P92:P96) -> 4412288.9
C99: Property, plant, and equipment, net | E99: $T | G99: 141247 | H99: 259726 | I99: 290566 | J99: 265929 | K99: =Drivers!K373 -> 246130.88 | L99: =Drivers!L373 -> 229366.07 | M99: =Drivers!M373 -> 212395.93 | N99: =Drivers!N373 -> 198167.36 | O99: =Drivers!O373 -> 186690.36 | P99: =Drivers!P373 -> 177115.69
C100: Equity investments | E100: $T | G100: 34925 | H100: 5531 | I100: 0 | J100: 0 | K100: 0 | L100: 0 | M100: 0 | N100: 0 | O100: 0 | P100: 0
C101: Marketable debt securities (non-current) | E101: $T | G101: 258933 | H101: 148970 | I101: 199901 | J101: 135004 | K101: =K93*K41 -> 196282.25 | L101: =L93*L41 -> 175930.29 | M101: =M93*M41 -> 140636.99 | N101: =N93*N41 -> 123751.43 | O101: =O93*O41 -> 102022.29 | P101: =P93*P41 -> 78982.963
C102: Right-of-use assets | E102: $T | G102: 34936 | H102: 25961 | I102: 0 | J102: 0 | K102: 0 | L102: 0 | M102: 0 | N102: 0 | O102: 0 | P102: 0
C103: Intangible assets, net | E103: $T | G103: 130788 | H103: 160105 | I103: 166271 | J103: 178314 | K103: 178314 | L103: 178314 | M103: 178314 | N103: 178314 | O103: 178314 | P103: 178314
C104: Goodwill | E104: $T | G104: 44406 | H104: 44406 | I104: 44406 | J104: 44406 | K104: 44406 | L104: 44406 | M104: 44406 | N104: 44406 | O104: 44406 | P104: 44406
C105: Other assets | E105: $T | G105: 20558 | H105: 16846 | I105: 57685 | J105: 62680 | K105: =K42*K62 -> 61757.395 | L105: =L42*L62 -> 52150 | M105: =M42*M62 -> 60024.865 | N105: =N42*N62 -> 63910.22 | O105: =O42*O62 -> 60682.421 | P105: =P42*P62 -> 49572.335
C106: Total assets | E106: $T | G106: =SUM(G97,G99:G105) -> 1522397 | H106: =SUM(H97,H99:H105) -> 1545444 | I106: =SUM(I97,I99:I105) -> 1491013 | J106: =SUM(J97,J99:J105) -> 1503456 | K106: =SUM(K97,K99:K105) -> 1504434.2 | L106: =SUM(L97,L99:L105) -> 1162273.4 | M106: =SUM(M97,M99:M105) -> 1422569.4 | N106: =SUM(N97,N99:N105) -> 2235992.1 | ... P106: =SUM(P97,P99:P105) -> 4940679.9
C108: LIABILITIES AND STOCKHOLDERS’ EQUITY
C110: Accounts payable | E110: $T | G110: 17138 | H110: 43274 | I110: 42114 | J110: 38756 | K110: =K44/(K57-EOMONTH(K57,-12))*K62 -> 58172.866 | L110: =L44/(L57-EOMONTH(L57,-12))*L62 -> 57150.685 | M110: =M44/(M57-EOMONTH(M57,-12))*M62 -> 85514.876 | N110: =N44/(N57-EOMONTH(N57,-12))*N62 -> 104770.85 | O110: =O44/(O57-EOMONTH(O57,-12))*O62 -> 121919.02 | P110: =P44/(P57-EOMONTH(P57,-12))*P62 -> 135814.62
C111: Accrued liabilities | E111: $T | G111: 145555 | H111: 204678 | I111: 196486 | J111: 240973 | K111: =K45*-K67 -> 246544.13 | L111: =L45*-L67 -> 197286.42 | M111: =M45*-M67 -> 129748.07 | N111: =N45*-N67 -> 87818.383 | O111: =O45*-O67 -> 93896.649 | P111: =P45*-P67 -> 69887.488
C112: Contract liabilities (current) | E112: $T | G112: 7609 | H112: 1479 | I112: 0 | J112: 0 | K112: 0 | L112: 0 | M112: 0 | N112: 0 | O112: 0 | P112: 0
C113: Lease liabilities (current) | E113: $T | G113: 11066 | H113: 11779 | I113: 12595 | J113: 10297 | K113: 13831 | L113: 13949 | M113: 9019 | N113: 6709 | O113: 5589 | P113: 467
C114: Liabilities for sales of future royalties (current) | E114: $T | G114: 0 | H114: 0 | I114: 29242 | J114: 49847 | K114: =Drivers!K35 -> 98223.832 | L114: =Drivers!L35 -> 104117.26 | M114: =Drivers!M35 -> 109323.13 | N114: =Drivers!N35 -> 114789.28 | O114: =Drivers!O35 -> 120528.75 | P114: =Drivers!P35 -> 126555.18
C115: Other liabilities (current) | E115: $T | G115: 0 | H115: 0 | I115: 0 | J115: 4280 | K115: =K50*K122 -> 285.51072 | L115: =L50*L122 -> 298.395 | M115: =M50*M122 -> 126 | N115: =N50*N122 -> 116 | O115: =O50*O122 -> 32 | P115: =P50*P122 -> 30.4
C116: Total current liabilities | E116: $T | G116: =SUM(G110:G115) -> 181368 | H116: =SUM(H110:H115) -> 261210 | I116: =SUM(I110:I115) -> 280437 | J116: =SUM(J110:J115) -> 344153 | K116: =SUM(K110:K115) -> 417057.34 | L116: =SUM(L110:L115) -> 372801.76 | M116: =SUM(M110:M115) -> 333731.08 | N116: =SUM(N110:N115) -> 314203.52 | ... P116: =SUM(P110:P115) -> 332754.69
C118: Contract liabilities (non-current) | E118: $T | G118: 1467 | H118: 0 | I118: 0 | J118: 0 | K118: 0 | L118: 0 | M118: 0 | N118: 0 | O118: 0 | P118: 0
C119: Lease liabilities (non-current) | E119: $T | G119: 30904 | H119: 19814 | I119: 30574 | J119: 30042 | K119: =K49*K99 -> 24160.233 | L119: =L49*L99 -> 24186.831 | M119: =M49*M99 -> 22413.497 | N119: =N49*N99 -> 20420.344 | O119: =O49*O99 -> 19541.732 | P119: =P49*P99 -> 18493.681
C120: Deferred tax liabilities | E120: $T | G120: 33306 | H120: 31667 | I120: 30058 | J120: 30058 | K120: 30058 | L120: 30058 | M120: 30058 | N120: 30058 | O120: 30058 | P120: 30058
C121: Liabilities for sales of future royalties (non-current) | E121: $T | G121: 351786 | H121: 875439 | I121: 862325 | J121: 819824 | K121: =Drivers!K36 -> 1136384.9 | L121: =Drivers!L36 -> 1094669.4 | M121: =Drivers!M36 -> 1049749.6 | N121: =Drivers!N36 -> 996605.77 | O121: =Drivers!O36 -> 937373.59 | P121: =Drivers!P36 -> 873255.17
C122: Other liabilities (non-current) | E122: $T | G122: 1005 | H122: 4820 | I122: 12205 | J122: 17082 | K122: =K65*K50 -> 9982.1462 | L122: =L65*L50 -> 9946.5 | M122: =M65*M50 -> 6300 | N122: =N65*N50 -> 5800 | O122: =O65*O50 -> 3200 | P122: =P65*P50 -> 3040
C123: Total liabilities | E123: $T | G123: =SUM(G116,G118:G122) -> 599836 | H123: =SUM(H116,H118:H122) -> 1192950 | I123: =SUM(I116,I118:I122) -> 1215599 | J123: =SUM(J116,J118:J122) -> 1241159 | K123: =SUM(K116,K118:K122) -> 1617642.7 | L123: =SUM(L116,L118:L122) -> 1531662.5 | M123: =SUM(M116,M118:M122) -> 1442252.2 | N123: =SUM(N116,N118:N122) -> 1367087.6 | ... P123: =SUM(P116,P118:P122) -> 1257601.5
C126: Noncontrolling interest | E126: $T | G126: 0 | H126: 0 | I126: 0 | J126: 7000 | K126: 7000 | L126: 7000 | M126: 7000 | N126: 7000 | O126: 7000 | P126: 7000
C128: STOCKHOLDER'S EQUITY
C130: Preferred stock | E130: $T | G130: 0 | H130: 0 | I130: 0 | J130: 0 | K130: 0 | L130: 0 | M130: 0 | N130: 0 | O130: 0 | P130: 0
C131: Common stock | E131: $T | G131: 69 | H131: 70 | I131: 82 | J131: 92 | K131: 92 | L131: 92 | M131: 92 | N131: 92 | O131: 92 | P131: 92
C132: Treasury stock, at cost | E132: $T | G132: 0 | H132: 0 | I132: -432 | J132: -3593 | K132: -3593 | L132: -3593 | M132: -3593 | N132: -3593 | O132: -3593 | P132: -3593
C133: Deferred compensation obligation | E133: $T | G133: 0 | H133: 0 | I133: 432 | J133: 3593 | K133: 3593 | L133: 3593 | M133: 3593 | N133: 3593 | O133: 3593 | P133: 3593
C134: Additional paid-in capital | E134: $T | G134: 2997497 | H134: 3140019 | I134: 3662346 | J134: 4212692 | K134: 4212692 | L134: 4212692 | M134: 4212692 | N134: 4212692 | O134: 4212692 | P134: 4212692
C135: Accumulated other comprehensive (loss) income | E135: $T | G135: -1404 | H135: -6573 | I135: 647 | J135: -643 | K135: -643 | L135: -643 | M135: -643 | N135: -643 | O135: -643 | P135: -643
...

Sheet Drivers
B2: =Company_Name&" - Revenue Drivers" -> Ultragenyx Pharmaceutical Inc. - Revenue Drivers | I2: Historical | O2: Projected:
B3: Commercial Products | E3: Units: | G3: =Model!G3 -> 44561 | H3: =EOMONTH(G3,12) -> 44926 | I3: =EOMONTH(H3,12) -> 45291 | J3: =EOMONTH(I3,12) -> 45657 | K3: =EOMONTH(J3,12) -> 46022 | L3: =EOMONTH(K3,12) -> 46387 | M3: =EOMONTH(L3,12) -> 46752 | N3: =EOMONTH(M3,12) -> 47118 | O3: =EOMONTH(N3,12) -> 47483 | ... AE3: =EOMONTH(AD3,12) -> 53327
B4: COMMERCIAL PRODUCTS
C6: Product sales | E6: $T | G6: =Model!G59 -> 77017 | H6: =Model!H59 -> 118927 | I6: =Model!I59 -> 180413 | J6: =Model!J59 -> 285415 | K6: =SUM(K27,K81,K112,K161) -> 375393.05 | L6: =SUM(L27,L81,L112,L161,L216,L264,L312,L361) -> 585021.11 | M6: =SUM(M27,M81,M112,M161,M216,M264,M312,M361) -> 864635.16 | N6: =SUM(N27,N81,N112,N161,N216,N264,N312,N361) -> 1245100.3 | O6: =SUM(O27,O81,O112,O161,O216,O264,O312,O361) -> 1652459.4 | P6: =SUM(P27,P81,P112,P161,P216,P264,P312,P361) -> 2089814.3 | Q6: =SUM(Q27,Q81,Q112,Q161,Q216,Q264,Q312,Q361) -> 2473172 | R6: =SUM(R27,R81,R112,R161,R216,R264,R312,R361) -> 2636940.8 | S6: =SUM(S27,S81,S112,S161,S216,S264,S312,S361) -> 2659930 | ... AE6: =SUM(AE27,AE81,AE112,AE161,AE216,AE264,AE312,AE361) -> 1081252.4
C7: Royalty revenue | E7: $T | G7: =Model!G60 -> 0 | H7: =Model!H60 -> 21692 | I7: =Model!I60 -> 182652 | J7: =Model!J60 -> 274815 | K7: =K29 -> 296122.5 | L7: =L29 -> 316851.07 | M7: =M29 -> 335862.14 | N7: =N29 -> 352655.24 | O7: =O29 -> 370288.01 | P7: =P29 -> 388802.41 | Q7: =Q29 -> 408242.53 | R7: =R29 -> 428654.65 | ... AE7: =AE29 -> 0
C8: Non-cash collaboration royalty revenue | E8: $T | G8: =Model!G61 -> 189149 | H8: =Model!H61 -> 236716 | I8: =Model!I61 -> 69705 | J8: =Model!J61 -> 0 | K8: 0 | L8: 0 | M8: 0 | N8: 0 | O8: 0 | P8: 0 | Q8: 0 | R8: 0 | S8: 0 | T8: 0 | U8: 0 | V8: 0 | W8: 0 | X8: 0 | Y8: 0 | Z8: 0 | AA8: 0 | AB8: 0 | AC8: 0 | AD8: 0 | AE8: 0
C9: Total revenues | E9: $T | G9: =Model!G62 -> 266166 | H9: =Model!H62 -> 377335 | I9: =Model!I62 -> 432770 | J9: =Model!J62 -> 560230 | K9: =SUM(K6:K8) -> 671515.55 | L9: =Model!L62 -> 745000 | M9: =SUM(M6:M8) -> 1200497.3 | N9: =SUM(N6:N8) -> 1597755.5 | O9: =SUM(O6:O8) -> 2022747.4 | P9: =SUM(P6:P8) -> 2478616.7 | Q9: =SUM(Q6:Q8) -> 2881414.6 | R9: =SUM(R6:R8) -> 3065595.5 | S9: =SUM(S6:S8) -> 2981421 | T9: =SUM(T6:T8) -> 2623781.7 | ... AE9: =SUM(AE6:AE8) -> 1081252.4
C10: % Growth | H10: =H9/G9-1 -> 0.41766792 | I10: =I9/H9-1 -> 0.1469119 | J10: =J9/I9-1 -> 0.29452134 | K10: =K9/J9-1 -> 0.19864261 | L10: =L9/K9-1 -> 0.10943075 | M10: =M9/L9-1 -> 0.61140577 | N10: =N9/M9-1 -> 0.33091136 | O10: =O9/N9-1 -> 0.26599305 | ... W10: =W9/V9-1 -> -0.33991469
C12: Cost of sales | E12: $T | G12: 16008 | H12: 28320 | I12: 45209 | J12: 76728 | K12: =Model!K64 -> 109000 | L12: =Model!L64 -> 89175.452 | M12: =Model!M64 -> 143697.84 | N12: =Model!N64 -> 143797.99 | O12: =Model!O64 -> 182047.26 | P12: =SUM(P47,P84,P115,P164) -> 139024.68 | Q12: =Q9*0.09 -> 259327.31 | R12: =R9*0.09 -> 275903.59 | S12: =S9*0.09 -> 268327.89 | T12: =T9*0.09 -> 236140.35 | U12: =U9*0.09 -> 212616.59 | V12: =V9*0.09 -> 161692.6 | W12: =W9*0.09 -> 106730.91 | X12: =X9*0.09 -> 97441.802 | ... AE12: =AE9*0.09 -> 97312.718
C13: Research and development | E13: $T | G13: 497153 | H13: 705789 | I13: 648449 | J13: 697865 | K13: =Model!K65 -> 349000 | L13: =Model!L65 -> 331550 | M13: =Model!M65 -> 315000 | N13: =Model!N65 -> 290000 | O13: =Model!O65 -> 320000 | P13: =O13*0.95 -> 304000 | Q13: =P13*0.95 -> 288800 | R13: =Q13*0.95 -> 274360 | S13: =R13*0.95 -> 260642 | T13: =S13*0.95 -> 247609.9 | U13: =T13*0.95 -> 235229.4 | V13: =U13*0.95 -> 223467.93 | W13: =V13*0.95 -> 212294.54 | ... AE13: =AD13*0.95 -> 140840.53
C14: Selling, general and administrative | E14: $T | G14: 219982 | H14: 278139 | I14: 309799 | J14: 321610 | K14: =Model!K66 -> 750000 | L14: =Model!L66 -> 712500 | M14: =Model!M66 -> 441750 | N14: =Model!N66 -> 273885 | O14: =Model!O66 -> 400000 | P14: =P17 -> 304000 | Q14: =Q17 -> 288800 | R14: =R17 -> 274360 | S14: =S17 -> 260642 | T14: =T17 -> 247609.9 | U14: =U17 -> 235229.4 | V14: =V17 -> 223467.93 | W14: =W17 -> 212294.54 | ... AE14: =AE17 -> 200000
C15: Total operating expenses | E15: $T | G15: =-SUM(G12:G14) -> -733143 | H15: =-SUM(H12:H14) -> -1012248 | I15: =-SUM(I12:I14) -> -1003457 | J15: =-SUM(J12:J14) -> -1096203 | K15: =-SUM(K12:K14) -> -1208000 | L15: =-SUM(L12:L14) -> -1133225.5 | M15: =-SUM(M12:M14) -> -900447.84 | N15: =-SUM(N12:N14) -> -707682.99 | ... AE15: =-SUM(AE12:AE14) -> -438153.25
C17: SG&A | K17: =INDEX($K$18:$AE$20,MATCH(OpEx,$C$18:$C$20,0),1) -> 300000 | L17: =INDEX($K$18:$AE$20,MATCH(OpEx,$C$18:$C$20,0),2) -> 280000 | M17: =INDEX($K$18:$AE$20,MATCH(OpEx,$C$18:$C$20,0),3) -> 260000 | N17: =INDEX($K$18:$AE$20,MATCH(OpEx,$C$18:$C$20,0),4) -> 290000 | O17: =INDEX($K$18:$AE$20,MATCH(OpEx,$C$18:$C$20,0),5) -> 320000 | P17: =INDEX($K$18:$AE$20,MATCH(OpEx,$C$18:$C$20,0),6) -> 304000 | Q17: =INDEX($K$18:$AE$20,MATCH(OpEx,$C$18:$C$20,0),7) -> 288800 | R17: =INDEX($K$18:$AE$20,MATCH(OpEx,$C$18:$C$20,0),8) -> 274360 | S17: =INDEX($K$18:$AE$20,MATCH(OpEx,$C$18:$C$20,0),9) -> 260642 | T17: =INDEX($K$18:$AE$20,MATCH(OpEx,$C$18:$C$20,0),10) -> 247609.9 | U17: =INDEX($K$18:$AE$20,MATCH(OpEx,$C$18:$C$20,0),11) -> 235229.4 | V17: =INDEX($K$18:$AE$20,MATCH(OpEx,$C$18:$C$20,0),12) -> 223467.93 | W17: =INDEX($K$18:$AE$20,MATCH(OpEx,$C$18:$C$20,0),13) -> 212294.54 | X17: =INDEX($K$18:$AE$20,MATCH(OpEx,$C$18:$C$20,0),14) -> 201679.81 | Y17: =INDEX($K$18:$AE$20,MATCH(OpEx,$C$18:$C$20,0),15) -> 200000 | Z17: =INDEX($K$18:$AE$20,MATCH(OpEx,$C$18:$C$20,0),16) -> 200000 | AA17: =INDEX($K$18:$AE$20,MATCH(OpEx,$C$18:$C$20,0),17) -> 200000 | AB17: =INDEX($K$18:$AE$20,MATCH(OpEx,$C$18:$C$20,0),18) -> 200000 | AC17: =INDEX($K$18:$AE$20,MATCH(OpEx,$C$18:$C$20,0),19) -> 200000 | AD17: =INDEX($K$18:$AE$20,MATCH(OpEx,$C$18:$C$20,0),20) -> 200000 | AE17: =INDEX($K$18:$AE$20,MATCH(OpEx,$C$18:$C$20,0),21) -> 200000
C18: Upside | K18: 200000 | L18: 210000 | M18: 230000 | N18: 270000 | O18: 250000 | P18: =O18-10000 -> 240000 | Q18: =P18-10000 -> 230000 | R18: =Q18-10000 -> 220000 | S18: =R18-10000 -> 210000 | T18: =S18-10000 -> 200000 | U18: 200000 | V18: 200000 | W18: 200000 | X18: 200000 | Y18: 200000 | Z18: 200000 | AA18: 200000 | AB18: 200000 | AC18: 200000 | AD18: 200000 | AE18: 200000
C19: Base | G19: 219982 | H19: 278139 | I19: 309799 | J19: 321610 | K19: 300000 | L19: 280000 | M19: 260000 | N19: 290000 | O19: 320000 | P19: =O19*0.95 -> 304000 | Q19: =P19*0.95 -> 288800 | R19: =Q19*0.95 -> 274360 | S19: =R19*0.95 -> 260642 | T19: =S19*0.95 -> 247609.9 | U19: =T19*0.95 -> 235229.4 | V19: =U19*0.95 -> 223467.93 | W19: =V19*0.95 -> 212294.54 | X19: =W19*0.95 -> 201679.81 | Y19: 200000 | Z19: 200000 | AA19: 200000 | AB19: 200000 | AC19: 200000 | AD19: 200000 | AE19: 200000
C20: Downside | K20: 350000 | L20: 330000 | M20: 300000 | N20: 320000 | O20: 350000 | P20: =O20*0.95 -> 332500 | Q20: =P20*0.95 -> 315875 | R20: =Q20*0.95 -> 300081.25 | S20: =R20*0.95 -> 285077.19 | T20: =S20*0.95 -> 270823.33 | U20: =T20*0.95 -> 257282.16 | V20: =U20*0.95 -> 244418.05 | W20: =V20*0.95 -> 232197.15 | ... Y20: =X20*0.95 -> 209557.93 | Z20: 200000 | AA20: 200000 | AB20: 200000 | AC20: 200000 | AD20: 200000 | AE20: 200000
B22: CRYSVITA | P22: LOE
C24: Crysvita total revenue | E24: $T | G24: 210815 | H24: 279394 | I24: 328054 | J24: 409524 | K24: 481000 | L24: =SUM(L27,L29) -> 659851.07 | M24: =SUM(M27,M29) -> 747462.14 | N24: =SUM(N27,N29) -> 805415.24 | O24: =SUM(O27,O29) -> 854741.21 | P24: =SUM(P27,P29) -> 902322.8 | Q24: =SUM(Q27,Q29) -> 947438.94 | R24: =SUM(R27,R29) -> 994810.88 | S24: =SUM(S27,S29) -> 746108.16 | ... V24: =SUM(V27,V29) -> 431250.52
C25: % Growth | H25: =H24/G24-1 -> 0.32530418 | I25: =I24/H24-1 -> 0.17416265 | J25: =J24/I24-1 -> 0.24834326 | K25: =K24/J24-1 -> 0.17453434 | L25: =L24/K24-1 -> 0.37183175 | M25: =M24/L24-1 -> 0.132774 | N25: =N24/M24-1 -> 0.077533167 | O25: =O24/N24-1 -> 0.061242896 | ... V25: =V24/U24-1 -> -0.15
C27: Crysvita product sales | E27: $T | G27: 21422 | H27: 42678 | I27: 75697 | J27: 134709 | K27: 245000 | L27: =K27*(1+L28) -> 343000 | M27: =L27*(1+M28) -> 411600 | N27: =M27*(1+N28) -> 452760 | O27: =N27*(1+O28) -> 484453.2 | P27: =O27*(1+P28) -> 513520.39 | Q27: =P27*(1+Q28) -> 539196.41 | R27: =Q27*(1+R28) -> 566156.23 | S27: =R27*(1+S28) -> 424617.17 | ... V27: =U27*(1+V28) -> 245428.73
C28: % Growth | E28: % | H28: =H27/G27-1 -> 0.99225096 | I28: =I27/H27-1 -> 0.7736773 | J28: =J27/I27-1 -> 0.77958175 | K28: 0.6 | L28: 0.4 | M28: 0.2 | N28: 0.1 | O28: 0.07 | P28: 0.06 | Q28: 0.05 | R28: 0.05 | S28: -0.25 | T28: -0.2 | U28: -0.15 | V28: -0.15
C29: Crysvita royalty/rev-share stream | E29: $T | G29: 189393 | H29: 236716 | I29: 252357 | J29: 274815 | K29: =J29*(1+K30) -> 296122.5 | L29: =K29*(1+L30) -> 316851.07 | M29: =L29*(1+M30) -> 335862.14 | N29: =M29*(1+N30) -> 352655.24 | O29: =N29*(1+O30) -> 370288.01 | P29: =O29*(1+P30) -> 388802.41 | Q29: =P29*(1+Q30) -> 408242.53 | R29: =Q29*(1+R30) -> 428654.65 | ... V29: =U29*(1+V30) -> 185821.79
C30: % Growth | H30: =H29/G29-1 -> 0.24986668 | I30: =I29/H29-1 -> 0.066074959 | J30: =J29/I29-1 -> 0.088992974 | K30: =AVERAGE(I30:J30) -> 0.077533967 | L30: 0.07 | M30: 0.06 | N30: 0.05 | O30: 0.05 | P30: =AVERAGE(N30:O30) -> 0.05 | Q30: =AVERAGE(O30:P30) -> 0.05 | R30: =AVERAGE(P30:Q30) -> 0.05 | S30: -0.25 | T30: -0.2 | U30: -0.15 | V30: -0.15
C32: Royalty revenue applied to reduce liability (repayment) % Royalty stream | E32: % | G32: =-G40/G29 -> 0.09478175 | H32: =-H40/H29 -> 0.091637236 | I32: =-I40/I29 -> 0.2350123 | J32: =-J40/J29 -> 0.30906974 | K32: =IF(K39>0,31%,0) -> 0.31 | L32: =IF(L39>0,31%,0) -> 0.31 | M32: =IF(M39>0,31%,0) -> 0.31 | N32: =IF(N39>0,31%,0) -> 0.31 | O32: =IF(O39>0,31%,0) -> 0.31 | P32: =IF(P39>0,31%,0) -> 0.31 | Q32: =IF(Q39>0,31%,0) -> 0.31 | R32: =IF(R39>0,31%,0) -> 0.31 | ... V32: =IF(V39>0,31%,0) -> 0.31
C35: Liabilities for sales of future royalties (current) | E35: $T | G35: =Model!G114 -> 0 | H35: =Model!H114 -> 0 | I35: =Model!I114 -> 29242 | J35: =Model!J114 -> 49847 | K35: =-L40 -> 98223.832 | L35: =-M40 -> 104117.26 | M35: =-N40 -> 109323.13 | N35: =-O40 -> 114789.28 | O35: =-P40 -> 120528.75 | P35: =-Q40 -> 126555.18 | Q35: =-R40 -> 132882.94 | R35: =-S40 -> 99662.207 | ... V35: =-W40 -> 0
C36: Liabilities for sales of future royalties (non-current) | E36: $T | G36: =Model!G121 -> 351786 | H36: =Model!H121 -> 875439 | I36: =Model!I121 -> 862325 | J36: =Model!J121 -> 819824 | K36: =K37-K35 -> 1136384.9 | L36: =L37-L35 -> 1094669.4 | M36: =M37-M35 -> 1049749.6 | N36: =N37-N35 -> 996605.77 | O36: =O37-O35 -> 937373.59 | P36: =P37-P35 -> 873255.17 | Q36: =Q37-Q35 -> 802817.76 | R36: =R37-R35 -> 765111.63 | ... V36: =V37-V35 -> 808514.71
C37: Liabilities for sales of future royalties (total) | E37: $T | G37: =SUM(G35:G36) -> 351786 | H37: =SUM(H35:H36) -> 875439 | I37: =SUM(I35:I36) -> 891567 | J37: =SUM(J35:J36) -> 869671 | K37: =K43 -> 1234608.8 | L37: =L43 -> 1198786.6 | M37: =M43 -> 1159072.7 | N37: =N43 -> 1111395.1 | O37: =O43 -> 1057902.3 | P37: =P43 -> 999810.35 | Q37: =Q43 -> 935700.7 | R37: =R43 -> 864773.84 | ... V37: =V43 -> 808514.71
C39: Liabilities for sales of future royalties — Beginning of year | E39: $T | G39: 335665 | H39: =G43 -> 351786 | I39: =H43 -> 875439 | J39: =I43 -> 891567 | K39: =J43 -> 869671 | L39: =K43 -> 1234608.8 | M39: =L43 -> 1198786.6 | N39: =M43 -> 1159072.7 | O39: =N43 -> 1111395.1 | ... V39: =U43 -> 804026.67
C40: Less: Royalty revenue applied to reduce liability (repayment) | E40: $T | G40: -17951 | H40: -21692 | I40: -59307 | J40: -84937 | K40: =IF(K29*K32<K39,-K29*K32,-K39) -> -91797.974 | L40: =IF(L29*L32<L39,-L29*L32,-L39) -> -98223.832 | M40: =IF(M29*M32<M39,-M29*M32,-M39) -> -104117.26 | N40: =IF(N29*N32<N39,-N29*N32,-N39) -> -109323.13 | O40: =IF(O29*O32<O39,-O29*O32,-O39) -> -114789.28 | P40: =IF(P29*P32<P39,-P29*P32,-P39) -> -120528.75 | Q40: =IF(Q29*Q32<Q39,-Q29*Q32,-Q39) -> -126555.18 | R40: =IF(R29*R32<R39,-R29*R32,-R39) -> -132882.94 | ... V40: =IF(V29*V32<V39,-V29*V32,-V39) -> -57604.755
C41: Proceeds from sale of future royalties | E41: $T | G41: =Model!G183 -> 0 | H41: =Model!H183 -> 490950 | I41: =Model!I183 -> 0 | J41: =Model!J183 -> 0 | K41: 400000 | L41: 0 | M41: 0 | N41: 0 | O41: 0 | P41: 0 | Q41: 0 | R41: 0 | S41: 0 | T41: 0 | U41: 0 | V41: 0
C42: Add: Non-cash interest expense (accretion) | E42: $T | G42: 34072 | H42: 54395 | I42: 75435 | J42: =Model!J155 -> 63041 | K42: =AVERAGE(G42:J42) -> 56735.75 | L42: =AVERAGE(H42:K42) -> 62401.688 | M42: =AVERAGE(I42:L42) -> 64403.359 | N42: =AVERAGE(J42:M42) -> 61645.449 | O42: =AVERAGE(K42:N42) -> 61296.562 | P42: =AVERAGE(L42:O42) -> 62436.764 | Q42: =AVERAGE(M42:P42) -> 62445.534 | R42: =AVERAGE(N42:Q42) -> 61956.077 | ... V42: =AVERAGE(R42:U42) -> 62092.795
C43: Liabilities for sales of future royalties — End of year | E43: $T | G43: =SUM(G39:G42) -> 351786 | H43: =SUM(H39:H42) -> 875439 | I43: =SUM(I39:I42) -> 891567 | J43: =SUM(J39:J42) -> 869671 | K43: =SUM(K39:K42) -> 1234608.8 | L43: =SUM(L39:L42) -> 1198786.6 | M43: =SUM(M39:M42) -> 1159072.7 | N43: =SUM(N39:N42) -> 1111395.1 | ... V43: =SUM(V39:V42) -> 808514.71
C45: Non-cash interest expense on liabilities for sales of future royalties (P&L) | E45: $T | G45: 29422 | H45: 43015 | I45: 66004 | J45: 63041
C47: COGS (Revenue Weighted) | E47: $ | G47: =(G24/G9)*G12 -> 12679.029 | H47: =(H24/H9)*H12 -> 20969.266 | I47: =(I24/I9)*I12 -> 34269.92 | J47: =(J24/J9)*J12 -> 56087.602 | K47: =K24*K48 -> 45288.301 | L47: =L24*L48 -> 67738.57 | M47: =M24*M48 -> 81890.855 | N47: =N24*N48 -> 89265.863 | O47: =O24*O48 -> 89150.035 | P47: =P24*P48 -> 96401.599 | Q47: =Q24*Q48 -> 102211.7 | R47: =R24*R48 -> 106905.36 | ... V47: =V24*V48 -> 46205.915
C48: Incremental COGS % Revenue | E48: % | G48: =G47/G24 -> 0.060142918 | H48: =H47/H24 -> 0.075052672 | I48: =I47/I24 -> 0.10446427 | J48: =J47/J24 -> 0.13695804 | K48: =AVERAGE(G48:J48) -> 0.094154473 | L48: =AVERAGE(H48:K48) -> 0.10265736 | M48: =AVERAGE(I48:L48) -> 0.10955853 | N48: =AVERAGE(J48:M48) -> 0.1108321 | O48: =AVERAGE(K48:N48) -> 0.10430062 | P48: =AVERAGE(L48:O48) -> 0.10683715 | Q48: =AVERAGE(M48:P48) -> 0.1078821 | R48: =AVERAGE(N48:Q48) -> 0.10746299 | ... V48: =AVERAGE(R48:U48) -> 0.10714402
B52: DOJOLVI | T52: LOE
C54: GLOBAL
C55: LC-FAOD Ex- U.S. | E55: # | G55: 10781.645 | H55: 10835.824 | I55: 10890.275 | J55: 10945 | K55: 11000 | L55: 11055 | M55: 11110 | N55: 11165.5 | O55: 11221.5 | P55: 11278 | Q55: 11334 | R55: 11390.5 | S55: 11448 | T55: 11505.5 | U55: 11563 | V55: 11620.5 | W55: 11678
C56: % Growth | E56: % | H56: 0.005 | I56: 0.005 | J56: 0.005 | K56: 0.005 | L56: 0.005 | M56: 0.005 | N56: 0.005 | O56: 0.005 | P56: 0.005 | Q56: 0.005 | R56: 0.005 | S56: 0.005 | T56: 0.005 | U56: 0.005 | V56: 0.005 | W56: 0.005
C58: UNITED STATES
C59: LC-FAOD (eligible) | E59: # | G59: 3100 | H59: 3200 | I59: 3300 | J59: 3400 | K59: 3500 | L59: 3675 | M59: 3822 | N59: 3937 | O59: 4035 | P59: 4116 | Q59: 4178 | R59: 4219 | S59: 4261 | T59: 4304 | U59: 4304 | V59: 4304 | W59: 4304
C60: % Growth | E60: % | H60: 0.032258065 | I60: 0.03125 | J60: 0.03030303 | K60: =K59/J59-1 -> 0.029411765 | L60: 0.05 | M60: 0.04 | N60: 0.03 | O60: 0.025 | P60: 0.02 | Q60: 0.015 | R60: 0.01 | S60: 0.01 | T60: 0.01 | U60: 0 | V60: 0 | W60: 0
C62: LC-FAOD - effective penetration | E62: % | G62: 0.087 | H62: 0.059 | I62: 0.073 | J62: 0.089 | K62: =INDEX($K$63:$W$65,MATCH(Scenario,$C$63:$C$65,0),1) -> 0.09 | L62: =INDEX($K$63:$W$65,MATCH(Scenario,$C$63:$C$65,0),2) -> 0.105 | M62: =INDEX($K$63:$W$65,MATCH(Scenario,$C$63:$C$65,0),3) -> 0.12 | N62: =INDEX($K$63:$W$65,MATCH(Scenario,$C$63:$C$65,0),4) -> 0.13 | O62: =INDEX($K$63:$W$65,MATCH(Scenario,$C$63:$C$65,0),5) -> 0.14 | P62: =INDEX($K$63:$W$65,MATCH(Scenario,$C$63:$C$65,0),6) -> 0.145 | Q62: =INDEX($K$63:$W$65,MATCH(Scenario,$C$63:$C$65,0),7) -> 0.148 | R62: =INDEX($K$63:$W$65,MATCH(Scenario,$C$63:$C$65,0),8) -> 0.15 | S62: =INDEX($K$63:$W$65,MATCH(Scenario,$C$63:$C$65,0),9) -> 0.185 | T62: =INDEX($K$63:$W$65,MATCH(Scenario,$C$63:$C$65,0),10) -> 0.15 | U62: =INDEX($K$63:$W$65,MATCH(Scenario,$C$63:$C$65,0),11) -> 0.12 | V62: =INDEX($K$63:$W$65,MATCH(Scenario,$C$63:$C$65,0),12) -> 0.09 | W62: =INDEX($K$63:$W$65,MATCH(Scenario,$C$63:$C$65,0),13) -> 0.07
C63: Upside | E63: % | K63: 0.11 | L63: 0.125 | M63: 0.14 | N63: 0.15 | O63: 0.16 | P63: 0.165 | Q63: 0.168 | R63: 0.17 | S63: 0.17 | T63: 0.17 | U63: 0.14 | V63: 0.11 | W63: 0.09
C64: Base | E64: % | K64: 0.09 | L64: 0.105 | M64: 0.12 | N64: 0.13 | O64: 0.14 | P64: 0.145 | Q64: 0.148 | R64: 0.15 | S64: 0.185 | T64: 0.15 | U64: 0.12 | V64: 0.09 | W64: 0.07
C65: Downside | E65: % | K65: 0.07 | L65: 0.085 | M65: 0.1 | N65: 0.11 | O65: 0.12 | P65: 0.125 | Q65: 0.128 | R65: 0.13 | S65: 0.196 | T65: 0.13 | U65: 0.1 | V65: 0.07 | W65: 0.05
C67: Net annual revenue per treated patient (ASP) | E67: $T | G67: 147 | H67: 293 | I67: 293 | J67: 293 | K67: =INDEX($K$68:$W$70,MATCH(Scenario,$C$68:$C$70,0),1) -> 304 | L67: =INDEX($K$68:$W$70,MATCH(Scenario,$C$68:$C$70,0),2) -> 313.12 | M67: =INDEX($K$68:$W$70,MATCH(Scenario,$C$68:$C$70,0),3) -> 322.5136 | N67: =INDEX($K$68:$W$70,MATCH(Scenario,$C$68:$C$70,0),4) -> 332.18901 | O67: =INDEX($K$68:$W$70,MATCH(Scenario,$C$68:$C$70,0),5) -> 342.15468 | P67: =INDEX($K$68:$W$70,MATCH(Scenario,$C$68:$C$70,0),6) -> 352.41932 | Q67: =INDEX($K$68:$W$70,MATCH(Scenario,$C$68:$C$70,0),7) -> 362.9919 | R67: =INDEX($K$68:$W$70,MATCH(Scenario,$C$68:$C$70,0),8) -> 373.88166 | S67: =INDEX($K$68:$W$70,MATCH(Scenario,$C$68:$C$70,0),9) -> 385.0981 | T67: =INDEX($K$68:$W$70,MATCH(Scenario,$C$68:$C$70,0),10) -> 200 | U67: =INDEX($K$68:$W$70,MATCH(Scenario,$C$68:$C$70,0),11) -> 180 | V67: =INDEX($K$68:$W$70,MATCH(Scenario,$C$68:$C$70,0),12) -> 160 | W67: =INDEX($K$68:$W$70,MATCH(Scenario,$C$68:$C$70,0),13) -> 140
C68: Upside | E68: $T | K68: 370 | L68: 381 | M68: 392 | N68: 400 | O68: 408 | P68: 416 | Q68: 420 | R68: 424 | S68: 429 | T68: 220 | U68: =T68-20 -> 200 | V68: =U68-20 -> 180 | W68: =V68-20 -> 160
C69: Base | E69: $T | K69: 304 | L69: =K69*(1+0.03) -> 313.12 | M69: =L69*(1+0.03) -> 322.5136 | N69: =M69*(1+0.03) -> 332.18901 | O69: =N69*(1+0.03) -> 342.15468 | P69: =O69*(1+0.03) -> 352.41932 | Q69: =P69*(1+0.03) -> 362.9919 | R69: =Q69*(1+0.03) -> 373.88166 | S69: =R69*(1+0.03) -> 385.0981 | T69: 200 | U69: =T69-20 -> 180 | V69: =U69-20 -> 160 | W69: =V69-20 -> 140
C70: Downside | E70: $T | K70: 270 | L70: =K70*1.03 -> 278.1 | M70: =L70*1.03 -> 286.443 | N70: =M70*1.03 -> 295.03629 | O70: =N70*1.03 -> 303.88738 | P70: =O70*1.03 -> 313.004 | Q70: =P70*1.03 -> 322.39412 | R70: =Q70*1.03 -> 332.06594 | S70: =R70*1.03 -> 342.02792 | T70: 180 | U70: =T70-20 -> 160 | V70: =U70-20 -> 140 | W70: =V70-20 -> 120
C72: Treated patients (calculated) | E72: # | G72: 270 | H72: 190 | I72: 241 | J72: 301 | K72: =INDEX($K$73:$W$75,MATCH(Scenario,$C$73:$C$75,0),1) -> 315 | L72: =INDEX($K$73:$W$75,MATCH(Scenario,$C$73:$C$75,0),2) -> 385.875 | M72: =INDEX($K$73:$W$75,MATCH(Scenario,$C$73:$C$75,0),3) -> 458.64 | N72: =INDEX($K$73:$W$75,MATCH(Scenario,$C$73:$C$75,0),4) -> 511.81 | O72: =INDEX($K$73:$W$75,MATCH(Scenario,$C$73:$C$75,0),5) -> 564.9 | P72: =INDEX($K$73:$W$75,MATCH(Scenario,$C$73:$C$75,0),6) -> 596.82 | Q72: =INDEX($K$73:$W$75,MATCH(Scenario,$C$73:$C$75,0),7) -> 618.344 | R72: =INDEX($K$73:$W$75,MATCH(Scenario,$C$73:$C$75,0),8) -> 632.85 | S72: =INDEX($K$73:$W$75,MATCH(Scenario,$C$73:$C$75,0),9) -> 788.285 | T72: =INDEX($K$73:$W$75,MATCH(Scenario,$C$73:$C$75,0),10) -> 645.6 | U72: =INDEX($K$73:$W$75,MATCH(Scenario,$C$73:$C$75,0),11) -> 516.48 | V72: =INDEX($K$73:$W$75,MATCH(Scenario,$C$73:$C$75,0),12) -> 387.36 | W72: =INDEX($K$73:$W$75,MATCH(Scenario,$C$73:$C$75,0),13) -> 301.28
C73: Upside | E73: # | K73: =K$59*K63 -> 385 | L73: =L$59*L63 -> 459.375 | M73: =M$59*M63 -> 535.08 | N73: =N$59*N63 -> 590.55 | O73: =O$59*O63 -> 645.6 | P73: =P$59*P63 -> 679.14 | Q73: =Q$59*Q63 -> 701.904 | R73: =R$59*R63 -> 717.23 | ... W73: =W$59*W63 -> 387.36
C74: Base | E74: # | K74: =K$59*K64 -> 315 | L74: =L$59*L64 -> 385.875 | M74: =M$59*M64 -> 458.64 | N74: =N$59*N64 -> 511.81 | O74: =O$59*O64 -> 564.9 | P74: =P$59*P64 -> 596.82 | Q74: =Q$59*Q64 -> 618.344 | R74: =R$59*R64 -> 632.85 | ... W74: =W$59*W64 -> 301.28
C75: Downside | E75: # | K75: =K$59*K65 -> 245 | L75: =L$59*L65 -> 312.375 | M75: =M$59*M65 -> 382.2 | N75: =N$59*N65 -> 433.07 | O75: =O$59*O65 -> 484.2 | P75: =P$59*P65 -> 514.5 | Q75: =Q$59*Q65 -> 534.784 | R75: =R$59*R65 -> 548.47 | ... W75: =W$59*W65 -> 215.2
C77: Dojolvi product sales (reported) | E77: $T | G77: 39560 | H77: 55612 | I77: 70633 | J77: 88194 | K77: =K67*K72 -> 95760 | L77: =L72*L67 -> 120825.18 | M77: =M72*M67 -> 147917.64 | N77: =N72*N67 -> 170017.66 | O77: =O72*O67 -> 193283.18 | P77: =P72*P67 -> 210330.9 | Q77: =Q72*Q67 -> 224453.86 | R77: =R72*R67 -> 236611.01 | S77: =S72*S67 -> 303567.06 | ... W77: =W72*W67 -> 42179.2
H78: =H77/G77-1 -> 0.4057634 | I78: =I77/H77-1 -> 0.27010357 | J78: =J77/I77-1 -> 0.24862316 | K78: =K77/J77-1 -> 0.085788149 | L78: =L77/K77-1 -> 0.26175 | M78: =M77/L77-1 -> 0.22422857 | N78: =N77/M77-1 -> 0.1494076 | O78: =O77/N77-1 -> 0.1368418 | ... W78: =W77/V77-1 -> -0.31944444
C80: Royalties to Baylor Research | E80: $T | F80: 0.07 | K80: =-K77*$F$80 -> -6703.2 | L80: =-L77*$F$80 -> -8457.7626 | M80: =-M77*$F$80 -> -10354.235 | N80: =-N77*$F$80 -> -11901.236 | O80: =-O77*$F$80 -> -13529.822 | P80: =-P77*$F$80 -> -14723.163 | Q80: =-Q77*$F$80 -> -15711.77 | R80: =-R77*$F$80 -> -16562.77 | ... W80: =-W77*$F$80 -> -2952.544
C81: ="Revenue to "&Company_Name -> Revenue to Ultragenyx Pharmaceutical Inc. | E81: $T | K81: =SUM(K77,K80) -> 89056.8 | L81: =SUM(L77,L80) -> 112367.42 | M81: =SUM(M77,M80) -> 137563.4 | N81: =SUM(N77,N80) -> 158116.42 | O81: =SUM(O77,O80) -> 179753.36 | P81: =SUM(P77,P80) -> 195607.73 | Q81: =SUM(Q77,Q80) -> 208742.09 | R81: =SUM(R77,R80) -> 220048.24 | ... W81: =SUM(W77,W80) -> 39226.656
L82: =L81/K81-1 -> 0.26175 | M82: =M81/L81-1 -> 0.22422857 | N82: =N81/M81-1 -> 0.1494076 | O82: =O81/N81-1 -> 0.1368418 | P82: =P81/O81-1 -> 0.088200743 | Q82: =Q81/P81-1 -> 0.067146409 | R82: =R81/Q81-1 -> 0.054163217 | S82: =S81/R81-1 -> 0.28297946 | ... W82: =W81/V81-1 -> -0.31944444
C84: COGS (Revenue Weighted) | E84: $ | G84: =(G77/G9)*G12 -> 2379.2538 | H84: =(H77/H9)*H12 -> 4173.8292 | I84: =(I77/I9)*I12 -> 7378.6244 | J84: =(J77/J9)*J12 -> 12078.877 | K84: =K77*K85 -> 9016.2323 | L84: =L77*L85 -> 12403.594 | M84: =M77*M85 -> 16205.639 | N84: =N77*N85 -> 18843.414 | O84: =O77*O85 -> 20159.555 | P84: =P77*P85 -> 22471.154 | Q84: =Q77*Q85 -> 24214.554 | R84: =R77*R85 -> 25426.927 | ... W84: =W77*W85 -> 4515.8856
C85: % COGS | E85: % | G85: =G84/G77 -> 0.060142918 | H85: =H84/H77 -> 0.075052672 | I85: =I84/I77 -> 0.10446427 | J85: =J84/J77 -> 0.13695804 | K85: =AVERAGE(G85:J85) -> 0.094154473 | L85: =AVERAGE(H85:K85) -> 0.10265736 | M85: =AVERAGE(I85:L85) -> 0.10955853 | N85: =AVERAGE(J85:M85) -> 0.1108321 | O85: =AVERAGE(K85:N85) -> 0.10430062 | P85: =AVERAGE(L85:O85) -> 0.10683715 | Q85: =AVERAGE(M85:P85) -> 0.1078821 | R85: =AVERAGE(N85:Q85) -> 0.10746299 | ... W85: =AVERAGE(S85:V85) -> 0.10706428
B87: EVKEEZA | Q87: LOE
C89: ULTRAGENYX TERRITORIES
C90: HoFH (eligible) | E90: # | G90: 2200 | H90: 2250 | I90: 2300 | J90: 2350 | K90: =J90*(1+K91) -> 2538 | L90: =K90*(1+L91) -> 2741.04 | M90: =L90*(1+M91) -> 2960.3232 | N90: =M90*(1+N91) -> 3197.1491 | O90: =N90*(1+O91) -> 3452.921 | P90: =O90*(1+P91) -> 3729.1547 | Q90: =P90*(1+Q91) -> 4027.487 | R90: 4000 | S90: =R90*(1+S91) -> 4320 | T90: =S90*(1+T91) -> 4665.6 | U90: =T90*(1+U91) -> 5038.848 | V90: =U90*(1+V91) -> 5441.9558 | W90: =V90*(1+W91) -> 5877.3123
C91: % Growth | E91: % | H91: 0.08 | I91: 0.08 | J91: 0.08 | K91: 0.08 | L91: 0.08 | M91: 0.08 | N91: 0.08 | O91: 0.08 | P91: 0.08 | Q91: 0.08 | R91: 0.08 | S91: 0.08 | T91: 0.08 | U91: 0.08 | V91: 0.08 | W91: 0.08
C93: HoFH - effective penetration RARE Territories
C94: Upside | E94: % | K94: 0.065 | L94: 0.075 | M94: 0.095 | N94: 0.11 | O94: 0.125 | P94: 0.135 | Q94: 0.14 | R94: 0.145 | S94: 0.15 | T94: 0.155 | U94: 0.14 | V94: 0.11 | W94: 0.09
C95: Base | E95: % | K95: 0.055 | L95: 0.055 | M95: 0.07 | N95: 0.085 | O95: 0.09 | P95: 0.095 | Q95: 0.1 | R95: 0.11 | S95: 0.115 | T95: 0.12 | U95: 0.11 | V95: 0.09 | W95: 0.07
C96: Downside | E96: % | K96: 0.045 | L96: 0.04 | M96: 0.05 | N96: 0.06 | O96: 0.07 | P96: 0.075 | Q96: 0.08 | R96: 0.085 | S96: 0.09 | T96: 0.095 | U96: 0.085 | V96: 0.07 | W96: 0.055
C98: Net annual revenue per treated patient (ASP) | E98: $T | G98: 450 | H98: 450 | I98: 450 | J98: 450 | K98: =INDEX($K$99:$W$101,MATCH(Scenario,$C$99:$C$101,0),1) -> 460 | L98: =INDEX($K$99:$W$101,MATCH(Scenario,$C$99:$C$101,0),2) -> 470 | M98: =INDEX($K$99:$W$101,MATCH(Scenario,$C$99:$C$101,0),3) -> 480 | N98: =INDEX($K$99:$W$101,MATCH(Scenario,$C$99:$C$101,0),4) -> 490 | O98: =INDEX($K$99:$W$101,MATCH(Scenario,$C$99:$C$101,0),5) -> 500 | P98: =INDEX($K$99:$W$101,MATCH(Scenario,$C$99:$C$101,0),6) -> 510 | Q98: =INDEX($K$99:$W$101,MATCH(Scenario,$C$99:$C$101,0),7) -> 520 | R98: =INDEX($K$99:$W$101,MATCH(Scenario,$C$99:$C$101,0),8) -> 260 | S98: =INDEX($K$99:$W$101,MATCH(Scenario,$C$99:$C$101,0),9) -> 240 | T98: =INDEX($K$99:$W$101,MATCH(Scenario,$C$99:$C$101,0),10) -> 220 | U98: =INDEX($K$99:$W$101,MATCH(Scenario,$C$99:$C$101,0),11) -> 200 | V98: =INDEX($K$99:$W$101,MATCH(Scenario,$C$99:$C$101,0),12) -> 180 | W98: =INDEX($K$99:$W$101,MATCH(Scenario,$C$99:$C$101,0),13) -> 160
C99: Upside | E99: $T | K99: 483 | L99: 494 | M99: 504 | N99: 514 | O99: 525 | P99: 536 | Q99: 546 | R99: 270 | S99: 250 | T99: 230 | U99: 210 | V99: 190 | W99: 170
C100: Base | E100: $T | K100: 460 | L100: 470 | M100: 480 | N100: 490 | O100: 500 | P100: 510 | Q100: 520 | R100: 260 | S100: 240 | T100: 220 | U100: 200 | V100: 180 | W100: 160
C101: Downside | E101: $T | K101: 414 | L101: 423 | M101: 432 | N101: 441 | O101: 450 | P101: 459 | Q101: 468 | R101: 230 | S101: 210 | T101: 190 | U101: 170 | V101: 150 | W101: 130
C103: Treated patients (calculated) | E103: # | G103: 0 | H103: 0 | I103: 8 | J103: 71 | K103: =INDEX($K$104:$W$106,MATCH(Scenario,$C$104:$C$106,0),1) -> 139.59 | L103: =INDEX($K$104:$W$106,MATCH(Scenario,$C$104:$C$106,0),2) -> 150.7572 | M103: =INDEX($K$104:$W$106,MATCH(Scenario,$C$104:$C$106,0),3) -> 207.22262 | N103: =INDEX($K$104:$W$106,MATCH(Scenario,$C$104:$C$106,0),4) -> 271.75767 | O103: =INDEX($K$104:$W$106,MATCH(Scenario,$C$104:$C$106,0),5) -> 310.76289 | P103: =INDEX($K$104:$W$106,MATCH(Scenario,$C$104:$C$106,0),6) -> 354.26969 | Q103: =INDEX($K$104:$W$106,MATCH(Scenario,$C$104:$C$106,0),7) -> 402.7487 | R103: =INDEX($K$104:$W$106,MATCH(Scenario,$C$104:$C$106,0),8) -> 440 | S103: =INDEX($K$104:$W$106,MATCH(Scenario,$C$104:$C$106,0),9) -> 496.8 | T103: =INDEX($K$104:$W$106,MATCH(Scenario,$C$104:$C$106,0),10) -> 559.872 | U103: =INDEX($K$104:$W$106,MATCH(Scenario,$C$104:$C$106,0),11) -> 554.27328 | V103: =INDEX($K$104:$W$106,MATCH(Scenario,$C$104:$C$106,0),12) -> 489.77603 | W103: =INDEX($K$104:$W$106,MATCH(Scenario,$C$104:$C$106,0),13) -> 411.41186
C104: Upside | E104: # | K104: =K$90*K94 -> 164.97 | L104: =L$90*L94 -> 205.578 | M104: =M$90*M94 -> 281.2307 | N104: =N$90*N94 -> 351.6864 | O104: =O$90*O94 -> 431.61512 | P104: =P$90*P94 -> 503.43588 | Q104: =Q$90*Q94 -> 563.84818 | R104: =R$90*R94 -> 580 | ... W104: =W$90*W94 -> 528.95811
C105: Base | E105: # | K105: =K$90*K95 -> 139.59 | L105: =L$90*L95 -> 150.7572 | M105: =M$90*M95 -> 207.22262 | N105: =N$90*N95 -> 271.75767 | O105: =O$90*O95 -> 310.76289 | P105: =P$90*P95 -> 354.26969 | Q105: =Q$90*Q95 -> 402.7487 | R105: =R$90*R95 -> 440 | ... W105: =W$90*W95 -> 411.41186
C106: Downside | E106: # | K106: =K$90*K96 -> 114.21 | L106: =L$90*L96 -> 109.6416 | M106: =M$90*M96 -> 148.01616 | N106: =N$90*N96 -> 191.82894 | O106: =O$90*O96 -> 241.70447 | P106: =P$90*P96 -> 279.6866 | Q106: =Q$90*Q96 -> 322.19896 | R106: =R$90*R96 -> 340 | ... W106: =W$90*W96 -> 323.25218
C108: Evkeeza Revenue | E108: $T | I108: =I98*I103 -> 3600 | J108: =J98*J103 -> 31950 | K108: 59000 | L108: =L98*L103 -> 70855.884 | M108: =M98*M103 -> 99466.86 | N108: =N98*N103 -> 133161.26 | O108: =O98*O103 -> 155381.44 | P108: =P98*P103 -> 180677.54 | Q108: =Q98*Q103 -> 209429.33 | R108: =R98*R103 -> 114400 | S108: =S98*S103 -> 119232 | ... W108: =W98*W103 -> 65825.898
C109: % Growth | E109: % | J109: =J108/I108-1 -> 7.875 | K109: =K108/J108-1 -> 0.84663537 | L109: =L108/K108-1 -> 0.20094719 | M109: =M108/L108-1 -> 0.4037911 | N109: =N108/M108-1 -> 0.33875 | O109: =O108/N108-1 -> 0.16686675 | P109: =P108/O108-1 -> 0.1628 | Q109: =Q108/P108-1 -> 0.15913313 | ... W109: =W108/V108-1 -> -0.25333333
C111: Transfer Price to Regeneron % Net Sales | E111: $T | F111: 0.3 | I111: =-I108*$F$111 -> -1080 | J111: =-J108*$F$111 -> -9585 | K111: =-K108*$F$111 -> -17700 | L111: =-L108*$F$111 -> -21256.765 | M111: =-M108*$F$111 -> -29840.058 | N111: =-N108*$F$111 -> -39948.377 | O111: =-O108*$F$111 -> -46614.433 | P111: =-P108*$F$111 -> -54203.263 | ... W111: =-W108*$F$111 -> -19747.769
C112: ="Revenue to "&Company_Name -> Revenue to Ultragenyx Pharmaceutical Inc. | E112: $T | I112: =SUM(I108,I111) -> 2520 | J112: =SUM(J108,J111) -> 22365 | K112: =SUM(K108,K111) -> 41300 | L112: =SUM(L108,L111) -> 49599.119 | M112: =SUM(M108,M111) -> 69626.802 | N112: =SUM(N108,N111) -> 93212.881 | O112: =SUM(O108,O111) -> 108767.01 | P112: =SUM(P108,P111) -> 126474.28 | ... W112: =SUM(W108,W111) -> 46078.128
J113: =J112/I112-1 -> 7.875 | K113: =K112/J112-1 -> 0.84663537 | L113: =L112/K112-1 -> 0.20094719 | M113: =M112/L112-1 -> 0.4037911 | N113: =N112/M112-1 -> 0.33875 | O113: =O112/N112-1 -> 0.16686675 | P113: =P112/O112-1 -> 0.1628 | Q113: =Q112/P112-1 -> 0.15913313 | ... W113: =W112/V112-1 -> -0.25333333
C115: COGS (Revenue Weighted) | E115: $ | I115: =(I108/I9)*I12 -> 376.07135 | J115: =(J108/J9)*J12 -> 4375.8092 | K115: =K108*K116 -> 7080 | L115: =L108*L116 -> 7794.1472 | M115: =M108*M116 -> 9946.686 | N115: =N108*N116 -> 11984.513 | O115: =O108*O116 -> 13984.33 | P115: =P108*P116 -> 16260.979 | Q115: =Q108*Q116 -> 18848.639 | R115: =R108*R116 -> 10296 | ... W115: =W108*W116 -> 5924.3308
C116: % COGS | E116: % | I116: =I115/I112 -> 0.14923466 | J116: =J115/J112 -> 0.19565434 | K116: 0.12 | L116: 0.11 | M116: 0.1 | N116: 0.09 | O116: 0.09 | P116: 0.09 | Q116: 0.09 | R116: 0.09 | S116: 0.09 | T116: 0.09 | U116: 0.09 | V116: 0.09 | W116: 0.09
B119: MEPSEVII | U119: LOE
C121: ULTRAGENYX TERRITORIES
C122: MPS VII (eligible) | E122: # | G122: 160 | H122: 161 | I122: 162 | J122: 162 | K122: 163 | L122: 164 | M122: 165 | N122: 166 | O122: 166 | P122: 167 | Q122: 168 | R122: 169 | S122: 170 | T122: 170 | U122: 171 | V122: 172 | W122: 173
C123: % Growth | E123: % | H123: 0.005 | I123: 0.005 | J123: 0.005 | K123: 0.005 | L123: 0.005 | M123: 0.005 | N123: 0.005 | O123: 0.005 | P123: 0.005 | Q123: 0.005 | R123: 0.005 | S123: 0.005 | T123: 0.005 | U123: 0.005 | V123: 0.005 | W123: 0.005
C125: E.U + Japan
C126: MPS VII (eligible) | E126: # | G126: 50 | H126: 50 | I126: 51 | J126: 51 | K126: 51 | L126: 51 | M126: 52 | N126: 52 | O126: 52 | P126: 53 | Q126: 53 | R126: 53 | S126: 54 | T126: 54 | U126: 54 | V126: 54 | W126: 54
C127: % Growth | E127: % | H127: 0.005 | I127: 0.005 | J127: 0.005 | K127: 0.005 | L127: 0.005 | M127: 0.005 | N127: 0.005 | O127: 0.005 | P127: 0.005 | Q127: 0.005 | R127: 0.005 | S127: 0.005 | T127: 0.005 | U127: 0.005 | V127: 0.005 | W127: 0.005
C129: Ultragenyx Territories - effective penetration | E129: %
C130: Upside | E130: % | G130: 0.269 | H130: 0.342 | I130: 0.5 | J130: 0.5 | K130: 0.32 | L130: 0.34 | M130: 0.36 | N130: 0.38 | O130: 0.4 | P130: 0.42 | Q130: 0.43 | R130: 0.44 | S130: 0.45 | T130: 0.46 | U130: 0.4 | V130: =U130-4% -> 0.36 | W130: =V130-4% -> 0.32
C131: Base | E131: % | K131: 0.26 | L131: 0.28 | M131: 0.3 | N131: 0.32 | O131: 0.34 | P131: 0.36 | Q131: 0.37 | R131: 0.38 | S131: 0.39 | T131: 0.4 | U131: 0.36 | V131: =U131-4% -> 0.32 | W131: =V131-4% -> 0.28
C132: Downside | E132: % | K132: 0.21 | L132: 0.22 | M132: 0.24 | N132: 0.26 | O132: 0.28 | P132: 0.3 | Q132: 0.31 | R132: 0.32 | S132: 0.33 | T132: 0.34 | U132: 0.3 | V132: =U132-4% -> 0.26 | W132: =V132-4% -> 0.22
C134: E.U + Japan - effective penetration | E134: %
C135: Upside | E135: % | G135: 0.3 | H135: 0.34 | I135: 0.38 | J135: 0.4 | K135: 0.47 | L135: 0.49 | M135: 0.51 | N135: 0.53 | O135: 0.55 | P135: 0.57 | Q135: 0.58 | R135: 0.59 | S135: 0.6 | T135: 0.6 | U135: 0.54 | V135: =U135-4% -> 0.5 | W135: =V135-4% -> 0.46
C136: Base | E136: % | K136: 0.42 | L136: 0.44 | M136: 0.46 | N136: 0.48 | O136: 0.5 | P136: 0.52 | Q136: 0.53 | R136: 0.54 | S136: 0.55 | T136: 0.55 | U136: 0.5 | V136: =U136-4% -> 0.46 | W136: =V136-4% -> 0.42
C137: Downside | E137: % | K137: 0.36 | L137: 0.38 | M137: 0.4 | N137: 0.42 | O137: 0.44 | P137: 0.46 | Q137: 0.47 | R137: 0.48 | S137: 0.49 | T137: 0.49 | U137: 0.45 | V137: =U137-4% -> 0.41 | W137: =V137-4% -> 0.37
C139: Net annual revenue per treated patient (ASP) | E139: $T | G139: 375 | H139: 375 | I139: 375 | J139: 375 | K139: =INDEX($K$140:$W$142,MATCH(Scenario,$C$140:$C$142),1) -> 382 | L139: =INDEX($K$140:$W$142,MATCH(Scenario,$C$140:$C$142),2) -> 390 | M139: =INDEX($K$140:$W$142,MATCH(Scenario,$C$140:$C$142),3) -> 398 | N139: =INDEX($K$140:$W$142,MATCH(Scenario,$C$140:$C$142),4) -> 406 | O139: =INDEX($K$140:$W$142,MATCH(Scenario,$C$140:$C$142),5) -> 414 | P139: =INDEX($K$140:$W$142,MATCH(Scenario,$C$140:$C$142),6) -> 422 | Q139: =INDEX($K$140:$W$142,MATCH(Scenario,$C$140:$C$142),7) -> 431 | R139: =INDEX($K$140:$W$142,MATCH(Scenario,$C$140:$C$142),8) -> 440 | S139: =INDEX($K$140:$W$142,MATCH(Scenario,$C$140:$C$142),9) -> 448 | T139: =INDEX($K$140:$W$142,MATCH(Scenario,$C$140:$C$142),10) -> 457 | U139: =INDEX($K$140:$W$142,MATCH(Scenario,$C$140:$C$142),11) -> 466 | V139: =INDEX($K$140:$W$142,MATCH(Scenario,$C$140:$C$142),12) -> 240 | W139: =INDEX($K$140:$W$142,MATCH(Scenario,$C$140:$C$142),13) -> 220
...

Sheet Q3
B2: =Company_Name&" - Q3 Financial Results" -> Ultragenyx Pharmaceutical Inc. - Q3 Financial Results
B3: ($ in Thousands Except Per Share and Per Unit Data)
B6: Reported Income Statement and Cash Flow Statement Figures from Q3: | H6: FY25- Q1 | I6: FY25- Q2 | J6: FY25- Q3
C8: Revenue: | H8: 139292 | I8: 166496 | J8: 159933
C9: Annual Revenue Growth Rate: | I9: =I8/H8-1 -> 0.19530196 | J9: =J8/I8-1 -> -0.039418364
C10: Operating Income (EBIT): | H10: -142939 | I10: -107888 | J10: -170890
C11: Annual Operating Margin: | H11: =+H10/H8 -> -1.0261824 | I11: =+I10/I8 -> -0.64799154 | J11: =+J10/J8 -> -1.0685099
C13: Taxes, Excluding Effect of Interest: | H13: -1310 | I13: -947 | J13: -873
C15: Net Operating Profit After Tax (NOPAT): | H15: =SUM(H10,H13) -> -144249 | I15: =SUM(I10,I13) -> -108835 | J15: =SUM(J10,J13) -> -171763
C17: Adjustments for Non-Cash Charges:
C18: Depreciation & Amortization: | H18: 8990 | I18: 8619 | J18: 8606
C19: Deferred Income Taxes: | H19: 0 | I19: 0 | J19: 0
C20: Other Operating Activities: | H20: 32091 | I20: 20030 | J20: 25525
C21: Total Adjustments for Non-Cash Charges: | H21: =SUM(H18:H20) -> 41081 | I21: =SUM(I18:I20) -> 28649 | J21: =SUM(J18:J20) -> 34131
C23: Net Change in Working Capital:
C24: Accounts Receivable: | H24: 10062 | I24: -12653 | J24: 5425
C25: Inventories: | H25: -763 | I25: 208 | J25: -5595
C26: Accounts Payable: | H26: -48454 | I26: -9682 | J26: 45124
C27: Other Liabilities: | H27: -1324 | I27: -2460 | J27: -1278
C28: Total Net Change in Working Capital: | H28: =SUM(H24:H27) -> -40479 | I28: =SUM(I24:I27) -> -24587 | J28: =SUM(J24:J27) -> 43676
C30: Capital Expenditures and Acquisitions: | H30: -1324 | I30: -2460 | J30: -1278
C32: Q3 Unlevered Free Cash Flow: | H32: =SUM(H15,H21,H28,H30) -> -144971 | I32: =SUM(I15,I21,I28,I30) -> -107233 | J32: =SUM(J15,J21,J28,J30) -> -95234

Sheet rNPV
H2: Historical | P2: Projected:
B3: =Ticker&"- Risk-Adjusted Net Present Value Calculation" -> RARE- Risk-Adjusted Net Present Value Calculation | E3: Units: | H3: 44377 | I3: 44742 | J3: 45107 | K3: 45473 | L3: 45838 | M3: 46203 | N3: 46568 | O3: 46934 | P3: 47299 | Q3: =EOMONTH(P3,12) -> 47664 | R3: =EOMONTH(Q3,12) -> 48029 | S3: =EOMONTH(R3,12) -> 48395 | T3: =EOMONTH(S3,12) -> 48760 | U3: =EOMONTH(T3,12) -> 49125 | V3: =EOMONTH(U3,12) -> 49490 | W3: =EOMONTH(V3,12) -> 49856 | X3: =EOMONTH(W3,12) -> 50221 | ... AF3: =EOMONTH(AE3,12) -> 53143
C5: OpEx: | D5: Base
C6: Scenario: | D6: Base | I6: Terminal Value - Multiples Method: | N6: Terminal Value - Perpetuity Growth Method: | S6: UX - 111 | W6: Company Wide
S7: Risk-Adjusted Net Present Value - Output | W7: Sum of DCF and rNPV Outputs
I8: Median CY 26 TEV / EBITDA of Comps: | L8: =[2]PubComps!S37 -> 14.299154 | N8: Expected Long-Term GDP Growth: | Q8: 0.015
I9: Median CY 26 TEV / EBITDA of Target: | L9: =[2]PubComps!S41 -> 0 | S9: NPV of rFCFs | U9: =NPV(Discount_Rate,J109:V109) -> 735051.07 | W9: UX - 111 | Y9: =U12 -> 7.5343488
W10: DTX - 401 | Y10: =U21 -> 7.9530104
I11: Baseline Terminal EBITDA Multiple: | L11: =INDEX(L12:L14,MATCH(Scenario,I12:I14,0),1) -> 9 | N11: Baseline Terminal FCF Growth Rate: | Q11: =INDEX(Q12:Q14,MATCH(Scenario,N12:N14,0),1) -> -0.015 | S11: Shares Outstanding | U11: =Diluted*Units -> 97560 | W11: DTX - 301 | Y11: =U30 -> 0.46160697
I12: Upside | L12: 10 | N12: Upside | Q12: -0.01 | S12: Implied Price per Share | U12: =U9/U11 -> 7.5343488 | W12: GTX - 102 | Y12: =U39 -> 11.027859
C13: Company Name: | E13: Name | G13: =Company_Name -> Ultragenyx Pharmaceutical Inc. | I13: Base | L13: 9 | N13: Base | Q13: -0.015 | W13: DCF | Y13: =L38 -> 26.602275
C14: Ticker: | E14: Name | G14: =Ticker -> RARE | I14: Downside | L14: 8 | N14: Downside | Q14: -0.02 | W14: Total Implied Share Price | Y14: =SUM(Y9:Y13) -> 53.5791
C15: Current Share Price: | E15: $ / Share | G15: 23.5 | S15: DTX - 401 | W15: Premium / (Discount) to Current: | Y15: =Y14/G15-1 -> 1.2799617
C16: Diluted Shares Outstanding: | E16: M Shares | G16: =Diluted -> 97.56 | S16: Risk-Adjusted Net Present Value - Output
I17: Baseline Terminal Value: | L17: =L11*(W86/Units) -> 1494.3886 | N17: Baseline Terminal Value: | Q17: =(W86*(1+Terminal_Growth_Rate)/(Discount_Rate-Q11)*(1+Discount_Rate)^0.5)/Units -> 1484.0401
C18: Effective Tax Rate: | E18: % | G18: 0.12 | I18: Implied Terminal FCF Growth Rate: | L18: =(W83*(1+Discount_Rate)^0.5*Discount_Rate - L17) / (W83*(1+Discount_Rate)^0.5 + L17) -> 0.085621653 | N18: Implied Terminal EBITDA Multiple: | Q18: =Q17/(W86/Units) -> 8.9376754 | S18: NPV of rFCFs | U18: =NPV(Discount_Rate,J132:W132) -> 775895.69
C19: Discount Rate (WACC): | E19: % | G19: 0.1
I20: (+) Present Value of Terminal Value: | L20: =L17/((1+Discount_Rate)^12) -> 476.15828 | N20: (+) Present Value of Terminal Value: | Q20: =Q17/((1+Discount_Rate)^12) -> 472.8609 | S20: Shares Outstanding | U20: =Diluted*Units -> 97560
C21: Current Equity Value: | G21: =G15*G16 -> 2292.66 | I21: (+) Present Value of UFCF: | L21: =NPV(Discount_Rate,L83:W83)/Units -> 1952.4306 | N21: (+) Present Value of UFCF: | Q21: =NPV(Discount_Rate,L83:W83)/Units -> 1952.4306 | S21: Implied Price per Share | U21: =U18/U20 -> 7.9530104
C22: (-) Cash & Investments: | G22: =-Model!J92/Units -> -173.729 | I22: Implied Enterprise Value: | L22: =SUM(L20:L21) -> 2428.5889 | N22: Implied Enterprise Value: | Q22: =SUM(Q20:Q21) -> 2425.2915
C23: (-) Net Operating Losses: | G23: 0
C24: (+) Debt & Finance Leases: | G24: 0 | I24: % of implied TEV from Terminal Value: | L24: =L20/L22 -> 0.19606376 | N24: % of implied TEV from Terminal Value: | Q24: =Q20/Q22 -> 0.19497075 | S24: DTX - 301
C25: (+) Preferred Stock: | G25: 0 | S25: Risk-Adjusted Net Present Value - Output
C26: (+) Operating Leases: | G26: 0 | I26: (+) Cash and Investments: | L26: =-G22 -> 173.729 | N26: (+) Cash and Investments: | Q26: =L26 -> 173.729
C27: (+) Noncontrolling Interests: | G27: 7 | I27: (+) Net Operating Losses: | L27: =-G23 -> 0 | N27: (+) Net Operating Losses: | Q27: =L27 -> 0 | S27: NPV of rFCFs | U27: =NPV(Discount_Rate,J154:X154) -> 45034.376
C28: (+) Unfunded Pensions: | G28: 0 | I28: (-)Debt and Finance Leases: | L28: =-G24 -> 0 | N28: (-)Debt and Finance Leases: | Q28: =L28 -> 0
C29: Current Enterprise Value: | G29: =SUM(G21:G28) -> 2125.931 | I29: (-)Preferred Stock: | L29: =-G25 -> 0 | N29: (-)Preferred Stock: | Q29: =L29 -> 0 | S29: Shares Outstanding | U29: =Diluted*Units -> 97560
I30: (-) Operating Leases: | L30: =-G26 -> 0 | N30: (-) Operating Leases: | Q30: =L30 -> 0 | S30: Implied Price per Share | U30: =U27/U29 -> 0.46160697
I31: (-) Noncontrolling Interests: | L31: =-G27 -> -7 | N31: (-) Noncontrolling Interests: | Q31: =L31 -> -7
I32: (-)Unfunded Pensions: | L32: =-G28 -> 0 | N32: (-)Unfunded Pensions: | Q32: =L32 -> 0
S33: GTX - 102
I34: Implied Equity Value: | L34: =L22+SUM(L26:L32) -> 2595.3179 | N34: Implied Equity Value: | Q34: =SUM(Q22:Q33) -> 2592.2155 | S34: Risk-Adjusted Net Present Value - Output
I36: Diluted Shares Outstanding: | L36: =_xlfn.SINGLE(Diluted) -> 97.56 | N36: Diluted Shares Outstanding: | Q36: =_xlfn.SINGLE(Diluted) -> 97.56 | S36: NPV of rFCFs | U36: =NPV(Discount_Rate,J177:AF177) -> 1075877.9
I38: Implied Share Price from DCF: | L38: =L34/L36 -> 26.602275 | N38: Implied Share Price from DCF: | Q38: =Q34/Q36 -> 26.570475 | S38: Shares Outstanding | U38: =Diluted*Units -> 97560
I39: Premium / (Discount) to Current: | L39: =L38/G15-1 -> 0.13201169 | N39: Premium / (Discount) to Current: | Q39: =Q38/G15-1 -> 0.1306585 | S39: Implied Price per Share | U39: =U36/U38 -> 11.027859
H41: Historical | P41: Projected:
B42: ="Free Cash Flow - "&Company_Name -> Free Cash Flow - Ultragenyx Pharmaceutical Inc. | E42: Units: | H42: =H3 -> 44377 | I42: =I3 -> 44742 | J42: =J3 -> 45107 | K42: =K3 -> 45473 | L42: =L3 -> 45838 | M42: =M3 -> 46203 | N42: =N3 -> 46568 | O42: =O3 -> 46934 | ... X42: =X3 -> 50221 | Y42: =EOMONTH(X42,12) -> 50586 | Z42: =EOMONTH(Y42,12) -> 50951 | AA42: =EOMONTH(Z42,12) -> 51317 | AB42: =EOMONTH(AA42,12) -> 51682 | AC42: =EOMONTH(AB42,12) -> 52047 | AD42: =EOMONTH(AC42,12) -> 52412 | AE42: =EOMONTH(AD42,12) -> 52778 | AF42: =EOMONTH(AE42,12) -> 53143
B43: ASSUMPTIONS
C45: COGS % Revenue | D45: 0.12
C47: Company - Wide
C48: Cost of sales | E48: $T | H48: =-Drivers!G12 -> -16008 | I48: =-Drivers!H12 -> -28320 | J48: =-Drivers!I12 -> -45209 | K48: =-Drivers!J12 -> -76728 | L48: =-Drivers!K12 -> -109000 | M48: =-Drivers!L12 -> -89175.452 | N48: =-Drivers!M12 -> -143697.84 | O48: =-Drivers!N12 -> -143797.99 | ... AF48: =-Drivers!AE12 -> -97312.718
C49: Selling, general and administrative | E49: $T | H49: =-Drivers!G14 -> -219982 | I49: =-Drivers!H14 -> -278139 | J49: =-Drivers!I14 -> -309799 | K49: =-Drivers!J14 -> -321610 | L49: =-Drivers!K13 -> -349000 | M49: =-Drivers!L13 -> -331550 | N49: =-Drivers!M13 -> -315000 | O49: =-Drivers!N13 -> -290000 | P49: =-Drivers!O13 -> -320000 | Q49: =-Drivers!P14 -> -304000 | R49: =-Drivers!Q14 -> -288800 | S49: =-Drivers!R14 -> -274360 | T49: =-Drivers!S14 -> -260642 | U49: =-Drivers!T14 -> -247609.9 | V49: =-Drivers!U14 -> -235229.4 | W49: =-Drivers!V14 -> -223467.93 | X49: =-Drivers!W14 -> -212294.54 | ... AF49: =-Drivers!AE14 -> -200000
C50: Research and development | E50: $T | H50: =-Drivers!G13 -> -497153 | I50: =-Drivers!H13 -> -705789 | J50: =-Drivers!I13 -> -648449 | K50: =-Drivers!J13 -> -697865 | L50: =-Drivers!K14 -> -750000 | M50: =-Drivers!L14 -> -712500 | N50: =-Drivers!M14 -> -441750 | O50: =-Drivers!N14 -> -273885 | P50: =-Drivers!O14 -> -400000 | Q50: =-Drivers!P13 -> -304000 | R50: =-Drivers!Q13 -> -288800 | S50: =-Drivers!R13 -> -274360 | T50: =-Drivers!S13 -> -260642 | U50: =-Drivers!T13 -> -247609.9 | V50: =-Drivers!U13 -> -235229.4 | W50: =-Drivers!V13 -> -223467.93 | X50: =-Drivers!W13 -> -212294.54 | ... AF50: =-Drivers!AE13 -> -140840.53
C51: Total operating expenses | E51: $T | H51: -733143 | I51: -1012248 | J51: -1003457 | K51: -1096203 | L51: =SUM(L48:L50) -> -1208000 | M51: =SUM(M48:M50) -> -1133225.5 | N51: =SUM(N48:N50) -> -900447.84 | O51: =SUM(O48:O50) -> -707682.99 | P51: =SUM(P48:P50) -> -902047.26 | Q51: =SUM(Q48:Q50) -> -747024.68 | R51: =SUM(R48:R50) -> -836927.31 | S51: -833528.34 | T51: -833528.34 | U51: -833528.34 | V51: -833528.34 | W51: -833528.34 | X51: -833528.34 | Y51: -833528.34 | Z51: -833528.34 | AA51: -833528.34 | AB51: -833528.34 | AC51: -833528.34 | AD51: -833528.34 | AE51: -833528.34 | AF51: -833528.34
C53: Pipeline
C54: Cost of sales | E54: $T | H54: =SUM(H93,H116,H138,H161) -> 0 | I54: =SUM(I93,I116,I138,I161) -> 0 | J54: =SUM(J93,J116,J138,J161) -> 0 | K54: =SUM(K93,K116,K138,K161) -> 0 | L54: =SUM(L93,L116,L138,L161) -> 0 | M54: =SUM(M93,M116,M138,M161) -> -34760.297 | N54: =SUM(N93,N116,N138,N161) -> -66969.108 | O54: =SUM(O93,O116,O138,O161) -> -111408.63 | ... AF54: =SUM(AF93,AF116,AF138,AF161) -> -145906.71
C55: Selling, general and administrative | E55: $T | H55: =SUM(H94,H117,H139,H162) -> 0 | I55: =SUM(I94,I117,I139,I162) -> 0 | J55: =SUM(J94,J117,J139,J162) -> 0 | K55: =SUM(K94,K117,K139,K162) -> -20000 | L55: =SUM(L94,L117,L139,L162) -> -80000 | M55: =SUM(M94,M117,M139,M162) -> -160000 | N55: =SUM(N94,N117,N139,N162) -> -187142.54 | O55: =SUM(O94,O117,O139,O162) -> -126018.14 | ... AF55: =SUM(AF94,AF117,AF139,AF162) -> -10000
C56: Research and development | E56: $T | H56: =SUM(H95,H118,H140,H163) -> 0 | I56: =SUM(I95,I118,I140,I163) -> 0 | J56: =SUM(J95,J118,J140,J163) -> -159075 | K56: =SUM(K95,K118,K140,K163) -> -208251 | L56: =SUM(L95,L118,L140,L163) -> -271159.07 | M56: =SUM(M95,M118,M140,M163) -> -130000 | N56: =SUM(N95,N118,N140,N163) -> -160000 | O56: =SUM(O95,O118,O140,O163) -> -50000 | ... AF56: =SUM(AF95,AF118,AF140,AF163) -> -10000
C57: Total operating expenses | E57: $T
C59: Working capital | E59: $T | H59: =SUM(Model!G94:G96)-SUM(Model!G110:G112) -> -53894 | I59: =SUM(Model!H94:H96)-SUM(Model!H110:H112) -> -113294 | J59: =SUM(Model!I94:I96)-SUM(Model!I110:I112) -> -83625 | K59: =SUM(Model!J94:J96)-SUM(Model!J110:J112) -> -72631 | L59: =SUM(Model!K94:K96)-SUM(Model!K110:K112) -> -49437.128 | M59: =SUM(Model!L94:L96)-SUM(Model!L110:L112) -> 45196.69 | N59: =SUM(Model!M94:M96)-SUM(Model!M110:M112) -> 217246.46 | O59: =SUM(Model!N94:N96)-SUM(Model!N110:N112) -> 330699.48 | ... Q59: =SUM(Model!P94:P96)-SUM(Model!P110:P112) -> 508685.84 | R59: =Drivers!Q9*rNPV!R60 -> 506953.51 | S59: =Drivers!R9*rNPV!S60 -> 416734.32 | T59: =Drivers!S9*rNPV!T60 -> 286034.87 | U59: =Drivers!T9*rNPV!U60 -> 146772.01 | V59: =Drivers!U9*rNPV!V60 -> 118120.33 | W59: =Drivers!V9*rNPV!W60 -> 89829.223 | X59: =Drivers!W9*rNPV!X60 -> 59294.95 | Y59: =Drivers!X9*rNPV!Y60 -> 54134.334 | ... AF59: =Drivers!AE9*rNPV!AF60 -> 54062.621
C60: % Revenue | E60: % | H60: =H59/H69 -> -0.20373847 | I60: =I59/I69 -> -0.32071235 | J60: =J59/J69 -> -0.19483514 | K60: =K59/K69 -> -0.13051169 | L60: =L59/L69 -> -0.077756152 | M60: =M59/M69 -> 0.051465582 | N60: =N59/N69 -> 0.2121407 | O60: =O59/O69 -> 0.29001231 | P60: =P59/P69 -> 0.31013784 | Q60: =AVERAGE(M60:P60) -> 0.21593911 | R60: =Q60-4% -> 0.17593911 | S60: =R60-4% -> 0.13593911 | T60: =S60-4% -> 0.095939109 | U60: =T60-4% -> 0.055939109 | V60: 0.05 | W60: 0.05 | X60: 0.05 | Y60: 0.05 | Z60: 0.05 | AA60: 0.05 | AB60: 0.05 | AC60: 0.05 | AD60: 0.05 | AE60: 0.05 | AF60: 0.05
C62: CapEx | E62: $T | H62: =-Drivers!G370 -> -73093 | I62: =-Drivers!H370 -> -116123 | J62: =-Drivers!I370 -> -44267 | K62: =-Drivers!J370 -> -7491 | L62: =-Drivers!K370 -> -6980 | M62: =-Drivers!L370 -> -6631 | N62: =-Drivers!M370 -> -3150 | O62: =-Drivers!N370 -> -2900 | ... Q62: =-Drivers!P370 -> -3040 | R62: =AVERAGE(H62:Q62) -> -26687.5 | S62: =AVERAGE(I62:R62) -> -22046.95 | T62: =AVERAGE(J62:S62) -> -12639.345 | U62: =AVERAGE(K62:T62) -> -9476.5795 | V62: =AVERAGE(L62:U62) -> -9675.1375 | W62: =AVERAGE(M62:V62) -> -9944.6512 | X62: =AVERAGE(N62:W62) -> -10276.016 | Y62: =AVERAGE(O62:X62) -> -10988.618 | ... AF62: =AVERAGE(V62:AE62) -> -11381.732
C64: D&A | E64: $T | H64: =-Drivers!G385 -> -13239 | I64: =-Drivers!H385 -> -18220 | J64: =-Drivers!I385 -> -26006 | K64: =-Drivers!J385 -> -35543 | L64: =-Drivers!K385 -> -26778.119 | M64: =-Drivers!L385 -> -23395.807 | N64: =-Drivers!M385 -> -20120.143 | O64: =-Drivers!N385 -> -17128.566 | ... Q64: =-Drivers!P385 -> -12614.671 | R64: =AVERAGE(H64:Q64) -> -20772.231 | S64: =AVERAGE(I64:R64) -> -21525.554 | T64: =AVERAGE(J64:S64) -> -21856.109 | U64: =AVERAGE(K64:T64) -> -21441.12 | V64: =AVERAGE(L64:U64) -> -20030.932 | W64: =AVERAGE(M64:V64) -> -19356.214 | X64: =AVERAGE(N64:W64) -> -18952.254 | Y64: =AVERAGE(O64:X64) -> -18835.465 | ... AF64: =AVERAGE(V64:AE64) -> -19542.244
C65: % Revenue | E65: %
B67: COMMERCIAL PRODUCTS
C69: Revenue | E69: $ | H69: =SUM(Drivers!G24,Drivers!G77,Drivers!G108,Drivers!G154,Drivers!G157) -> 264525.4 | I69: =SUM(Drivers!H24,Drivers!H77,Drivers!H108,Drivers!H154,Drivers!H157) -> 353257.36 | J69: =SUM(Drivers!I24,Drivers!I77,Drivers!I108,Drivers!I154,Drivers!I157) -> 429209.02 | K69: =SUM(Drivers!J24,Drivers!J77,Drivers!J108,Drivers!J154,Drivers!J157) -> 556509.54 | L69: =SUM(Drivers!K24,Drivers!K77,Drivers!K108,Drivers!K154,Drivers!K157) -> 635797 | M69: =SUM(Drivers!L24,Drivers!L77,Drivers!L108,Drivers!L154,Drivers!L157) -> 878192.54 | N69: =SUM(Drivers!M24,Drivers!M77,Drivers!M108,Drivers!M154,Drivers!M157) -> 1024067.8 | O69: =SUM(Drivers!N24,Drivers!N77,Drivers!N108,Drivers!N154,Drivers!N157) -> 1140294.6 | ... W69: =SUM(Drivers!V24,Drivers!V77,Drivers!V108,Drivers!V154,Drivers!V157) -> 600559
C71: COGS | E71: $ | H71: =-H69*0.09 -> -23807.286 | I71: =-I69*0.09 -> -31793.163 | J71: =-J69*0.09 -> -38628.812 | K71: =-K69*0.09 -> -50085.859 | L71: =-L69*0.09 -> -57221.73 | M71: =-M69*0.09 -> -79037.328 | N71: =-N69*0.09 -> -92166.101 | O71: =-O69*0.09 -> -102626.52 | ... W71: =-W69*0.09 -> -54050.31
C72: SG&A | E72: $ | H72: =H49-H55 -> -219982 | I72: =I49-I55 -> -278139 | J72: =J49-J55 -> -309799 | K72: =K49-K55 -> -301610 | L72: =L49-L55 -> -269000 | M72: =M49-M55 -> -171550 | N72: =N49-N55 -> -127857.46 | O72: =O49-O55 -> -163981.86 | ... W72: =W49-W55 -> -193467.93
C73: R&D | E73: $ | H73: =H50-H56 -> -497153 | I73: =I50-I56 -> -705789 | J73: =J50-J56 -> -489374 | K73: =K50-K56 -> -489614 | L73: =L50-L56 -> -478840.93 | M73: =M50-M56 -> -582500 | N73: =N50-N56 -> -281750 | O73: =O50-O56 -> -223885 | ... W73: =W50-W56 -> -193467.93
C74: EBIT | E74: $ | H74: =SUM(H69:H73) -> -476416.89 | I74: =SUM(I69:I73) -> -662463.8 | J74: =SUM(J69:J73) -> -408592.79 | K74: =SUM(K69:K73) -> -284800.32 | L74: =SUM(L69:L73) -> -169265.66 | M74: =SUM(M69:M73) -> 45105.208 | N74: =SUM(N69:N73) -> 522294.23 | O74: =SUM(O69:O73) -> 649801.26 | ... W74: =SUM(W69:W73) -> 159572.82
C76: Tax | E76: $ | H76: =Model!G80 -> -1044 | I76: =Model!H80 -> -5696 | J76: =Model!I80 -> 1825 | K76: =Model!J80 -> -1597 | L76: =(L69/Drivers!K$9)*Model!K$80 -> 0 | M76: =(M69/Drivers!L$9)*Model!L$80 -> 0 | N76: =(N69/Drivers!M$9)*Model!M$80 -> -7938.5202 | O76: =(O69/Drivers!N$9)*Model!N$80 -> -24653.043 | P76: =(P69/Drivers!O$9)*Model!O$80 -> -27824.991 | Q76: =(Q69/Drivers!P$9)*Model!P$80 -> -42798.757 | R76: =R74*-Tax_Rate -> -170058.02 | S76: =S74*-Tax_Rate -> -167611.72 | T76: =T74*-Tax_Rate -> -138927.36 | U76: =U74*-Tax_Rate -> -83614.233 | V76: =V74*-Tax_Rate -> -61795.616 | W76: =W74*-Tax_Rate -> -33510.293
C77: NOPAT | E77: $ | H77: =SUM(H74:H76) -> -477460.89 | I77: =SUM(I74:I76) -> -668159.8 | J77: =SUM(J74:J76) -> -406767.79 | K77: =SUM(K74:K76) -> -286397.32 | L77: =SUM(L74:L76) -> -169265.66 | M77: =SUM(M74:M76) -> 45105.208 | N77: =SUM(N74:N76) -> 514355.71 | O77: =SUM(O74:O76) -> 625148.22 | ... W77: =SUM(W74:W76) -> 126062.53
C79: Royalty Expense | E79: $ | H79: =SUM(Drivers!G80,Drivers!G111,Drivers!G160) -> -179.52 | I79: =SUM(Drivers!H80,Drivers!H111,Drivers!H160) -> -231.54714 | J79: =SUM(Drivers!I80,Drivers!I111,Drivers!I160) -> -1421.548 | K79: =SUM(Drivers!J80,Drivers!J111,Drivers!J160) -> -9925.527 | L79: =SUM(Drivers!K80,Drivers!K111,Drivers!K160) -> -24403.95 | M79: =SUM(Drivers!L80,Drivers!L111,Drivers!L160) -> -30152.108 | N79: =SUM(Drivers!M80,Drivers!M111,Drivers!M160) -> -40670.3 | O79: =SUM(Drivers!N80,Drivers!N111,Drivers!N160) -> -52356.301 | ... W79: =SUM(Drivers!V80,Drivers!V111,Drivers!V160) -> -31084.417
C80: Change in Working Capital | E80: $ | H80: =(G$59-H$59)*(H69/Drivers!G$9) -> 53561.807 | I80: =(H$59-I$59)*(I69/Drivers!H$9) -> 55609.703 | J80: =(I$59-J$59)*(J69/Drivers!I$9) -> -29424.873 | K80: =(J$59-K$59)*(K69/Drivers!J$9) -> -10920.989 | L80: =(K$59-L$59)*(L69/Drivers!K$9) -> -21960.168 | M80: =(L$59-M$59)*(M69/Drivers!L$9) -> -111552.63 | N80: =(M$59-N$59)*(N69/Drivers!M$9) -> -146764.7 | O80: =(N$59-O$59)*(O69/Drivers!N$9) -> -80969.756 | ... W80: =(V$59-W$59)*(W69/Drivers!V$9) -> 9457.1004
C81: CapEx | E81: $ | H81: =H$62*(H69/Drivers!G$9) -> -72642.468 | I81: =I$62*(I69/Drivers!H$9) -> -108713.22 | J81: =J$62*(J69/Drivers!I$9) -> -43902.756 | K81: =K$62*(K69/Drivers!J$9) -> -7441.2526 | L81: =L$62*(L69/Drivers!K$9) -> -6608.7272 | M81: =M$62*(M69/Drivers!L$9) -> -7816.503 | N81: =N$62*(N69/Drivers!M$9) -> -2687.0644 | O81: =O$62*(O69/Drivers!N$9) -> -2069.6874 | ... W81: =W$62*(W69/Drivers!V$9) -> -3324.28
C82: D&A | E82: $ | H82: =-H64*(H69/Drivers!G9) -> 13157.397 | I82: =-I64*(I69/Drivers!H9) -> 17057.387 | J82: =-J64*(J69/Drivers!I9) -> 25792.014 | K82: =-K64*(K69/Drivers!J9) -> 35306.961 | L82: =-L64*(L69/Drivers!K9) -> 25353.766 | M82: =-M64*(M69/Drivers!L9) -> 27578.555 | N82: =-N64*(N69/Drivers!M9) -> 17163.212 | O82: =-O64*(O69/Drivers!N9) -> 12224.406 | ... W82: =-W64*(W69/Drivers!V9) -> 6470.3601
C83: Free Cash Flow | E83: $ | H83: =SUM(H77:H82) -> -483563.67 | I83: =SUM(I77:I82) -> -704437.48 | J83: =SUM(J77:J82) -> -455724.96 | K83: =SUM(K77:K82) -> -279378.13 | L83: =SUM(L77:L82) -> -196884.74 | M83: =SUM(M77:M82) -> -76837.483 | N83: =SUM(N77:N82) -> 341396.85 | O83: =SUM(O77:O82) -> 501976.88 | ... W83: =SUM(W77:W82) -> 107581.29
C84: margin | E84: % | H84: =H83/H69 -> -1.8280425 | I84: =I83/I69 -> -1.9941197 | J84: =J83/J69 -> -1.0617786 | K84: =K83/K69 -> -0.50201858 | L84: =L83/L69 -> -0.30966604 | M84: =M83/M69 -> -0.087495031 | N84: =N83/N69 -> 0.33337329 | O84: =O83/O69 -> 0.44021682 | ... W84: =W83/W69 -> 0.17913526
C86: EBITDA | E86: $ | H86: =H74+H82 -> -463259.49 | I86: =I74+I82 -> -645406.41 | J86: =J74+J82 -> -382800.78 | K86: =K74+K82 -> -249493.36 | L86: =L74+L82 -> -143911.89 | M86: =M74+M82 -> 72683.762 | N86: =N74+N82 -> 539457.44 | O86: =O74+O82 -> 662025.67 | ... W86: =W74+W82 -> 166043.18
C87: margin | H87: =H86/H69 -> -1.7512855 | I87: =I86/I69 -> -1.8270148 | J87: =J86/J69 -> -0.89187496 | K87: =K86/K69 -> -0.4483182 | L87: =L86/L69 -> -0.22634881 | M87: =M86/M69 -> 0.082765179 | N87: =N86/N69 -> 0.52677903 | O87: =O86/O69 -> 0.58057422 | ... W87: =W86/W69 -> 0.27648105
B89: =Drivers!B169 -> UX-111 | S89: LOE
C91: Revenue | E91: $ | L91: =Drivers!K211 -> 0 | M91: =Drivers!L211 -> 31512.78 | N91: =Drivers!M211 -> 96838.167 | O91: =Drivers!N211 -> 198684.51 | P91: =Drivers!O211 -> 305114.77 | Q91: =Drivers!P211 -> 426267.18 | R91: =Drivers!Q211 -> 531537.24 | S91: =Drivers!R211 -> 586958.77 | ... V91: =Drivers!U211 -> 406289.84
C93: COGS | E93: $ | L93: =-L91*0.09 -> 0 | M93: =-M91*COGS -> -3781.5336 | N93: =-N91*COGS -> -11620.58 | O93: =-O91*COGS -> -23842.141 | P93: =-P91*COGS -> -36613.773 | Q93: =-Q91*COGS -> -51152.061 | R93: =-R91*COGS -> -63784.469 | S93: =-S91*COGS -> -70435.053 | T93: =-T91*COGS -> -69883.561 | ... V93: =-V91*COGS -> -48754.78
C94: SG&A | E94: $ | K94: -10000 | L94: -30000 | M94: -50000 | N94: =-N91*0.5 -> -48419.083 | O94: =-O91*0.15 -> -29802.677 | P94: -10000 | Q94: -10000 | R94: -10000 | S94: -10000 | T94: -10000 | U94: -10000 | V94: -10000
C95: R&D | E95: $ | J95: -24412 | K95: -41323 | L95: -70700.14 | M95: -15000 | N95: -10000 | O95: -10000 | P95: -10000 | Q95: -10000 | R95: -10000 | S95: -10000 | T95: -10000 | U95: -10000 | V95: -10000
C96: EBIT | E96: $ | J96: =SUM(J91:J95) -> -24412 | K96: =SUM(K91:K95) -> -51323 | L96: =SUM(L91:L95) -> -100700.14 | M96: =SUM(M91:M95) -> -37268.754 | N96: =SUM(N91:N95) -> 26798.503 | O96: =SUM(O91:O95) -> 135039.69 | P96: =SUM(P91:P95) -> 248501 | Q96: =SUM(Q91:Q95) -> 355115.11 | ... V96: =SUM(V91:V95) -> 337535.06
C98: Tax | E98: $ | L98: =(L91/Drivers!K$9)*Model!K$80 -> 0 | M98: =(M91/Drivers!L$9)*Model!L$80 -> 0 | N98: =(N91/Drivers!M$9)*Model!M$80 -> -750.68442 | O98: =(O91/Drivers!N$9)*Model!N$80 -> -4295.5371 | P98: =(P91/Drivers!O$9)*Model!O$80 -> -6860.2577 | Q98: =(Q91/Drivers!P$9)*Model!P$80 -> -13713.646 | R98: =R96*-Tax_Rate -> -94028.082 | S98: =S96*-Tax_Rate -> -104269.98 | T98: =T96*-Tax_Rate -> -103420.68 | U98: =U96*-Tax_Rate -> -90089.288 | V98: =V96*-Tax_Rate -> -70882.362
C99: NOPAT | E99: $ | J99: =SUM(J96:J98) -> -24412 | K99: =SUM(K96:K98) -> -51323 | L99: =SUM(L96:L98) -> -100700.14 | M99: =SUM(M96:M98) -> -37268.754 | N99: =SUM(N96:N98) -> 26047.819 | O99: =SUM(O96:O98) -> 130744.16 | P99: =SUM(P96:P98) -> 241640.74 | Q99: =SUM(Q96:Q98) -> 341401.47 | ... V99: =SUM(V96:V98) -> 266652.69
C101: Royalty Expense | E101: $ | J101: =-SUM(Drivers!I239:I240) -> 0 | K101: =-SUM(Drivers!J239:J240) -> 0 | L101: =-SUM(Drivers!K214:K215) -> 0 | M101: =-SUM(Drivers!L214:L215) -> 2521.0224 | N101: =-SUM(Drivers!M214:M215) -> 7747.0534 | O101: =-SUM(Drivers!N214:N215) -> 14223.754 | P101: =-SUM(Drivers!O214:O215) -> 20995.095 | Q101: =-SUM(Drivers!P214:P215) -> 27239.06 | R101: =-SUM(Drivers!Q214:Q215) -> 32178.04 | S101: =-SUM(Drivers!R214:R215) -> 33843.793 | ... V101: =-SUM(Drivers!U214:U215) -> 20555.35
C102: Change in Working Capital | E102: $ | J102: =(I$59-J$59)*(J91/Drivers!I$9) -> 0 | K102: =(J$59-K$59)*(K91/Drivers!J$9) -> 0 | L102: =(K$59-L$59)*(L91/Drivers!K$9) -> 0 | M102: =(L$59-M$59)*(M91/Drivers!L$9) -> -4002.9191 | N102: =(M$59-N$59)*(N91/Drivers!M$9) -> -13878.402 | O102: =(N$59-O$59)*(O91/Drivers!N$9) -> -14108.14 | P102: =(O$59-P$59)*(P91/Drivers!O$9) -> -8010.7906 | Q102: =(P$59-Q$59)*(Q91/Drivers!P$9) -> -21476.44 | ... V102: =(U$59-V$59)*(V91/Drivers!U$9) -> 4927.554
C103: CapEx | E103: $ | J103: =J$62*(J91/Drivers!I$9) -> 0 | K103: =K$62*(K91/Drivers!J$9) -> 0 | L103: =L$62*(L91/Drivers!K$9) -> 0 | M103: =M$62*(M91/Drivers!L$9) -> -280.48489 | N103: =N$62*(N91/Drivers!M$9) -> -254.09489 | O103: =O$62*(O91/Drivers!N$9) -> -360.62156 | P103: =P$62*(P91/Drivers!O$9) -> -482.69363 | Q103: =Q$62*(Q91/Drivers!P$9) -> -522.81266 | ... V103: =V$62*(V91/Drivers!U$9) -> -1663.943
C104: D&A | E104: $ | J104: =-J$64*(J91/Drivers!I$9) -> 0 | K104: =-K$64*(K91/Drivers!J$9) -> 0 | L104: =-L$64*(L91/Drivers!K$9) -> 0 | M104: =-M$64*(M91/Drivers!L$9) -> 989.62003 | N104: =-N$64*(N91/Drivers!M$9) -> 1622.9922 | O104: =-O$64*(O91/Drivers!N$9) -> 2129.9759 | P104: =-P$64*(P91/Drivers!O$9) -> 2213.9049 | Q104: =-Q$64*(Q91/Drivers!P$9) -> 2169.4441 | ... V104: =-V$64*(V91/Drivers!U$9) -> 3444.9464
C105: Free Cash Flow | E105: $ | J105: =SUM(J99:J104) -> -24412 | K105: =SUM(K99:K104) -> -51323 | L105: =SUM(L99:L104) -> -100700.14 | M105: =SUM(M99:M104) -> -38041.515 | N105: =SUM(N99:N104) -> 21285.367 | O105: =SUM(O99:O104) -> 132629.13 | P105: =SUM(P99:P104) -> 256356.26 | Q105: =SUM(Q99:Q104) -> 348810.72 | ... V105: =SUM(V99:V104) -> 293916.6
C106: margin | E106: % | L106: =L105/L91 -> #DIV/0! | M106: =M105/M91 -> -1.2071774 | N106: =N105/N91 -> 0.21980349 | O106: =O105/O91 -> 0.66753631 | P106: =P105/P91 -> 0.84019615 | Q106: =Q105/Q91 -> 0.8182913 | R106: =R105/R91 -> 0.7245609 | S106: =S105/S91 -> 0.75520066 | ... V106: =V105/V91 -> 0.72341608
C108: Probability of Success | E108: % | J108: 0.8 | K108: 0.8 | L108: 0.8 | M108: 0.8 | N108: 0.8 | O108: 0.8 | P108: 0.8 | Q108: 0.8 | R108: 0.8 | S108: 0.8 | T108: 0.8 | U108: 0.8 | V108: 0.8
C109: rFCF | E109: $ | J109: =J105*J108 -> -19529.6 | K109: =K105*K108 -> -41058.4 | L109: =L105*L108 -> -80560.112 | M109: =M105*M108 -> -30433.212 | N109: =N105*N108 -> 17028.294 | O109: =O105*O108 -> 106103.3 | P109: =P105*P108 -> 205085.01 | Q109: =Q105*Q108 -> 279048.58 | ... V109: =V105*V108 -> 235133.28
C110: margin | M110: =M109/M91 -> -0.9657419 | N110: =N109/N91 -> 0.17584279 | O110: =O109/O91 -> 0.53402905 | P110: =P109/P91 -> 0.67215692 | Q110: =Q109/Q91 -> 0.65463304 | R110: =R109/R91 -> 0.57964872 | S110: =S109/S91 -> 0.60416053 | T110: =T109/T91 -> 0.61668848 | ... V110: =V109/V91 -> 0.57873287
B112: =Drivers!B218 -> DTX - 401 | U112: LOE
C114: Revenue | E114: $ | L114: =Drivers!K260 -> 0 | M114: =Drivers!L260 -> 258156.36 | N114: =Drivers!M260 -> 363316.09 | O114: =Drivers!N260 -> 424658.71 | P114: =Drivers!O260 -> 452395.94 | Q114: =Drivers!P260 -> 443023.37 | R114: =Drivers!Q260 -> 437654.91 | S114: =Drivers!R260 -> 419041.47 | ... W114: =Drivers!V260 -> 380830.7
C116: COGS | E116: $ | L116: =-L114*COGS -> 0 | M116: =-M114*COGS -> -30978.763 | N116: =-N114*COGS -> -43597.931 | O116: =-O114*COGS -> -50959.045 | P116: =-P114*COGS -> -54287.513 | Q116: =-Q114*COGS -> -53162.804 | R116: =-R114*COGS -> -52518.589 | S116: =-S114*COGS -> -50284.976 | ... W116: =-W114*COGS -> -45699.684
C117: SG&A | E117: $ | J117: 0 | K117: -10000 | L117: -30000 | M117: -50000 | N117: =-M114*0.15 -> -38723.454 | O117: =-N114*0.07 -> -25432.126 | P117: -20000 | Q117: -15000 | R117: -10000 | S117: -10000 | T117: -10000 | U117: -10000 | V117: -10000 | W117: -10000
C118: R&D | E118: $ | J118: -72103 | K118: -75340 | L118: -85064.14 | M118: -15000 | N118: -10000 | O118: -10000 | P118: -10000 | Q118: -10000 | R118: -10000 | S118: -10000 | T118: -10000 | U118: -10000 | V118: -10000 | W118: -10000
C119: EBIT | E119: $ | J119: =SUM(J114:J118) -> -72103 | K119: =SUM(K114:K118) -> -85340 | L119: =SUM(L114:L118) -> -115064.14 | M119: =SUM(M114:M118) -> 162177.6 | N119: =SUM(N114:N118) -> 270994.71 | O119: =SUM(O114:O118) -> 338267.54 | P119: =SUM(P114:P118) -> 368108.43 | Q119: =SUM(Q114:Q118) -> 364860.57 | ... W119: =SUM(W114:W118) -> 315131.01
C121: Tax | E121: $ | L121: =(L114/Drivers!K$9)*Model!K$80 -> 0 | M121: =(M114/Drivers!L$9)*Model!L$80 -> 0 | N121: =(N114/Drivers!M$9)*Model!M$80 -> -2816.4074 | O121: =(O114/Drivers!N$9)*Model!N$80 -> -9181.0741 | P121: =(P114/Drivers!O$9)*Model!O$80 -> -10171.755 | Q121: =(Q114/Drivers!P$9)*Model!P$80 -> -14252.718 | R121: =R119*-Tax_Rate -> -76678.627 | S121: =S119*-Tax_Rate -> -73238.863 | T121: =T119*-Tax_Rate -> -71675.137 | U121: =U119*-Tax_Rate -> -68764.814 | V121: =V119*-Tax_Rate -> -67750.458 | W121: =W119*-Tax_Rate -> -66177.513
C122: NOPAT | E122: $ | J122: =SUM(J119:J121) -> -72103 | K122: =SUM(K119:K121) -> -85340 | L122: =SUM(L119:L121) -> -115064.14 | M122: =SUM(M119:M121) -> 162177.6 | N122: =SUM(N119:N121) -> 268178.3 | O122: =SUM(O119:O121) -> 329086.46 | P122: =SUM(P119:P121) -> 357936.67 | Q122: =SUM(Q119:Q121) -> 350607.85 | ... W122: =SUM(W119:W121) -> 248953.5
C124: Royalty Expense | J124: 0 | K124: 0 | L124: 0 | M124: =-Drivers!K263 -> 0 | N124: =-Drivers!L263 -> -2760 | O124: =-Drivers!M263 -> -11349 | P124: =-Drivers!N263 -> -23268 | Q124: =-Drivers!O263 -> -35594 | R124: =-Drivers!P263 -> -42702 | S124: =-Drivers!Q263 -> -43535 | T124: =-Drivers!R263 -> -38180 | ... W124: =-Drivers!U263 -> -20394
C125: Change in Working Capital | E125: $ | J125: =(I$59-J$59)*(J114/Drivers!I$9) -> 0 | K125: =(J$59-K$59)*(K114/Drivers!J$9) -> 0 | L125: =(K$59-L$59)*(L114/Drivers!K$9) -> 0 | M125: =(L$59-M$59)*(M114/Drivers!L$9) -> -32792.379 | N125: =(M$59-N$59)*(N114/Drivers!M$9) -> -52068.798 | O125: =(N$59-O$59)*(O114/Drivers!N$9) -> -30154.059 | P125: =(O$59-P$59)*(P114/Drivers!O$9) -> -11877.659 | Q125: =(P$59-Q$59)*(Q114/Drivers!P$9) -> -22320.66 | ... W125: =(V$59-W$59)*(W114/Drivers!V$9) -> 5997.003
C126: CapEx | E126: $ | J126: =J$62*(J114/Drivers!I$9) -> 0 | K126: =K$62*(K114/Drivers!J$9) -> 0 | L126: =L$62*(L114/Drivers!K$9) -> 0 | M126: =M$62*(M114/Drivers!L$9) -> -2297.7649 | N126: =N$62*(N114/Drivers!M$9) -> -953.30968 | O126: =O$62*(O114/Drivers!N$9) -> -770.77516 | P126: =P$62*(P114/Drivers!O$9) -> -715.69344 | Q126: =Q$62*(Q114/Drivers!P$9) -> -543.36397 | ... W126: =W$62*(W114/Drivers!V$9) -> -2108.0158
C127: D&A | E127: $ | J127: =-J$64*(J114/Drivers!I$9) -> 0 | K127: =-K$64*(K114/Drivers!J$9) -> 0 | L127: =-L$64*(L114/Drivers!K$9) -> 0 | M127: =-M$64*(M114/Drivers!L$9) -> 8107.0824 | N127: =-N$64*(N114/Drivers!M$9) -> 6089.1196 | O127: =-O$64*(O114/Drivers!N$9) -> 4552.508 | P127: =-P$64*(P114/Drivers!O$9) -> 3282.5732 | Q127: =-Q$64*(Q114/Drivers!P$9) -> 2254.723 | ... W127: =-W$64*(W114/Drivers!V$9) -> 4103.0302
C128: Free Cash Flow | E128: $ | J128: =SUM(J122:J127) -> -72103 | K128: =SUM(K122:K127) -> -85340 | L128: =SUM(L122:L127) -> -115064.14 | M128: =SUM(M122:M127) -> 135194.54 | N128: =SUM(N122:N127) -> 218485.31 | O128: =SUM(O122:O127) -> 291365.14 | P128: =SUM(P122:P127) -> 325357.89 | Q128: =SUM(Q122:Q127) -> 294404.55 | ... W128: =SUM(W122:W127) -> 236551.52
...

Sheet WACC
B2: ="WACC Analysis - "&_xlfn.SINGLE(Company_Name) -> WACC Analysis - Ultragenyx Pharmaceutical Inc.
B3: ($ USD in Millions Except Per Share Amounts in USD as Stated)
B5: Discount Rate Calculations - Assumptions:
B6: Risk-Free Rate: | F6: 0.045
B7: Equity Risk Premium: | F7: 0.035
B8: Pre-Tax Cost of Debt: | F8: 0.02532108
B9: Cost of Preferred Stock: | F9: 0
B11: Company Name: | C11: Ticker: | D11: Levered Beta: | E11: (+) Debt & Capital Leases: | G11: (+) Preferred Stock: | I11: Equity Value: | K11: Effective Tax Rate:
B12: Comparable Companies - Unlevered Beta Calculation:
D13: Levered | G13: Preferred | I13: Equity | L13: Unlevered
B14: Name | C14: Ticker | D14: Beta | E14: Debt | F14: % Debt | G14: Stock | H14: % Preferred | I14: Value | J14: % Equity | K14: Tax Rate | L14: Beta
B15: =INDEX(Pub_Comps_Range,MATCH(B$11,Pub_Comps_Params,0),MATCH($C15,Pub_Comps_Tickers,0)) -> Amicus Therapeutics, Inc. | C15: FOLD | D15: =INDEX(Pub_Comps_Range,MATCH(D$11,Pub_Comps_Params,0),MATCH($C15,Pub_Comps_Tickers,0)) -> 1.78 | E15: =INDEX(Pub_Comps_Range,MATCH(E$11,Pub_Comps_Params,0),MATCH($C15,Pub_Comps_Tickers,0)) -> 442 | F15: =E15/(E15+G15+I15) -> 0.12021708 | G15: =INDEX(Pub_Comps_Range,MATCH(G$11,Pub_Comps_Params,0),MATCH($C15,Pub_Comps_Tickers,0)) -> 0 | H15: =G15/(E15+G15+I15) -> 0 | I15: =INDEX(Pub_Comps_Range,MATCH(I$11,Pub_Comps_Params,0),MATCH($C15,Pub_Comps_Tickers,0)) -> 3234.6821 | J15: =$I15/($E15+$G15+$I15) -> 0.87978292 | K15: =INDEX(Pub_Comps_Range,MATCH(K$11,Pub_Comps_Params,0),MATCH($C15,Pub_Comps_Tickers,0)) -> 0.2 | L15: =IFERROR(D15/(1+(E15/I15)*(1-K15)+G15/I15),"N/A") -> 1.6045935
B16: =INDEX(Pub_Comps_Range,MATCH(B$11,Pub_Comps_Params,0),MATCH($C16,Pub_Comps_Tickers,0)) -> GE Healthcare Technologies Inc. | C16: BMRN | D16: =INDEX(Pub_Comps_Range,MATCH(D$11,Pub_Comps_Params,0),MATCH($C16,Pub_Comps_Tickers,0)) -> 1.27 | E16: =INDEX(Pub_Comps_Range,MATCH(E$11,Pub_Comps_Params,0),MATCH($C16,Pub_Comps_Tickers,0)) -> 604 | F16: =E16/(E16+G16+I16) -> 0.053205687 | G16: =INDEX(Pub_Comps_Range,MATCH(G$11,Pub_Comps_Params,0),MATCH($C16,Pub_Comps_Tickers,0)) -> 0 | H16: =G16/(E16+G16+I16) -> 0 | I16: =INDEX(Pub_Comps_Range,MATCH(I$11,Pub_Comps_Params,0),MATCH($C16,Pub_Comps_Tickers,0)) -> 10748.17 | J16: =$I16/($E16+$G16+$I16) -> 0.94679431 | K16: =INDEX(Pub_Comps_Range,MATCH(K$11,Pub_Comps_Params,0),MATCH($C16,Pub_Comps_Tickers,0)) -> 0.234 | L16: =IFERROR(D16/(1+(E16/I16)*(1-K16)+G16/I16),"N/A") -> 1.2175879
B17: =INDEX(Pub_Comps_Range,MATCH(B$11,Pub_Comps_Params,0),MATCH($C17,Pub_Comps_Tickers,0)) -> Sarepta Therapeutics, Inc. | C17: SRPT | D17: =INDEX(Pub_Comps_Range,MATCH(D$11,Pub_Comps_Params,0),MATCH($C17,Pub_Comps_Tickers,0)) -> 1.26 | E17: =INDEX(Pub_Comps_Range,MATCH(E$11,Pub_Comps_Params,0),MATCH($C17,Pub_Comps_Tickers,0)) -> 1260 | F17: =E17/(E17+G17+I17) -> 0.36696692 | G17: =INDEX(Pub_Comps_Range,MATCH(G$11,Pub_Comps_Params,0),MATCH($C17,Pub_Comps_Tickers,0)) -> 0 | H17: =G17/(E17+G17+I17) -> 0 | I17: =INDEX(Pub_Comps_Range,MATCH(I$11,Pub_Comps_Params,0),MATCH($C17,Pub_Comps_Tickers,0)) -> 2173.552 | J17: =$I17/($E17+$G17+$I17) -> 0.63303308 | K17: =INDEX(Pub_Comps_Range,MATCH(K$11,Pub_Comps_Params,0),MATCH($C17,Pub_Comps_Tickers,0)) -> 0.2 | L17: =IFERROR(D17/(1+(E17/I17)*(1-K17)+G17/I17),"N/A") -> 0.8607986
B18: =INDEX(Pub_Comps_Range,MATCH(B$11,Pub_Comps_Params,0),MATCH($C18,Pub_Comps_Tickers,0)) -> PTC Therapeutics, Inc. | C18: PTCT | D18: =INDEX(Pub_Comps_Range,MATCH(D$11,Pub_Comps_Params,0),MATCH($C18,Pub_Comps_Tickers,0)) -> 2.15 | E18: =INDEX(Pub_Comps_Range,MATCH(E$11,Pub_Comps_Params,0),MATCH($C18,Pub_Comps_Tickers,0)) -> 2492 | F18: =E18/(E18+G18+I18) -> 0.67740106 | G18: =INDEX(Pub_Comps_Range,MATCH(G$11,Pub_Comps_Params,0),MATCH($C18,Pub_Comps_Tickers,0)) -> 0 | H18: =G18/(E18+G18+I18) -> 0 | I18: =INDEX(Pub_Comps_Range,MATCH(I$11,Pub_Comps_Params,0),MATCH($C18,Pub_Comps_Tickers,0)) -> 1186.766 | J18: =$I18/($E18+$G18+$I18) -> 0.32259894 | K18: =INDEX(Pub_Comps_Range,MATCH(K$11,Pub_Comps_Params,0),MATCH($C18,Pub_Comps_Tickers,0)) -> 0.2 | L18: =IFERROR(D18/(1+(E18/I18)*(1-K18)+G18/I18),"N/A") -> 0.8022809
B19: =INDEX(Pub_Comps_Range,MATCH(B$11,Pub_Comps_Params,0),MATCH($C19,Pub_Comps_Tickers,0)) -> Travere Therapeutics, Inc. | C19: TVTX | D19: =INDEX(Pub_Comps_Range,MATCH(D$11,Pub_Comps_Params,0),MATCH($C19,Pub_Comps_Tickers,0)) -> 1.08 | E19: =INDEX(Pub_Comps_Range,MATCH(E$11,Pub_Comps_Params,0),MATCH($C19,Pub_Comps_Tickers,0)) -> 329 | F19: =E19/(E19+G19+I19) -> 0.11647064 | G19: =INDEX(Pub_Comps_Range,MATCH(G$11,Pub_Comps_Params,0),MATCH($C19,Pub_Comps_Tickers,0)) -> 0 | H19: =G19/(E19+G19+I19) -> 0 | I19: =INDEX(Pub_Comps_Range,MATCH(I$11,Pub_Comps_Params,0),MATCH($C19,Pub_Comps_Tickers,0)) -> 2495.7461 | J19: =$I19/($E19+$G19+$I19) -> 0.88352936 | K19: =INDEX(Pub_Comps_Range,MATCH(K$11,Pub_Comps_Params,0),MATCH($C19,Pub_Comps_Tickers,0)) -> 0.2 | L19: =IFERROR(D19/(1+(E19/I19)*(1-K19)+G19/I19),"N/A") -> 0.97696935
B20: =INDEX(Pub_Comps_Range,MATCH(B$11,Pub_Comps_Params,0),MATCH($C20,Pub_Comps_Tickers,0)) -> CareDx, Inc | C20: CPRX | D20: =INDEX(Pub_Comps_Range,MATCH(D$11,Pub_Comps_Params,0),MATCH($C20,Pub_Comps_Tickers,0)) -> 2.56 | E20: =INDEX(Pub_Comps_Range,MATCH(E$11,Pub_Comps_Params,0),MATCH($C20,Pub_Comps_Tickers,0)) -> 2.9 | F20: =E20/(E20+G20+I20) -> 0.0010121313 | G20: =INDEX(Pub_Comps_Range,MATCH(G$11,Pub_Comps_Params,0),MATCH($C20,Pub_Comps_Tickers,0)) -> 0 | H20: =G20/(E20+G20+I20) -> 0 | I20: =INDEX(Pub_Comps_Range,MATCH(I$11,Pub_Comps_Params,0),MATCH($C20,Pub_Comps_Tickers,0)) -> 2862.341 | J20: =$I20/($E20+$G20+$I20) -> 0.99898787 | K20: =INDEX(Pub_Comps_Range,MATCH(K$11,Pub_Comps_Params,0),MATCH($C20,Pub_Comps_Tickers,0)) -> 0.239 | L20: =IFERROR(D20/(1+(E20/I20)*(1-K20)+G20/I20),"N/A") -> 2.5580277
B22: Median: | D22: =MEDIAN(D15:D19) -> 1.27 | E22: =MEDIAN(E15:E19) -> 604 | F22: =MEDIAN(F15:F19) -> 0.12021708 | G22: =MEDIAN(G15:G19) -> 0 | H22: =MEDIAN(H15:H19) -> 0 | I22: =MEDIAN(I15:I19) -> 2495.7461 | J22: =MEDIAN(J15:J19) -> 0.87978292 | K22: =MEDIAN(K15:K19) -> 0.2 | L22: =MEDIAN(L15:L19) -> 0.97696935
B24: =Company_Name -> Ultragenyx Pharmaceutical Inc. | C24: =Ticker -> RARE | D24: =INDEX(Pub_Comps_Range,MATCH(D$11,Pub_Comps_Params,0),MATCH($C24,Pub_Comps_Tickers,0)) -> 2.24 | E24: =INDEX(Pub_Comps_Range,MATCH(E$11,Pub_Comps_Params,0),MATCH($C24,Pub_Comps_Tickers,0)) -> 0 | F24: =E24/($E24+$G24+$I24) -> 0 | G24: =INDEX(Pub_Comps_Range,MATCH(G$11,Pub_Comps_Params,0),MATCH($C24,Pub_Comps_Tickers,0)) -> 0 | H24: =G24/($E24+$G24+$I24) -> 0 | I24: =INDEX(Pub_Comps_Range,MATCH(I$11,Pub_Comps_Params,0),MATCH($C24,Pub_Comps_Tickers,0)) -> 2322.1817 | J24: =I24/($E24+$G24+$I24) -> 1 | K24: 0.132 | L24: =IFERROR(D24/(1+(E24/I24)*(1-K24)+G24/I24),"N/A") -> 2.24
B26: =TEXT(Company_Name,"")& " - Levered Beta & WACC Calculation:" -> Ultragenyx Pharmaceutical Inc. - Levered Beta & WACC Calculation:
D27: Unlevered | G27: Preferred | I27: Equity | L27: Levered
C28: Ticker | D28: Beta | E28: Debt | F28: % Debt | G28: Stock | H28: % Preferred | I28: Value | J28: % Equity | K28: Tax Rate | L28: Beta
B29: Current Capital Structure: | C29: =C24 -> RARE | D29: =L24 -> 2.24 | E29: 5461 | F29: 0.033001557 | G29: 0 | H29: 0 | I29: 160016.04 | J29: 0.96699844 | K29: 0.132 | L29: =D29*(1+E29/I29*(1-K29)+G29/I29) -> 2.3063554
B30: "Optimal" Capital Structure: | D30: =L22 -> 0.97696935 | E30: =(E29+I29)*F30 -> 19893.167 | F30: =F22 -> 0.12021708 | G30: 0 | H30: 0 | I30: =(I29+E29)*J30 -> 145583.87 | J30: =J22 -> 0.87978292 | K30: 0.132 | L30: =D30*(1+E30/I30*(1-K30)+G30/I30) -> 1.0928448
B32: Cost of Equity Based on Comparables, Current Capital Structure: | L32: =Risk_Free_Rate+Equity_Risk_Premium*L29 -> 0.12572244
B33: Cost of Equity Based on Comparables, "Optimal" Capital Structure: | L33: =Risk_Free_Rate+Equity_Risk_Premium*L30 -> 0.083249567
B34: Cost of Equity Based on Historical Beta: | L34: =Risk_Free_Rate+Equity_Risk_Premium*D24 -> 0.1234
B36: WACC, Current Capital Structure: | L36: =L32*J29+Cost_of_Debt*(1-K29)*F29+Cost_of_Preferred*H29 -> 0.12229873
B37: WACC, "Optimal" Capital Structure: | L37: =L33*J30+Cost_of_Debt*(1-K30)*F30+Cost_of_Preferred*H30 -> 0.075883762
B38: WACC, Current Capital Structure and Historical Cost of Equity: | L38: =L34*J29+Cost_of_Debt*(1-K29)*F29+Cost_of_Preferred*H29 -> 0.12005294
B40: Average WACC Produced by All Methods: | L40: =AVERAGE(L36:L38) -> 0.10607848

Sheet Valsum
B2: ="Valuation Summary - "&Company_Name -> Valuation Summary - Ultragenyx Pharmaceutical Inc.
B3: ($ USD in Millions Except Per Share Amounts in USD as Stated)
B5: ="Valuation Statistics - "&TEXT(Company_Name,"") -> Valuation Statistics - Ultragenyx Pharmaceutical Inc. | C5: Range of Valuation Multiples / Premiums | I5: Implied Per-Share Value Range
D7: 75th | F7: 25th | H7: Applicable | J7: 25th | L7: 75th
C8: Maximum | D8: Percentile | E8: Median | F8: Percentile | G8: Minimum | H8: Company | I8: Minimum | J8: Percentile | K8: Median | L8: Percentile | M8: Maximum
B9: Methodology Name | C9: Multiple | D9: Multiple | E9: Multiple | F9: Multiple | G9: Multiple | H9: Figure | I9: Multiple | J9: Multiple | K9: Multiple | L9: Multiple | M9: Multiple
B11: Public Company Comparables:
B12: LTM TEV / Revenue: | C12: {=TRANSPOSE(PubComps!N34:V38)} -> 5.8962067 | D12: 5.2155071 | E12: 3.4784195 | F12: 1.6291963 | G12: 1.0702661 | H12: {=TRANSPOSE(PubComps!N21:V21)} -> 560.23 | I12: =(I34+SUM($E$33:$E$39))/$E$42 -> 7.0558646 | J12: =(J34+SUM($E$33:$E$39))/$E$42 -> 10.265474 | K12: =(K34+SUM($E$33:$E$39))/$E$42 -> 20.884481 | L12: =(L34+SUM($E$33:$E$39))/$E$42 -> 30.859558 | M12: =(M34+SUM($E$33:$E$39))/$E$42 -> 34.768418
B13: ="CY "&TEXT(EOMONTH(Hist_Year,12),"YY")&" TEV / Revenue:" -> CY 25 TEV / Revenue: | C13: 5.9060244 | D13: 5.666591 | E13: 5.4271576 | F13: 4.2677447 | G13: 3.1083318 | H13: 673 | I13: =(I35+SUM($E$33:$E$39))/$E$42 -> 22.352217 | J13: =(J35+SUM($E$33:$E$39))/$E$42 -> 30.350217 | K13: =(K35+SUM($E$33:$E$39))/$E$42 -> 38.348217 | L13: =(L35+SUM($E$33:$E$39))/$E$42 -> 39.999905 | M13: =(M35+SUM($E$33:$E$39))/$E$42 -> 41.651593
B14: ="CY "&TEXT(EOMONTH(Hist_Year,24),"YY")&" TEV / Revenue:" -> CY 26 TEV / Revenue: | C14: 5.5507026 | D14: 4.3761929 | E14: 3.268504 | F14: 2.2367003 | G14: 1.6480868 | H14: 745 | I14: =(I36+SUM($E$33:$E$39))/$E$42 -> 13.495281 | J14: =(J36+SUM($E$33:$E$39))/$E$42 -> 17.990126 | K14: =(K36+SUM($E$33:$E$39))/$E$42 -> 25.869316 | L14: =(L36+SUM($E$33:$E$39))/$E$42 -> 34.32799 | M14: =(M36+SUM($E$33:$E$39))/$E$42 -> 43.29693
B15: LTM TEV / EBITDA: | C15: 74.534544 | D15: 29.046088 | E15: 10.759602 | F15: 6.3951731 | G15: 2.6728924 | H15: -535.973 | I15: =(I37+SUM($E$33:$E$39))/$E$42 -> -13.774325 | J15: =(J37+SUM($E$33:$E$39))/$E$42 -> -34.22371 | K15: =(K37+SUM($E$33:$E$39))/$E$42 -> -58.200912 | L15: =(L37+SUM($E$33:$E$39))/$E$42 -> -158.66281 | M15: =(M37+SUM($E$33:$E$39))/$E$42 -> -408.5663
B16: ="CY "&TEXT(EOMONTH(Hist_Year,12),"YY")&" TEV / EBITDA:" -> CY 25 TEV / EBITDA: | C16: 44.333534 | D16: 29.930265 | E16: 15.526997 | F16: 15.216953 | G16: 14.906909 | H16: -508.22188 | I16: =(I38+SUM($E$33:$E$39))/$E$42 -> -76.745 | J16: =(J38+SUM($E$33:$E$39))/$E$42 -> -78.360121 | K16: =(K38+SUM($E$33:$E$39))/$E$42 -> -79.975241 | L16: =(L38+SUM($E$33:$E$39))/$E$42 -> -155.00657 | M16: =(M38+SUM($E$33:$E$39))/$E$42 -> -230.03789
B17: ="CY "&TEXT(EOMONTH(Hist_Year,24),"YY")&" TEV / EBITDA:" -> CY 26 TEV / EBITDA: | C17: 48.091854 | D17: 20.675825 | E17: 13.125439 | F17: 9.7785333 | G17: 7.5513216 | H17: -364.82964 | I17: =(I39+SUM($E$33:$E$39))/$E$42 -> -27.328526 | J17: =(J39+SUM($E$33:$E$39))/$E$42 -> -35.657276 | K17: =(K39+SUM($E$33:$E$39))/$E$42 -> -48.173168 | L17: =(L39+SUM($E$33:$E$39))/$E$42 -> -76.408148 | M17: =(M39+SUM($E$33:$E$39))/$E$42 -> -178.93152
B18: LTM P / E: | C18: 20.669558 | D18: 16.869804 | E18: 13.07005 | F18: 7.3251489 | G18: 1.5802477 | H18: -569.183 | I18: =(I40+SUM($E$33:$E$39))/$E$42 -> -8.309503 | J18: =(J40+SUM($E$33:$E$39))/$E$42 -> -41.826315 | K18: =(K40+SUM($E$33:$E$39))/$E$42 -> -75.343126 | L18: =(L40+SUM($E$33:$E$39))/$E$42 -> -97.511589 | M18: =(M40+SUM($E$33:$E$39))/$E$42 -> -119.68005
B19: ="CY "&TEXT(EOMONTH(Hist_Year,12),"YY")&" P / E:" -> CY 25 P / E: | C19: 20.433783 | D19: 19.289409 | E19: 18.145034 | F19: 17.000659 | G19: 15.856285 | H19: -586.93659 | I19: =(I41+SUM($E$33:$E$39))/$E$42 -> -94.483997 | J19: =(J41+SUM($E$33:$E$39))/$E$42 -> -101.36874 | K19: =(K41+SUM($E$33:$E$39))/$E$42 -> -108.25348 | L19: =(L41+SUM($E$33:$E$39))/$E$42 -> -115.13822 | M19: =(M41+SUM($E$33:$E$39))/$E$42 -> -122.02296
B20: ="CY "&TEXT(EOMONTH(Hist_Year,24),"YY")&" P / E:" -> CY 26 P / E: | C20: 40.433526 | D20: 34.188303 | E20: 14.770238 | F20: 12.527005 | G20: 11.500275 | H20: -451.2666 | I20: =(I42+SUM($E$33:$E$39))/$E$42 -> -52.284902 | J20: =(J42+SUM($E$33:$E$39))/$E$42 -> -57.034069 | K20: =(K42+SUM($E$33:$E$39))/$E$42 -> -67.410209 | L20: =(L42+SUM($E$33:$E$39))/$E$42 -> -157.22903 | M20: =(M42+SUM($E$33:$E$39))/$E$42 -> -186.11649
B29: Discounted Cash Flow Analysis:
B30: (9.9% - 11.9% WACC, 5.5% - 8.5% Free Cash Flow Growth Rate
B32: Implied Enterprise Value: | E32: =rNPV!G21 -> 2292.66
B33: (+) Cash and Investments: | E33: =[1]DCF!L29 -> 88.775
B34: (+) Net Operating Losses: | E34: =[1]DCF!L30 -> 0 | G34: Enterprise Value --> | I34: =G12*$H12 -> 599.59515 | J34: =F12*$H12 -> 912.72467 | K34: =E12*$H12 -> 1948.715 | L34: =D12*$H12 -> 2921.8835 | M34: =C12*$H12 -> 3303.2319
B35: (-)Debt and Finance Leases: | E35: =[1]DCF!L31 -> 0 | G35: Enterprise Value --> | I35: =G13*$H13 -> 2091.9073 | J35: =F13*$H13 -> 2872.1922 | K35: =E13*$H13 -> 3652.477 | L35: =D13*$H13 -> 3813.6157 | M35: =C13*$H13 -> 3974.7544
B36: (-)Preferred Stock: | E36: =[1]DCF!L32 -> 0 | G36: Enterprise Value --> | I36: =G14*$H14 -> 1227.8247 | J36: =F14*$H14 -> 1666.3417 | K36: =E14*$H14 -> 2435.0355 | L36: =D14*$H14 -> 3260.2637 | M36: =C14*$H14 -> 4135.2734
B37: (-) Operating Leases: | E37: =[1]DCF!L33 -> 0 | G37: Enterprise Value --> | I37: =G15*$H15 -> -1432.5982 | J37: =F15*$H15 -> -3427.6401 | K37: =E15*$H15 -> -5766.856 | L37: =D15*$H15 -> -15567.919 | M37: =C15*$H15 -> -39948.503
B38: (-) Noncontrolling Interests: | E38: =[1]DCF!L34 -> 0 | G38: Enterprise Value --> | I38: =G16*$H16 -> -7576.0172 | J38: =F16*$H16 -> -7733.5884 | K38: =E16*$H16 -> -7891.1595 | L38: =D16*$H16 -> -15211.216 | M38: =C16*$H16 -> -22531.272
B39: (-)Unfunded Pensions: | E39: =[1]DCF!L35 -> 0 | G39: Enterprise Value --> | I39: =G17*$H17 -> -2754.946 | J39: =F17*$H17 -> -3567.4988 | K39: =E17*$H17 -> -4788.5493 | L39: =D17*$H17 -> -7543.1539 | M39: =C17*$H17 -> -17545.334
B40: Implied Equity Value: | E40: =SUM(E32:E39) -> 2381.435 | G40: Equity Value --> | I40: =G18*$H18 -> -899.45011 | J40: =F18*$H18 -> -4169.3503 | K40: =E18*$H18 -> -7439.2504 | L40: =D18*$H18 -> -9602.0056 | M40: =C18*$H18 -> -11764.761
G41: Equity Value --> | I41: =G19*$H19 -> -9306.6337 | J41: =F19*$H19 -> -9978.3091 | K41: =E19*$H19 -> -10649.984 | L41: =D19*$H19 -> -11321.66 | M41: =C19*$H19 -> -11993.335
B42: Diluted Shares Outstanding: | E42: =Diluted -> 97.56 | G42: Equity Value --> | I42: =G20*$H20 -> -5189.69 | J42: =F20*$H20 -> -5653.0187 | K42: =E20*$H20 -> -6665.315 | L42: =D20*$H20 -> -15428.039 | M42: =C20*$H20 -> -18246.3
B44: Implied Share Price from DCF: | E44: =E40/E42 -> 24.409953 | G44: Enterprise Value --> | I44: =+G23*$H23 -> 0 | J44: =H23*F23 -> 0 | K44: =H23*E23 -> 0 | L44: =H23*D23 -> 0 | M44: =H23*C23 -> 0
B45: Premium / (Discount) to Current: | E45: =E44/Share_Price-1 -> 0.031697077 | G45: Enterprise Value --> | I45: =+G24*$H24 -> 0 | J45: =H24*F24 -> 0 | K45: =H24*E24 -> 0 | L45: =H24*D24 -> 0 | M45: =H24*C24 -> 0

Sheet PubComps
B2: Comparable Companies – Medical Device and Imaging Technology
B3: ($ USD in Millions Except Per Share Amounts in USD as Stated)
B5: Company Name: | C5: Ticker: | D5: Share Price: | E5: Total Diluted Shares: | F5: Equity Value: | G5: Levered Beta: | H5: Effective Tax Rate: | I5: (-) Cash & Cash-Equivalents: | J5: (+) Debt & Capital Leases: | K5: (+) Preferred Stock: | L5: (+) Noncontrolling Interests: | M5: Enterprise Value: | N5: LTM Revenue: | O5: 2025-12-31 Revenue: | P5: 2026-12-31 Revenue: | Q5: LTM EBITDA: | R5: 2025-12-31 EBITDA: | S5: 2026-12-31 EBITDA: | T5: LTM Reported Net Income: | U5: 2025-12-31 Reported Net Income: | V5: 2026-12-31 Reported Net Income: | W5: Year 1 Projected Revenue Growth: | X5: Year 1 Projected EBITDA Growth: | Y5: LTM EBITDA Margin: | Z5: 2025-12-31 EBITDA Margin: | AA5: 2026-12-31 EBITDA Margin:
B6: Operating Statistics: | F6: Capitalization | W6: Projected | X6: Projected
D7: Share | E7: Diluted | F7: Equity | L7: Other & | M7: Enterprise | N7: Revenue | Q7: EBITDA | T7: Net Income | W7: Revenue | X7: EBITDA | Y7: EBITDA Margin
B8: Company Name | C8: Ticker | D8: Price | E8: Shares | F8: Value | G8: Beta | H8: Tax Rate | I8: Cash | J8: Debt | K8: Preferred | L8: NCI | M8: Value | N8: LTM | O8: 46022 | P8: =EOMONTH(O8,12) -> 46387 | Q8: =$N$8 -> LTM | R8: =+$O$8 -> 46022 | S8: =+$P$8 -> 46387 | T8: =$N$8 -> LTM | U8: =+$O$8 -> 46022 | V8: =+$P$8 -> 46387 | W8: Growth | X8: Growth | Y8: =$N$8 -> LTM | Z8: =+$O$8 -> 46022 | AA8: =+$P$8 -> 46387
B9: =INDEX(Pub_Comps_Range,MATCH(B$5,Pub_Comps_Params,0),MATCH($C9,Pub_Comps_Tickers,0)) -> Amicus Therapeutics, Inc. | C9: FOLD | D9: =INDEX(Pub_Comps_Range,MATCH(D$5,Pub_Comps_Params,0),MATCH($C9,Pub_Comps_Tickers,0)) -> 14.31 | E9: =INDEX(Pub_Comps_Range,MATCH(E$5,Pub_Comps_Params,0),MATCH($C9,Pub_Comps_Tickers,0)) -> 226.04347 | F9: =INDEX(Pub_Comps_Range,MATCH(F$5,Pub_Comps_Params,0),MATCH($C9,Pub_Comps_Tickers,0)) -> 3234.6821 | G9: =INDEX(Pub_Comps_Range,MATCH(G$5,Pub_Comps_Params,0),MATCH($C9,Pub_Comps_Tickers,0)) -> 1.78 | H9: =INDEX(Pub_Comps_Range,MATCH(H$5,Pub_Comps_Params,0),MATCH($C9,Pub_Comps_Tickers,0)) -> 0.2 | I9: =INDEX(Pub_Comps_Range,MATCH(I$5,Pub_Comps_Params,0),MATCH($C9,Pub_Comps_Tickers,0)) -> -263 | J9: =INDEX(Pub_Comps_Range,MATCH(J$5,Pub_Comps_Params,0),MATCH($C9,Pub_Comps_Tickers,0)) -> 442 | K9: =INDEX(Pub_Comps_Range,MATCH(K$5,Pub_Comps_Params,0),MATCH($C9,Pub_Comps_Tickers,0)) -> 0 | ... AA9: =INDEX(Pub_Comps_Range,MATCH(AA$5,Pub_Comps_Params,0),MATCH($C9,Pub_Comps_Tickers,0)) -> 0.2
B10: =INDEX(Pub_Comps_Range,MATCH(B$5,Pub_Comps_Params,0),MATCH($C10,Pub_Comps_Tickers,0)) -> GE Healthcare Technologies Inc. | C10: BMRN | D10: =INDEX(Pub_Comps_Range,MATCH(D$5,Pub_Comps_Params,0),MATCH($C10,Pub_Comps_Tickers,0)) -> 55.69 | E10: =INDEX(Pub_Comps_Range,MATCH(E$5,Pub_Comps_Params,0),MATCH($C10,Pub_Comps_Tickers,0)) -> 193 | F10: =INDEX(Pub_Comps_Range,MATCH(F$5,Pub_Comps_Params,0),MATCH($C10,Pub_Comps_Tickers,0)) -> 10748.17 | G10: =INDEX(Pub_Comps_Range,MATCH(G$5,Pub_Comps_Params,0),MATCH($C10,Pub_Comps_Tickers,0)) -> 1.27 | H10: =INDEX(Pub_Comps_Range,MATCH(H$5,Pub_Comps_Params,0),MATCH($C10,Pub_Comps_Tickers,0)) -> 0.234 | I10: =INDEX(Pub_Comps_Range,MATCH(I$5,Pub_Comps_Params,0),MATCH($C10,Pub_Comps_Tickers,0)) -> -1477 | J10: =INDEX(Pub_Comps_Range,MATCH(J$5,Pub_Comps_Params,0),MATCH($C10,Pub_Comps_Tickers,0)) -> 604 | K10: =INDEX(Pub_Comps_Range,MATCH(K$5,Pub_Comps_Params,0),MATCH($C10,Pub_Comps_Tickers,0)) -> 0 | ... AA10: =INDEX(Pub_Comps_Range,MATCH(AA$5,Pub_Comps_Params,0),MATCH($C10,Pub_Comps_Tickers,0)) -> 0.3106359
B11: =INDEX(Pub_Comps_Range,MATCH(B$5,Pub_Comps_Params,0),MATCH($C11,Pub_Comps_Tickers,0)) -> Sarepta Therapeutics, Inc. | C11: SRPT | D11: =INDEX(Pub_Comps_Range,MATCH(D$5,Pub_Comps_Params,0),MATCH($C11,Pub_Comps_Tickers,0)) -> 20.74 | E11: =INDEX(Pub_Comps_Range,MATCH(E$5,Pub_Comps_Params,0),MATCH($C11,Pub_Comps_Tickers,0)) -> 104.8 | F11: =INDEX(Pub_Comps_Range,MATCH(F$5,Pub_Comps_Params,0),MATCH($C11,Pub_Comps_Tickers,0)) -> 2173.552 | G11: =INDEX(Pub_Comps_Range,MATCH(G$5,Pub_Comps_Params,0),MATCH($C11,Pub_Comps_Tickers,0)) -> 1.26 | H11: =INDEX(Pub_Comps_Range,MATCH(H$5,Pub_Comps_Params,0),MATCH($C11,Pub_Comps_Tickers,0)) -> 0.2 | I11: =INDEX(Pub_Comps_Range,MATCH(I$5,Pub_Comps_Params,0),MATCH($C11,Pub_Comps_Tickers,0)) -> -851 | J11: =INDEX(Pub_Comps_Range,MATCH(J$5,Pub_Comps_Params,0),MATCH($C11,Pub_Comps_Tickers,0)) -> 1260 | K11: =INDEX(Pub_Comps_Range,MATCH(K$5,Pub_Comps_Params,0),MATCH($C11,Pub_Comps_Tickers,0)) -> 0 | ... AA11: =INDEX(Pub_Comps_Range,MATCH(AA$5,Pub_Comps_Params,0),MATCH($C11,Pub_Comps_Tickers,0)) -> 0.21825144
B12: =INDEX(Pub_Comps_Range,MATCH(B$5,Pub_Comps_Params,0),MATCH($C12,Pub_Comps_Tickers,0)) -> PTC Therapeutics, Inc. | C12: PTCT | D12: =INDEX(Pub_Comps_Range,MATCH(D$5,Pub_Comps_Params,0),MATCH($C12,Pub_Comps_Tickers,0)) -> 14.42 | E12: =INDEX(Pub_Comps_Range,MATCH(E$5,Pub_Comps_Params,0),MATCH($C12,Pub_Comps_Tickers,0)) -> 82.3 | F12: =INDEX(Pub_Comps_Range,MATCH(F$5,Pub_Comps_Params,0),MATCH($C12,Pub_Comps_Tickers,0)) -> 1186.766 | G12: =INDEX(Pub_Comps_Range,MATCH(G$5,Pub_Comps_Params,0),MATCH($C12,Pub_Comps_Tickers,0)) -> 2.15 | H12: =INDEX(Pub_Comps_Range,MATCH(H$5,Pub_Comps_Params,0),MATCH($C12,Pub_Comps_Tickers,0)) -> 0.2 | I12: =INDEX(Pub_Comps_Range,MATCH(I$5,Pub_Comps_Params,0),MATCH($C12,Pub_Comps_Tickers,0)) -> -1707 | J12: =INDEX(Pub_Comps_Range,MATCH(J$5,Pub_Comps_Params,0),MATCH($C12,Pub_Comps_Tickers,0)) -> 2492 | K12: =INDEX(Pub_Comps_Range,MATCH(K$5,Pub_Comps_Params,0),MATCH($C12,Pub_Comps_Tickers,0)) -> 0 | ... AA12: =INDEX(Pub_Comps_Range,MATCH(AA$5,Pub_Comps_Params,0),MATCH($C12,Pub_Comps_Tickers,0)) -> 0.042752868
B13: =INDEX(Pub_Comps_Range,MATCH(B$5,Pub_Comps_Params,0),MATCH($C13,Pub_Comps_Tickers,0)) -> Travere Therapeutics, Inc. | C13: TVTX | D13: =INDEX(Pub_Comps_Range,MATCH(D$5,Pub_Comps_Params,0),MATCH($C13,Pub_Comps_Tickers,0)) -> 27.83 | E13: =INDEX(Pub_Comps_Range,MATCH(E$5,Pub_Comps_Params,0),MATCH($C13,Pub_Comps_Tickers,0)) -> 89.678265 | F13: =INDEX(Pub_Comps_Range,MATCH(F$5,Pub_Comps_Params,0),MATCH($C13,Pub_Comps_Tickers,0)) -> 2495.7461 | G13: =INDEX(Pub_Comps_Range,MATCH(G$5,Pub_Comps_Params,0),MATCH($C13,Pub_Comps_Tickers,0)) -> 1.08 | H13: =INDEX(Pub_Comps_Range,MATCH(H$5,Pub_Comps_Params,0),MATCH($C13,Pub_Comps_Tickers,0)) -> 0.2 | I13: =INDEX(Pub_Comps_Range,MATCH(I$5,Pub_Comps_Params,0),MATCH($C13,Pub_Comps_Tickers,0)) -> -254 | J13: =INDEX(Pub_Comps_Range,MATCH(J$5,Pub_Comps_Params,0),MATCH($C13,Pub_Comps_Tickers,0)) -> 329 | K13: =INDEX(Pub_Comps_Range,MATCH(K$5,Pub_Comps_Params,0),MATCH($C13,Pub_Comps_Tickers,0)) -> 0 | ... AA13: =INDEX(Pub_Comps_Range,MATCH(AA$5,Pub_Comps_Params,0),MATCH($C13,Pub_Comps_Tickers,0)) -> 0.26900585
B14: =INDEX(Pub_Comps_Range,MATCH(B$5,Pub_Comps_Params,0),MATCH($C14,Pub_Comps_Tickers,0)) -> CareDx, Inc | C14: CPRX | D14: =INDEX(Pub_Comps_Range,MATCH(D$5,Pub_Comps_Params,0),MATCH($C14,Pub_Comps_Tickers,0)) -> 23.29 | E14: =INDEX(Pub_Comps_Range,MATCH(E$5,Pub_Comps_Params,0),MATCH($C14,Pub_Comps_Tickers,0)) -> 122.9 | F14: =INDEX(Pub_Comps_Range,MATCH(F$5,Pub_Comps_Params,0),MATCH($C14,Pub_Comps_Tickers,0)) -> 2862.341 | G14: =INDEX(Pub_Comps_Range,MATCH(G$5,Pub_Comps_Params,0),MATCH($C14,Pub_Comps_Tickers,0)) -> 2.56 | H14: =INDEX(Pub_Comps_Range,MATCH(H$5,Pub_Comps_Params,0),MATCH($C14,Pub_Comps_Tickers,0)) -> 0.239 | I14: =INDEX(Pub_Comps_Range,MATCH(I$5,Pub_Comps_Params,0),MATCH($C14,Pub_Comps_Tickers,0)) -> -689 | J14: =INDEX(Pub_Comps_Range,MATCH(J$5,Pub_Comps_Params,0),MATCH($C14,Pub_Comps_Tickers,0)) -> 2.9 | K14: =INDEX(Pub_Comps_Range,MATCH(K$5,Pub_Comps_Params,0),MATCH($C14,Pub_Comps_Tickers,0)) -> 0 | ... AA14: =INDEX(Pub_Comps_Range,MATCH(AA$5,Pub_Comps_Params,0),MATCH($C14,Pub_Comps_Tickers,0)) -> 0.45203252
B15: Maximum | D15: =MAX(D9:D13) -> 55.69 | F15: =MAX(F9:F13) -> 10748.17 | M15: =MAX(M9:M13) -> 9875.17 | N15: =MAX(N9:N13) -> 3094 | O15: =MAX(O9:O13) -> 3177 | P15: =MAX(P9:P13) -> 3554 | Q15: =MAX(Q9:Q13) -> 737.69 | R15: =MAX(R9:R13) -> 636 | S15: =MAX(S9:S13) -> 1104 | T15: =MAX(T9:T13) -> 751 | ... AA15: =MAX(AA9:AA13) -> 0.3106359
B16: 75th Percentile | D16: =QUARTILE(D9:D13,3) -> 27.83 | F16: =QUARTILE(F9:F13,3) -> 3234.6821 | M16: =QUARTILE(M9:M13,3) -> 3413.6821 | N16: =QUARTILE(N9:N13,3) -> 2413 | O16: =QUARTILE(O9:O13,3) -> 629 | P16: =QUARTILE(P9:P13,3) -> 1567 | Q16: =QUARTILE(Q9:Q13,3) -> 711.3 | R16: =QUARTILE(R9:R13,3) -> 77 | S16: =QUARTILE(S9:S13,3) -> 342 | T16: =QUARTILE(T9:T13,3) -> 520 | ... AA16: =QUARTILE(AA9:AA13,3) -> 0.26900585
B17: Median | D17: =MEDIAN(D9:D13) -> 20.74 | F17: =MEDIAN(F9:F13) -> 2495.7461 | M17: =MEDIAN(M9:M13) -> 2582.552 | N17: =MEDIAN(N9:N13) -> 1779 | O17: =MEDIAN(O9:O13) -> 0 | P17: =MEDIAN(P9:P13) -> 959 | Q17: =MEDIAN(Q9:Q13) -> 45.8 | R17: =MEDIAN(R9:R13) -> 0 | S17: =MEDIAN(S9:S13) -> 184 | T17: =MEDIAN(T9:T13) -> -14 | ... AA17: =MEDIAN(AA9:AA13) -> 0.21825144
B18: 25th Percentile | D18: =QUARTILE(D9:D13,1) -> 14.42 | F18: =QUARTILE(F9:F13,1) -> 2173.552 | M18: =QUARTILE(M9:M13,1) -> 2570.7461 | N18: =QUARTILE(N9:N13,1) -> 599 | O18: =QUARTILE(O9:O13,1) -> 0 | P18: =QUARTILE(P9:P13,1) -> 745 | Q18: =QUARTILE(Q9:Q13,1) -> -82 | R18: =QUARTILE(R9:R13,1) -> 0 | S18: =QUARTILE(S9:S13,1) -> 149 | T18: =QUARTILE(T9:T13,1) -> -88 | ... AA18: =QUARTILE(AA9:AA13,1) -> 0.2
B19: Minimum | D19: =MIN(D9:D13) -> 14.31 | F19: =MIN(F9:F13) -> 1186.766 | M19: =MIN(M9:M13) -> 1971.766 | N19: =MIN(N9:N13) -> 436 | O19: =MIN(O9:O13) -> 0 | P19: =MIN(P9:P13) -> 684 | Q19: =MIN(Q9:Q13) -> -87 | R19: =MIN(R9:R13) -> 0 | S19: =MIN(S9:S13) -> 41 | T19: =MIN(T9:T13) -> -271 | ... AA19: =MIN(AA9:AA13) -> 0.042752868
B21: =INDEX(Pub_Comps_Range,MATCH(B$5,Pub_Comps_Params,0),MATCH($C21,Pub_Comps_Tickers,0)) -> Ultragenyx Pharmaceutical Inc. | C21: =Ticker -> RARE | D21: =Share_Price -> 23.66 | E21: =INDEX(Pub_Comps_Range,MATCH(E$5,Pub_Comps_Params,0),MATCH($C21,Pub_Comps_Tickers,0)) -> 98.148 | F21: =INDEX(Pub_Comps_Range,MATCH(F$5,Pub_Comps_Params,0),MATCH($C21,Pub_Comps_Tickers,0)) -> 2322.1817 | G21: =INDEX(Pub_Comps_Range,MATCH(G$5,Pub_Comps_Params,0),MATCH($C21,Pub_Comps_Tickers,0)) -> 2.24 | H21: =INDEX(Pub_Comps_Range,MATCH(H$5,Pub_Comps_Params,0),MATCH($C21,Pub_Comps_Tickers,0)) -> 0.21 | I21: =INDEX(Pub_Comps_Range,MATCH(I$5,Pub_Comps_Params,0),MATCH($C21,Pub_Comps_Tickers,0)) -> -88.775 | J21: =INDEX(Pub_Comps_Range,MATCH(J$5,Pub_Comps_Params,0),MATCH($C21,Pub_Comps_Tickers,0)) -> 0 | K21: =INDEX(Pub_Comps_Range,MATCH(K$5,Pub_Comps_Params,0),MATCH($C21,Pub_Comps_Tickers,0)) -> 0 | L21: =INDEX(Pub_Comps_Range,MATCH(L$5,Pub_Comps_Params,0),MATCH($C21,Pub_Comps_Tickers,0)) -> 0 | ... V21: =INDEX(Pub_Comps_Range,MATCH(V$5,Pub_Comps_Params,0),MATCH($C21,Pub_Comps_Tickers,0)) -> -451.2666 | W21: =MIN(W10:W15) -> 0.064013841 | X21: =MIN(X10:X15) -> 0.2139738 | Y21: =MIN(Y10:Y15) -> -0.19954128 | Z21: =MIN(Z10:Z15) -> 0.20018886 | AA21: =MIN(AA10:AA15) -> 0.042752868
B23: Company Name: | C23: Ticker: | D23: Share Price: | F23: Equity Value: | M23: Enterprise Value: | N23: LTM EV / Revenue: | O23: 2025-12-31 EV / Revenue: | P23: 2026-12-31 EV / Revenue: | Q23: LTM EV / EBITDA: | R23: 2025-12-31 EV / EBITDA: | S23: 2026-12-31 EV / EBITDA: | T23: LTM P / E: | U23: 2025-12-31 P / E: | V23: 2026-12-31 P / E:
B24: Valuation Statistics: | F24: Capitalization | N24: Enterprise Value / | Q24: Enterprise Value /
F25: Equity | M25: Enterprise | N25: Revenue | Q25: EBITDA | T25: P / E Multiple
B26: Company Name | F26: Value | M26: Value | N26: =$N$8 -> LTM | O26: =+$O$8 -> 46022 | P26: =+$P$8 -> 46387 | Q26: =$N$8 -> LTM | R26: =+$O$8 -> 46022 | S26: =+$P$8 -> 46387 | T26: =$N$8 -> LTM | U26: =+$O$8 -> 46022 | V26: =+$P$8 -> 46387
B27: =INDEX(Pub_Comps_Range,MATCH(B$23,Pub_Comps_Params,0),MATCH($C27,Pub_Comps_Tickers,0)) -> Amicus Therapeutics, Inc. | C27: FOLD | D27: =INDEX(Pub_Comps_Range,MATCH(D$23,Pub_Comps_Params,0),MATCH($C27,Pub_Comps_Tickers,0)) -> 14.31 | F27: =INDEX(Pub_Comps_Range,MATCH(F$23,Pub_Comps_Params,0),MATCH($C27,Pub_Comps_Tickers,0)) -> 3234.6821 | M27: =INDEX(Pub_Comps_Range,MATCH(M$23,Pub_Comps_Params,0),MATCH($C27,Pub_Comps_Tickers,0)) -> 3413.6821 | N27: =INDEX(Pub_Comps_Range,MATCH(N$23,Pub_Comps_Params,0),MATCH($C27,Pub_Comps_Tickers,0)) -> 5.6989685 | O27: =INDEX(Pub_Comps_Range,MATCH(O$23,Pub_Comps_Params,0),MATCH($C27,Pub_Comps_Tickers,0)) -> 5.4271576 | P27: =INDEX(Pub_Comps_Range,MATCH(P$23,Pub_Comps_Params,0),MATCH($C27,Pub_Comps_Tickers,0)) -> 4.5821236 | Q27: =INDEX(Pub_Comps_Range,MATCH(Q$23,Pub_Comps_Params,0),MATCH($C27,Pub_Comps_Tickers,0)) -> 74.534544 | R27: =INDEX(Pub_Comps_Range,MATCH(R$23,Pub_Comps_Params,0),MATCH($C27,Pub_Comps_Tickers,0)) -> 44.333534 | S27: =INDEX(Pub_Comps_Range,MATCH(S$23,Pub_Comps_Params,0),MATCH($C27,Pub_Comps_Tickers,0)) -> 22.910618 | T27: =INDEX(Pub_Comps_Range,MATCH(T$23,Pub_Comps_Params,0),MATCH($C27,Pub_Comps_Tickers,0)) -> NM | ... V27: =INDEX(Pub_Comps_Range,MATCH(V$23,Pub_Comps_Params,0),MATCH($C27,Pub_Comps_Tickers,0)) -> 40.433526
B28: =INDEX(Pub_Comps_Range,MATCH(B$23,Pub_Comps_Params,0),MATCH($C28,Pub_Comps_Tickers,0)) -> GE Healthcare Technologies Inc. | C28: BMRN | D28: =INDEX(Pub_Comps_Range,MATCH(D$23,Pub_Comps_Params,0),MATCH($C28,Pub_Comps_Tickers,0)) -> 55.69 | F28: =INDEX(Pub_Comps_Range,MATCH(F$23,Pub_Comps_Params,0),MATCH($C28,Pub_Comps_Tickers,0)) -> 10748.17 | M28: =INDEX(Pub_Comps_Range,MATCH(M$23,Pub_Comps_Params,0),MATCH($C28,Pub_Comps_Tickers,0)) -> 9875.17 | N28: =INDEX(Pub_Comps_Range,MATCH(N$23,Pub_Comps_Params,0),MATCH($C28,Pub_Comps_Tickers,0)) -> 3.1917162 | O28: =INDEX(Pub_Comps_Range,MATCH(O$23,Pub_Comps_Params,0),MATCH($C28,Pub_Comps_Tickers,0)) -> 3.1083318 | P28: =INDEX(Pub_Comps_Range,MATCH(P$23,Pub_Comps_Params,0),MATCH($C28,Pub_Comps_Tickers,0)) -> 2.7786072 | Q28: =INDEX(Pub_Comps_Range,MATCH(Q$23,Pub_Comps_Params,0),MATCH($C28,Pub_Comps_Tickers,0)) -> 13.88327 | R28: =INDEX(Pub_Comps_Range,MATCH(R$23,Pub_Comps_Params,0),MATCH($C28,Pub_Comps_Tickers,0)) -> 15.526997 | S28: =INDEX(Pub_Comps_Range,MATCH(S$23,Pub_Comps_Params,0),MATCH($C28,Pub_Comps_Tickers,0)) -> 8.9449004 | T28: =INDEX(Pub_Comps_Range,MATCH(T$23,Pub_Comps_Params,0),MATCH($C28,Pub_Comps_Tickers,0)) -> 20.669558 | ... V28: =INDEX(Pub_Comps_Range,MATCH(V$23,Pub_Comps_Params,0),MATCH($C28,Pub_Comps_Tickers,0)) -> 12.527005
B29: =INDEX(Pub_Comps_Range,MATCH(B$23,Pub_Comps_Params,0),MATCH($C29,Pub_Comps_Tickers,0)) -> Sarepta Therapeutics, Inc. | C29: SRPT | D29: =INDEX(Pub_Comps_Range,MATCH(D$23,Pub_Comps_Params,0),MATCH($C29,Pub_Comps_Tickers,0)) -> 20.74 | F29: =INDEX(Pub_Comps_Range,MATCH(F$23,Pub_Comps_Params,0),MATCH($C29,Pub_Comps_Tickers,0)) -> 2173.552 | M29: =INDEX(Pub_Comps_Range,MATCH(M$23,Pub_Comps_Params,0),MATCH($C29,Pub_Comps_Tickers,0)) -> 2582.552 | N29: =INDEX(Pub_Comps_Range,MATCH(N$23,Pub_Comps_Params,0),MATCH($C29,Pub_Comps_Tickers,0)) -> 1.0702661 | O29: =INDEX(Pub_Comps_Range,MATCH(O$23,Pub_Comps_Params,0),MATCH($C29,Pub_Comps_Tickers,0)) -> N/A | P29: =INDEX(Pub_Comps_Range,MATCH(P$23,Pub_Comps_Params,0),MATCH($C29,Pub_Comps_Tickers,0)) -> 1.6480868 | Q29: =INDEX(Pub_Comps_Range,MATCH(Q$23,Pub_Comps_Params,0),MATCH($C29,Pub_Comps_Tickers,0)) -> NM | R29: =INDEX(Pub_Comps_Range,MATCH(R$23,Pub_Comps_Params,0),MATCH($C29,Pub_Comps_Tickers,0)) -> N/A | S29: =INDEX(Pub_Comps_Range,MATCH(S$23,Pub_Comps_Params,0),MATCH($C29,Pub_Comps_Tickers,0)) -> 7.5513216 | T29: =INDEX(Pub_Comps_Range,MATCH(T$23,Pub_Comps_Params,0),MATCH($C29,Pub_Comps_Tickers,0)) -> NM | ... V29: =INDEX(Pub_Comps_Range,MATCH(V$23,Pub_Comps_Params,0),MATCH($C29,Pub_Comps_Tickers,0)) -> 11.500275
B30: =INDEX(Pub_Comps_Range,MATCH(B$23,Pub_Comps_Params,0),MATCH($C30,Pub_Comps_Tickers,0)) -> PTC Therapeutics, Inc. | C30: PTCT | D30: =INDEX(Pub_Comps_Range,MATCH(D$23,Pub_Comps_Params,0),MATCH($C30,Pub_Comps_Tickers,0)) -> 14.42 | F30: =INDEX(Pub_Comps_Range,MATCH(F$23,Pub_Comps_Params,0),MATCH($C30,Pub_Comps_Tickers,0)) -> 1186.766 | M30: =INDEX(Pub_Comps_Range,MATCH(M$23,Pub_Comps_Params,0),MATCH($C30,Pub_Comps_Tickers,0)) -> 1971.766 | N30: =INDEX(Pub_Comps_Range,MATCH(N$23,Pub_Comps_Params,0),MATCH($C30,Pub_Comps_Tickers,0)) -> 1.1083564 | O30: =INDEX(Pub_Comps_Range,MATCH(O$23,Pub_Comps_Params,0),MATCH($C30,Pub_Comps_Tickers,0)) -> N/A | P30: =INDEX(Pub_Comps_Range,MATCH(P$23,Pub_Comps_Params,0),MATCH($C30,Pub_Comps_Tickers,0)) -> 2.0560647 | Q30: =INDEX(Pub_Comps_Range,MATCH(Q$23,Pub_Comps_Params,0),MATCH($C30,Pub_Comps_Tickers,0)) -> 2.6728924 | R30: =INDEX(Pub_Comps_Range,MATCH(R$23,Pub_Comps_Params,0),MATCH($C30,Pub_Comps_Tickers,0)) -> N/A | S30: =INDEX(Pub_Comps_Range,MATCH(S$23,Pub_Comps_Params,0),MATCH($C30,Pub_Comps_Tickers,0)) -> 48.091854 | T30: =INDEX(Pub_Comps_Range,MATCH(T$23,Pub_Comps_Params,0),MATCH($C30,Pub_Comps_Tickers,0)) -> 1.5802477 | ... V30: =INDEX(Pub_Comps_Range,MATCH(V$23,Pub_Comps_Params,0),MATCH($C30,Pub_Comps_Tickers,0)) -> NM
B31: =INDEX(Pub_Comps_Range,MATCH(B$23,Pub_Comps_Params,0),MATCH($C31,Pub_Comps_Tickers,0)) -> Travere Therapeutics, Inc. | C31: TVTX | D31: =INDEX(Pub_Comps_Range,MATCH(D$23,Pub_Comps_Params,0),MATCH($C31,Pub_Comps_Tickers,0)) -> 27.83 | F31: =INDEX(Pub_Comps_Range,MATCH(F$23,Pub_Comps_Params,0),MATCH($C31,Pub_Comps_Tickers,0)) -> 2495.7461 | M31: =INDEX(Pub_Comps_Range,MATCH(M$23,Pub_Comps_Params,0),MATCH($C31,Pub_Comps_Tickers,0)) -> 2570.7461 | N31: =INDEX(Pub_Comps_Range,MATCH(N$23,Pub_Comps_Params,0),MATCH($C31,Pub_Comps_Tickers,0)) -> 5.8962067 | O31: =INDEX(Pub_Comps_Range,MATCH(O$23,Pub_Comps_Params,0),MATCH($C31,Pub_Comps_Tickers,0)) -> N/A | P31: =INDEX(Pub_Comps_Range,MATCH(P$23,Pub_Comps_Params,0),MATCH($C31,Pub_Comps_Tickers,0)) -> 3.7584007 | Q31: =INDEX(Pub_Comps_Range,MATCH(Q$23,Pub_Comps_Params,0),MATCH($C31,Pub_Comps_Tickers,0)) -> NM | R31: =INDEX(Pub_Comps_Range,MATCH(R$23,Pub_Comps_Params,0),MATCH($C31,Pub_Comps_Tickers,0)) -> N/A | S31: =INDEX(Pub_Comps_Range,MATCH(S$23,Pub_Comps_Params,0),MATCH($C31,Pub_Comps_Tickers,0)) -> 13.971446 | T31: =INDEX(Pub_Comps_Range,MATCH(T$23,Pub_Comps_Params,0),MATCH($C31,Pub_Comps_Tickers,0)) -> NM | ... V31: =INDEX(Pub_Comps_Range,MATCH(V$23,Pub_Comps_Params,0),MATCH($C31,Pub_Comps_Tickers,0)) -> 34.188303
B32: =INDEX(Pub_Comps_Range,MATCH(B$23,Pub_Comps_Params,0),MATCH($C32,Pub_Comps_Tickers,0)) -> CareDx, Inc | C32: CPRX | D32: =INDEX(Pub_Comps_Range,MATCH(D$23,Pub_Comps_Params,0),MATCH($C32,Pub_Comps_Tickers,0)) -> 23.29 | F32: =INDEX(Pub_Comps_Range,MATCH(F$23,Pub_Comps_Params,0),MATCH($C32,Pub_Comps_Tickers,0)) -> 2862.341 | M32: =INDEX(Pub_Comps_Range,MATCH(M$23,Pub_Comps_Params,0),MATCH($C32,Pub_Comps_Tickers,0)) -> 2176.241 | N32: =INDEX(Pub_Comps_Range,MATCH(N$23,Pub_Comps_Params,0),MATCH($C32,Pub_Comps_Tickers,0)) -> 3.7651228 | O32: =INDEX(Pub_Comps_Range,MATCH(O$23,Pub_Comps_Params,0),MATCH($C32,Pub_Comps_Tickers,0)) -> 5.9060244 | P32: =INDEX(Pub_Comps_Range,MATCH(P$23,Pub_Comps_Params,0),MATCH($C32,Pub_Comps_Tickers,0)) -> 5.5507026 | Q32: =INDEX(Pub_Comps_Range,MATCH(Q$23,Pub_Comps_Params,0),MATCH($C32,Pub_Comps_Tickers,0)) -> 7.6359333 | R32: =INDEX(Pub_Comps_Range,MATCH(R$23,Pub_Comps_Params,0),MATCH($C32,Pub_Comps_Tickers,0)) -> 14.906909 | S32: =INDEX(Pub_Comps_Range,MATCH(S$23,Pub_Comps_Params,0),MATCH($C32,Pub_Comps_Tickers,0)) -> 12.279432 | T32: =INDEX(Pub_Comps_Range,MATCH(T$23,Pub_Comps_Params,0),MATCH($C32,Pub_Comps_Tickers,0)) -> 13.07005 | ... V32: =INDEX(Pub_Comps_Range,MATCH(V$23,Pub_Comps_Params,0),MATCH($C32,Pub_Comps_Tickers,0)) -> 14.770238
B34: Maximum | F34: =MAX(F27:F32) -> 10748.17 | M34: =MAX(M27:M32) -> 9875.17 | N34: =MAX(N27:N32) -> 5.8962067 | O34: =MAX(O27:O32) -> 5.9060244 | P34: =MAX(P27:P32) -> 5.5507026 | Q34: =MAX(Q27:Q32) -> 74.534544 | R34: =MAX(R27:R32) -> 44.333534 | S34: =MAX(S27:S32) -> 48.091854 | T34: =MAX(T27:T32) -> 20.669558 | ... V34: =MAX(V27:V32) -> 40.433526
B35: 75th Percentile | F35: =QUARTILE(F27:F32,3) -> 3141.5968 | M35: =QUARTILE(M27:M32,3) -> 3205.8996 | N35: =QUARTILE(N27:N32,3) -> 5.2155071 | O35: =QUARTILE(O27:O32,3) -> 5.666591 | P35: =QUARTILE(P27:P32,3) -> 4.3761929 | Q35: =QUARTILE(Q27:Q32,3) -> 29.046088 | R35: =QUARTILE(R27:R32,3) -> 29.930265 | S35: =QUARTILE(S27:S32,3) -> 20.675825 | T35: =QUARTILE(T27:T32,3) -> 16.869804 | ... V35: =QUARTILE(V27:V32,3) -> 34.188303
B36: Median | F36: =MEDIAN(F27:F32) -> 2679.0436 | M36: =MEDIAN(M27:M32) -> 2576.6491 | N36: =MEDIAN(N27:N32) -> 3.4784195 | O36: =MEDIAN(O27:O32) -> 5.4271576 | P36: =MEDIAN(P27:P32) -> 3.268504 | Q36: =MEDIAN(Q27:Q32) -> 10.759602 | R36: =MEDIAN(R27:R32) -> 15.526997 | S36: =MEDIAN(S27:S32) -> 13.125439 | T36: =MEDIAN(T27:T32) -> 13.07005 | ... V36: =MEDIAN(V27:V32) -> 14.770238
B37: 25th Percentile | F37: =QUARTILE(F27:F32,1) -> 2254.1005 | M37: =QUARTILE(M27:M32,1) -> 2274.8673 | N37: =QUARTILE(N27:N32,1) -> 1.6291963 | O37: =QUARTILE(O27:O32,1) -> 4.2677447 | P37: =QUARTILE(P27:P32,1) -> 2.2367003 | Q37: =QUARTILE(Q27:Q32,1) -> 6.3951731 | R37: =QUARTILE(R27:R32,1) -> 15.216953 | S37: =QUARTILE(S27:S32,1) -> 9.7785333 | T37: =QUARTILE(T27:T32,1) -> 7.3251489 | ... V37: =QUARTILE(V27:V32,1) -> 12.527005
B38: Minimum | F38: =MIN(F27:F32) -> 1186.766 | M38: =MIN(M27:M32) -> 1971.766 | N38: =MIN(N27:N32) -> 1.0702661 | O38: =MIN(O27:O32) -> 3.1083318 | P38: =MIN(P27:P32) -> 1.6480868 | Q38: =MIN(Q27:Q32) -> 2.6728924 | R38: =MIN(R27:R32) -> 14.906909 | S38: =MIN(S27:S32) -> 7.5513216 | T38: =MIN(T27:T32) -> 1.5802477 | ... V38: =MIN(V27:V32) -> 11.500275
B40: =INDEX(Pub_Comps_Range,MATCH(B$23,Pub_Comps_Params,0),MATCH($C40,Pub_Comps_Tickers,0)) -> Ultragenyx Pharmaceutical Inc. | C40: =Ticker -> RARE | F40: =INDEX(Pub_Comps_Range,MATCH(F$23,Pub_Comps_Params,0),MATCH($C40,Pub_Comps_Tickers,0)) -> 2322.1817 | M40: =INDEX(Pub_Comps_Range,MATCH(M$23,Pub_Comps_Params,0),MATCH($C40,Pub_Comps_Tickers,0)) -> 2233.4067 | N40: =INDEX(Pub_Comps_Range,MATCH(N$23,Pub_Comps_Params,0),MATCH($C40,Pub_Comps_Tickers,0)) -> 3.9865889 | O40: =INDEX(Pub_Comps_Range,MATCH(O$23,Pub_Comps_Params,0),MATCH($C40,Pub_Comps_Tickers,0)) -> 3.3185835 | P40: =INDEX(Pub_Comps_Range,MATCH(P$23,Pub_Comps_Params,0),MATCH($C40,Pub_Comps_Tickers,0)) -> 2.9978613 | Q40: =INDEX(Pub_Comps_Range,MATCH(Q$23,Pub_Comps_Params,0),MATCH($C40,Pub_Comps_Tickers,0)) -> NM | R40: =INDEX(Pub_Comps_Range,MATCH(R$23,Pub_Comps_Params,0),MATCH($C40,Pub_Comps_Tickers,0)) -> NM | S40: =INDEX(Pub_Comps_Range,MATCH(S$23,Pub_Comps_Params,0),MATCH($C40,Pub_Comps_Tickers,0)) -> NM | T40: =INDEX(Pub_Comps_Range,MATCH(T$23,Pub_Comps_Params,0),MATCH($C40,Pub_Comps_Tickers,0)) -> NM | ... V40: =INDEX(Pub_Comps_Range,MATCH(V$23,Pub_Comps_Params,0),MATCH($C40,Pub_Comps_Tickers,0)) -> NM

Sheet Pubcomps_Data
C3: Ticker: | H3: =Ticker -> RARE | M3: BMRN | R3: SRPT | W3: PTCT | AB3: TVTX | AG3: FOLD | AL3: CPRX
C4: Company Name: | H4: =Company_Name -> Ultragenyx Pharmaceutical Inc. | M4: GE Healthcare Technologies Inc. | R4: Sarepta Therapeutics, Inc. | W4: PTC Therapeutics, Inc. | AB4: Travere Therapeutics, Inc. | AG4: Amicus Therapeutics, Inc. | AL4: CareDx, Inc
E5: Calendarization: | J5: Calendarization: | O5: Calendarization: | T5: Calendarization: | Y5: Calendarization: | AD5: Calendarization: | AI5: Calendarization:
E6: N/A | F6: N/A | G6: =Hist_Year -> 45657 | H6: =Hist_Year -> 45657 | J6: 45565 | K6: 45930 | L6: 45657 | M6: 45930 | O6: 45472 | P6: 45836 | Q6: 45657 | R6: 45836 | T6: 45473 | U6: 45838 | V6: 45657 | W6: 45838 | Y6: 45565 | Z6: 45930 | AA6: 45657 | AB6: 45930 | AD6: 45565 | AE6: 45930 | AF6: 45657 | AG6: 45930 | AI6: 45473 | AJ6: 45838 | AK6: 45657 | AL6: 45838
E7: Old Partial | F7: New Partial | G7: FY | H7: LTM | J7: Old Partial | K7: New Partial | L7: FY | M7: LTM | O7: Old Partial | P7: New Partial | Q7: FY | R7: LTM | T7: Old Partial | U7: New Partial | V7: FY | W7: LTM | Y7: Old Partial | Z7: New Partial | AA7: FY | AB7: LTM | AD7: Old Partial | AE7: New Partial | AF7: FY | AG7: LTM | AI7: Old Partial | AJ7: New Partial | AK7: FY | AL7: LTM
C8: LTM Revenue: | G8: =Model!J62/Units -> 560.23 | H8: =G8+F8-E8 -> 560.23 | M8: 3094 | O8: 1243 | P8: 1755 | Q8: 1901 | R8: =+Q8+P8-O8 -> 2413 | T8: 593 | U8: 1565 | V8: 807 | W8: =+V8+U8-T8 -> 1779 | Y8: 158 | Z8: 361 | AA8: 233 | AB8: =+AA8+Z8-Y8 -> 436 | AD8: 378 | AE8: 449 | AF8: 528 | AG8: =+AF8+AE8-AD8 -> 599 | AI8: 350 | AJ8: 436 | AK8: 492 | AL8: =+AK8+AJ8-AI8 -> 578
C9: LTM Reported Net Income: | G9: =Model!J81/Units -> -569.183 | H9: =G9+F9-E9 -> -569.183 | M9: 520 | O9: 76 | P9: -430 | Q9: 235 | R9: =+Q9+P9-O9 -> -271 | T9: -297 | U9: 817 | V9: -363 | W9: =+V9+U9-T9 -> 751 | Y9: -261 | Z9: -28 | AA9: -321 | AB9: =+AA9+Z9-Y9 -> -88 | AD9: -70 | AE9: -28 | AF9: -56 | AG9: =+AF9+AE9-AD9 -> -14 | AI9: 107 | AJ9: 162 | AK9: 164 | AL9: =+AK9+AJ9-AI9 -> 219
C11: LTM Operating Income (EBIT): | G11: =Model!J69/Units -> -535.973 | H11: =G11+F11-E11 -> -535.973 | M11: 711.3 | O11: 65 | P11: -244 | Q11: 227 | R11: =+Q11+P11-O11 -> -82 | T11: -263 | U11: 826 | V11: -219 | W11: =+V11+U11-T11 -> 870 | Y11: -193 | Z11: -28 | AA11: -252 | AB11: =+AA11+Z11-Y11 -> -87 | AD11: -27.5 | AE11: -1.3 | AF11: 19.6 | AG11: =+AF11+AE11-AD11 -> 45.8 | AI11: 142 | AJ11: 211 | AK11: 216 | AL11: =+AK11+AJ11-AI11 -> 285
C12: (+) Non-Recurring Items in EBIT: | H12: =G12+F12-E12 -> 0 | M12: 0 | R12: =+Q12+P12-O12 -> 0 | U12: 0 | V12: -168 | W12: =+V12+U12-T12 -> -168 | Z12: 0 | AA12: 0 | AB12: =+AA12+Z12-Y12 -> 0 | AF12: 0 | AG12: =+AF12+AE12-AD12 -> 0 | AK12: 0 | AL12: =+AK12+AJ12-AI12 -> 0
C13: (+) Depreciation & Amortization: | H13: =G13+F13-E13 -> 0 | M13: 0 | R13: =+Q13+P13-O13 -> 0 | T13: 0 | U13: 0 | V13: 35.69 | W13: =+V13+U13-T13 -> 35.69 | Y13: 0 | Z13: 0 | AA13: 0 | AB13: =+AA13+Z13-Y13 -> 0 | AD13: 0 | AE13: 0 | AF13: 0 | AG13: =+AF13+AE13-AD13 -> 0 | AI13: 0 | AJ13: 0 | AK13: 0 | AL13: =+AK13+AJ13-AI13 -> 0
C14: LTM EBITDA: | H14: =SUM(H11:H13) -> -535.973 | M14: =SUM(M11:M13) -> 711.3 | R14: =SUM(R11:R13) -> -82 | W14: =SUM(W11:W13) -> 737.69 | AB14: =SUM(AB11:AB13) -> -87 | AG14: =SUM(AG11:AG13) -> 45.8 | AL14: =SUM(AL11:AL13) -> 285
C16: Effective Tax Rate: | H16: =Tax_Rate -> 0.21 | M16: 0.234 | R16: 0.2 | W16: 0.2 | AB16: 0.2 | AG16: 0.2 | AL16: 0.239
E18: Balance Sheet Data: | J18: Balance Sheet Data: | O18: Balance Sheet Data: | T18: Balance Sheet Data: | Y18: Balance Sheet Data: | AD18: Balance Sheet Data: | AI18: Balance Sheet Data:
C19: (-) Cash & Cash-Equivalents: | H19: =[1]DCF!G22 -> -88.775 | M19: -1477 | R19: -851 | W19: -1707 | AB19: -254 | AG19: -263 | AL19: -689
C20: (-) Equity Investments: | H20: =[1]DCF!G23 -> 0 | M20: 0 | R20: 0 | W20: 0 | AB20: 0 | AG20: 0 | AL20: 0
C21: (-) Other Non-Core Assets, Net: | H21: =[1]DCF!G24 -> 0 | M21: 0 | R21: 0 | W21: 0 | AB21: 0 | AG21: 0 | AL21: 0
C22: (-) Net Operating Losses: | H22: =[1]DCF!G25 -> 0 | M22: 0 | R22: 0 | W22: 0 | AB22: 0 | AG22: 0 | AL22: 0
C23: (+) Debt & Capital Leases: | H23: =[1]DCF!G26 -> 0 | M23: 604 | R23: 1260 | W23: 2492 | AB23: 329 | AG23: 442 | AL23: 2.9
C24: (+) Preferred Stock: | H24: =[1]DCF!G27 -> 0 | M24: 0 | R24: 0 | W24: 0 | AB24: 0 | AG24: 0 | AL24: 0
C25: (+) Noncontrolling Interests: | H25: =[1]DCF!G28 -> 0 | M25: 0 | R25: 0 | W25: 0 | AB25: 0 | AG25: 0 | AL25: 0
C26: (+) Unfunded Pension Obligations: | H26: 0 | M26: 0 | R26: 0 | W26: 0 | AB26: 0 | AG26: 0 | AL26: 0
C27: (+) Restructuring & Other Liabilities: | H27: =[1]DCF!G30 -> 0 | M27: 0 | R27: 0 | AB27: 0 | AG27: 0
E29: Projected Financials: | J29: Projected Financials: | O29: Projected Financials: | T29: Projected Financials: | Y29: Projected Financials: | AD29: Projected Financials: | AI29: Projected Financials:
E30: =Forward_Year_1 -> 46022 | F30: =Forward_Year_2 -> 46387 | G30: =Forward_Year_3 -> 46752 | J30: =Forward_Year_1 -> 46022 | K30: =Forward_Year_2 -> 46387 | L30: =Forward_Year_3 -> 46752 | O30: =Forward_Year_1 -> 46022 | P30: =Forward_Year_2 -> 46387 | Q30: =Forward_Year_3 -> 46752 | T30: =Forward_Year_1 -> 46022 | U30: =Forward_Year_2 -> 46387 | V30: =Forward_Year_3 -> 46752 | Y30: =Forward_Year_1 -> 46022 | Z30: =Forward_Year_2 -> 46387 | AA30: =Forward_Year_3 -> 46752 | AD30: =Forward_Year_1 -> 46022 | AE30: =Forward_Year_2 -> 46387 | AF30: =Forward_Year_3 -> 46752 | AI30: =Forward_Year_1 -> 46022 | AJ30: =Forward_Year_2 -> 46387 | AK30: =Forward_Year_3 -> 46752
C31: Revenue: | E31: =Model!K62/Units -> 673 | F31: =Model!L62/Units -> 745 | G31: =Model!M62/Units -> 1200.4973 | J31: 3177 | K31: 3554 | L31: 3896 | O31: 0 | P31: 1567 | Q31: 1487 | T31: 0 | U31: 959 | V31: 1220 | Y31: 0 | Z31: 684 | AA31: 906 | AD31: 629 | AE31: 745 | AF31: 877 | AI31: 578 | AJ31: 615 | AK31: 669
C32: EBITDA: | E32: =Model!K83/Units -> -508.22188 | F32: =Model!L83/Units -> -364.82964 | G32: =Model!M83/Units -> 320.1696 | J32: 636 | K32: 1104 | L32: 1304 | O32: 0 | P32: 342 | Q32: 357 | T32: 0 | U32: 41 | V32: 264 | Y32: 0 | Z32: 184 | AA32: 463 | AD32: 77 | AE32: 149 | AF32: 247 | AI32: =248-19 -> 229 | AJ32: 278 | AK32: 330
C33: Reported Net Income: | E33: =Model!K81/Units -> -586.93659 | F33: =Model!L81/Units -> -451.2666 | G33: =Model!M81/Units -> 212.26982 | J33: 526 | K33: 858 | L33: 1040 | O33: 0 | P33: 189 | Q33: 238 | T33: 0 | U33: -128 | V33: 122 | Y33: 0 | Z33: 73 | AA33: 185 | AD33: -6 | AE33: 80 | AF33: 144 | AI33: 204 | AJ33: 219 | AK33: 248
E35: Diluted Shares Calculations: | J35: Diluted Shares Calculations: | O35: Diluted Shares Calculations: | T35: Diluted Shares Calculations: | Y35: Diluted Shares Calculations: | AD35: Diluted Shares Calculations: | AI35: Diluted Shares Calculations:
C36: Share Price: | H36: =Share_Price -> 23.66 | M36: 55.69 | R36: 20.74 | W36: 14.42 | AB36: 27.83 | AG36: 14.31 | AL36: 23.29
C37: Common Shares Outstanding: | H37: =Diluted -> 97.56 | M37: 193 | R37: 104.8 | W37: 80.3 | AB37: 89.5 | AG37: 225.2 | AL37: 122.9
C38: Options and Warrants:
F39: Total | G39: Strike | H39: Dilution | K39: Total | L39: Strike | M39: Dilution | P39: Total | Q39: Strike | R39: Dilution | U39: Total | V39: Strike | W39: Dilution | Z39: Total | AA39: Strike | AB39: Dilution | AE39: Total | AF39: Strike | AG39: Dilution | AJ39: Total | AK39: Strike | AL39: Dilution
H40: =IF(G40<H$35,F40-((F40*G40)/H$35),0) -> 0 | M40: =IF(L40<M$35,K40-((K40*L40)/M$35),0) -> 0 | R40: =IF(Q40<R$35,P40-((P40*Q40)/R$35),0) -> 0 | W40: =IF(V40<W$35,U40-((U40*V40)/W$35),0) -> 0 | AB40: =IF(AA40<AB$35,Z40-((Z40*AA40)/AB$35),0) -> 0 | AG40: =IF(AF40<AG$35,AE40-((AE40*AF40)/AG$35),0) -> 0 | AL40: =IF(AK40<AL$35,AJ40-((AJ40*AK40)/AL$35),0) -> 0
H41: =IF(G41<H$35,F41-((F41*G41)/H$35),0) -> 0 | M41: =IF(L41<M$35,K41-((K41*L41)/M$35),0) -> 0 | R41: =IF(Q41<R$35,P41-((P41*Q41)/R$35),0) -> 0 | W41: =IF(V41<W$35,U41-((U41*V41)/W$35),0) -> 0 | AB41: =IF(AA41<AB$35,Z41-((Z41*AA41)/AB$35),0) -> 0 | AG41: =IF(AF41<AG$35,AE41-((AE41*AF41)/AG$35),0) -> 0 | AL41: =IF(AK41<AL$35,AJ41-((AJ41*AK41)/AL$35),0) -> 0
H42: =IF(G42<H$35,F42-((F42*G42)/H$35),0) -> 0 | M42: =IF(L42<M$35,K42-((K42*L42)/M$35),0) -> 0 | R42: =IF(Q42<R$35,P42-((P42*Q42)/R$35),0) -> 0 | W42: =IF(V42<W$35,U42-((U42*V42)/W$35),0) -> 0 | AB42: =IF(AA42<AB$35,Z42-((Z42*AA42)/AB$35),0) -> 0 | AG42: =IF(AF42<AG$35,AE42-((AE42*AF42)/AG$35),0) -> 0 | AL42: =IF(AK42<AL$35,AJ42-((AJ42*AK42)/AL$35),0) -> 0
H43: =IF(G43<H$35,F43-((F43*G43)/H$35),0) -> 0 | M43: =IF(L43<M$35,K43-((K43*L43)/M$35),0) -> 0 | R43: =IF(Q43<R$35,P43-((P43*Q43)/R$35),0) -> 0 | W43: =IF(V43<W$35,U43-((U43*V43)/W$35),0) -> 0 | AB43: =IF(AA43<AB$35,Z43-((Z43*AA43)/AB$35),0) -> 0 | AG43: =IF(AF43<AG$35,AE43-((AE43*AF43)/AG$35),0) -> 0 | AL43: =IF(AK43<AL$35,AJ43-((AJ43*AK43)/AL$35),0) -> 0
H44: =IF(G44<H$35,F44-((F44*G44)/H$35),0) -> 0 | M44: =IF(L44<M$35,K44-((K44*L44)/M$35),0) -> 0 | R44: =IF(Q44<R$35,P44-((P44*Q44)/R$35),0) -> 0 | W44: =IF(V44<W$35,U44-((U44*V44)/W$35),0) -> 0 | AB44: =IF(AA44<AB$35,Z44-((Z44*AA44)/AB$35),0) -> 0 | AG44: =IF(AF44<AG$35,AE44-((AE44*AF44)/AG$35),0) -> 0 | AL44: =IF(AK44<AL$35,AJ44-((AJ44*AK44)/AL$35),0) -> 0
H45: =IF(G45<H$35,F45-((F45*G45)/H$35),0) -> 0 | M45: =IF(L45<M$35,K45-((K45*L45)/M$35),0) -> 0 | R45: =IF(Q45<R$35,P45-((P45*Q45)/R$35),0) -> 0 | W45: =IF(V45<W$35,U45-((U45*V45)/W$35),0) -> 0 | AB45: =IF(AA45<AB$35,Z45-((Z45*AA45)/AB$35),0) -> 0 | AG45: =IF(AF45<AG$35,AE45-((AE45*AF45)/AG$35),0) -> 0 | AL45: =IF(AK45<AL$35,AJ45-((AJ45*AK45)/AL$35),0) -> 0
H46: =IF(G46<H$35,F46-((F46*G46)/H$35),0) -> 0 | M46: =IF(L46<M$35,K46-((K46*L46)/M$35),0) -> 0 | R46: =IF(Q46<R$35,P46-((P46*Q46)/R$35),0) -> 0 | W46: =IF(V46<W$35,U46-((U46*V46)/W$35),0) -> 0 | AB46: =IF(AA46<AB$35,Z46-((Z46*AA46)/AB$35),0) -> 0 | AG46: =IF(AF46<AG$35,AE46-((AE46*AF46)/AG$35),0) -> 0 | AL46: =IF(AK46<AL$35,AJ46-((AJ46*AK46)/AL$35),0) -> 0
H47: =IF(G47<H$35,F47-((F47*G47)/H$35),0) -> 0 | M47: =IF(L47<M$35,K47-((K47*L47)/M$35),0) -> 0 | R47: =IF(Q47<R$35,P47-((P47*Q47)/R$35),0) -> 0 | W47: =IF(V47<W$35,U47-((U47*V47)/W$35),0) -> 0 | AB47: =IF(AA47<AB$35,Z47-((Z47*AA47)/AB$35),0) -> 0 | AG47: =IF(AF47<AG$35,AE47-((AE47*AF47)/AG$35),0) -> 0 | AL47: =IF(AK47<AL$35,AJ47-((AJ47*AK47)/AL$35),0) -> 0
H48: =IF(G48<H$35,F48-((F48*G48)/H$35),0) -> 0 | M48: =IF(L48<M$35,K48-((K48*L48)/M$35),0) -> 0 | R48: =IF(Q48<R$35,P48-((P48*Q48)/R$35),0) -> 0 | W48: =IF(V48<W$35,U48-((U48*V48)/W$35),0) -> 0 | AB48: =IF(AA48<AB$35,Z48-((Z48*AA48)/AB$35),0) -> 0 | AG48: =IF(AF48<AG$35,AE48-((AE48*AF48)/AG$35),0) -> 0 | AL48: =IF(AK48<AL$35,AJ48-((AJ48*AK48)/AL$35),0) -> 0
C50: Convertible Bonds: | E50: $ Amount | F50: Par Value | G50: Conv. Price | H50: Dilution | J50: $ Amount | K50: Par Value | L50: Conv. Price | M50: Dilution | O50: $ Amount | P50: Par Value | Q50: Conv. Price | R50: Dilution | T50: $ Amount | U50: Par Value | V50: Conv. Price | W50: Dilution | Y50: $ Amount | Z50: Par Value | AA50: Conv. Price | AB50: Dilution | AD50: $ Amount | AE50: Par Value | AF50: Conv. Price | AG50: Dilution | AI50: $ Amount | AJ50: Par Value | AK50: Conv. Price | AL50: Dilution
H51: =IFERROR(IF(G51>H$35,0,(+F51/G51)*E51/F51), 0) -> 0 | M51: =IFERROR(IF(L51>M$35,0,(+K51/L51)*J51/K51),0) -> 0 | R51: =IFERROR(IF(Q51>R$35,0,(+P51/Q51)*O51/P51),0) -> 0 | W51: =IFERROR(IF(V51>W$35,0,(+U51/V51)*T51/U51),0) -> 0 | AB51: =IFERROR(IF(AA51>AB$35,0,+Y51/AA51-(AB$35*(Y51/AA51)-Y51)*0.5/AB$35),0) -> 0 | AG51: =IFERROR(IF(AF51>AG$35,0,+AD51/AF51-(AG$35*(AD51/AF51)-AD51)*0.5/AG$35),0) -> 0 | AL51: =IFERROR(IF(AK51>AL$35,0,+AI51/AK51-(AL$35*(AI51/AK51)-AI51)*0.5/AL$35),0) -> 0
H52: =IFERROR(IF(G52>H$35,0,(+F52/G52)*E52/F52),0) -> 0 | M52: =IFERROR(IF(L52>M$35,0,(+K52/L52)*J52/K52),0) -> 0 | R52: =IFERROR(IF(Q52>R$35,0,(+P52/Q52)*O52/P52),0) -> 0 | W52: =IFERROR(IF(V52>W$35,0,(+U52/V52)*T52/U52),0) -> 0 | AB52: =IFERROR(IF(AA52>AB$35,0,(+Z52/AA52)*Y52/Z52),0) -> 0 | AG52: =IFERROR(IF(AF52>AG$35,0,(+AE52/AF52)*AD52/AE52),0) -> 0 | AL52: =IFERROR(IF(AK52>AL$35,0,(+AJ52/AK52)*AI52/AJ52),0) -> 0
G54: # RSUs | H54: Dilution | L54: # RSUs | M54: Dilution | Q54: # RSUs | R54: Dilution | V54: # RSUs | W54: Dilution | AA54: # RSUs | AB54: Dilution | AF54: # RSUs | AG54: Dilution | AK54: # RSUs | AL54: Dilution
C55: Restricted Stock Units (RSUs): | G55: =(321+105+91+71)/Units -> 0.588 | H55: =+G55 -> 0.588 | L55: 0 | M55: =+L55 -> 0 | Q55: 0 | R55: =+Q55 -> 0 | V55: 2 | W55: =+V55 -> 2 | AA55: =(3470929+976862+513318)/AB36/1000000 -> 0.17826479 | AB55: =+AA55 -> 0.17826479 | AF55: =(8164661+1555793+809887+769882+769882)/AG36/1000000 -> 0.84347345 | AG55: =+AF55 -> 0.84347345 | AK55: 0 | AL55: =+AK55 -> 0
C57: Total Diluted Shares: | H57: =+H55+SUM(H40:H48)+SUM(H51:H52)+H37 -> 98.148 | M57: =+M55+SUM(M40:M48)+SUM(M51:M52)+M37 -> 193 | R57: =+R55+SUM(R40:R48)+SUM(R51:R52)+R37 -> 104.8 | W57: =+W55+SUM(W40:W48)+SUM(W51:W52)+W37 -> 82.3 | AB57: =+AB55+SUM(AB40:AB48)+SUM(AB51:AB52)+AB37 -> 89.678265 | AG57: =+AG55+SUM(AG40:AG48)+SUM(AG51:AG52)+AG37 -> 226.04347 | AL57: =+AL55+SUM(AL40:AL48)+SUM(AL51:AL52)+AL37 -> 122.9
E59: Valuation Metrics: | J59: Valuation Metrics: | O59: Valuation Metrics: | T59: Valuation Metrics: | Y59: Valuation Metrics: | AD59: Valuation Metrics: | AI59: Valuation Metrics:
C61: Equity Value: | H61: =+H57*H36 -> 2322.1817 | M61: =+M57*M36 -> 10748.17 | R61: =+R57*R36 -> 2173.552 | W61: =+W57*W36 -> 1186.766 | AB61: =+AB57*AB36 -> 2495.7461 | AG61: =+AG57*AG36 -> 3234.6821 | AL61: =+AL57*AL36 -> 2862.341
C62: Enterprise Value: | H62: =+H61+SUM(H19:H27) -> 2233.4067 | M62: =+M61+SUM(M19:M27) -> 9875.17 | R62: =+R61+SUM(R19:R27) -> 2582.552 | W62: =+W61+SUM(W19:W27) -> 1971.766 | AB62: =+AB61+SUM(AB19:AB27) -> 2570.7461 | AG62: =+AG61+SUM(AG19:AG27) -> 3413.6821 | AL62: =+AL61+SUM(AL19:AL27) -> 2176.241
C63: Levered Beta: | H63: 2.24 | M63: 1.27 | R63: 1.26 | W63: 2.15 | AB63: 1.08 | AG63: 1.78 | AL63: 2.56
E65: Valuation Multiples: | J65: Valuation Multiples: | O65: Valuation Multiples: | T65: Valuation Multiples: | Y65: Valuation Multiples: | AD65: Valuation Multiples: | AI65: Valuation Multiples:
E66: =H7 -> LTM | F66: =E30 -> 46022 | G66: =F30 -> 46387 | H66: =G30 -> 46752 | J66: =M7 -> LTM | K66: =J30 -> 46022 | L66: =K30 -> 46387 | M66: =L30 -> 46752 | O66: =R7 -> LTM | P66: =O30 -> 46022 | Q66: =P30 -> 46387 | R66: =Q30 -> 46752 | T66: =W7 -> LTM | U66: =T30 -> 46022 | V66: =U30 -> 46387 | W66: =V30 -> 46752 | Y66: =AB7 -> LTM | Z66: =Y30 -> 46022 | AA66: =Z30 -> 46387 | AB66: =AA30 -> 46752 | AD66: =AG7 -> LTM | AE66: =AD30 -> 46022 | AF66: =AE30 -> 46387 | AG66: =AF30 -> 46752 | AI66: =AL7 -> LTM | AJ66: =AI30 -> 46022 | AK66: =AJ30 -> 46387 | AL66: =AK30 -> 46752
C67: EV / Revenue: | E67: =IFERROR(IF(OR(+H$62/H8<0,+H$62/H8>=100),"NM",+H$62/H8), "N/A") -> 3.9865889 | F67: =IFERROR(IF(OR(+H62/E31<0,+H62/E31>=100),"NM",+H62/E31), "N/A") -> 3.3185835 | G67: =IFERROR(IF(OR(+$H$62/F31<0,+$H$62/F31>=100),"NM",+$H$62/F31), "N/A") -> 2.9978613 | H67: =IFERROR(IF(OR(+$H$62/G31<0,+$H$62/G31>=100),"NM",+$H$62/G31), "N/A") -> 1.8604013 | J67: =IFERROR(IF(OR(+M$62/M8<0,+M$62/M8>=100),"NM",+M$62/M8),"N/A") -> 3.1917162 | K67: =IFERROR(IF(OR(+$M$62/J31<0,+$M$62/J31>=100),"NM",+$M$62/J31), "N/A") -> 3.1083318 | L67: =IFERROR(IF(OR(+$M$62/K31<0,+$M$62/K31>=100),"NM",+$M$62/K31), "N/A") -> 2.7786072 | M67: =IFERROR(IF(OR(+$M$62/L31<0,+$M$62/L31>=100),"NM",+$M$62/L31), "N/A") -> 2.5346946 | O67: =IFERROR(IF(OR(+R$62/R8<0,+R$62/R8>=100),"NM",+R$62/R8),"N/A") -> 1.0702661 | P67: =IFERROR(IF(OR(+$R$62/O31<0,+$R$62/O31>=100),"NM",+$R$62/O31), "N/A") -> N/A | Q67: =IFERROR(IF(OR(+R62/P31<0,+R62/P31>=100),"NM",+R62/P31), "N/A") -> 1.6480868 | R67: =IFERROR(IF(OR(+R62/Q31<0,+R62/Q31>=100),"NM",+R62/Q31), "N/A") -> 1.7367532 | T67: =IFERROR(IF(OR(+W$62/W8<0,+W$62/W8>=100),"NM",+W$62/W8),"N/A") -> 1.1083564 | U67: =IFERROR(IF(OR(+$W$62/T31<0,+$W$62/T31>=100),"NM",+$W$62/T31), "N/A") -> N/A | V67: =IFERROR(IF(OR(+$W$62/U31<0,+$W$62/U31>=100),"NM",+$W$62/U31), "N/A") -> 2.0560647 | W67: =IFERROR(IF(OR(+$W$62/V31<0,+$W$62/V31>=100),"NM",+$W$62/V31), "N/A") -> 1.6162016 | Y67: =IFERROR(IF(OR(+AB$62/AB8<0,+AB$62/AB8>=100),"NM",+AB$62/AB8),"N/A") -> 5.8962067 | Z67: =IFERROR(IF(OR(+$AB$62/Y31<0,+$AB$62/Y31>=100),"NM",+$AB$62/Y31), "N/A") -> N/A | AA67: =IFERROR(IF(OR(+$AB$62/Z31<0,+$AB$62/Z31>=100),"NM",+$AB$62/Z31), "N/A") -> 3.7584007 | AB67: =IFERROR(IF(OR(+$AB$62/AA31<0,+$AB$62/AA31>=100),"NM",+$AB$62/AA31), "N/A") -> 2.8374681 | AD67: =IFERROR(IF(OR(+AG$62/AG8<0,+AG$62/AG8>=100),"NM",+AG$62/AG8),"N/A") -> 5.6989685 | AE67: =IFERROR(IF(OR(+$AG$62/AD31<0,+$AG$62/AD31>=100),"NM",+$AG$62/AD31), "N/A") -> 5.4271576 | AF67: =IFERROR(IF(OR(+$AG$62/AE31<0,+$AG$62/AE31>=100),"NM",+$AG$62/AE31), "N/A") -> 4.5821236 | AG67: =IFERROR(IF(OR(+$AG$62/AF31<0,+$AG$62/AF31>=100),"NM",+$AG$62/AF31), "N/A") -> 3.8924539 | AI67: =IFERROR(IF(OR(+AL$62/AL8<0,+AL$62/AL8>=100),"NM",+AL$62/AL8),"N/A") -> 3.7651228 | AJ67: =IFERROR(IF(OR(+$AG$62/AI31<0,+$AG$62/AI31>=100),"NM",+$AG$62/AI31), "N/A") -> 5.9060244 | AK67: =IFERROR(IF(OR(+$AG$62/AJ31<0,+$AG$62/AJ31>=100),"NM",+$AG$62/AJ31), "N/A") -> 5.5507026 | AL67: =IFERROR(IF(OR(+$AG$62/AK31<0,+$AG$62/AK31>=100),"NM",+$AG$62/AK31), "N/A") -> 5.1026638
C68: EV / EBITDA: | E68: =IFERROR(IF(OR(+H$62/H14<0,+H$62/H14>=100),"NM",+H$62/H14), "N/A") -> NM | F68: =IFERROR(IF(OR(+$H$62/E32<0,+$H$62/E32>=100),"NM",+$H$62/E32), "N/A") -> NM | G68: =IFERROR(IF(OR(+$H$62/F32<0,+$H$62/F32>=100),"NM",+$H$62/F32), "N/A") -> NM | H68: =IFERROR(IF(OR(+$H$62/G32<0,+$H$62/G32>=100),"NM",+$H$62/G32), "N/A") -> 6.9756987 | J68: =IFERROR(IF(OR(+M$62/M14<0,+M$62/M14>=100),"NM",+M$62/M14),"N/A") -> 13.88327 | K68: =IFERROR(IF(OR(+$M$62/J32<0,+$M$62/J32>=100),"NM",+$M$62/J32),"N/A") -> 15.526997 | L68: =IFERROR(IF(OR(+$M$62/K32<0,+$M$62/K32>=100),"NM",+$M$62/K32),"N/A") -> 8.9449004 | M68: =IFERROR(IF(OR(+$M$62/L32<0,+$M$62/L32>=100),"NM",+$M$62/L32),"N/A") -> 7.5729831 | O68: =IFERROR(IF(OR(+$R$62/R14<0,+$R$62/R14>=100),"NM",+$R$62/R14),"N/A") -> NM | P68: =IFERROR(IF(OR(+$R$62/O32<0,+$R$62/O32>=100),"NM",+$R$62/O32),"N/A") -> N/A | Q68: =IFERROR(IF(OR(+$R$62/P32<0,+$R$62/P32>=100),"NM",+$R$62/P32),"N/A") -> 7.5513216 | R68: =IFERROR(IF(OR(+$R$62/Q32<0,+$R$62/Q32>=100),"NM",+$R$62/Q32),"N/A") -> 7.2340392 | T68: =IFERROR(IF(OR(+W$62/W14<0,+W$62/W14>=100),"NM",+W$62/W14),"N/A") -> 2.6728924 | U68: =IFERROR(IF(OR(+$W$62/T32<0,+$W$62/T32>=100),"NM",+$W$62/T32), "N/A") -> N/A | V68: =IFERROR(IF(OR(+$W$62/U32<0,+$W$62/U32>=100),"NM",+$W$62/U32), "N/A") -> 48.091854 | W68: =IFERROR(IF(OR(+$W$62/V32<0,+$W$62/V32>=100),"NM",+$W$62/V32), "N/A") -> 7.4688106 | Y68: =IFERROR(IF(OR(+AB$62/AB14<0,+AB$62/AB14>=100),"NM",+AB$62/AB14),"N/A") -> NM | Z68: =IFERROR(IF(OR(+$AB$62/Y32<0,+$AB$62/Y32>=100),"NM",+$AB$62/Y32),"N/A") -> N/A | AA68: =IFERROR(IF(OR(+$AB$62/Z32<0,+$AB$62/Z32>=100),"NM",+$AB$62/Z32),"N/A") -> 13.971446 | AB68: =IFERROR(IF(OR(+$AB$62/AA32<0,+$AB$62/AA32>=100),"NM",+$AB$62/AA32),"N/A") -> 5.5523674 | AD68: =IFERROR(IF(OR(+AG$62/AG14<0,+AG$62/AG14>=100),"NM",+AG$62/AG14),"N/A") -> 74.534544 | AE68: =IFERROR(IF(OR(+$AG$62/AD32<0,+$AG$62/AD32>=100),"NM",+$AG$62/AD32),"N/A") -> 44.333534 | AF68: =IFERROR(IF(OR(+$AG$62/AE32<0,+$AG$62/AE32>=100),"NM",+$AG$62/AE32),"N/A") -> 22.910618 | AG68: =IFERROR(IF(OR(+$AG$62/AF32<0,+$AG$62/AF32>=100),"NM",+$AG$62/AF32),"N/A") -> 13.820575 | AI68: =IFERROR(IF(OR(+AL$62/AL14<0,+AL$62/AL14>=100),"NM",+AL$62/AL14),"N/A") -> 7.6359333 | AJ68: =IFERROR(IF(OR(+$AG$62/AI32<0,+$AG$62/AI32>=100),"NM",+$AG$62/AI32),"N/A") -> 14.906909 | AK68: =IFERROR(IF(OR(+$AG$62/AJ32<0,+$AG$62/AJ32>=100),"NM",+$AG$62/AJ32),"N/A") -> 12.279432 | AL68: =IFERROR(IF(OR(+$AG$62/AK32<0,+$AG$62/AK32>=100),"NM",+$AG$62/AK32),"N/A") -> 10.344491
C69: P / E: | E69: =IFERROR(IF(OR(+H$61/H9<0,+H$61/H9>=100),"NM",+H$61/H9), "N/A") -> NM | F69: =IFERROR(IF(OR($H$61/E$33<0,+$H$61/E$33>=100),"NM",+$H$61/E$33), "N/A") -> NM | G69: =IFERROR(IF(OR(H61/F$33<0,+H61/F$33>=100),"NM",+H61/F$33), "N/A") -> NM | H69: =IFERROR(IF(OR(H61/G$33<0,+H61/G$33>=100),"NM",+H61/G$33), "N/A") -> 10.939764 | J69: =IFERROR(IF(OR(+M$61/M9<0,+M$61/M9>=100),"NM",+M$61/M9), "N/A") -> 20.669558 | K69: =IFERROR(IF(OR($M$61/J$33<0,+$M$61/J$33>=100),"NM",+$M$61/J$33), "N/A") -> 20.433783 | L69: =IFERROR(IF(OR(M61/K$33<0,+M61/K$33>=100),"NM",+M61/K$33), "N/A") -> 12.527005 | M69: =IFERROR(IF(OR(M61/L$33<0,+M61/L$33>=100),"NM",+M61/L$33), "N/A") -> 10.334779 | O69: =IFERROR(IF(OR(+R$61/R9<0,+R$61/R9>=100),"NM",+R$61/R9), "N/A") -> NM | P69: =IFERROR(IF(OR($R$61/O$33<0,+$R$61/O$33>=100),"NM",+$R$61/O$33), "N/A") -> N/A | Q69: =IFERROR(IF(OR(R61/P$33<0,+R61/P$33>=100),"NM",+R61/P$33), "N/A") -> 11.500275 | R69: =IFERROR(IF(OR(R61/Q$33<0,+R61/Q$33>=100),"NM",+R61/Q$33), "N/A") -> 9.1325714 | T69: =IFERROR(IF(OR(+W$61/W9<0,+W$61/W9>=100),"NM",+W$61/W9),"N/A") -> 1.5802477 | U69: =IFERROR(IF(OR(+W$61/T33<0,+W$61/T33>=100),"NM",+W$61/T33),"N/A") -> N/A | V69: =IFERROR(IF(OR(+W$61/U33<0,+W$61/U33>=100),"NM",+W$61/U33),"N/A") -> NM | W69: =IFERROR(IF(OR(+W$61/V33<0,+W$61/V33>=100),"NM",+W$61/V33),"N/A") -> 9.7275902 | Y69: =IFERROR(IF(OR(+AB$61/AB9<0,+AB$61/AB9>=100),"NM",+AB$61/AB9),"N/A") -> NM | Z69: =IFERROR(IF(OR(+$AB$61/Y33<0,+$AB$61/Y33>=100),"NM",+$AB$61/Y33),"N/A") -> N/A | AA69: =IFERROR(IF(OR(+$AB$61/Z33<0,+$AB$61/Z33>=100),"NM",+$AB$61/Z33),"N/A") -> 34.188303 | AB69: =IFERROR(IF(OR(+$AB$61/AA33<0,+$AB$61/AA33>=100),"NM",+$AB$61/AA33),"N/A") -> 13.49052 | AD69: =IFERROR(IF(OR(+AG$61/AG9<0,+AG$61/AG9>=100),"NM",+AG$61/AG9),"N/A") -> NM | AE69: =IFERROR(IF(OR(+$AG$61/AD33<0,+$AG$61/AD33>=100),"NM",+$AG$61/AD33),"N/A") -> NM | AF69: =IFERROR(IF(OR(+$AG$61/AE33<0,+$AG$61/AE33>=100),"NM",+$AG$61/AE33),"N/A") -> 40.433526 | AG69: =IFERROR(IF(OR(+$AG$61/AF33<0,+$AG$61/AF33>=100),"NM",+$AG$61/AF33),"N/A") -> 22.46307 | AI69: =IFERROR(IF(OR(+AL$61/AL9<0,+AL$61/AL9>=100),"NM",+AL$61/AL9),"N/A") -> 13.07005 | AJ69: =IFERROR(IF(OR(+$AG$61/AI33<0,+$AG$61/AI33>=100),"NM",+$AG$61/AI33),"N/A") -> 15.856285 | AK69: =IFERROR(IF(OR(+$AG$61/AJ33<0,+$AG$61/AJ33>=100),"NM",+$AG$61/AJ33),"N/A") -> 14.770238 | AL69: =IFERROR(IF(OR(+$AG$61/AK33<0,+$AG$61/AK33>=100),"NM",+$AG$61/AK33),"N/A") -> 13.043073
E71: Lookup Variables: | J71: Lookup Variables: | O71: Lookup Variables: | T71: Lookup Variables: | Y71: Lookup Variables: | AD71: Lookup Variables: | AI71: Lookup Variables:
C73: =TEXT(Forward_Year_1,"yyyy-mm-dd")&" "&C31 -> 2025-12-31 Revenue: | H73: =+E31 -> 673 | M73: =+J31 -> 3177 | R73: =+O31 -> 0 | W73: =+T31 -> 0 | AB73: =+Y31 -> 0 | AG73: =+AD31 -> 629 | AL73: =+AI31 -> 578
C74: =TEXT(Forward_Year_1,"yyyy-mm-dd")&" "&C32 -> 2025-12-31 EBITDA: | H74: =+E32 -> -508.22188 | M74: =+J32 -> 636 | R74: =+O32 -> 0 | W74: =+T32 -> 0 | AB74: =+Y32 -> 0 | AG74: =+AD32 -> 77 | AL74: =+AI32 -> 229
C75: =TEXT(Forward_Year_1,"yyyy-mm-dd")&" "&C33 -> 2025-12-31 Reported Net Income: | H75: =+E33 -> -586.93659 | M75: =+J33 -> 526 | R75: =+O33 -> 0 | W75: =+T33 -> 0 | AB75: =+Y33 -> 0 | AG75: =+AD33 -> -6 | AL75: =+AI33 -> 204
C77: =TEXT(Forward_Year_2,"yyyy-mm-dd")&" "&C31 -> 2026-12-31 Revenue: | H77: =+F31 -> 745 | M77: =+K31 -> 3554 | R77: =+P31 -> 1567 | W77: =+U31 -> 959 | AB77: =+Z31 -> 684 | AG77: =+AE31 -> 745 | AL77: =+AJ31 -> 615
C78: =TEXT(Forward_Year_2,"yyyy-mm-dd")&" "&C32 -> 2026-12-31 EBITDA: | H78: =+F32 -> -364.82964 | M78: =+K32 -> 1104 | R78: =+P32 -> 342 | W78: =+U32 -> 41 | AB78: =+Z32 -> 184 | AG78: =+AE32 -> 149 | AL78: =+AJ32 -> 278
C79: =TEXT(Forward_Year_2,"yyyy-mm-dd")&" "&C33 -> 2026-12-31 Reported Net Income: | H79: =+F33 -> -451.2666 | M79: =+K33 -> 858 | R79: =+P33 -> 189 | W79: =+U33 -> -128 | AB79: =+Z33 -> 73 | AG79: =+AE33 -> 80 | AL79: =+AJ33 -> 219
C81: =TEXT(Forward_Year_3,"yyyy-mm-dd")&" "&C31 -> 2027-12-31 Revenue: | H81: =+G31 -> 1200.4973 | M81: =+L31 -> 3896 | R81: =+Q31 -> 1487 | W81: =+V31 -> 1220 | AB81: =+AA31 -> 906 | AG81: =+AF31 -> 877 | AL81: =+AK31 -> 669
C82: =TEXT(Forward_Year_3,"yyyy-mm-dd")&" "&C32 -> 2027-12-31 EBITDA: | H82: =+G32 -> 320.1696 | M82: =+L32 -> 1304 | R82: =+Q32 -> 357 | W82: =+V32 -> 264 | AB82: =+AA32 -> 463 | AG82: =+AF32 -> 247 | AL82: =+AK32 -> 330
C83: =TEXT(Forward_Year_3,"yyyy-mm-dd")&" "&C33 -> 2027-12-31 Reported Net Income: | H83: =+G33 -> 212.26982 | M83: =+L33 -> 1040 | R83: =+Q33 -> 238 | W83: =+V33 -> 122 | AB83: =+AA33 -> 185 | AG83: =+AF33 -> 144 | AL83: =+AK33 -> 248
C85: Year 1 Projected Revenue Growth: | H85: =IFERROR(+H77/H73-1,"N/A") -> 0.10698366 | M85: =IFERROR(+M77/M73-1,"N/A") -> 0.11866541 | R85: =IFERROR(+R77/R73-1,"N/A") -> N/A | W85: =IFERROR(+W77/W73-1,"N/A") -> N/A | AB85: =IFERROR(+AB77/AB73-1,"N/A") -> N/A | AG85: =IFERROR(+AG77/AG73-1,"N/A") -> 0.18441971 | AL85: =IFERROR(+AL77/AL73-1,"N/A") -> 0.064013841
C86: Year 1 Projected EBITDA Growth: | H86: =IFERROR(+H78/H74-1,"N/A") -> -0.28214495 | M86: =IFERROR(+M78/M74-1,"N/A") -> 0.73584906 | R86: =IFERROR(+R78/R74-1,"N/A") -> N/A | W86: =IFERROR(+W78/W74-1,"N/A") -> N/A | AB86: =IFERROR(+AB78/AB74-1,"N/A") -> N/A | AG86: =IFERROR(+AG78/AG74-1,"N/A") -> 0.93506494 | AL86: =IFERROR(+AL78/AL74-1,"N/A") -> 0.2139738
C88: LTM EBITDA Margin: | H88: =IFERROR(+H14/H8,"N/A") -> -0.95670171 | M88: =IFERROR(+M14/M8,"N/A") -> 0.22989657 | R88: =IFERROR(+R14/R8,"N/A") -> -0.033982594 | W88: =IFERROR(+W14/W8,"N/A") -> 0.41466554 | AB88: =IFERROR(+AB14/AB8,"N/A") -> -0.19954128 | AG88: =IFERROR(+AG14/AG8,"N/A") -> 0.076460768 | AL88: =IFERROR(+AL14/AL8,"N/A") -> 0.49307958
C89: =TEXT(Forward_Year_1,"yyyy-mm-dd")&" EBITDA Margin:" -> 2025-12-31 EBITDA Margin: | H89: =IFERROR(+H74/H73,"N/A") -> -0.75515881 | M89: =IFERROR(+M74/M73,"N/A") -> 0.20018886 | R89: =IFERROR(+R74/R73,"N/A") -> N/A | W89: =IFERROR(+W74/W73,"N/A") -> N/A | AB89: =IFERROR(+AB74/AB73,"N/A") -> N/A | AG89: =IFERROR(+AG74/AG73,"N/A") -> 0.12241653 | AL89: =IFERROR(+AL74/AL73,"N/A") -> 0.39619377
C90: =TEXT(Forward_Year_2,"yyyy-mm-dd")&" EBITDA Margin:" -> 2026-12-31 EBITDA Margin: | H90: =IFERROR(+H78/H77,"N/A") -> -0.48970422 | M90: =IFERROR(+M78/M77,"N/A") -> 0.3106359 | R90: =IFERROR(+R78/R77,"N/A") -> 0.21825144 | W90: =IFERROR(+W78/W77,"N/A") -> 0.042752868 | AB90: =IFERROR(+AB78/AB77,"N/A") -> 0.26900585 | AG90: =IFERROR(+AG78/AG77,"N/A") -> 0.2 | AL90: =IFERROR(+AL78/AL77,"N/A") -> 0.45203252
C92: =TEXT(E66,"mm/dd/yyyy")&" "&C67 -> LTM EV / Revenue: | H92: =+E67 -> 3.9865889 | M92: =+J67 -> 3.1917162 | R92: =+O67 -> 1.0702661 | W92: =+T67 -> 1.1083564 | AB92: =+Y67 -> 5.8962067 | AG92: =+AD67 -> 5.6989685 | AL92: =+AI67 -> 3.7651228
C93: =TEXT(E66,"mm/dd/yyyy")&" "&C68 -> LTM EV / EBITDA: | H93: =+E68 -> NM | M93: =+J68 -> 13.88327 | R93: =+O68 -> NM | W93: =+T68 -> 2.6728924 | AB93: =+Y68 -> NM | AG93: =+AD68 -> 74.534544 | AL93: =+AI68 -> 7.6359333
C94: =TEXT(E66,"mm/dd/yyyy")&" "&C69 -> LTM P / E: | H94: =+E69 -> NM | M94: =+J69 -> 20.669558 | R94: =+O69 -> NM | W94: =+T69 -> 1.5802477 | AB94: =+Y69 -> NM | AG94: =+AD69 -> NM | AL94: =+AI69 -> 13.07005
C96: =TEXT(Forward_Year_1,"yyyy-mm-dd")&" "&C67 -> 2025-12-31 EV / Revenue: | H96: =+F67 -> 3.3185835 | M96: =+K67 -> 3.1083318 | R96: =+P67 -> N/A | W96: =+U67 -> N/A | AB96: =+Z67 -> N/A | AG96: =+AE67 -> 5.4271576 | AL96: =+AJ67 -> 5.9060244
C97: =TEXT(Forward_Year_1,"yyyy-mm-dd")&" "&C68 -> 2025-12-31 EV / EBITDA: | H97: =+F68 -> NM | M97: =+K68 -> 15.526997 | R97: =+P68 -> N/A | W97: =+U68 -> N/A | AB97: =+Z68 -> N/A | AG97: =+AE68 -> 44.333534 | AL97: =+AJ68 -> 14.906909
C98: =TEXT(Forward_Year_1,"yyyy-mm-dd")&" "&C69 -> 2025-12-31 P / E: | H98: =+F69 -> NM | M98: =+K69 -> 20.433783 | R98: =+P69 -> N/A | W98: =+U69 -> N/A | AB98: =+Z69 -> N/A | AG98: =+AE69 -> NM | AL98: =+AJ69 -> 15.856285
C100: =TEXT(Forward_Year_2,"yyyy-mm-dd")&" "&C67 -> 2026-12-31 EV / Revenue: | H100: =+G67 -> 2.9978613 | M100: =+L67 -> 2.7786072 | R100: =+Q67 -> 1.6480868 | W100: =+V67 -> 2.0560647 | AB100: =+AA67 -> 3.7584007 | AG100: =+AF67 -> 4.5821236 | AL100: =+AK67 -> 5.5507026
C101: =TEXT(Forward_Year_2,"yyyy-mm-dd")&" "&C68 -> 2026-12-31 EV / EBITDA: | H101: =+G68 -> NM | M101: =+L68 -> 8.9449004 | R101: =+Q68 -> 7.5513216 | W101: =+V68 -> 48.091854 | AB101: =+AA68 -> 13.971446 | AG101: =+AF68 -> 22.910618 | AL101: =+AK68 -> 12.279432
C102: =TEXT(Forward_Year_2,"yyyy-mm-dd")&" "&C69 -> 2026-12-31 P / E: | H102: =+G69 -> NM | M102: =+L69 -> 12.527005 | R102: =+Q69 -> 11.500275 | W102: =+V69 -> NM | AB102: =+AA69 -> 34.188303 | AG102: =+AF69 -> 40.433526 | AL102: =+AK69 -> 14.770238
C104: Corporate Website:

Sheet PPT
B3: =Company_Name&" - R&D Expense Breakout" -> Ultragenyx Pharmaceutical Inc. - R&D Expense Breakout | L3: Line item (USD m) | M3: Low | N3: Base | O3: High | Q3: Summary of DCF and rNPV Outputs
B4: Clinical programs: | C4: 2023 | D4: 2024 | E4: 2025 | F4: Change | G4: Change % | H4: 2023 | I4: 2024 | L4: Headcount reduction (%) | M4: 0.3 | N4: 0.3 | O4: 0.3 | Q4: OpEx case | S4: Upside | V4: Base | Y4: Downside
B5: Gene therapy programs | H5: Corporate | L5: SG&A total (FY24) | M5: 321.6 | N5: 321.6 | O5: 321.6 | R5: Upside | S5: Base | T5: Downside | U5: Upside | V5: Base | W5: Downside | X5: Upside | Y5: Base | Z5: Downside
B6: DTX301 | C6: 31439 | D6: 40831 | F6: 9392 | G6: 0.3 | H6: {=SUM(C20:C22/C23)} -> 0.36476577 | I6: {=SUM(D20:D22/D23)} -> 0.36091794 | J6: 0.32 | L6: SG&A stock-based comp (FY24) | M6: 70 | N6: 70 | O6: 70
B7: DTX401 | C7: 72103 | D7: 75340 | F7: 3237 | G7: 0.04 | L7: SG&A cash (FY24) | M7: =M5-M6 -> 251.6 | N7: =N5-N6 -> 251.6 | O7: =O5-O6 -> 251.6 | Q7: UX - 111 | R7: 12.467795 | S7: 8.6880949 | T7: 5.5376294 | U7: 12.306843 | V7: 8.7164687 | W7: 5.5386004 | X7: 12.327137 | Y7: 8.7353731 | Z7: 5.5392676
B8: UX701 | C8: 24079 | D8: 33207 | F8: 9128 | G8: 0.38 | H8: Commercial | L8: R&D total (FY24) | M8: 697.9 | N8: 697.9 | O8: 697.9 | Q8: DTX - 401 | R8: 13.710951 | S8: 9.3248371 | T8: 4.3534469 | U8: 13.537332 | V8: 9.3342771 | W8: 4.3429517 | X8: 13.550585 | Y8: 9.3469625 | Z8: 4.3392159
B9: UX111 | C9: 24412 | D9: 41323 | F9: 16911 | G9: 0.69 | H9: =SUM(C18:C19,C17)/C23 -> 0.2071065 | I9: =SUM(D17:D20)/D23 -> 0.2760104 | J9: 0.22 | L9: R&D stock-based comp (FY24) | M9: 86.6 | N9: 86.6 | O9: 86.6 | Q9: DTX - 301 | R9: 1.238403 | S9: 1.2171351 | T9: 1.273017 | U9: 1.1717406 | V9: 1.2335402 | W9: 1.2728337 | X9: 1.1796014 | Y9: 1.2432587 | Z9: 1.271614
B10: CMC costs | C10: 16672 | D10: 3459 | F10: -13213 | G10: -0.79 | L10: R&D cash (FY24) | M10: 611.2 | N10: 611.2 | O10: 611.2 | Q10: GTX - 102 | R10: 21.296026 | S10: 13.717531 | T10: 7.4326603 | U10: 21.153158 | V10: 13.727635 | W10: 7.4259371 | X10: 21.163271 | Y10: 13.732768 | Z10: 7.4204286
B11: Total gene therapy programs | C11: 168705 | D11: 194160 | F11: 25455 | G11: 0.15 | H11: Pipeline | L11: SG&A people-driven share of cash SG&A | M11: 0.4 | N11: 0.55 | O11: 0.7 | Q11: Commercial - DCF | R11: 34.504748 | S11: 27.425996 | T11: 21.853926 | U11: 29.522201 | V11: 23.212702 | W11: 17.582979 | X11: 26.695067 | Y11: 20.452842 | Z11: 14.806229
B12: Biologic and nucleic acid programs | H12: =SUM(C6:C10,C13:C15)/C23 -> 0.42812773 | I12: =SUM(D6:D10,D13:D15)/D23 -> 0.47918867 | J12: 0.43 | L12: R&D people-driven share of cash R&D | M12: 0.55 | N12: 0.65 | O12: 0.75 | Q12: Total Implied Share Price | R12: 83.217923 | S12: 60.373594 | T12: 40.45068 | U12: 77.691276 | V12: 56.224623 | W12: 36.163302 | X12: 74.915661 | Y12: 53.511204 | Z12: 33.376755
B13: GTX102 | C13: 31121 | D13: 50757 | F13: 19636 | G13: 0.63 | L13: SG&A people-driven share of cash $ | M13: =M7*M11 -> 100.64 | N13: =N7*N11 -> 138.38 | O13: =O7*O11 -> 176.12 | Q13: Premium / (Discount) to Current: | R13: 2.5411882 | S13: 1.5690891 | T13: 0.72130551 | U13: 2.3060117 | V13: 1.3925371 | W13: 0.53886389 | X13: 2.1879005 | Y13: 1.2770725 | Z13: 0.42028745
B14: UX053 | C14: 12821 | D14: 374 | F14: -12447 | G14: -0.97 | L14: R&D people-driven share of cash $ | M14: =M10*M12 -> 336.16 | N14: =N10*N12 -> 397.28 | O14: =O10*O12 -> 458.4
B15: UX143 | C15: 64972 | D15: 89118 | F15: 24146 | G15: 0.37
B16: Total biologic and nucleic acid programs | C16: 108914 | D16: 140249 | F16: 31335 | G16: 0.29 | L16: SG&A cost savings | M16: =M4*M13 -> 30.192 | N16: =N4*N13 -> 41.514 | O16: =O4*O13 -> 52.836
B17: Translational research | C17: 71820 | D17: 45702 | F17: -26118 | G17: -0.36 | L17: R&D cost savings | M17: =M14*M4 -> 100.848 | N17: =N14*N4 -> 119.184 | O17: =O14*O4 -> 137.52
B18: Upfront license, acquisition, and milestone fees | C18: 9000 | D18: 30450 | F18: 21450 | G18: 2.38 | L18: Total | M18: =SUM(M16:M17) -> 131.04 | N18: =SUM(N16:N17) -> 160.698 | O18: =SUM(O16:O17) -> 190.356
B19: Approved products | C19: 53478 | D19: 35432 | F19: -18046 | G19: -0.34
B20: Infrastructure | C20: 78929 | D20: 81034 | F20: 2105 | G20: 0.03
B21: Stock-based compensation | C21: 74531 | D21: 86616 | F21: 12085 | G21: 0.16
B22: Other research and development | C22: 83072 | D22: 84222 | F22: 1150 | G22: 0.01 | U22: Summary of DCF and rNPV Outputs
B23: Total research and development expenses | C23: 648449 | D23: 697865 | F23: 49416 | G23: 0.08 | V23: Upside | W23: Base | X23: Downside
U24: UX - 111 | V24: 12.306843 | W24: 8.7164687 | X24: 5.5386004
B25: R&D expected to fall off in 2026 | D25: =SUM(D7,D9,D15) -> 205781 | U25: DTX - 401 | V25: 13.537332 | W25: 9.3342771 | X25: 4.3429517
B26: Continuing R&D | D26: =D23-D25 -> 492084 | U26: DTX - 301 | V26: 1.1717406 | W26: 1.2335402 | X26: 1.2728337
U27: GTX - 102 | V27: 21.153158 | W27: 13.727635 | X27: 7.4259371
U28: Commercial - DCF | V28: 29.522201 | W28: 23.212702 | X28: 17.582979
U29: Total Implied Share Price | V29: 77.691276 | W29: 56.224623 | X29: 36.163302
U30: Premium / (Discount) to Current: | V30: 2.3060117 | W30: 1.3925371 | X30: 0.53886389
H31: Historical | N31: Projected:
A32: =Company_Name&" - Model Drivers and Assumptions" -> Ultragenyx Pharmaceutical Inc. - Model Drivers and Assumptions | D32: Units: | F32: 44561 | G32: =EOMONTH(F32,12) -> 44926 | H32: =EOMONTH(G32,12) -> 45291 | I32: =EOMONTH(H32,12) -> 45657 | J32: =EOMONTH(I32,12) -> 46022 | K32: =EOMONTH(J32,12) -> 46387 | L32: =EOMONTH(K32,12) -> 46752 | M32: =EOMONTH(L32,12) -> 47118 | N32: =EOMONTH(M32,12) -> 47483 | O32: =EOMONTH(N32,12) -> 47848
B34: Beginning Balance | D34: $T | F34: 0 | G34: 1862400 | H34: 1466600 | I34: 1664700 | J34: 1934900 | K34: 2186460.3 | L34: 2105704.4 | M34: 1727793.4 | N34: 996480.02 | O34: 0
B35: (+) NOLs Created | D35: $T | F35: 0 | G35: 0 | H35: 198100 | I35: 270200 | J35: 251560.34 | K35: 0 | L35: 0 | M35: 0 | N35: 0 | O35: 0
B36: (-) NOLs Used | D36: $T | F36: 0 | G36: -395800 | H36: 0 | I36: 0 | J36: 0 | K36: -80755.94 | L36: -377910.96 | M36: -731313.42 | N36: -996480.02 | O36: 0
B37: Other NOL Adjustments | D37: $T | F37: 0 | G37: 0 | H37: 0 | I37: 0 | J37: 0 | K37: 0 | L37: 0 | M37: 0 | N37: 0 | O37: 0
B38: Ending Balance | D38: $T | F38: 1862400 | G38: 1466600 | H38: 1664700 | I38: 1934900 | J38: 2186460.3 | K38: 2105704.4 | L38: 1727793.4 | M38: 996480.02 | N38: 0 | O38: 0
Q39: Scenario Matrix - Total Implied Share Price
B40: Taxable Income After NOL | D40: $T | F40: 0 | G40: 0 | H40: 0 | I40: 0 | J40: 0 | K40: 20188.985 | L40: 94477.74 | M40: 182828.35 | N40: 554311.13 | O40: 0 | Q40: OpEx case | R40: Upside | S40: Base | T40: Downside
B41: Cash Taxes Payable | D41: $T | F41: 0 | G41: 0 | H41: 0 | I41: 0 | J41: 0 | K41: 2422.6782 | L41: 11337.329 | M41: 21939.403 | N41: 66517.335 | O41: 0 | Q41: Scenario
B42: NOL Utilization Limit (% of EBT) | D42: $T | F42: 0.8 | G42: 0.8 | H42: 0.8 | I42: 0.8 | J42: 0.8 | K42: 0.8 | L42: 0.8 | M42: 0.8 | N42: 0.8 | O42: 0.8 | Q42: Upside | R42: 83.217923 | S42: 79.81386 | T42: 74.915661
Q43: Base | R43: 60.373594 | S43: 56.861263 | T43: 53.511204
Q44: Downside | R44: 40.45068 | S44: 36.020442 | T44: 33.376755
B50: Key Stats
B51: Initiation Date | D51: 46043 | J51: Initiation Date:
B52: Initiation Price | D52: 23.66 | J52: 46042
B53: Price | D53: 23.66 | J53: Initiation Price: $22.63
B54: Price Target | D54: 56.22 | J54: Current Price:
B55: 52 Week High - Low | D55: $18.41-$46.50 | J55: 22.63
B56: Shares Outstanding - Mil | D56: =Diluted -> 97.56 | J56: Target Price:
B57: Market Cap - Mil | D57: $B 2.183 | J57: 56.22
B58: Book Value / Share | D58: 2.6168204
B59: Cash per Share | D59: 7.5338253
B60: Dividend | D60: N/A
